Workbook

Sheet Resumen
A1: Taller de Simulación de Sistemas - Resumen Ejecutivo
A3: Problema 1: Decisión de inversión
A4: Regla de decisión | B4: Aceptar si P(TIR > TREMA) ≥ 90%
A5: P(TIR > TREMA) simulada | B5: =Problema1_Inversion!B129 -> 1
A6: TIR promedio simulada | B6: =Problema1_Inversion!B130 -> 0.27964866
A7: Decisión | B7: =Problema1_Inversion!B134 -> ACEPTAR el proyecto
A9: Problema 2: Número óptimo de camiones
A10: Número óptimo de camiones | B10: =Problema2_Camiones!B301 -> 12
A11: Costo total anual mínimo | B11: =Problema2_Camiones!B302 -> 1381066.6
A14: Nota: los valores se recalculan cada vez que se abre o modifica el archivo (las fórmulas usan RAND()). Para 'congelar' un escenario, copie las hojas y pegue los resultados como valores (Copiar > Pegado especial > Valores).

Sheet Problema1_Inversion
A1: Problema 1: Decisión de Inversión - Simulación Montecarlo
A3: Parámetros generales
A4: Tasa de impuestos | B4: 0.5
A5: TREMA | B5: 0.15
A6: Probabilidad mínima requerida P(TIR>TREMA) | B6: 0.9
A7: Vida fiscal del activo (años) | B7: 5
A8: Número de iteraciones simuladas | B8: 100
A10: Distribuciones triangulares (datos del enunciado)
A11: Variable | B11: Pesimista | C11: Probable | D11: Optimista | E11: Mín (a) | F11: Moda (m) | G11: Máx (b)
A12: Activo fijo inicial | B12: -100000 | C12: -70000 | D12: -60000 | E12: =MIN(B12,D12) -> -100000 | F12: =C12 -> -70000 | G12: =MAX(B12,D12) -> -60000
A13: Activo circulante inicial | B13: -40000 | C13: -30000 | D13: -25000 | E13: =MIN(B13,D13) -> -40000 | F13: =C13 -> -30000 | G13: =MAX(B13,D13) -> -25000
A14: Flujo antes de impuestos (anual) | B14: 30000 | C14: 40000 | D14: 45000 | E14: =MIN(B14,D14) -> 30000 | F14: =C14 -> 40000 | G14: =MAX(B14,D14) -> 45000
A15: Inflación Año 1 (%) | B15: 18 | C15: 15 | D15: 12 | E15: =MIN(B15,D15) -> 12 | F15: =C15 -> 15 | G15: =MAX(B15,D15) -> 18
A16: Inflación Año 2 (%) | B16: 18 | C16: 15 | D16: 12 | E16: =MIN(B16,D16) -> 12 | F16: =C16 -> 15 | G16: =MAX(B16,D16) -> 18
A17: Inflación Año 3 (%) | B17: 22 | C17: 18 | D17: 15 | E17: =MIN(B17,D17) -> 15 | F17: =C17 -> 18 | G17: =MAX(B17,D17) -> 22
A18: Inflación Año 4 (%) | B18: 25 | C18: 20 | D18: 18 | E18: =MIN(B18,D18) -> 18 | F18: =C18 -> 20 | G18: =MAX(B18,D18) -> 25
A19: Inflación Año 5 (%) | B19: 28 | C19: 22 | D19: 19 | E19: =MIN(B19,D19) -> 19 | F19: =C19 -> 22 | G19: =MAX(B19,D19) -> 28
A21: Nota: para las variables de inflación, 'Pesimista' es la tasa más alta (peor caso) y 'Optimista' la más baja; por eso Mín/Máx se toman como MIN/MAX(Pesimista,Optimista) y la Moda es siempre el valor 'Probable'.
A23: Simulación Montecarlo (una fila = una iteración / un escenario a 5 años)
A24: Iter | B24: U(Af) | C24: Af | D24: U(Ac) | E24: Ac | F24: U(F1) | G24: F1 | H24: U(F2) | I24: F2 | J24: U(F3) | K24: F3 | L24: U(F4) | M24: F4 | N24: U(F5) | O24: F5 | P24: U(Infl1) | Q24: Infl1% | R24: U(Infl2) | S24: Infl2% | T24: U(Infl3) | U24: Infl3% | V24: U(Infl4) | W24: Infl4% | X24: U(Infl5) | Y24: Infl5% | Z24: FlujoInfl1 | AA24: FlujoInfl2 | AB24: FlujoInfl3 | AC24: FlujoInfl4 | AD24: FlujoInfl5 | AE24: Deprec. | AF24: UAI1 | AG24: UAI2 | AH24: UAI3 | AI24: UAI4 | AJ24: UAI5 | AK24: Imp1 | AL24: Imp2 | AM24: Imp3 | AN24: Imp4 | AO24: Imp5 | AP24: UN1 | AQ24: UN2 | AR24: UN3 | AS24: UN4 | AT24: UN5 | AU24: Val.Rescate | AV24: FNE0 | AW24: FNE1 | AX24: FNE2 | AY24: FNE3 | AZ24: FNE4 | BA24: FNE5 | BB24: TIR | BC24: VPN(chk)
A25: 1 | B25: =RAND() -> 0.82663184 | C25: =IF(B25<=($F$12-$E$12)/($G$12-$E$12),$E$12+SQRT(B25*($G$12-$E$12)*($F$12-$E$12)),$G$12-SQRT((1-B25)*($G$12-$E$12)*($G$12-$F$12))) -> -68327.5 | D25: =RAND() -> 0.82663481 | E25: =IF(D25<=($F$13-$E$13)/($G$13-$E$13),$E$13+SQRT(D25*($G$13-$E$13)*($F$13-$E$13)),$G$13-SQRT((1-D25)*($G$13-$E$13)*($G$13-$F$13))) -> -28605.883 | F25: =RAND() -> 0.82665487 | G25: =IF(F25<=($F$14-$E$14)/($G$14-$E$14),$E$14+SQRT(F25*($G$14-$E$14)*($F$14-$E$14)),$G$14-SQRT((1-F25)*($G$14-$E$14)*($G$14-$F$14))) -> 41394.326 | H25: =RAND() -> 0.80394605 | I25: =IF(H25<=($F$14-$E$14)/($G$14-$E$14),$E$14+SQRT(H25*($G$14-$E$14)*($F$14-$E$14)),$G$14-SQRT((1-H25)*($G$14-$E$14)*($G$14-$F$14))) -> 41165.414 | J25: =RAND() -> 0.49070577 | K25: =IF(J25<=($F$14-$E$14)/($G$14-$E$14),$E$14+SQRT(J25*($G$14-$E$14)*($F$14-$E$14)),$G$14-SQRT((1-J25)*($G$14-$E$14)*($G$14-$F$14))) -> 38579.386 | L25: =RAND() -> 0.17425129 | M25: =IF(L25<=($F$14-$E$14)/($G$14-$E$14),$E$14+SQRT(L25*($G$14-$E$14)*($F$14-$E$14)),$G$14-SQRT((1-L25)*($G$14-$E$14)*($G$14-$F$14))) -> 35112.504 | N25: =RAND() -> 0.019864486 | O25: =IF(N25<=($F$14-$E$14)/($G$14-$E$14),$E$14+SQRT(N25*($G$14-$E$14)*($F$14-$E$14)),$G$14-SQRT((1-N25)*($G$14-$E$14)*($G$14-$F$14))) -> 31726.173 | P25: =RAND() -> 0.69179452 | Q25: =IF(P25<=($F$15-$E$15)/($G$15-$E$15),$E$15+SQRT(P25*($G$15-$E$15)*($F$15-$E$15)),$G$15-SQRT((1-P25)*($G$15-$E$15)*($G$15-$F$15))) -> 15.644645 | R25: =RAND() -> 0.9778088 | S25: =IF(R25<=($F$16-$E$16)/($G$16-$E$16),$E$16+SQRT(R25*($G$16-$E$16)*($F$16-$E$16)),$G$16-SQRT((1-R25)*($G$16-$E$16)*($G$16-$F$16))) -> 17.367986 | T25: =RAND() -> 0.4540416 | U25: =IF(T25<=($F$17-$E$17)/($G$17-$E$17),$E$17+SQRT(T25*($G$17-$E$17)*($F$17-$E$17)),$G$17-SQRT((1-T25)*($G$17-$E$17)*($G$17-$F$17))) -> 18.090162 | V25: =RAND() -> 0.54810444 | W25: =IF(V25<=($F$18-$E$18)/($G$18-$E$18),$E$18+SQRT(V25*($G$18-$E$18)*($F$18-$E$18)),$G$18-SQRT((1-V25)*($G$18-$E$18)*($G$18-$F$18))) -> 21.023023 | X25: =RAND() -> 0.38334141 | Y25: =IF(X25<=($F$19-$E$19)/($G$19-$E$19),$E$19+SQRT(X25*($G$19-$E$19)*($F$19-$E$19)),$G$19-SQRT((1-X25)*($G$19-$E$19)*($G$19-$F$19))) -> 22.229423 | Z25: =G25*(1+Q25/100) -> 47870.321 | AA25: =I25*(1+Q25/100)*(1+S25/100) -> 55873.731 | AB25: =K25*(1+Q25/100)*(1+S25/100)*(1+U25/100) -> 61836.402 | AC25: =M25*(1+Q25/100)*(1+S25/100)*(1+U25/100)*(1+W25/100) -> 68111.225 | AD25: =O25*(1+Q25/100)*(1+S25/100)*(1+U25/100)*(1+W25/100)*(1+Y25/100) -> 75222.947 | AE25: =ABS(C25)/$B$7 -> 13665.5 | AF25: =Z25-AE25 -> 34204.821 | AG25: =AA25-AE25 -> 42208.231 | AH25: =AB25-AE25 -> 48170.901 | AI25: =AC25-AE25 -> 54445.725 | AJ25: =AD25-AE25 -> 61557.446 | AK25: =AF25*$B$4 -> 17102.411 | AL25: =AG25*$B$4 -> 21104.115 | AM25: =AH25*$B$4 -> 24085.451 | AN25: =AI25*$B$4 -> 27222.862 | AO25: =AJ25*$B$4 -> 30778.723 | AP25: =AF25-AK25 -> 17102.411 | AQ25: =AG25-AL25 -> 21104.115 | AR25: =AH25-AM25 -> 24085.451 | AS25: =AI25-AN25 -> 27222.862 | AT25: =AJ25-AO25 -> 30778.723 | AU25: =0.2*ABS(C25)+1*ABS(E25) -> 42271.383 | AV25: =C25+E25 -> -96933.383 | AW25: =AP25+AE25 -> 30767.911 | AX25: =AQ25+AE25 -> 34769.615 | AY25: =AR25+AE25 -> 37750.951 | AZ25: =AS25+AE25 -> 40888.363 | BA25: =AT25+AE25+AU25 -> 86715.606 | BB25: =IFERROR(IRR(AV25:BA25,0.15),"n/a") -> 0.30985144 | BC25: =NPV($B$5,AW25:BA25)+AV25 -> 47425.045
A26: 2 | B26: =RAND() -> 0.73568615 | C26: =IF(B26<=($F$12-$E$12)/($G$12-$E$12),$E$12+SQRT(B26*($G$12-$E$12)*($F$12-$E$12)),$G$12-SQRT((1-B26)*($G$12-$E$12)*($G$12-$F$12))) -> -70287.656 | D26: =RAND() -> 0.4892787 | E26: =IF(D26<=($F$13-$E$13)/($G$13-$E$13),$E$13+SQRT(D26*($G$13-$E$13)*($F$13-$E$13)),$G$13-SQRT((1-D26)*($G$13-$E$13)*($G$13-$F$13))) -> -31433.098 | F26: =RAND() -> 0.50911251 | G26: =IF(F26<=($F$14-$E$14)/($G$14-$E$14),$E$14+SQRT(F26*($G$14-$E$14)*($F$14-$E$14)),$G$14-SQRT((1-F26)*($G$14-$E$14)*($G$14-$F$14))) -> 38738.814 | H26: =RAND() -> 0.1712769 | I26: =IF(H26<=($F$14-$E$14)/($G$14-$E$14),$E$14+SQRT(H26*($G$14-$E$14)*($F$14-$E$14)),$G$14-SQRT((1-H26)*($G$14-$E$14)*($G$14-$F$14))) -> 35068.682 | J26: =RAND() -> 0.37121602 | K26: =IF(J26<=($F$14-$E$14)/($G$14-$E$14),$E$14+SQRT(J26*($G$14-$E$14)*($F$14-$E$14)),$G$14-SQRT((1-J26)*($G$14-$E$14)*($G$14-$F$14))) -> 37462.064 | L26: =RAND() -> 0.79033492 | M26: =IF(L26<=($F$14-$E$14)/($G$14-$E$14),$E$14+SQRT(L26*($G$14-$E$14)*($F$14-$E$14)),$G$14-SQRT((1-L26)*($G$14-$E$14)*($G$14-$F$14))) -> 41034.539 | N26: =RAND() -> 0.45621254 | O26: =IF(N26<=($F$14-$E$14)/($G$14-$E$14),$E$14+SQRT(N26*($G$14-$E$14)*($F$14-$E$14)),$G$14-SQRT((1-N26)*($G$14-$E$14)*($G$14-$F$14))) -> 38272.356 | P26: =RAND() -> 0.012369476 | Q26: =IF(P26<=($F$15-$E$15)/($G$15-$E$15),$E$15+SQRT(P26*($G$15-$E$15)*($F$15-$E$15)),$G$15-SQRT((1-P26)*($G$15-$E$15)*($G$15-$F$15))) -> 12.471859 | R26: =RAND() -> 0.94876763 | S26: =IF(R26<=($F$16-$E$16)/($G$16-$E$16),$E$16+SQRT(R26*($G$16-$E$16)*($F$16-$E$16)),$G$16-SQRT((1-R26)*($G$16-$E$16)*($G$16-$F$16))) -> 17.039697 | T26: =RAND() -> 0.74369819 | U26: =IF(T26<=($F$17-$E$17)/($G$17-$E$17),$E$17+SQRT(T26*($G$17-$E$17)*($F$17-$E$17)),$G$17-SQRT((1-T26)*($G$17-$E$17)*($G$17-$F$17))) -> 19.32111 | V26: =RAND() -> 0.31989191 | W26: =IF(V26<=($F$18-$E$18)/($G$18-$E$18),$E$18+SQRT(V26*($G$18-$E$18)*($F$18-$E$18)),$G$18-SQRT((1-V26)*($G$18-$E$18)*($G$18-$F$18))) -> 20.121088 | X26: =RAND() -> 0.72899043 | Y26: =IF(X26<=($F$19-$E$19)/($G$19-$E$19),$E$19+SQRT(X26*($G$19-$E$19)*($F$19-$E$19)),$G$19-SQRT((1-X26)*($G$19-$E$19)*($G$19-$F$19))) -> 24.174491 | Z26: =G26*(1+Q26/100) -> 43570.265 | AA26: =I26*(1+Q26/100)*(1+S26/100) -> 46163.263 | AB26: =K26*(1+Q26/100)*(1+S26/100)*(1+U26/100) -> 58841.814 | AC26: =M26*(1+Q26/100)*(1+S26/100)*(1+U26/100)*(1+W26/100) -> 77421.781 | AD26: =O26*(1+Q26/100)*(1+S26/100)*(1+U26/100)*(1+W26/100)*(1+Y26/100) -> 89666.702 | AE26: =ABS(C26)/$B$7 -> 14057.531 | AF26: =Z26-AE26 -> 29512.733 | AG26: =AA26-AE26 -> 32105.732 | AH26: =AB26-AE26 -> 44784.282 | AI26: =AC26-AE26 -> 63364.25 | AJ26: =AD26-AE26 -> 75609.17 | AK26: =AF26*$B$4 -> 14756.367 | AL26: =AG26*$B$4 -> 16052.866 | AM26: =AH26*$B$4 -> 22392.141 | AN26: =AI26*$B$4 -> 31682.125 | AO26: =AJ26*$B$4 -> 37804.585 | AP26: =AF26-AK26 -> 14756.367 | AQ26: =AG26-AL26 -> 16052.866 | AR26: =AH26-AM26 -> 22392.141 | AS26: =AI26-AN26 -> 31682.125 | AT26: =AJ26-AO26 -> 37804.585 | AU26: =0.2*ABS(C26)+1*ABS(E26) -> 45490.63 | AV26: =C26+E26 -> -101720.75 | AW26: =AP26+AE26 -> 28813.898 | AX26: =AQ26+AE26 -> 30110.397 | AY26: =AR26+AE26 -> 36449.672 | AZ26: =AS26+AE26 -> 45739.656 | BA26: =AT26+AE26+AU26 -> 97352.746 | BB26: =IFERROR(IRR(AV26:BA26,0.15),"n/a") -> 0.28776846 | BC26: =NPV($B$5,AW26:BA26)+AV26 -> 44622.164
A27: 3 | B27: =RAND() -> 0.57666558 | C27: =IF(B27<=($F$12-$E$12)/($G$12-$E$12),$E$12+SQRT(B27*($G$12-$E$12)*($F$12-$E$12)),$G$12-SQRT((1-B27)*($G$12-$E$12)*($G$12-$F$12))) -> -73694.132 | D27: =RAND() -> 0.82663097 | E27: =IF(D27<=($F$13-$E$13)/($G$13-$E$13),$E$13+SQRT(D27*($G$13-$E$13)*($F$13-$E$13)),$G$13-SQRT((1-D27)*($G$13-$E$13)*($G$13-$F$13))) -> -28605.922 | F27: =RAND() -> 0.66092184 | G27: =IF(F27<=($F$14-$E$14)/($G$14-$E$14),$E$14+SQRT(F27*($G$14-$E$14)*($F$14-$E$14)),$G$14-SQRT((1-F27)*($G$14-$E$14)*($G$14-$F$14))) -> 39956.821 | H27: =RAND() -> 0.069820298 | I27: =IF(H27<=($F$14-$E$14)/($G$14-$E$14),$E$14+SQRT(H27*($G$14-$E$14)*($F$14-$E$14)),$G$14-SQRT((1-H27)*($G$14-$E$14)*($G$14-$F$14))) -> 33236.208 | J27: =RAND() -> 0.85151168 | K27: =IF(J27<=($F$14-$E$14)/($G$14-$E$14),$E$14+SQRT(J27*($G$14-$E$14)*($F$14-$E$14)),$G$14-SQRT((1-J27)*($G$14-$E$14)*($G$14-$F$14))) -> 41662.842 | L27: =RAND() -> 0.68065768 | M27: =IF(L27<=($F$14-$E$14)/($G$14-$E$14),$E$14+SQRT(L27*($G$14-$E$14)*($F$14-$E$14)),$G$14-SQRT((1-L27)*($G$14-$E$14)*($G$14-$F$14))) -> 40106.057 | N27: =RAND() -> 0.13458207 | O27: =IF(N27<=($F$14-$E$14)/($G$14-$E$14),$E$14+SQRT(N27*($G$14-$E$14)*($F$14-$E$14)),$G$14-SQRT((1-N27)*($G$14-$E$14)*($G$14-$F$14))) -> 34493.029 | P27: =RAND() -> 0.043776483 | Q27: =IF(P27<=($F$15-$E$15)/($G$15-$E$15),$E$15+SQRT(P27*($G$15-$E$15)*($F$15-$E$15)),$G$15-SQRT((1-P27)*($G$15-$E$15)*($G$15-$F$15))) -> 12.887681 | R27: =RAND() -> 0.4436478 | S27: =IF(R27<=($F$16-$E$16)/($G$16-$E$16),$E$16+SQRT(R27*($G$16-$E$16)*($F$16-$E$16)),$G$16-SQRT((1-R27)*($G$16-$E$16)*($G$16-$F$16))) -> 14.825891 | T27: =RAND() -> 0.53739312 | U27: =IF(T27<=($F$17-$E$17)/($G$17-$E$17),$E$17+SQRT(T27*($G$17-$E$17)*($F$17-$E$17)),$G$17-SQRT((1-T27)*($G$17-$E$17)*($G$17-$F$17))) -> 18.400973 | V27: =RAND() -> 0.99856806 | W27: =IF(V27<=($F$18-$E$18)/($G$18-$E$18),$E$18+SQRT(V27*($G$18-$E$18)*($F$18-$E$18)),$G$18-SQRT((1-V27)*($G$18-$E$18)*($G$18-$F$18))) -> 24.776129 | X27: =RAND() -> 0.39102299 | Y27: =IF(X27<=($F$19-$E$19)/($G$19-$E$19),$E$19+SQRT(X27*($G$19-$E$19)*($F$19-$E$19)),$G$19-SQRT((1-X27)*($G$19-$E$19)*($G$19-$F$19))) -> 22.265477 | Z27: =G27*(1+Q27/100) -> 45106.328 | AA27: =I27*(1+Q27/100)*(1+S27/100) -> 43082.198 | AB27: =K27*(1+Q27/100)*(1+S27/100)*(1+U27/100) -> 63942.636 | AC27: =M27*(1+Q27/100)*(1+S27/100)*(1+U27/100)*(1+W27/100) -> 76803.874 | AD27: =O27*(1+Q27/100)*(1+S27/100)*(1+U27/100)*(1+W27/100)*(1+Y27/100) -> 80762.237 | AE27: =ABS(C27)/$B$7 -> 14738.826 | AF27: =Z27-AE27 -> 30367.502 | AG27: =AA27-AE27 -> 28343.371 | AH27: =AB27-AE27 -> 49203.81 | AI27: =AC27-AE27 -> 62065.048 | AJ27: =AD27-AE27 -> 66023.41 | AK27: =AF27*$B$4 -> 15183.751 | AL27: =AG27*$B$4 -> 14171.686 | AM27: =AH27*$B$4 -> 24601.905 | AN27: =AI27*$B$4 -> 31032.524 | AO27: =AJ27*$B$4 -> 33011.705 | AP27: =AF27-AK27 -> 15183.751 | AQ27: =AG27-AL27 -> 14171.686 | AR27: =AH27-AM27 -> 24601.905 | AS27: =AI27-AN27 -> 31032.524 | AT27: =AJ27-AO27 -> 33011.705 | AU27: =0.2*ABS(C27)+1*ABS(E27) -> 43344.749 | AV27: =C27+E27 -> -102300.05 | AW27: =AP27+AE27 -> 29922.577 | AX27: =AQ27+AE27 -> 28910.512 | AY27: =AR27+AE27 -> 39340.731 | AZ27: =AS27+AE27 -> 45771.35 | BA27: =AT27+AE27+AU27 -> 91095.28 | BB27: =IFERROR(IRR(AV27:BA27,0.15),"n/a") -> 0.28427085 | BC27: =NPV($B$5,AW27:BA27)+AV27 -> 42907.62
A28: 4 | B28: =RAND() -> 0.7681186 | C28: =IF(B28<=($F$12-$E$12)/($G$12-$E$12),$E$12+SQRT(B28*($G$12-$E$12)*($F$12-$E$12)),$G$12-SQRT((1-B28)*($G$12-$E$12)*($G$12-$F$12))) -> -69630.813 | D28: =RAND() -> 0.82665304 | E28: =IF(D28<=($F$13-$E$13)/($G$13-$E$13),$E$13+SQRT(D28*($G$13-$E$13)*($F$13-$E$13)),$G$13-SQRT((1-D28)*($G$13-$E$13)*($G$13-$F$13))) -> -28605.693 | F28: =RAND() -> 0.33245451 | G28: =IF(F28<=($F$14-$E$14)/($G$14-$E$14),$E$14+SQRT(F28*($G$14-$E$14)*($F$14-$E$14)),$G$14-SQRT((1-F28)*($G$14-$E$14)*($G$14-$F$14))) -> 37061.74 | H28: =RAND() -> 0.45654278 | I28: =IF(H28<=($F$14-$E$14)/($G$14-$E$14),$E$14+SQRT(H28*($G$14-$E$14)*($F$14-$E$14)),$G$14-SQRT((1-H28)*($G$14-$E$14)*($G$14-$F$14))) -> 38275.35 | J28: =RAND() -> 0.77792104 | K28: =IF(J28<=($F$14-$E$14)/($G$14-$E$14),$E$14+SQRT(J28*($G$14-$E$14)*($F$14-$E$14)),$G$14-SQRT((1-J28)*($G$14-$E$14)*($G$14-$F$14))) -> 40918.833 | L28: =RAND() -> 0.084176257 | M28: =IF(L28<=($F$14-$E$14)/($G$14-$E$14),$E$14+SQRT(L28*($G$14-$E$14)*($F$14-$E$14)),$G$14-SQRT((1-L28)*($G$14-$E$14)*($G$14-$F$14))) -> 33553.37 | N28: =RAND() -> 0.95851476 | O28: =IF(N28<=($F$14-$E$14)/($G$14-$E$14),$E$14+SQRT(N28*($G$14-$E$14)*($F$14-$E$14)),$G$14-SQRT((1-N28)*($G$14-$E$14)*($G$14-$F$14))) -> 43236.086 | P28: =RAND() -> 0.28458482 | Q28: =IF(P28<=($F$15-$E$15)/($G$15-$E$15),$E$15+SQRT(P28*($G$15-$E$15)*($F$15-$E$15)),$G$15-SQRT((1-P28)*($G$15-$E$15)*($G$15-$F$15))) -> 14.2633 | R28: =RAND() -> 0.8404426 | S28: =IF(R28<=($F$16-$E$16)/($G$16-$E$16),$E$16+SQRT(R28*($G$16-$E$16)*($F$16-$E$16)),$G$16-SQRT((1-R28)*($G$16-$E$16)*($G$16-$F$16))) -> 16.305293 | T28: =RAND() -> 0.62256821 | U28: =IF(T28<=($F$17-$E$17)/($G$17-$E$17),$E$17+SQRT(T28*($G$17-$E$17)*($F$17-$E$17)),$G$17-SQRT((1-T28)*($G$17-$E$17)*($G$17-$F$17))) -> 18.74914 | V28: =RAND() -> 0.93692937 | W28: =IF(V28<=($F$18-$E$18)/($G$18-$E$18),$E$18+SQRT(V28*($G$18-$E$18)*($F$18-$E$18)),$G$18-SQRT((1-V28)*($G$18-$E$18)*($G$18-$F$18))) -> 23.514244 | X28: =RAND() -> 0.026550924 | Y28: =IF(X28<=($F$19-$E$19)/($G$19-$E$19),$E$19+SQRT(X28*($G$19-$E$19)*($F$19-$E$19)),$G$19-SQRT((1-X28)*($G$19-$E$19)*($G$19-$F$19))) -> 19.846685 | Z28: =G28*(1+Q28/100) -> 42347.967 | AA28: =I28*(1+Q28/100)*(1+S28/100) -> 50865.745 | AB28: =K28*(1+Q28/100)*(1+S28/100)*(1+U28/100) -> 64574.337 | AC28: =M28*(1+Q28/100)*(1+S28/100)*(1+U28/100)*(1+W28/100) -> 65401.83 | AD28: =O28*(1+Q28/100)*(1+S28/100)*(1+U28/100)*(1+W28/100)*(1+Y28/100) -> 101001.11 | AE28: =ABS(C28)/$B$7 -> 13926.163 | AF28: =Z28-AE28 -> 28421.805 | AG28: =AA28-AE28 -> 36939.582 | AH28: =AB28-AE28 -> 50648.174 | AI28: =AC28-AE28 -> 51475.668 | AJ28: =AD28-AE28 -> 87074.949 | AK28: =AF28*$B$4 -> 14210.902 | AL28: =AG28*$B$4 -> 18469.791 | AM28: =AH28*$B$4 -> 25324.087 | AN28: =AI28*$B$4 -> 25737.834 | AO28: =AJ28*$B$4 -> 43537.474 | AP28: =AF28-AK28 -> 14210.902 | AQ28: =AG28-AL28 -> 18469.791 | AR28: =AH28-AM28 -> 25324.087 | AS28: =AI28-AN28 -> 25737.834 | AT28: =AJ28-AO28 -> 43537.474 | AU28: =0.2*ABS(C28)+1*ABS(E28) -> 42531.856 | AV28: =C28+E28 -> -98236.506 | AW28: =AP28+AE28 -> 28137.065 | AX28: =AQ28+AE28 -> 32395.954 | AY28: =AR28+AE28 -> 39250.25 | AZ28: =AS28+AE28 -> 39663.997 | BA28: =AT28+AE28+AU28 -> 99995.493 | BB28: =IFERROR(IRR(AV28:BA28,0.15),"n/a") -> 0.30545121 | BC28: =NPV($B$5,AW28:BA28)+AV28 -> 48927.63
A29: 5 | B29: =RAND() -> 0.19381824 | C29: =IF(B29<=($F$12-$E$12)/($G$12-$E$12),$E$12+SQRT(B29*($G$12-$E$12)*($F$12-$E$12)),$G$12-SQRT((1-B29)*($G$12-$E$12)*($G$12-$F$12))) -> -84749.364 | D29: =RAND() -> 0.82663934 | E29: =IF(D29<=($F$13-$E$13)/($G$13-$E$13),$E$13+SQRT(D29*($G$13-$E$13)*($F$13-$E$13)),$G$13-SQRT((1-D29)*($G$13-$E$13)*($G$13-$F$13))) -> -28605.835 | F29: =RAND() -> 0.55097777 | G29: =IF(F29<=($F$14-$E$14)/($G$14-$E$14),$E$14+SQRT(F29*($G$14-$E$14)*($F$14-$E$14)),$G$14-SQRT((1-F29)*($G$14-$E$14)*($G$14-$F$14))) -> 39091.021 | H29: =RAND() -> 0.85548194 | I29: =IF(H29<=($F$14-$E$14)/($G$14-$E$14),$E$14+SQRT(H29*($G$14-$E$14)*($F$14-$E$14)),$G$14-SQRT((1-H29)*($G$14-$E$14)*($G$14-$F$14))) -> 41707.758 | J29: =RAND() -> 0.69741289 | K29: =IF(J29<=($F$14-$E$14)/($G$14-$E$14),$E$14+SQRT(J29*($G$14-$E$14)*($F$14-$E$14)),$G$14-SQRT((1-J29)*($G$14-$E$14)*($G$14-$F$14))) -> 40236.175 | L29: =RAND() -> 0.8597159 | M29: =IF(L29<=($F$14-$E$14)/($G$14-$E$14),$E$14+SQRT(L29*($G$14-$E$14)*($F$14-$E$14)),$G$14-SQRT((1-L29)*($G$14-$E$14)*($G$14-$F$14))) -> 41756.343 | N29: =RAND() -> 0.6074277 | O29: =IF(N29<=($F$14-$E$14)/($G$14-$E$14),$E$14+SQRT(N29*($G$14-$E$14)*($F$14-$E$14)),$G$14-SQRT((1-N29)*($G$14-$E$14)*($G$14-$F$14))) -> 39545.373 | P29: =RAND() -> 0.33006981 | Q29: =IF(P29<=($F$15-$E$15)/($G$15-$E$15),$E$15+SQRT(P29*($G$15-$E$15)*($F$15-$E$15)),$G$15-SQRT((1-P29)*($G$15-$E$15)*($G$15-$F$15))) -> 14.437469 | R29: =RAND() -> 0.96284864 | S29: =IF(R29<=($F$16-$E$16)/($G$16-$E$16),$E$16+SQRT(R29*($G$16-$E$16)*($F$16-$E$16)),$G$16-SQRT((1-R29)*($G$16-$E$16)*($G$16-$F$16))) -> 17.182244 | T29: =RAND() -> 0.3155942 | U29: =IF(T29<=($F$17-$E$17)/($G$17-$E$17),$E$17+SQRT(T29*($G$17-$E$17)*($F$17-$E$17)),$G$17-SQRT((1-T29)*($G$17-$E$17)*($G$17-$F$17))) -> 17.574389 | V29: =RAND() -> 0.42512194 | W29: =IF(V29<=($F$18-$E$18)/($G$18-$E$18),$E$18+SQRT(V29*($G$18-$E$18)*($F$18-$E$18)),$G$18-SQRT((1-V29)*($G$18-$E$18)*($G$18-$F$18))) -> 20.514386 | X29: =RAND() -> 0.68209028 | Y29: =IF(X29<=($F$19-$E$19)/($G$19-$E$19),$E$19+SQRT(X29*($G$19-$E$19)*($F$19-$E$19)),$G$19-SQRT((1-X29)*($G$19-$E$19)*($G$19-$F$19))) -> 23.856677 | Z29: =G29*(1+Q29/100) -> 44734.775 | AA29: =I29*(1+Q29/100)*(1+S29/100) -> 55930.269 | AB29: =K29*(1+Q29/100)*(1+S29/100)*(1+U29/100) -> 63439.459 | AC29: =M29*(1+Q29/100)*(1+S29/100)*(1+U29/100)*(1+W29/100) -> 79342.182 | AD29: =O29*(1+Q29/100)*(1+S29/100)*(1+U29/100)*(1+W29/100)*(1+Y29/100) -> 93067.229 | AE29: =ABS(C29)/$B$7 -> 16949.873 | AF29: =Z29-AE29 -> 27784.902 | AG29: =AA29-AE29 -> 38980.396 | AH29: =AB29-AE29 -> 46489.586 | AI29: =AC29-AE29 -> 62392.309 | AJ29: =AD29-AE29 -> 76117.356 | AK29: =AF29*$B$4 -> 13892.451 | AL29: =AG29*$B$4 -> 19490.198 | AM29: =AH29*$B$4 -> 23244.793 | AN29: =AI29*$B$4 -> 31196.155 | AO29: =AJ29*$B$4 -> 38058.678 | AP29: =AF29-AK29 -> 13892.451 | AQ29: =AG29-AL29 -> 19490.198 | AR29: =AH29-AM29 -> 23244.793 | AS29: =AI29-AN29 -> 31196.155 | AT29: =AJ29-AO29 -> 38058.678 | AU29: =0.2*ABS(C29)+1*ABS(E29) -> 45555.708 | AV29: =C29+E29 -> -113355.2 | AW29: =AP29+AE29 -> 30842.324 | AX29: =AQ29+AE29 -> 36440.071 | AY29: =AR29+AE29 -> 40194.666 | AZ29: =AS29+AE29 -> 48146.028 | BA29: =AT29+AE29+AU29 -> 100564.26 | BB29: =IFERROR(IRR(AV29:BA29,0.15),"n/a") -> 0.27759994 | BC29: =NPV($B$5,AW29:BA29)+AV29 -> 44972.644
A30: 6 | B30: =RAND() -> 0.66374771 | C30: =IF(B30<=($F$12-$E$12)/($G$12-$E$12),$E$12+SQRT(B30*($G$12-$E$12)*($F$12-$E$12)),$G$12-SQRT((1-B30)*($G$12-$E$12)*($G$12-$F$12))) -> -71777.717 | D30: =RAND() -> 0.63794646 | E30: =IF(D30<=($F$13-$E$13)/($G$13-$E$13),$E$13+SQRT(D30*($G$13-$E$13)*($F$13-$E$13)),$G$13-SQRT((1-D30)*($G$13-$E$13)*($G$13-$F$13))) -> -30217.773 | F30: =RAND() -> 0.49711484 | G30: =IF(F30<=($F$14-$E$14)/($G$14-$E$14),$E$14+SQRT(F30*($G$14-$E$14)*($F$14-$E$14)),$G$14-SQRT((1-F30)*($G$14-$E$14)*($G$14-$F$14))) -> 38635.232 | H30: =RAND() -> 0.8581453 | I30: =IF(H30<=($F$14-$E$14)/($G$14-$E$14),$E$14+SQRT(H30*($G$14-$E$14)*($F$14-$E$14)),$G$14-SQRT((1-H30)*($G$14-$E$14)*($G$14-$F$14))) -> 41738.236 | J30: =RAND() -> 0.75625222 | K30: =IF(J30<=($F$14-$E$14)/($G$14-$E$14),$E$14+SQRT(J30*($G$14-$E$14)*($F$14-$E$14)),$G$14-SQRT((1-J30)*($G$14-$E$14)*($G$14-$F$14))) -> 40724.362 | L30: =RAND() -> 0.053590434 | M30: =IF(L30<=($F$14-$E$14)/($G$14-$E$14),$E$14+SQRT(L30*($G$14-$E$14)*($F$14-$E$14)),$G$14-SQRT((1-L30)*($G$14-$E$14)*($G$14-$F$14))) -> 32835.236 | N30: =RAND() -> 0.11994285 | O30: =IF(N30<=($F$14-$E$14)/($G$14-$E$14),$E$14+SQRT(N30*($G$14-$E$14)*($F$14-$E$14)),$G$14-SQRT((1-N30)*($G$14-$E$14)*($G$14-$F$14))) -> 34241.63 | P30: =RAND() -> 0.33170663 | Q30: =IF(P30<=($F$15-$E$15)/($G$15-$E$15),$E$15+SQRT(P30*($G$15-$E$15)*($F$15-$E$15)),$G$15-SQRT((1-P30)*($G$15-$E$15)*($G$15-$F$15))) -> 14.443506 | R30: =RAND() -> 0.42195999 | S30: =IF(R30<=($F$16-$E$16)/($G$16-$E$16),$E$16+SQRT(R30*($G$16-$E$16)*($F$16-$E$16)),$G$16-SQRT((1-R30)*($G$16-$E$16)*($G$16-$F$16))) -> 14.755954 | T30: =RAND() -> 0.28228413 | U30: =IF(T30<=($F$17-$E$17)/($G$17-$E$17),$E$17+SQRT(T30*($G$17-$E$17)*($F$17-$E$17)),$G$17-SQRT((1-T30)*($G$17-$E$17)*($G$17-$F$17))) -> 17.434742 | V30: =RAND() -> 0.70398216 | W30: =IF(V30<=($F$18-$E$18)/($G$18-$E$18),$E$18+SQRT(V30*($G$18-$E$18)*($F$18-$E$18)),$G$18-SQRT((1-V30)*($G$18-$E$18)*($G$18-$F$18))) -> 21.781208 | X30: =RAND() -> 0.90041359 | Y30: =IF(X30<=($F$19-$E$19)/($G$19-$E$19),$E$19+SQRT(X30*($G$19-$E$19)*($F$19-$E$19)),$G$19-SQRT((1-X30)*($G$19-$E$19)*($G$19-$F$19))) -> 25.68102 | Z30: =G30*(1+Q30/100) -> 44215.514 | AA30: =I30*(1+Q30/100)*(1+S30/100) -> 54815.133 | AB30: =K30*(1+Q30/100)*(1+S30/100)*(1+U30/100) -> 62808.332 | AC30: =M30*(1+Q30/100)*(1+S30/100)*(1+U30/100)*(1+W30/100) -> 61671.342 | AD30: =O30*(1+Q30/100)*(1+S30/100)*(1+U30/100)*(1+W30/100)*(1+Y30/100) -> 80829.033 | AE30: =ABS(C30)/$B$7 -> 14355.543 | AF30: =Z30-AE30 -> 29859.97 | AG30: =AA30-AE30 -> 40459.59 | AH30: =AB30-AE30 -> 48452.789 | AI30: =AC30-AE30 -> 47315.798 | AJ30: =AD30-AE30 -> 66473.49 | AK30: =AF30*$B$4 -> 14929.985 | AL30: =AG30*$B$4 -> 20229.795 | AM30: =AH30*$B$4 -> 24226.394 | AN30: =AI30*$B$4 -> 23657.899 | AO30: =AJ30*$B$4 -> 33236.745 | AP30: =AF30-AK30 -> 14929.985 | AQ30: =AG30-AL30 -> 20229.795 | AR30: =AH30-AM30 -> 24226.394 | AS30: =AI30-AN30 -> 23657.899 | AT30: =AJ30-AO30 -> 33236.745 | AU30: =0.2*ABS(C30)+1*ABS(E30) -> 44573.316 | AV30: =C30+E30 -> -101995.49 | AW30: =AP30+AE30 -> 29285.528 | AX30: =AQ30+AE30 -> 34585.338 | AY30: =AR30+AE30 -> 38581.938 | AZ30: =AS30+AE30 -> 38013.443 | BA30: =AT30+AE30+AU30 -> 92165.605 | BB30: =IFERROR(IRR(AV30:BA30,0.15),"n/a") -> 0.28571923 | BC30: =NPV($B$5,AW30:BA30)+AV30 -> 42546.825
A31: 7 | B31: =RAND() -> 0.51212291 | C31: =IF(B31<=($F$12-$E$12)/($G$12-$E$12),$E$12+SQRT(B31*($G$12-$E$12)*($F$12-$E$12)),$G$12-SQRT((1-B31)*($G$12-$E$12)*($G$12-$F$12))) -> -75209.932 | D31: =RAND() -> 0.018736182 | E31: =IF(D31<=($F$13-$E$13)/($G$13-$E$13),$E$13+SQRT(D31*($G$13-$E$13)*($F$13-$E$13)),$G$13-SQRT((1-D31)*($G$13-$E$13)*($G$13-$F$13))) -> -38323.567 | F31: =RAND() -> 0.61144922 | G31: =IF(F31<=($F$14-$E$14)/($G$14-$E$14),$E$14+SQRT(F31*($G$14-$E$14)*($F$14-$E$14)),$G$14-SQRT((1-F31)*($G$14-$E$14)*($G$14-$F$14))) -> 39576.919 | H31: =RAND() -> 0.23195874 | I31: =IF(H31<=($F$14-$E$14)/($G$14-$E$14),$E$14+SQRT(H31*($G$14-$E$14)*($F$14-$E$14)),$G$14-SQRT((1-H31)*($G$14-$E$14)*($G$14-$F$14))) -> 35898.628 | J31: =RAND() -> 0.45270296 | K31: =IF(J31<=($F$14-$E$14)/($G$14-$E$14),$E$14+SQRT(J31*($G$14-$E$14)*($F$14-$E$14)),$G$14-SQRT((1-J31)*($G$14-$E$14)*($G$14-$F$14))) -> 38240.476 | L31: =RAND() -> 0.010492232 | M31: =IF(L31<=($F$14-$E$14)/($G$14-$E$14),$E$14+SQRT(L31*($G$14-$E$14)*($F$14-$E$14)),$G$14-SQRT((1-L31)*($G$14-$E$14)*($G$14-$F$14))) -> 31254.526 | N31: =RAND() -> 0.66779112 | O31: =IF(N31<=($F$14-$E$14)/($G$14-$E$14),$E$14+SQRT(N31*($G$14-$E$14)*($F$14-$E$14)),$G$14-SQRT((1-N31)*($G$14-$E$14)*($G$14-$F$14))) -> 40008.44 | P31: =RAND() -> 0.55017989 | Q31: =IF(P31<=($F$15-$E$15)/($G$15-$E$15),$E$15+SQRT(P31*($G$15-$E$15)*($F$15-$E$15)),$G$15-SQRT((1-P31)*($G$15-$E$15)*($G$15-$F$15))) -> 15.154519 | R31: =RAND() -> 0.045019567 | S31: =IF(R31<=($F$16-$E$16)/($G$16-$E$16),$E$16+SQRT(R31*($G$16-$E$16)*($F$16-$E$16)),$G$16-SQRT((1-R31)*($G$16-$E$16)*($G$16-$F$16))) -> 12.900196 | T31: =RAND() -> 0.067817709 | U31: =IF(T31<=($F$17-$E$17)/($G$17-$E$17),$E$17+SQRT(T31*($G$17-$E$17)*($F$17-$E$17)),$G$17-SQRT((1-T31)*($G$17-$E$17)*($G$17-$F$17))) -> 16.193387 | V31: =RAND() -> 0.81916137 | W31: =IF(V31<=($F$18-$E$18)/($G$18-$E$18),$E$18+SQRT(V31*($G$18-$E$18)*($F$18-$E$18)),$G$18-SQRT((1-V31)*($G$18-$E$18)*($G$18-$F$18))) -> 22.48418 | X31: =RAND() -> 0.0045708448 | Y31: =IF(X31<=($F$19-$E$19)/($G$19-$E$19),$E$19+SQRT(X31*($G$19-$E$19)*($F$19-$E$19)),$G$19-SQRT((1-X31)*($G$19-$E$19)*($G$19-$F$19))) -> 19.351302 | Z31: =G31*(1+Q31/100) -> 45574.611 | AA31: =I31*(1+Q31/100)*(1+S31/100) -> 46671.69 | AB31: =K31*(1+Q31/100)*(1+S31/100)*(1+U31/100) -> 57767.075 | AC31: =M31*(1+Q31/100)*(1+S31/100)*(1+U31/100)*(1+W31/100) -> 57829.575 | AD31: =O31*(1+Q31/100)*(1+S31/100)*(1+U31/100)*(1+W31/100)*(1+Y31/100) -> 88351.895 | AE31: =ABS(C31)/$B$7 -> 15041.986 | AF31: =Z31-AE31 -> 30532.625 | AG31: =AA31-AE31 -> 31629.704 | AH31: =AB31-AE31 -> 42725.089 | AI31: =AC31-AE31 -> 42787.589 | AJ31: =AD31-AE31 -> 73309.909 | AK31: =AF31*$B$4 -> 15266.312 | AL31: =AG31*$B$4 -> 15814.852 | AM31: =AH31*$B$4 -> 21362.544 | AN31: =AI31*$B$4 -> 21393.794 | AO31: =AJ31*$B$4 -> 36654.955 | AP31: =AF31-AK31 -> 15266.312 | AQ31: =AG31-AL31 -> 15814.852 | AR31: =AH31-AM31 -> 21362.544 | AS31: =AI31-AN31 -> 21393.794 | AT31: =AJ31-AO31 -> 36654.955 | AU31: =0.2*ABS(C31)+1*ABS(E31) -> 53365.553 | AV31: =C31+E31 -> -113533.5 | AW31: =AP31+AE31 -> 30308.299 | AX31: =AQ31+AE31 -> 30856.838 | AY31: =AR31+AE31 -> 36404.531 | AZ31: =AS31+AE31 -> 36435.781 | BA31: =AT31+AE31+AU31 -> 105062.49 | BB31: =IFERROR(IRR(AV31:BA31,0.15),"n/a") -> 0.24455219 | BC31: =NPV($B$5,AW31:BA31)+AV31 -> 33157.22
A32: 8 | B32: =RAND() -> 0.17427903 | C32: =IF(B32<=($F$12-$E$12)/($G$12-$E$12),$E$12+SQRT(B32*($G$12-$E$12)*($F$12-$E$12)),$G$12-SQRT((1-B32)*($G$12-$E$12)*($G$12-$F$12))) -> -85538.505 | D32: =RAND() -> 0.02859565 | E32: =IF(D32<=($F$13-$E$13)/($G$13-$E$13),$E$13+SQRT(D32*($G$13-$E$13)*($F$13-$E$13)),$G$13-SQRT((1-D32)*($G$13-$E$13)*($G$13-$F$13))) -> -37928.926 | F32: =RAND() -> 0.066689029 | G32: =IF(F32<=($F$14-$E$14)/($G$14-$E$14),$E$14+SQRT(F32*($G$14-$E$14)*($F$14-$E$14)),$G$14-SQRT((1-F32)*($G$14-$E$14)*($G$14-$F$14))) -> 33162.808 | H32: =RAND() -> 0.74357846 | I32: =IF(H32<=($F$14-$E$14)/($G$14-$E$14),$E$14+SQRT(H32*($G$14-$E$14)*($F$14-$E$14)),$G$14-SQRT((1-H32)*($G$14-$E$14)*($G$14-$F$14))) -> 40614.613 | J32: =RAND() -> 0.84819713 | K32: =IF(J32<=($F$14-$E$14)/($G$14-$E$14),$E$14+SQRT(J32*($G$14-$E$14)*($F$14-$E$14)),$G$14-SQRT((1-J32)*($G$14-$E$14)*($G$14-$F$14))) -> 41625.801 | L32: =RAND() -> 0.33018622 | M32: =IF(L32<=($F$14-$E$14)/($G$14-$E$14),$E$14+SQRT(L32*($G$14-$E$14)*($F$14-$E$14)),$G$14-SQRT((1-L32)*($G$14-$E$14)*($G$14-$F$14))) -> 37037.608 | N32: =RAND() -> 0.34023402 | O32: =IF(N32<=($F$14-$E$14)/($G$14-$E$14),$E$14+SQRT(N32*($G$14-$E$14)*($F$14-$E$14)),$G$14-SQRT((1-N32)*($G$14-$E$14)*($G$14-$F$14))) -> 37143.886 | P32: =RAND() -> 0.15140253 | Q32: =IF(P32<=($F$15-$E$15)/($G$15-$E$15),$E$15+SQRT(P32*($G$15-$E$15)*($F$15-$E$15)),$G$15-SQRT((1-P32)*($G$15-$E$15)*($G$15-$F$15))) -> 13.650832 | R32: =RAND() -> 0.39101179 | S32: =IF(R32<=($F$16-$E$16)/($G$16-$E$16),$E$16+SQRT(R32*($G$16-$E$16)*($F$16-$E$16)),$G$16-SQRT((1-R32)*($G$16-$E$16)*($G$16-$F$16))) -> 14.652963 | T32: =RAND() -> 0.094103501 | U32: =IF(T32<=($F$17-$E$17)/($G$17-$E$17),$E$17+SQRT(T32*($G$17-$E$17)*($F$17-$E$17)),$G$17-SQRT((1-T32)*($G$17-$E$17)*($G$17-$F$17))) -> 16.405764 | V32: =RAND() -> 0.43755949 | W32: =IF(V32<=($F$18-$E$18)/($G$18-$E$18),$E$18+SQRT(V32*($G$18-$E$18)*($F$18-$E$18)),$G$18-SQRT((1-V32)*($G$18-$E$18)*($G$18-$F$18))) -> 20.563175 | X32: =RAND() -> 0.52333982 | Y32: =IF(X32<=($F$19-$E$19)/($G$19-$E$19),$E$19+SQRT(X32*($G$19-$E$19)*($F$19-$E$19)),$G$19-SQRT((1-X32)*($G$19-$E$19)*($G$19-$F$19))) -> 22.926574 | Z32: =G32*(1+Q32/100) -> 37689.807 | AA32: =I32*(1+Q32/100)*(1+S32/100) -> 52922.485 | AB32: =K32*(1+Q32/100)*(1+S32/100)*(1+U32/100) -> 63138.607 | AC32: =M32*(1+Q32/100)*(1+S32/100)*(1+U32/100)*(1+W32/100) -> 67731.392 | AD32: =O32*(1+Q32/100)*(1+S32/100)*(1+U32/100)*(1+W32/100)*(1+Y32/100) -> 83498.789 | AE32: =ABS(C32)/$B$7 -> 17107.701 | AF32: =Z32-AE32 -> 20582.106 | AG32: =AA32-AE32 -> 35814.784 | AH32: =AB32-AE32 -> 46030.906 | AI32: =AC32-AE32 -> 50623.691 | AJ32: =AD32-AE32 -> 66391.088 | AK32: =AF32*$B$4 -> 10291.053 | AL32: =AG32*$B$4 -> 17907.392 | AM32: =AH32*$B$4 -> 23015.453 | AN32: =AI32*$B$4 -> 25311.845 | AO32: =AJ32*$B$4 -> 33195.544 | AP32: =AF32-AK32 -> 10291.053 | AQ32: =AG32-AL32 -> 17907.392 | AR32: =AH32-AM32 -> 23015.453 | AS32: =AI32-AN32 -> 25311.845 | AT32: =AJ32-AO32 -> 33195.544 | AU32: =0.2*ABS(C32)+1*ABS(E32) -> 55036.627 | AV32: =C32+E32 -> -123467.43 | AW32: =AP32+AE32 -> 27398.754 | AX32: =AQ32+AE32 -> 35015.093 | AY32: =AR32+AE32 -> 40123.154 | AZ32: =AS32+AE32 -> 42419.546 | BA32: =AT32+AE32+AU32 -> 105339.87 | BB32: =IFERROR(IRR(AV32:BA32,0.15),"n/a") -> 0.22833334 | BC32: =NPV($B$5,AW32:BA32)+AV32 -> 29841.685
A33: 9 | B33: =RAND() -> 0.72044843 | C33: =IF(B33<=($F$12-$E$12)/($G$12-$E$12),$E$12+SQRT(B33*($G$12-$E$12)*($F$12-$E$12)),$G$12-SQRT((1-B33)*($G$12-$E$12)*($G$12-$F$12))) -> -70596.971 | D33: =RAND() -> 0.72022988 | E33: =IF(D33<=($F$13-$E$13)/($G$13-$E$13),$E$13+SQRT(D33*($G$13-$E$13)*($F$13-$E$13)),$G$13-SQRT((1-D33)*($G$13-$E$13)*($G$13-$F$13))) -> -29580.694 | F33: =RAND() -> 0.88312814 | G33: =IF(F33<=($F$14-$E$14)/($G$14-$E$14),$E$14+SQRT(F33*($G$14-$E$14)*($F$14-$E$14)),$G$14-SQRT((1-F33)*($G$14-$E$14)*($G$14-$F$14))) -> 42039.36 | H33: =RAND() -> 0.63794847 | I33: =IF(H33<=($F$14-$E$14)/($G$14-$E$14),$E$14+SQRT(H33*($G$14-$E$14)*($F$14-$E$14)),$G$14-SQRT((1-H33)*($G$14-$E$14)*($G$14-$F$14))) -> 39782.243 | J33: =RAND() -> 0.028614554 | K33: =IF(J33<=($F$14-$E$14)/($G$14-$E$14),$E$14+SQRT(J33*($G$14-$E$14)*($F$14-$E$14)),$G$14-SQRT((1-J33)*($G$14-$E$14)*($G$14-$F$14))) -> 32071.758 | L33: =RAND() -> 0.95338697 | M33: =IF(L33<=($F$14-$E$14)/($G$14-$E$14),$E$14+SQRT(L33*($G$14-$E$14)*($F$14-$E$14)),$G$14-SQRT((1-L33)*($G$14-$E$14)*($G$14-$F$14))) -> 43130.247 | N33: =RAND() -> 0.53321793 | O33: =IF(N33<=($F$14-$E$14)/($G$14-$E$14),$E$14+SQRT(N33*($G$14-$E$14)*($F$14-$E$14)),$G$14-SQRT((1-N33)*($G$14-$E$14)*($G$14-$F$14))) -> 38943.304 | P33: =RAND() -> 0.32516844 | Q33: =IF(P33<=($F$15-$E$15)/($G$15-$E$15),$E$15+SQRT(P33*($G$15-$E$15)*($F$15-$E$15)),$G$15-SQRT((1-P33)*($G$15-$E$15)*($G$15-$F$15))) -> 14.419304 | R33: =RAND() -> 0.78168539 | S33: =IF(R33<=($F$16-$E$16)/($G$16-$E$16),$E$16+SQRT(R33*($G$16-$E$16)*($F$16-$E$16)),$G$16-SQRT((1-R33)*($G$16-$E$16)*($G$16-$F$16))) -> 16.017662 | T33: =RAND() -> 0.02392253 | U33: =IF(T33<=($F$17-$E$17)/($G$17-$E$17),$E$17+SQRT(T33*($G$17-$E$17)*($F$17-$E$17)),$G$17-SQRT((1-T33)*($G$17-$E$17)*($G$17-$F$17))) -> 15.708783 | V33: =RAND() -> 0.18269094 | W33: =IF(V33<=($F$18-$E$18)/($G$18-$E$18),$E$18+SQRT(V33*($G$18-$E$18)*($F$18-$E$18)),$G$18-SQRT((1-V33)*($G$18-$E$18)*($G$18-$F$18))) -> 19.599273 | X33: =RAND() -> 0.25411311 | Y33: =IF(X33<=($F$19-$E$19)/($G$19-$E$19),$E$19+SQRT(X33*($G$19-$E$19)*($F$19-$E$19)),$G$19-SQRT((1-X33)*($G$19-$E$19)*($G$19-$F$19))) -> 21.619361 | Z33: =G33*(1+Q33/100) -> 48101.143 | AA33: =I33*(1+Q33/100)*(1+S33/100) -> 52809.575 | AB33: =K33*(1+Q33/100)*(1+S33/100)*(1+U33/100) -> 49262.053 | AC33: =M33*(1+Q33/100)*(1+S33/100)*(1+U33/100)*(1+W33/100) -> 79231.927 | AD33: =O33*(1+Q33/100)*(1+S33/100)*(1+U33/100)*(1+W33/100)*(1+Y33/100) -> 87006.919 | AE33: =ABS(C33)/$B$7 -> 14119.394 | AF33: =Z33-AE33 -> 33981.749 | AG33: =AA33-AE33 -> 38690.181 | AH33: =AB33-AE33 -> 35142.659 | AI33: =AC33-AE33 -> 65112.533 | AJ33: =AD33-AE33 -> 72887.525 | AK33: =AF33*$B$4 -> 16990.874 | AL33: =AG33*$B$4 -> 19345.09 | AM33: =AH33*$B$4 -> 17571.33 | AN33: =AI33*$B$4 -> 32556.266 | AO33: =AJ33*$B$4 -> 36443.763 | AP33: =AF33-AK33 -> 16990.874 | AQ33: =AG33-AL33 -> 19345.09 | AR33: =AH33-AM33 -> 17571.33 | AS33: =AI33-AN33 -> 32556.266 | AT33: =AJ33-AO33 -> 36443.763 | AU33: =0.2*ABS(C33)+1*ABS(E33) -> 43700.088 | AV33: =C33+E33 -> -100177.67 | AW33: =AP33+AE33 -> 31110.269 | AX33: =AQ33+AE33 -> 33464.485 | AY33: =AR33+AE33 -> 31690.724 | AZ33: =AS33+AE33 -> 46675.661 | BA33: =AT33+AE33+AU33 -> 94263.245 | BB33: =IFERROR(IRR(AV33:BA33,0.15),"n/a") -> 0.29874082 | BC33: =NPV($B$5,AW33:BA33)+AV33 -> 46568.319
A34: 10 | B34: =RAND() -> 0.62062305 | C34: =IF(B34<=($F$12-$E$12)/($G$12-$E$12),$E$12+SQRT(B34*($G$12-$E$12)*($F$12-$E$12)),$G$12-SQRT((1-B34)*($G$12-$E$12)*($G$12-$F$12))) -> -72709.935 | D34: =RAND() -> 0.97826352 | E34: =IF(D34<=($F$13-$E$13)/($G$13-$E$13),$E$13+SQRT(D34*($G$13-$E$13)*($F$13-$E$13)),$G$13-SQRT((1-D34)*($G$13-$E$13)*($G$13-$F$13))) -> -26276.807 | F34: =RAND() -> 0.10269749 | G34: =IF(F34<=($F$14-$E$14)/($G$14-$E$14),$E$14+SQRT(F34*($G$14-$E$14)*($F$14-$E$14)),$G$14-SQRT((1-F34)*($G$14-$E$14)*($G$14-$F$14))) -> 33924.872 | H34: =RAND() -> 0.53101758 | I34: =IF(H34<=($F$14-$E$14)/($G$14-$E$14),$E$14+SQRT(H34*($G$14-$E$14)*($F$14-$E$14)),$G$14-SQRT((1-H34)*($G$14-$E$14)*($G$14-$F$14))) -> 38924.833 | J34: =RAND() -> 0.78504987 | K34: =IF(J34<=($F$14-$E$14)/($G$14-$E$14),$E$14+SQRT(J34*($G$14-$E$14)*($F$14-$E$14)),$G$14-SQRT((1-J34)*($G$14-$E$14)*($G$14-$F$14))) -> 40984.871 | L34: =RAND() -> 0.033574154 | M34: =IF(L34<=($F$14-$E$14)/($G$14-$E$14),$E$14+SQRT(L34*($G$14-$E$14)*($F$14-$E$14)),$G$14-SQRT((1-L34)*($G$14-$E$14)*($G$14-$F$14))) -> 32244.131 | N34: =RAND() -> 0.44027591 | O34: =IF(N34<=($F$14-$E$14)/($G$14-$E$14),$E$14+SQRT(N34*($G$14-$E$14)*($F$14-$E$14)),$G$14-SQRT((1-N34)*($G$14-$E$14)*($G$14-$F$14))) -> 38126.585 | P34: =RAND() -> 0.19837427 | Q34: =IF(P34<=($F$15-$E$15)/($G$15-$E$15),$E$15+SQRT(P34*($G$15-$E$15)*($F$15-$E$15)),$G$15-SQRT((1-P34)*($G$15-$E$15)*($G$15-$F$15))) -> 13.889639 | R34: =RAND() -> 0.90957486 | S34: =IF(R34<=($F$16-$E$16)/($G$16-$E$16),$E$16+SQRT(R34*($G$16-$E$16)*($F$16-$E$16)),$G$16-SQRT((1-R34)*($G$16-$E$16)*($G$16-$F$16))) -> 16.724205 | T34: =RAND() -> 0.73095059 | U34: =IF(T34<=($F$17-$E$17)/($G$17-$E$17),$E$17+SQRT(T34*($G$17-$E$17)*($F$17-$E$17)),$G$17-SQRT((1-T34)*($G$17-$E$17)*($G$17-$F$17))) -> 19.255299 | V34: =RAND() -> 0.49387781 | W34: =IF(V34<=($F$18-$E$18)/($G$18-$E$18),$E$18+SQRT(V34*($G$18-$E$18)*($F$18-$E$18)),$G$18-SQRT((1-V34)*($G$18-$E$18)*($G$18-$F$18))) -> 20.791167 | X34: =RAND() -> 0.029949303 | Y34: =IF(X34<=($F$19-$E$19)/($G$19-$E$19),$E$19+SQRT(X34*($G$19-$E$19)*($F$19-$E$19)),$G$19-SQRT((1-X34)*($G$19-$E$19)*($G$19-$F$19))) -> 19.899239 | Z34: =G34*(1+Q34/100) -> 38636.915 | AA34: =I34*(1+Q34/100)*(1+S34/100) -> 51745.418 | AB34: =K34*(1+Q34/100)*(1+S34/100)*(1+U34/100) -> 64975.017 | AC34: =M34*(1+Q34/100)*(1+S34/100)*(1+U34/100)*(1+W34/100) -> 61745.979 | AD34: =O34*(1+Q34/100)*(1+S34/100)*(1+U34/100)*(1+W34/100)*(1+Y34/100) -> 87539.153 | AE34: =ABS(C34)/$B$7 -> 14541.987 | AF34: =Z34-AE34 -> 24094.928 | AG34: =AA34-AE34 -> 37203.431 | AH34: =AB34-AE34 -> 50433.03 | AI34: =AC34-AE34 -> 47203.992 | AJ34: =AD34-AE34 -> 72997.166 | AK34: =AF34*$B$4 -> 12047.464 | AL34: =AG34*$B$4 -> 18601.715 | AM34: =AH34*$B$4 -> 25216.515 | AN34: =AI34*$B$4 -> 23601.996 | AO34: =AJ34*$B$4 -> 36498.583 | AP34: =AF34-AK34 -> 12047.464 | AQ34: =AG34-AL34 -> 18601.715 | AR34: =AH34-AM34 -> 25216.515 | AS34: =AI34-AN34 -> 23601.996 | AT34: =AJ34-AO34 -> 36498.583 | AU34: =0.2*ABS(C34)+1*ABS(E34) -> 40818.794 | AV34: =C34+E34 -> -98986.742 | AW34: =AP34+AE34 -> 26589.451 | AX34: =AQ34+AE34 -> 33143.702 | AY34: =AR34+AE34 -> 39758.502 | AZ34: =AS34+AE34 -> 38143.983 | BA34: =AT34+AE34+AU34 -> 91859.364 | BB34: =IFERROR(IRR(AV34:BA34,0.15),"n/a") -> 0.28807629 | BC34: =NPV($B$5,AW34:BA34)+AV34 -> 42817.066
A35: 11 | B35: =RAND() -> 0.80797898 | C35: =IF(B35<=($F$12-$E$12)/($G$12-$E$12),$E$12+SQRT(B35*($G$12-$E$12)*($F$12-$E$12)),$G$12-SQRT((1-B35)*($G$12-$E$12)*($G$12-$F$12))) -> -68764.041 | D35: =RAND() -> 0.34923049 | E35: =IF(D35<=($F$13-$E$13)/($G$13-$E$13),$E$13+SQRT(D35*($G$13-$E$13)*($F$13-$E$13)),$G$13-SQRT((1-D35)*($G$13-$E$13)*($G$13-$F$13))) -> -32762.281 | F35: =RAND() -> 0.012939758 | G35: =IF(F35<=($F$14-$E$14)/($G$14-$E$14),$E$14+SQRT(F35*($G$14-$E$14)*($F$14-$E$14)),$G$14-SQRT((1-F35)*($G$14-$E$14)*($G$14-$F$14))) -> 31393.185 | H35: =RAND() -> 0.18271697 | I35: =IF(H35<=($F$14-$E$14)/($G$14-$E$14),$E$14+SQRT(H35*($G$14-$E$14)*($F$14-$E$14)),$G$14-SQRT((1-H35)*($G$14-$E$14)*($G$14-$F$14))) -> 35235.222 | J35: =RAND() -> 0.91758734 | K35: =IF(J35<=($F$14-$E$14)/($G$14-$E$14),$E$14+SQRT(J35*($G$14-$E$14)*($F$14-$E$14)),$G$14-SQRT((1-J35)*($G$14-$E$14)*($G$14-$F$14))) -> 42513.848 | L35: =RAND() -> 0.44609021 | M35: =IF(L35<=($F$14-$E$14)/($G$14-$E$14),$E$14+SQRT(L35*($G$14-$E$14)*($F$14-$E$14)),$G$14-SQRT((1-L35)*($G$14-$E$14)*($G$14-$F$14))) -> 38180.069 | N35: =RAND() -> 0.87090274 | O35: =IF(N35<=($F$14-$E$14)/($G$14-$E$14),$E$14+SQRT(N35*($G$14-$E$14)*($F$14-$E$14)),$G$14-SQRT((1-N35)*($G$14-$E$14)*($G$14-$F$14))) -> 41888.361 | P35: =RAND() -> 0.58066393 | Q35: =IF(P35<=($F$15-$E$15)/($G$15-$E$15),$E$15+SQRT(P35*($G$15-$E$15)*($F$15-$E$15)),$G$15-SQRT((1-P35)*($G$15-$E$15)*($G$15-$F$15))) -> 15.252629 | R35: =RAND() -> 0.73127958 | S35: =IF(R35<=($F$16-$E$16)/($G$16-$E$16),$E$16+SQRT(R35*($G$16-$E$16)*($F$16-$E$16)),$G$16-SQRT((1-R35)*($G$16-$E$16)*($G$16-$F$16))) -> 15.800689 | T35: =RAND() -> 0.89648235 | U35: =IF(T35<=($F$17-$E$17)/($G$17-$E$17),$E$17+SQRT(T35*($G$17-$E$17)*($F$17-$E$17)),$G$17-SQRT((1-T35)*($G$17-$E$17)*($G$17-$F$17))) -> 20.297504 | V35: =RAND() -> 0.86914543 | W35: =IF(V35<=($F$18-$E$18)/($G$18-$E$18),$E$18+SQRT(V35*($G$18-$E$18)*($F$18-$E$18)),$G$18-SQRT((1-V35)*($G$18-$E$18)*($G$18-$F$18))) -> 22.859928 | X35: =RAND() -> 0.44205125 | Y35: =IF(X35<=($F$19-$E$19)/($G$19-$E$19),$E$19+SQRT(X35*($G$19-$E$19)*($F$19-$E$19)),$G$19-SQRT((1-X35)*($G$19-$E$19)*($G$19-$F$19))) -> 22.51099 | Z35: =G35*(1+Q35/100) -> 36181.471 | AA35: =I35*(1+Q35/100)*(1+S35/100) -> 47026.103 | AB35: =K35*(1+Q35/100)*(1+S35/100)*(1+U35/100) -> 68257.286 | AC35: =M35*(1+Q35/100)*(1+S35/100)*(1+U35/100)*(1+W35/100) -> 75312.24 | AD35: =O35*(1+Q35/100)*(1+S35/100)*(1+U35/100)*(1+W35/100)*(1+Y35/100) -> 101227.21 | AE35: =ABS(C35)/$B$7 -> 13752.808 | AF35: =Z35-AE35 -> 22428.663 | AG35: =AA35-AE35 -> 33273.295 | AH35: =AB35-AE35 -> 54504.478 | AI35: =AC35-AE35 -> 61559.432 | AJ35: =AD35-AE35 -> 87474.404 | AK35: =AF35*$B$4 -> 11214.331 | AL35: =AG35*$B$4 -> 16636.647 | AM35: =AH35*$B$4 -> 27252.239 | AN35: =AI35*$B$4 -> 30779.716 | AO35: =AJ35*$B$4 -> 43737.202 | AP35: =AF35-AK35 -> 11214.331 | AQ35: =AG35-AL35 -> 16636.647 | AR35: =AH35-AM35 -> 27252.239 | AS35: =AI35-AN35 -> 30779.716 | AT35: =AJ35-AO35 -> 43737.202 | AU35: =0.2*ABS(C35)+1*ABS(E35) -> 46515.089 | AV35: =C35+E35 -> -101526.32 | AW35: =AP35+AE35 -> 24967.139 | AX35: =AQ35+AE35 -> 30389.456 | AY35: =AR35+AE35 -> 41005.047 | AZ35: =AS35+AE35 -> 44532.524 | BA35: =AT35+AE35+AU35 -> 104005.1 | BB35: =IFERROR(IRR(AV35:BA35,0.15),"n/a") -> 0.29154918 | BC35: =NPV($B$5,AW35:BA35)+AV35 -> 47295.044
A36: 12 | B36: =RAND() -> 0.95701985 | C36: =IF(B36<=($F$12-$E$12)/($G$12-$E$12),$E$12+SQRT(B36*($G$12-$E$12)*($F$12-$E$12)),$G$12-SQRT((1-B36)*($G$12-$E$12)*($G$12-$F$12))) -> -64146.331 | D36: =RAND() -> 0.5972987 | E36: =IF(D36<=($F$13-$E$13)/($G$13-$E$13),$E$13+SQRT(D36*($G$13-$E$13)*($F$13-$E$13)),$G$13-SQRT((1-D36)*($G$13-$E$13)*($G$13-$F$13))) -> -30534.547 | F36: =RAND() -> 0.7688166 | G36: =IF(F36<=($F$14-$E$14)/($G$14-$E$14),$E$14+SQRT(F36*($G$14-$E$14)*($F$14-$E$14)),$G$14-SQRT((1-F36)*($G$14-$E$14)*($G$14-$F$14))) -> 40836.017 | H36: =RAND() -> 0.15144827 | I36: =IF(H36<=($F$14-$E$14)/($G$14-$E$14),$E$14+SQRT(H36*($G$14-$E$14)*($F$14-$E$14)),$G$14-SQRT((1-H36)*($G$14-$E$14)*($G$14-$F$14))) -> 34766.261 | J36: =RAND() -> 0.096934961 | K36: =IF(J36<=($F$14-$E$14)/($G$14-$E$14),$E$14+SQRT(J36*($G$14-$E$14)*($F$14-$E$14)),$G$14-SQRT((1-J36)*($G$14-$E$14)*($G$14-$F$14))) -> 33813.167 | L36: =RAND() -> 0.66153866 | M36: =IF(L36<=($F$14-$E$14)/($G$14-$E$14),$E$14+SQRT(L36*($G$14-$E$14)*($F$14-$E$14)),$G$14-SQRT((1-L36)*($G$14-$E$14)*($G$14-$F$14))) -> 39961.466 | N36: =RAND() -> 0.28976594 | O36: =IF(N36<=($F$14-$E$14)/($G$14-$E$14),$E$14+SQRT(N36*($G$14-$E$14)*($F$14-$E$14)),$G$14-SQRT((1-N36)*($G$14-$E$14)*($G$14-$F$14))) -> 36592.791 | P36: =RAND() -> 0.53040766 | Q36: =IF(P36<=($F$15-$E$15)/($G$15-$E$15),$E$15+SQRT(P36*($G$15-$E$15)*($F$15-$E$15)),$G$15-SQRT((1-P36)*($G$15-$E$15)*($G$15-$F$15))) -> 15.092654 | R36: =RAND() -> 0.81349215 | S36: =IF(R36<=($F$16-$E$16)/($G$16-$E$16),$E$16+SQRT(R36*($G$16-$E$16)*($F$16-$E$16)),$G$16-SQRT((1-R36)*($G$16-$E$16)*($G$16-$F$16))) -> 16.16775 | T36: =RAND() -> 0.40690281 | U36: =IF(T36<=($F$17-$E$17)/($G$17-$E$17),$E$17+SQRT(T36*($G$17-$E$17)*($F$17-$E$17)),$G$17-SQRT((1-T36)*($G$17-$E$17)*($G$17-$F$17))) -> 17.923176 | V36: =RAND() -> 0.23155294 | W36: =IF(V36<=($F$18-$E$18)/($G$18-$E$18),$E$18+SQRT(V36*($G$18-$E$18)*($F$18-$E$18)),$G$18-SQRT((1-V36)*($G$18-$E$18)*($G$18-$F$18))) -> 19.800484 | X36: =RAND() -> 0.37895831 | Y36: =IF(X36<=($F$19-$E$19)/($G$19-$E$19),$E$19+SQRT(X36*($G$19-$E$19)*($F$19-$E$19)),$G$19-SQRT((1-X36)*($G$19-$E$19)*($G$19-$F$19))) -> 22.208951 | Z36: =G36*(1+Q36/100) -> 46999.256 | AA36: =I36*(1+Q36/100)*(1+S36/100) -> 46482.68 | AB36: =K36*(1+Q36/100)*(1+S36/100)*(1+U36/100) -> 53311.168 | AC36: =M36*(1+Q36/100)*(1+S36/100)*(1+U36/100)*(1+W36/100) -> 75480.076 | AD36: =O36*(1+Q36/100)*(1+S36/100)*(1+U36/100)*(1+W36/100)*(1+Y36/100) -> 84467.466 | AE36: =ABS(C36)/$B$7 -> 12829.266 | AF36: =Z36-AE36 -> 34169.989 | AG36: =AA36-AE36 -> 33653.414 | AH36: =AB36-AE36 -> 40481.902 | AI36: =AC36-AE36 -> 62650.81 | AJ36: =AD36-AE36 -> 71638.2 | AK36: =AF36*$B$4 -> 17084.995 | AL36: =AG36*$B$4 -> 16826.707 | AM36: =AH36*$B$4 -> 20240.951 | AN36: =AI36*$B$4 -> 31325.405 | AO36: =AJ36*$B$4 -> 35819.1 | AP36: =AF36-AK36 -> 17084.995 | AQ36: =AG36-AL36 -> 16826.707 | AR36: =AH36-AM36 -> 20240.951 | AS36: =AI36-AN36 -> 31325.405 | AT36: =AJ36-AO36 -> 35819.1 | AU36: =0.2*ABS(C36)+1*ABS(E36) -> 43363.813 | AV36: =C36+E36 -> -94680.877 | AW36: =AP36+AE36 -> 29914.261 | AX36: =AQ36+AE36 -> 29655.973 | AY36: =AR36+AE36 -> 33070.217 | AZ36: =AS36+AE36 -> 44154.671 | BA36: =AT36+AE36+AU36 -> 92012.179 | BB36: =IFERROR(IRR(AV36:BA36,0.15),"n/a") -> 0.30532255 | BC36: =NPV($B$5,AW36:BA36)+AV36 -> 46491.796
... A124: 100 | B124: =RAND() -> 0.39101962 | C124: =IF(B124<=($F$12-$E$12)/($G$12-$E$12),$E$12+SQRT(B124*($G$12-$E$12)*($F$12-$E$12)),$G$12-SQRT((1-B124)*($G$12-$E$12)*($G$12-$F$12))) -> -78338.432 | D124: =RAND() -> 0.53350086 | E124: =IF(D124<=($F$13-$E$13)/($G$13-$E$13),$E$13+SQRT(D124*($G$13-$E$13)*($F$13-$E$13)),$G$13-SQRT((1-D124)*($G$13-$E$13)*($G$13-$F$13))) -> -31054.323 | F124: =RAND() -> 0.70033639 | G124: =IF(F124<=($F$14-$E$14)/($G$14-$E$14),$E$14+SQRT(F124*($G$14-$E$14)*($F$14-$E$14)),$G$14-SQRT((1-F124)*($G$14-$E$14)*($G$14-$F$14))) -> 40259.244 | H124: =RAND() -> 0.094108034 | I124: =IF(H124<=($F$14-$E$14)/($G$14-$E$14),$E$14+SQRT(H124*($G$14-$E$14)*($F$14-$E$14)),$G$14-SQRT((1-H124)*($G$14-$E$14)*($G$14-$F$14))) -> 33757.154 | J124: =RAND() -> 0.013906637 | K124: =IF(J124<=($F$14-$E$14)/($G$14-$E$14),$E$14+SQRT(J124*($G$14-$E$14)*($F$14-$E$14)),$G$14-SQRT((1-J124)*($G$14-$E$14)*($G$14-$F$14))) -> 31444.298 | L124: =RAND() -> 0.43754206 | M124: =IF(L124<=($F$14-$E$14)/($G$14-$E$14),$E$14+SQRT(L124*($G$14-$E$14)*($F$14-$E$14)),$G$14-SQRT((1-L124)*($G$14-$E$14)*($G$14-$F$14))) -> 38101.315 | N124: =RAND() -> 0.99673108 | O124: =IF(N124<=($F$14-$E$14)/($G$14-$E$14),$E$14+SQRT(N124*($G$14-$E$14)*($F$14-$E$14)),$G$14-SQRT((1-N124)*($G$14-$E$14)*($G$14-$F$14))) -> 44504.855 | P124: =RAND() -> 0.52332293 | Q124: =IF(P124<=($F$15-$E$15)/($G$15-$E$15),$E$15+SQRT(P124*($G$15-$E$15)*($F$15-$E$15)),$G$15-SQRT((1-P124)*($G$15-$E$15)*($G$15-$F$15))) -> 15.070804 | R124: =RAND() -> 0.58715516 | S124: =IF(R124<=($F$16-$E$16)/($G$16-$E$16),$E$16+SQRT(R124*($G$16-$E$16)*($F$16-$E$16)),$G$16-SQRT((1-R124)*($G$16-$E$16)*($G$16-$F$16))) -> 15.273976 | T124: =RAND() -> 0.72044578 | U124: =IF(T124<=($F$17-$E$17)/($G$17-$E$17),$E$17+SQRT(T124*($G$17-$E$17)*($F$17-$E$17)),$G$17-SQRT((1-T124)*($G$17-$E$17)*($G$17-$F$17))) -> 19.20223 | V124: =RAND() -> 0.237792 | W124: =IF(V124<=($F$18-$E$18)/($G$18-$E$18),$E$18+SQRT(V124*($G$18-$E$18)*($F$18-$E$18)),$G$18-SQRT((1-V124)*($G$18-$E$18)*($G$18-$F$18))) -> 19.824579 | X124: =RAND() -> 0.88314742 | Y124: =IF(X124<=($F$19-$E$19)/($G$19-$E$19),$E$19+SQRT(X124*($G$19-$E$19)*($F$19-$E$19)),$G$19-SQRT((1-X124)*($G$19-$E$19)*($G$19-$F$19))) -> 25.488021 | Z124: =G124*(1+Q124/100) -> 46326.636 | AA124: =I124*(1+Q124/100)*(1+S124/100) -> 44777.748 | AB124: =K124*(1+Q124/100)*(1+S124/100)*(1+U124/100) -> 49719.036 | AC124: =M124*(1+Q124/100)*(1+S124/100)*(1+U124/100)*(1+W124/100) -> 72188.278 | AD124: =O124*(1+Q124/100)*(1+S124/100)*(1+U124/100)*(1+W124/100)*(1+Y124/100) -> 105812.35 | AE124: =ABS(C124)/$B$7 -> 15667.686 | AF124: =Z124-AE124 -> 30658.949 | AG124: =AA124-AE124 -> 29110.061 | AH124: =AB124-AE124 -> 34051.35 | AI124: =AC124-AE124 -> 56520.591 | AJ124: =AD124-AE124 -> 90144.666 | AK124: =AF124*$B$4 -> 15329.475 | AL124: =AG124*$B$4 -> 14555.031 | AM124: =AH124*$B$4 -> 17025.675 | AN124: =AI124*$B$4 -> 28260.296 | AO124: =AJ124*$B$4 -> 45072.333 | AP124: =AF124-AK124 -> 15329.475 | AQ124: =AG124-AL124 -> 14555.031 | AR124: =AH124-AM124 -> 17025.675 | AS124: =AI124-AN124 -> 28260.296 | AT124: =AJ124-AO124 -> 45072.333 | AU124: =0.2*ABS(C124)+1*ABS(E124) -> 46722.01 | AV124: =C124+E124 -> -109392.76 | AW124: =AP124+AE124 -> 30997.161 | AX124: =AQ124+AE124 -> 30222.717 | AY124: =AR124+AE124 -> 32693.361 | AZ124: =AS124+AE124 -> 43927.982 | BA124: =AT124+AE124+AU124 -> 107462.03 | BB124: =IFERROR(IRR(AV124:BA124,0.15),"n/a") -> 0.26675362 | BC124: =NPV($B$5,AW124:BA124)+AV124 -> 40454.017
A126: Resultados de la simulación
A127: Número de iteraciones (N) | B127: =$B$8 -> 100
A128: Casos con TIR > TREMA | B128: =COUNTIF(BB25:BB124,">"&$B$5) -> 100
A129: P(TIR > TREMA) | B129: =B128/B127 -> 1
A130: TIR promedio | B130: =AVERAGE(BB25:BB124) -> 0.27964866
A131: Desviación estándar TIR | B131: =STDEV(BB25:BB124) -> 0.026550203
A132: TIR mínima | B132: =MIN(BB25:BB124) -> 0.20628875
A133: TIR máxima | B133: =MAX(BB25:BB124) -> 0.33488897
A134: Decisión | B134: =IF(B129>=$B$6,"ACEPTAR el proyecto","RECHAZAR el proyecto") -> ACEPTAR el proyecto
A136: Distribución de frecuencia de la TIR (para el gráfico)
A137: Límite inferior | B137: Límite superior | C137: Frecuencia
A138: -0.3 | B138: -0.2 | C138: =COUNTIFS(BB25:BB124,">="&A138,BB25:BB124,"<"&B138) -> 0
A139: -0.2 | B139: -0.1 | C139: =COUNTIFS(BB25:BB124,">="&A139,BB25:BB124,"<"&B139) -> 0
A140: -0.1 | B140: 0 | C140: =COUNTIFS(BB25:BB124,">="&A140,BB25:BB124,"<"&B140) -> 0
A141: 0 | B141: 0.1 | C141: =COUNTIFS(BB25:BB124,">="&A141,BB25:BB124,"<"&B141) -> 0
A142: 0.1 | B142: 0.2 | C142: =COUNTIFS(BB25:BB124,">="&A142,BB25:BB124,"<"&B142) -> 0
A143: 0.2 | B143: 0.3 | C143: =COUNTIFS(BB25:BB124,">="&A143,BB25:BB124,"<"&B143) -> 76
A144: 0.3 | B144: 0.4 | C144: =COUNTIFS(BB25:BB124,">="&A144,BB25:BB124,"<"&B144) -> 24
A145: 0.4 | B145: 0.5 | C145: =COUNTIFS(BB25:BB124,">="&A145,BB25:BB124,"<"&B145) -> 0
A146: 0.5 | B146: 0.6 | C146: =COUNTIFS(BB25:BB124,">="&A146,BB25:BB124,"<"&B146) -> 0
A147: 0.6 | B147: 0.7 | C147: =COUNTIFS(BB25:BB124,">="&A147,BB25:BB124,"<"&B147) -> 0
A148: 0.7 | B148: 0.8 | C148: =COUNTIFS(BB25:BB124,">="&A148,BB25:BB124,"<"&B148) -> 0
A149: 0.8 | B149: 0.9 | C149: =COUNTIFS(BB25:BB124,">="&A149,BB25:BB124,"<"&B149) -> 0

Sheet Problema2_Camiones
A1: Problema 2: Número Óptimo de Camiones - Simulación Montecarlo
A3: Parámetros generales
A4: Costo anual por camión ($) | B4: 100000
A5: Costo transporte externo ($/ton) | B5: 100
A6: Días laborables al año (días simulados) | B6: 250
A7: Distancia planta-depósito (km, informativo) | B7: 30
A8: Número máximo de camiones a evaluar | B8: 16
A10: Distribución de producción diaria (toneladas)
A11: Límite inf. | B11: Límite sup. | C11: Probabilidad | D11: Ancho | E11: Cum. inf.
A12: 50 | B12: 55 | C12: 0.1 | D12: =B12-A12 -> 5 | E12: 0
A13: 55 | B13: 60 | C13: 0.15 | D13: =B13-A13 -> 5 | E13: =E12+C12 -> 0.1
A14: 60 | B14: 65 | C14: 0.3 | D14: =B14-A14 -> 5 | E14: =E13+C13 -> 0.25
A15: 65 | B15: 70 | C15: 0.35 | D15: =B15-A15 -> 5 | E15: =E14+C14 -> 0.55
A16: 75 | B16: 80 | C16: 0.08 | D16: =B16-A16 -> 5 | E16: =E15+C15 -> 0.9
A17: 80 | B17: 85 | C17: 0.02 | D17: =B17-A17 -> 5 | E17: =E16+C16 -> 0.98
A19: Nota: no hay probabilidad asignada al tramo 70-75 ton en el enunciado original; los datos se respetan tal cual (suman 1.00 sin ese tramo).
A21: Distribución de toneladas diarias trasladadas por camión
A22: Límite inf. | B22: Límite sup. | C22: Probabilidad | D22: Ancho | E22: Cum. inf.
A23: 4 | B23: 4.5 | C23: 0.3 | D23: =B23-A23 -> 0.5 | E23: 0
A24: 4.5 | B24: 5 | C24: 0.4 | D24: =B24-A24 -> 0.5 | E24: =E23+C23 -> 0.3
A25: 5 | B25: 5.5 | C25: 0.2 | D25: =B25-A25 -> 0.5 | E25: =E24+C24 -> 0.7
A26: 5.5 | B26: 6 | C26: 0.1 | D26: =B26-A26 -> 0.5 | E26: =E25+C25 -> 0.9
A29: Simulación diaria (una fila = un día simulado)
A30: Día | B30: U(Prod) | C30: Producción | D30: U(Cam1) | E30: U(Cam2) | F30: U(Cam3) | G30: U(Cam4) | H30: U(Cam5) | I30: U(Cam6) | J30: U(Cam7) | K30: U(Cam8) | L30: U(Cam9) | M30: U(Cam10) | N30: U(Cam11) | O30: U(Cam12) | P30: U(Cam13) | Q30: U(Cam14) | R30: U(Cam15) | S30: U(Cam16) | T30: Cap.Cam1 | U30: Cap.Cam2 | V30: Cap.Cam3 | W30: Cap.Cam4 | X30: Cap.Cam5 | Y30: Cap.Cam6 | Z30: Cap.Cam7 | AA30: Cap.Cam8 | AB30: Cap.Cam9 | AC30: Cap.Cam10 | AD30: Cap.Cam11 | AE30: Cap.Cam12 | AF30: Cap.Cam13 | AG30: Cap.Cam14 | AH30: Cap.Cam15 | AI30: Cap.Cam16 | AJ30: CapTot(N=1) | AK30: CapTot(N=2) | AL30: CapTot(N=3) | AM30: CapTot(N=4) | AN30: CapTot(N=5) | AO30: CapTot(N=6) | AP30: CapTot(N=7) | AQ30: CapTot(N=8) | AR30: CapTot(N=9) | AS30: CapTot(N=10) | AT30: CapTot(N=11) | AU30: CapTot(N=12) | AV30: CapTot(N=13) | AW30: CapTot(N=14) | AX30: CapTot(N=15) | AY30: CapTot(N=16) | AZ30: Exced.(N=1) | BA30: Exced.(N=2) | BB30: Exced.(N=3) | BC30: Exced.(N=4) | BD30: Exced.(N=5) | BE30: Exced.(N=6) | BF30: Exced.(N=7) | BG30: Exced.(N=8) | BH30: Exced.(N=9) | BI30: Exced.(N=10) | BJ30: Exced.(N=11) | BK30: Exced.(N=12) | BL30: Exced.(N=13) | BM30: Exced.(N=14) | BN30: Exced.(N=15) | BO30: Exced.(N=16)
A31: 1 | B31: =RAND() -> 0.60915374 | C31: =LOOKUP(B31,$E$12:$E$17,$A$12:$A$17)+LOOKUP(B31,$E$12:$E$17,$D$12:$D$17)*(B31-LOOKUP(B31,$E$12:$E$17))/LOOKUP(B31,$E$12:$E$17,$C$12:$C$17) -> 65.845053 | D31: =RAND() -> 0.31988983 | E31: =RAND() -> 0.50911934 | F31: =RAND() -> 0.17128616 | G31: =RAND() -> 0.99483189 | H31: =RAND() -> 0.7309513 | I31: =RAND() -> 0.3198959 | J31: =RAND() -> 0.72899881 | K31: =RAND() -> 0.66608251 | ... S31: =RAND() -> 0.85298424 | T31: =LOOKUP(D31,$E$23:$E$26,$A$23:$A$26)+LOOKUP(D31,$E$23:$E$26,$D$23:$D$26)*(D31-LOOKUP(D31,$E$23:$E$26))/LOOKUP(D31,$E$23:$E$26,$C$23:$C$26) -> 4.5248623 | U31: =LOOKUP(E31,$E$23:$E$26,$A$23:$A$26)+LOOKUP(E31,$E$23:$E$26,$D$23:$D$26)*(E31-LOOKUP(E31,$E$23:$E$26))/LOOKUP(E31,$E$23:$E$26,$C$23:$C$26) -> 4.7613992 | V31: =LOOKUP(F31,$E$23:$E$26,$A$23:$A$26)+LOOKUP(F31,$E$23:$E$26,$D$23:$D$26)*(F31-LOOKUP(F31,$E$23:$E$26))/LOOKUP(F31,$E$23:$E$26,$C$23:$C$26) -> 4.2854769 | W31: =LOOKUP(G31,$E$23:$E$26,$A$23:$A$26)+LOOKUP(G31,$E$23:$E$26,$D$23:$D$26)*(G31-LOOKUP(G31,$E$23:$E$26))/LOOKUP(G31,$E$23:$E$26,$C$23:$C$26) -> 5.9741595 | X31: =LOOKUP(H31,$E$23:$E$26,$A$23:$A$26)+LOOKUP(H31,$E$23:$E$26,$D$23:$D$26)*(H31-LOOKUP(H31,$E$23:$E$26))/LOOKUP(H31,$E$23:$E$26,$C$23:$C$26) -> 5.0773782 | Y31: =LOOKUP(I31,$E$23:$E$26,$A$23:$A$26)+LOOKUP(I31,$E$23:$E$26,$D$23:$D$26)*(I31-LOOKUP(I31,$E$23:$E$26))/LOOKUP(I31,$E$23:$E$26,$C$23:$C$26) -> 4.5248699 | Z31: =LOOKUP(J31,$E$23:$E$26,$A$23:$A$26)+LOOKUP(J31,$E$23:$E$26,$D$23:$D$26)*(J31-LOOKUP(J31,$E$23:$E$26))/LOOKUP(J31,$E$23:$E$26,$C$23:$C$26) -> 5.072497 | AA31: =LOOKUP(K31,$E$23:$E$26,$A$23:$A$26)+LOOKUP(K31,$E$23:$E$26,$D$23:$D$26)*(K31-LOOKUP(K31,$E$23:$E$26))/LOOKUP(K31,$E$23:$E$26,$C$23:$C$26) -> 4.9576031 | ... AI31: =LOOKUP(S31,$E$23:$E$26,$A$23:$A$26)+LOOKUP(S31,$E$23:$E$26,$D$23:$D$26)*(S31-LOOKUP(S31,$E$23:$E$26))/LOOKUP(S31,$E$23:$E$26,$C$23:$C$26) -> 5.3824606 | AJ31: =SUM($T31:T31) -> 4.5248623 | AK31: =SUM($T31:U31) -> 9.2862615 | AL31: =SUM($T31:V31) -> 13.571738 | AM31: =SUM($T31:W31) -> 19.545898 | AN31: =SUM($T31:X31) -> 24.623276 | AO31: =SUM($T31:Y31) -> 29.148146 | AP31: =SUM($T31:Z31) -> 34.220643 | AQ31: =SUM($T31:AA31) -> 39.178246 | ... AY31: =SUM($T31:AI31) -> 79.393584 | AZ31: =MAX(C31-AJ31,0) -> 61.320191 | BA31: =MAX(C31-AK31,0) -> 56.558792 | BB31: =MAX(C31-AL31,0) -> 52.273315 | BC31: =MAX(C31-AM31,0) -> 46.299156 | BD31: =MAX(C31-AN31,0) -> 41.221777 | BE31: =MAX(C31-AO31,0) -> 36.696908 | BF31: =MAX(C31-AP31,0) -> 31.62441 | BG31: =MAX(C31-AQ31,0) -> 26.666807 | BH31: =MAX(C31-AR31,0) -> 21.820982 | BI31: =MAX(C31-AS31,0) -> 16.869807 | BJ31: =MAX(C31-AT31,0) -> 12.753458 | BK31: =MAX(C31-AU31,0) -> 6.7967848 | BL31: =MAX(C31-AV31,0) -> 1.4179969 | BM31: =MAX(C31-AW31,0) -> 0 | BN31: =MAX(C31-AX31,0) -> 0 | BO31: =MAX(C31-AY31,0) -> 0
A32: 2 | B32: =RAND() -> 0.0031077661 | C32: =LOOKUP(B32,$E$12:$E$17,$A$12:$A$17)+LOOKUP(B32,$E$12:$E$17,$D$12:$D$17)*(B32-LOOKUP(B32,$E$12:$E$17))/LOOKUP(B32,$E$12:$E$17,$C$12:$C$17) -> 50.155388 | D32: =RAND() -> 0.13455294 | E32: =RAND() -> 0.56464051 | F32: =RAND() -> 0.49387872 | G32: =RAND() -> 0.043791569 | H32: =RAND() -> 0.86673185 | I32: =RAND() -> 0.029941251 | J32: =RAND() -> 0.44364603 | K32: =RAND() -> 0.80795518 | ... S32: =RAND() -> 0.37122035 | T32: =LOOKUP(D32,$E$23:$E$26,$A$23:$A$26)+LOOKUP(D32,$E$23:$E$26,$D$23:$D$26)*(D32-LOOKUP(D32,$E$23:$E$26))/LOOKUP(D32,$E$23:$E$26,$C$23:$C$26) -> 4.2242549 | U32: =LOOKUP(E32,$E$23:$E$26,$A$23:$A$26)+LOOKUP(E32,$E$23:$E$26,$D$23:$D$26)*(E32-LOOKUP(E32,$E$23:$E$26))/LOOKUP(E32,$E$23:$E$26,$C$23:$C$26) -> 4.8308006 | V32: =LOOKUP(F32,$E$23:$E$26,$A$23:$A$26)+LOOKUP(F32,$E$23:$E$26,$D$23:$D$26)*(F32-LOOKUP(F32,$E$23:$E$26))/LOOKUP(F32,$E$23:$E$26,$C$23:$C$26) -> 4.7423484 | W32: =LOOKUP(G32,$E$23:$E$26,$A$23:$A$26)+LOOKUP(G32,$E$23:$E$26,$D$23:$D$26)*(G32-LOOKUP(G32,$E$23:$E$26))/LOOKUP(G32,$E$23:$E$26,$C$23:$C$26) -> 4.0729859 | X32: =LOOKUP(H32,$E$23:$E$26,$A$23:$A$26)+LOOKUP(H32,$E$23:$E$26,$D$23:$D$26)*(H32-LOOKUP(H32,$E$23:$E$26))/LOOKUP(H32,$E$23:$E$26,$C$23:$C$26) -> 5.4168296 | Y32: =LOOKUP(I32,$E$23:$E$26,$A$23:$A$26)+LOOKUP(I32,$E$23:$E$26,$D$23:$D$26)*(I32-LOOKUP(I32,$E$23:$E$26))/LOOKUP(I32,$E$23:$E$26,$C$23:$C$26) -> 4.0499021 | Z32: =LOOKUP(J32,$E$23:$E$26,$A$23:$A$26)+LOOKUP(J32,$E$23:$E$26,$D$23:$D$26)*(J32-LOOKUP(J32,$E$23:$E$26))/LOOKUP(J32,$E$23:$E$26,$C$23:$C$26) -> 4.6795575 | AA32: =LOOKUP(K32,$E$23:$E$26,$A$23:$A$26)+LOOKUP(K32,$E$23:$E$26,$D$23:$D$26)*(K32-LOOKUP(K32,$E$23:$E$26))/LOOKUP(K32,$E$23:$E$26,$C$23:$C$26) -> 5.269888 | ... AI32: =LOOKUP(S32,$E$23:$E$26,$A$23:$A$26)+LOOKUP(S32,$E$23:$E$26,$D$23:$D$26)*(S32-LOOKUP(S32,$E$23:$E$26))/LOOKUP(S32,$E$23:$E$26,$C$23:$C$26) -> 4.5890254 | AJ32: =SUM($T32:T32) -> 4.2242549 | AK32: =SUM($T32:U32) -> 9.0550555 | AL32: =SUM($T32:V32) -> 13.797404 | AM32: =SUM($T32:W32) -> 17.87039 | AN32: =SUM($T32:X32) -> 23.28722 | AO32: =SUM($T32:Y32) -> 27.337122 | AP32: =SUM($T32:Z32) -> 32.016679 | AQ32: =SUM($T32:AA32) -> 37.286567 | ... AY32: =SUM($T32:AI32) -> 75.464877 | AZ32: =MAX(C32-AJ32,0) -> 45.931133 | BA32: =MAX(C32-AK32,0) -> 41.100333 | BB32: =MAX(C32-AL32,0) -> 36.357984 | BC32: =MAX(C32-AM32,0) -> 32.284998 | BD32: =MAX(C32-AN32,0) -> 26.868169 | BE32: =MAX(C32-AO32,0) -> 22.818267 | BF32: =MAX(C32-AP32,0) -> 18.138709 | BG32: =MAX(C32-AQ32,0) -> 12.868821 | BH32: =MAX(C32-AR32,0) -> 8.5833677 | BI32: =MAX(C32-AS32,0) -> 3.7866254 | BJ32: =MAX(C32-AT32,0) -> 0 | BK32: =MAX(C32-AU32,0) -> 0 | BL32: =MAX(C32-AV32,0) -> 0 | BM32: =MAX(C32-AW32,0) -> 0 | BN32: =MAX(C32-AX32,0) -> 0 | BO32: =MAX(C32-AY32,0) -> 0
A33: 3 | B33: =RAND() -> 0.58171982 | C33: =LOOKUP(B33,$E$12:$E$17,$A$12:$A$17)+LOOKUP(B33,$E$12:$E$17,$D$12:$D$17)*(B33-LOOKUP(B33,$E$12:$E$17))/LOOKUP(B33,$E$12:$E$17,$C$12:$C$17) -> 65.45314 | D33: =RAND() -> 0.18271338 | E33: =RAND() -> 0.76812308 | F33: =RAND() -> 0.27023915 | G33: =RAND() -> 0.79034091 | H33: =RAND() -> 0.45623484 | I33: =RAND() -> 0.012377229 | J33: =RAND() -> 0.91757893 | K33: =RAND() -> 0.62432845 | ... S33: =RAND() -> 0.77792123 | T33: =LOOKUP(D33,$E$23:$E$26,$A$23:$A$26)+LOOKUP(D33,$E$23:$E$26,$D$23:$D$26)*(D33-LOOKUP(D33,$E$23:$E$26))/LOOKUP(D33,$E$23:$E$26,$C$23:$C$26) -> 4.3045223 | U33: =LOOKUP(E33,$E$23:$E$26,$A$23:$A$26)+LOOKUP(E33,$E$23:$E$26,$D$23:$D$26)*(E33-LOOKUP(E33,$E$23:$E$26))/LOOKUP(E33,$E$23:$E$26,$C$23:$C$26) -> 5.1703077 | V33: =LOOKUP(F33,$E$23:$E$26,$A$23:$A$26)+LOOKUP(F33,$E$23:$E$26,$D$23:$D$26)*(F33-LOOKUP(F33,$E$23:$E$26))/LOOKUP(F33,$E$23:$E$26,$C$23:$C$26) -> 4.4503986 | W33: =LOOKUP(G33,$E$23:$E$26,$A$23:$A$26)+LOOKUP(G33,$E$23:$E$26,$D$23:$D$26)*(G33-LOOKUP(G33,$E$23:$E$26))/LOOKUP(G33,$E$23:$E$26,$C$23:$C$26) -> 5.2258523 | X33: =LOOKUP(H33,$E$23:$E$26,$A$23:$A$26)+LOOKUP(H33,$E$23:$E$26,$D$23:$D$26)*(H33-LOOKUP(H33,$E$23:$E$26))/LOOKUP(H33,$E$23:$E$26,$C$23:$C$26) -> 4.6952935 | Y33: =LOOKUP(I33,$E$23:$E$26,$A$23:$A$26)+LOOKUP(I33,$E$23:$E$26,$D$23:$D$26)*(I33-LOOKUP(I33,$E$23:$E$26))/LOOKUP(I33,$E$23:$E$26,$C$23:$C$26) -> 4.0206287 | Z33: =LOOKUP(J33,$E$23:$E$26,$A$23:$A$26)+LOOKUP(J33,$E$23:$E$26,$D$23:$D$26)*(J33-LOOKUP(J33,$E$23:$E$26))/LOOKUP(J33,$E$23:$E$26,$C$23:$C$26) -> 5.5878947 | AA33: =LOOKUP(K33,$E$23:$E$26,$A$23:$A$26)+LOOKUP(K33,$E$23:$E$26,$D$23:$D$26)*(K33-LOOKUP(K33,$E$23:$E$26))/LOOKUP(K33,$E$23:$E$26,$C$23:$C$26) -> 4.9054106 | ... AI33: =LOOKUP(S33,$E$23:$E$26,$A$23:$A$26)+LOOKUP(S33,$E$23:$E$26,$D$23:$D$26)*(S33-LOOKUP(S33,$E$23:$E$26))/LOOKUP(S33,$E$23:$E$26,$C$23:$C$26) -> 5.1948031 | AJ33: =SUM($T33:T33) -> 4.3045223 | AK33: =SUM($T33:U33) -> 9.47483 | AL33: =SUM($T33:V33) -> 13.925229 | AM33: =SUM($T33:W33) -> 19.151081 | AN33: =SUM($T33:X33) -> 23.846374 | AO33: =SUM($T33:Y33) -> 27.867003 | AP33: =SUM($T33:Z33) -> 33.454898 | AQ33: =SUM($T33:AA33) -> 38.360308 | ... AY33: =SUM($T33:AI33) -> 77.75811 | AZ33: =MAX(C33-AJ33,0) -> 61.148618 | BA33: =MAX(C33-AK33,0) -> 55.97831 | BB33: =MAX(C33-AL33,0) -> 51.527912 | BC33: =MAX(C33-AM33,0) -> 46.302059 | BD33: =MAX(C33-AN33,0) -> 41.606766 | BE33: =MAX(C33-AO33,0) -> 37.586137 | BF33: =MAX(C33-AP33,0) -> 31.998243 | BG33: =MAX(C33-AQ33,0) -> 27.092832 | BH33: =MAX(C33-AR33,0) -> 22.55228 | BI33: =MAX(C33-AS33,0) -> 17.869667 | BJ33: =MAX(C33-AT33,0) -> 12.125718 | BK33: =MAX(C33-AU33,0) -> 7.4300681 | BL33: =MAX(C33-AV33,0) -> 3.4263092 | BM33: =MAX(C33-AW33,0) -> 0 | BN33: =MAX(C33-AX33,0) -> 0 | BO33: =MAX(C33-AY33,0) -> 0
A34: 4 | B34: =RAND() -> 0.8260671 | C34: =LOOKUP(B34,$E$12:$E$17,$A$12:$A$17)+LOOKUP(B34,$E$12:$E$17,$D$12:$D$17)*(B34-LOOKUP(B34,$E$12:$E$17))/LOOKUP(B34,$E$12:$E$17,$C$12:$C$17) -> 68.943816 | D34: =RAND() -> 0.58068008 | E34: =RAND() -> 0.31990424 | F34: =RAND() -> 0.41664697 | G34: =RAND() -> 0.37122632 | H34: =RAND() -> 0.79033727 | I34: =RAND() -> 0.45621491 | J34: =RAND() -> 0.72899161 | K34: =RAND() -> 0.73128022 | ... S34: =RAND() -> 0.079857195 | T34: =LOOKUP(D34,$E$23:$E$26,$A$23:$A$26)+LOOKUP(D34,$E$23:$E$26,$D$23:$D$26)*(D34-LOOKUP(D34,$E$23:$E$26))/LOOKUP(D34,$E$23:$E$26,$C$23:$C$26) -> 4.8508501 | U34: =LOOKUP(E34,$E$23:$E$26,$A$23:$A$26)+LOOKUP(E34,$E$23:$E$26,$D$23:$D$26)*(E34-LOOKUP(E34,$E$23:$E$26))/LOOKUP(E34,$E$23:$E$26,$C$23:$C$26) -> 4.5248803 | V34: =LOOKUP(F34,$E$23:$E$26,$A$23:$A$26)+LOOKUP(F34,$E$23:$E$26,$D$23:$D$26)*(F34-LOOKUP(F34,$E$23:$E$26))/LOOKUP(F34,$E$23:$E$26,$C$23:$C$26) -> 4.6458087 | W34: =LOOKUP(G34,$E$23:$E$26,$A$23:$A$26)+LOOKUP(G34,$E$23:$E$26,$D$23:$D$26)*(G34-LOOKUP(G34,$E$23:$E$26))/LOOKUP(G34,$E$23:$E$26,$C$23:$C$26) -> 4.5890329 | X34: =LOOKUP(H34,$E$23:$E$26,$A$23:$A$26)+LOOKUP(H34,$E$23:$E$26,$D$23:$D$26)*(H34-LOOKUP(H34,$E$23:$E$26))/LOOKUP(H34,$E$23:$E$26,$C$23:$C$26) -> 5.2258432 | Y34: =LOOKUP(I34,$E$23:$E$26,$A$23:$A$26)+LOOKUP(I34,$E$23:$E$26,$D$23:$D$26)*(I34-LOOKUP(I34,$E$23:$E$26))/LOOKUP(I34,$E$23:$E$26,$C$23:$C$26) -> 4.6952686 | Z34: =LOOKUP(J34,$E$23:$E$26,$A$23:$A$26)+LOOKUP(J34,$E$23:$E$26,$D$23:$D$26)*(J34-LOOKUP(J34,$E$23:$E$26))/LOOKUP(J34,$E$23:$E$26,$C$23:$C$26) -> 5.072479 | AA34: =LOOKUP(K34,$E$23:$E$26,$A$23:$A$26)+LOOKUP(K34,$E$23:$E$26,$D$23:$D$26)*(K34-LOOKUP(K34,$E$23:$E$26))/LOOKUP(K34,$E$23:$E$26,$C$23:$C$26) -> 5.0782006 | ... AI34: =LOOKUP(S34,$E$23:$E$26,$A$23:$A$26)+LOOKUP(S34,$E$23:$E$26,$D$23:$D$26)*(S34-LOOKUP(S34,$E$23:$E$26))/LOOKUP(S34,$E$23:$E$26,$C$23:$C$26) -> 4.1330953 | AJ34: =SUM($T34:T34) -> 4.8508501 | AK34: =SUM($T34:U34) -> 9.3757304 | AL34: =SUM($T34:V34) -> 14.021539 | AM34: =SUM($T34:W34) -> 18.610572 | AN34: =SUM($T34:X34) -> 23.836415 | AO34: =SUM($T34:Y34) -> 28.531684 | AP34: =SUM($T34:Z34) -> 33.604163 | AQ34: =SUM($T34:AA34) -> 38.682363 | ... AY34: =SUM($T34:AI34) -> 76.539092 | AZ34: =MAX(C34-AJ34,0) -> 64.092966 | BA34: =MAX(C34-AK34,0) -> 59.568085 | BB34: =MAX(C34-AL34,0) -> 54.922277 | BC34: =MAX(C34-AM34,0) -> 50.333244 | BD34: =MAX(C34-AN34,0) -> 45.1074 | BE34: =MAX(C34-AO34,0) -> 40.412132 | BF34: =MAX(C34-AP34,0) -> 35.339653 | BG34: =MAX(C34-AQ34,0) -> 30.261452 | BH34: =MAX(C34-AR34,0) -> 26.121158 | BI34: =MAX(C34-AS34,0) -> 21.613024 | BJ34: =MAX(C34-AT34,0) -> 17.592417 | BK34: =MAX(C34-AU34,0) -> 11.799871 | BL34: =MAX(C34-AV34,0) -> 6.0846166 | BM34: =MAX(C34-AW34,0) -> 1.0121516 | BN34: =MAX(C34-AX34,0) -> 0 | BO34: =MAX(C34-AY34,0) -> 0
A35: 5 | B35: =RAND() -> 0.45489109 | C35: =LOOKUP(B35,$E$12:$E$17,$A$12:$A$17)+LOOKUP(B35,$E$12:$E$17,$D$12:$D$17)*(B35-LOOKUP(B35,$E$12:$E$17))/LOOKUP(B35,$E$12:$E$17,$C$12:$C$17) -> 63.414852 | D35: =RAND() -> 0.89647198 | E35: =RAND() -> 0.84044141 | F35: =RAND() -> 0.57666312 | G35: =RAND() -> 0.57666837 | H35: =RAND() -> 0.66092604 | I35: =RAND() -> 0.06982225 | J35: =RAND() -> 0.94878743 | K35: =RAND() -> 0.62255978 | ... S35: =RAND() -> 0.026561199 | T35: =LOOKUP(D35,$E$23:$E$26,$A$23:$A$26)+LOOKUP(D35,$E$23:$E$26,$D$23:$D$26)*(D35-LOOKUP(D35,$E$23:$E$26))/LOOKUP(D35,$E$23:$E$26,$C$23:$C$26) -> 5.49118 | U35: =LOOKUP(E35,$E$23:$E$26,$A$23:$A$26)+LOOKUP(E35,$E$23:$E$26,$D$23:$D$26)*(E35-LOOKUP(E35,$E$23:$E$26))/LOOKUP(E35,$E$23:$E$26,$C$23:$C$26) -> 5.3511035 | V35: =LOOKUP(F35,$E$23:$E$26,$A$23:$A$26)+LOOKUP(F35,$E$23:$E$26,$D$23:$D$26)*(F35-LOOKUP(F35,$E$23:$E$26))/LOOKUP(F35,$E$23:$E$26,$C$23:$C$26) -> 4.8458289 | W35: =LOOKUP(G35,$E$23:$E$26,$A$23:$A$26)+LOOKUP(G35,$E$23:$E$26,$D$23:$D$26)*(G35-LOOKUP(G35,$E$23:$E$26))/LOOKUP(G35,$E$23:$E$26,$C$23:$C$26) -> 4.8458355 | X35: =LOOKUP(H35,$E$23:$E$26,$A$23:$A$26)+LOOKUP(H35,$E$23:$E$26,$D$23:$D$26)*(H35-LOOKUP(H35,$E$23:$E$26))/LOOKUP(H35,$E$23:$E$26,$C$23:$C$26) -> 4.9511575 | Y35: =LOOKUP(I35,$E$23:$E$26,$A$23:$A$26)+LOOKUP(I35,$E$23:$E$26,$D$23:$D$26)*(I35-LOOKUP(I35,$E$23:$E$26))/LOOKUP(I35,$E$23:$E$26,$C$23:$C$26) -> 4.1163704 | Z35: =LOOKUP(J35,$E$23:$E$26,$A$23:$A$26)+LOOKUP(J35,$E$23:$E$26,$D$23:$D$26)*(J35-LOOKUP(J35,$E$23:$E$26))/LOOKUP(J35,$E$23:$E$26,$C$23:$C$26) -> 5.7439372 | AA35: =LOOKUP(K35,$E$23:$E$26,$A$23:$A$26)+LOOKUP(K35,$E$23:$E$26,$D$23:$D$26)*(K35-LOOKUP(K35,$E$23:$E$26))/LOOKUP(K35,$E$23:$E$26,$C$23:$C$26) -> 4.9031997 | ... AI35: =LOOKUP(S35,$E$23:$E$26,$A$23:$A$26)+LOOKUP(S35,$E$23:$E$26,$D$23:$D$26)*(S35-LOOKUP(S35,$E$23:$E$26))/LOOKUP(S35,$E$23:$E$26,$C$23:$C$26) -> 4.0442687 | AJ35: =SUM($T35:T35) -> 5.49118 | AK35: =SUM($T35:U35) -> 10.842283 | AL35: =SUM($T35:V35) -> 15.688112 | AM35: =SUM($T35:W35) -> 20.533948 | AN35: =SUM($T35:X35) -> 25.485105 | AO35: =SUM($T35:Y35) -> 29.601476 | AP35: =SUM($T35:Z35) -> 35.345413 | AQ35: =SUM($T35:AA35) -> 40.248613 | ... AY35: =SUM($T35:AI35) -> 78.68989 | AZ35: =MAX(C35-AJ35,0) -> 57.923672 | BA35: =MAX(C35-AK35,0) -> 52.572568 | BB35: =MAX(C35-AL35,0) -> 47.726739 | BC35: =MAX(C35-AM35,0) -> 42.880904 | BD35: =MAX(C35-AN35,0) -> 37.929746 | BE35: =MAX(C35-AO35,0) -> 33.813376 | BF35: =MAX(C35-AP35,0) -> 28.069439 | BG35: =MAX(C35-AQ35,0) -> 23.166239 | BH35: =MAX(C35-AR35,0) -> 17.787455 | BI35: =MAX(C35-AS35,0) -> 12.678193 | BJ35: =MAX(C35-AT35,0) -> 7.7023871 | BK35: =MAX(C35-AU35,0) -> 2.7512087 | BL35: =MAX(C35-AV35,0) -> 0 | BM35: =MAX(C35-AW35,0) -> 0 | BN35: =MAX(C35-AX35,0) -> 0 | BO35: =MAX(C35-AY35,0) -> 0
A36: 6 | B36: =RAND() -> 0.56593107 | C36: =LOOKUP(B36,$E$12:$E$17,$A$12:$A$17)+LOOKUP(B36,$E$12:$E$17,$D$12:$D$17)*(B36-LOOKUP(B36,$E$12:$E$17))/LOOKUP(B36,$E$12:$E$17,$C$12:$C$17) -> 65.227587 | D36: =RAND() -> 0.31991222 | E36: =RAND() -> 0.069809293 | F36: =RAND() -> 0.44365368 | G36: =RAND() -> 0.72898158 | H36: =RAND() -> 0.85153177 | I36: =RAND() -> 0.19384467 | J36: =RAND() -> 0.53740936 | K36: =RAND() -> 0.57667833 | ... S36: =RAND() -> 0.69739949 | T36: =LOOKUP(D36,$E$23:$E$26,$A$23:$A$26)+LOOKUP(D36,$E$23:$E$26,$D$23:$D$26)*(D36-LOOKUP(D36,$E$23:$E$26))/LOOKUP(D36,$E$23:$E$26,$C$23:$C$26) -> 4.5248903 | U36: =LOOKUP(E36,$E$23:$E$26,$A$23:$A$26)+LOOKUP(E36,$E$23:$E$26,$D$23:$D$26)*(E36-LOOKUP(E36,$E$23:$E$26))/LOOKUP(E36,$E$23:$E$26,$C$23:$C$26) -> 4.1163488 | V36: =LOOKUP(F36,$E$23:$E$26,$A$23:$A$26)+LOOKUP(F36,$E$23:$E$26,$D$23:$D$26)*(F36-LOOKUP(F36,$E$23:$E$26))/LOOKUP(F36,$E$23:$E$26,$C$23:$C$26) -> 4.6795671 | W36: =LOOKUP(G36,$E$23:$E$26,$A$23:$A$26)+LOOKUP(G36,$E$23:$E$26,$D$23:$D$26)*(G36-LOOKUP(G36,$E$23:$E$26))/LOOKUP(G36,$E$23:$E$26,$C$23:$C$26) -> 5.0724539 | X36: =LOOKUP(H36,$E$23:$E$26,$A$23:$A$26)+LOOKUP(H36,$E$23:$E$26,$D$23:$D$26)*(H36-LOOKUP(H36,$E$23:$E$26))/LOOKUP(H36,$E$23:$E$26,$C$23:$C$26) -> 5.3788294 | Y36: =LOOKUP(I36,$E$23:$E$26,$A$23:$A$26)+LOOKUP(I36,$E$23:$E$26,$D$23:$D$26)*(I36-LOOKUP(I36,$E$23:$E$26))/LOOKUP(I36,$E$23:$E$26,$C$23:$C$26) -> 4.3230744 | Z36: =LOOKUP(J36,$E$23:$E$26,$A$23:$A$26)+LOOKUP(J36,$E$23:$E$26,$D$23:$D$26)*(J36-LOOKUP(J36,$E$23:$E$26))/LOOKUP(J36,$E$23:$E$26,$C$23:$C$26) -> 4.7967617 | AA36: =LOOKUP(K36,$E$23:$E$26,$A$23:$A$26)+LOOKUP(K36,$E$23:$E$26,$D$23:$D$26)*(K36-LOOKUP(K36,$E$23:$E$26))/LOOKUP(K36,$E$23:$E$26,$C$23:$C$26) -> 4.8458479 | ... AI36: =LOOKUP(S36,$E$23:$E$26,$A$23:$A$26)+LOOKUP(S36,$E$23:$E$26,$D$23:$D$26)*(S36-LOOKUP(S36,$E$23:$E$26))/LOOKUP(S36,$E$23:$E$26,$C$23:$C$26) -> 4.9967494 | AJ36: =SUM($T36:T36) -> 4.5248903 | AK36: =SUM($T36:U36) -> 8.6412391 | AL36: =SUM($T36:V36) -> 13.320806 | AM36: =SUM($T36:W36) -> 18.39326 | AN36: =SUM($T36:X36) -> 23.77209 | AO36: =SUM($T36:Y36) -> 28.095164 | AP36: =SUM($T36:Z36) -> 32.891926 | AQ36: =SUM($T36:AA36) -> 37.737774 | ... AY36: =SUM($T36:AI36) -> 77.154106 | AZ36: =MAX(C36-AJ36,0) -> 60.702696 | BA36: =MAX(C36-AK36,0) -> 56.586348 | BB36: =MAX(C36-AL36,0) -> 51.906781 | BC36: =MAX(C36-AM36,0) -> 46.834327 | BD36: =MAX(C36-AN36,0) -> 41.455497 | BE36: =MAX(C36-AO36,0) -> 37.132423 | BF36: =MAX(C36-AP36,0) -> 32.335661 | BG36: =MAX(C36-AQ36,0) -> 27.489813 | BH36: =MAX(C36-AR36,0) -> 22.513996 | BI36: =MAX(C36-AS36,0) -> 17.700266 | BJ36: =MAX(C36-AT36,0) -> 12.749108 | BK36: =MAX(C36-AU36,0) -> 6.756202 | BL36: =MAX(C36-AV36,0) -> 2.5319102 | BM36: =MAX(C36-AW36,0) -> 0 | BN36: =MAX(C36-AX36,0) -> 0 | BO36: =MAX(C36-AY36,0) -> 0
A37: 7 | B37: =RAND() -> 0.8548181 | C37: =LOOKUP(B37,$E$12:$E$17,$A$12:$A$17)+LOOKUP(B37,$E$12:$E$17,$D$12:$D$17)*(B37-LOOKUP(B37,$E$12:$E$17))/LOOKUP(B37,$E$12:$E$17,$C$12:$C$17) -> 69.354544 | D37: =RAND() -> 0.82663044 | E37: =RAND() -> 0.069798415 | F37: =RAND() -> 0.44364859 | G37: =RAND() -> 0.39102309 | H37: =RAND() -> 0.85973202 | I37: =RAND() -> 0.76811926 | J37: =RAND() -> 0.60744038 | K37: =RAND() -> 0.85152931 | ... S37: =RAND() -> 0.084194327 | T37: =LOOKUP(D37,$E$23:$E$26,$A$23:$A$26)+LOOKUP(D37,$E$23:$E$26,$D$23:$D$26)*(D37-LOOKUP(D37,$E$23:$E$26))/LOOKUP(D37,$E$23:$E$26,$C$23:$C$26) -> 5.3165761 | U37: =LOOKUP(E37,$E$23:$E$26,$A$23:$A$26)+LOOKUP(E37,$E$23:$E$26,$D$23:$D$26)*(E37-LOOKUP(E37,$E$23:$E$26))/LOOKUP(E37,$E$23:$E$26,$C$23:$C$26) -> 4.1163307 | V37: =LOOKUP(F37,$E$23:$E$26,$A$23:$A$26)+LOOKUP(F37,$E$23:$E$26,$D$23:$D$26)*(F37-LOOKUP(F37,$E$23:$E$26))/LOOKUP(F37,$E$23:$E$26,$C$23:$C$26) -> 4.6795607 | W37: =LOOKUP(G37,$E$23:$E$26,$A$23:$A$26)+LOOKUP(G37,$E$23:$E$26,$D$23:$D$26)*(G37-LOOKUP(G37,$E$23:$E$26))/LOOKUP(G37,$E$23:$E$26,$C$23:$C$26) -> 4.6137789 | X37: =LOOKUP(H37,$E$23:$E$26,$A$23:$A$26)+LOOKUP(H37,$E$23:$E$26,$D$23:$D$26)*(H37-LOOKUP(H37,$E$23:$E$26))/LOOKUP(H37,$E$23:$E$26,$C$23:$C$26) -> 5.3993301 | Y37: =LOOKUP(I37,$E$23:$E$26,$A$23:$A$26)+LOOKUP(I37,$E$23:$E$26,$D$23:$D$26)*(I37-LOOKUP(I37,$E$23:$E$26))/LOOKUP(I37,$E$23:$E$26,$C$23:$C$26) -> 5.1702982 | Z37: =LOOKUP(J37,$E$23:$E$26,$A$23:$A$26)+LOOKUP(J37,$E$23:$E$26,$D$23:$D$26)*(J37-LOOKUP(J37,$E$23:$E$26))/LOOKUP(J37,$E$23:$E$26,$C$23:$C$26) -> 4.8843005 | AA37: =LOOKUP(K37,$E$23:$E$26,$A$23:$A$26)+LOOKUP(K37,$E$23:$E$26,$D$23:$D$26)*(K37-LOOKUP(K37,$E$23:$E$26))/LOOKUP(K37,$E$23:$E$26,$C$23:$C$26) -> 5.3788233 | ... AI37: =LOOKUP(S37,$E$23:$E$26,$A$23:$A$26)+LOOKUP(S37,$E$23:$E$26,$D$23:$D$26)*(S37-LOOKUP(S37,$E$23:$E$26))/LOOKUP(S37,$E$23:$E$26,$C$23:$C$26) -> 4.1403239 | AJ37: =SUM($T37:T37) -> 5.3165761 | AK37: =SUM($T37:U37) -> 9.4329068 | AL37: =SUM($T37:V37) -> 14.112468 | AM37: =SUM($T37:W37) -> 18.726246 | AN37: =SUM($T37:X37) -> 24.125576 | AO37: =SUM($T37:Y37) -> 29.295875 | AP37: =SUM($T37:Z37) -> 34.180175 | AQ37: =SUM($T37:AA37) -> 39.558998 | ... AY37: =SUM($T37:AI37) -> 79.602795 | AZ37: =MAX(C37-AJ37,0) -> 64.037968 | BA37: =MAX(C37-AK37,0) -> 59.921637 | BB37: =MAX(C37-AL37,0) -> 55.242077 | BC37: =MAX(C37-AM37,0) -> 50.628298 | BD37: =MAX(C37-AN37,0) -> 45.228968 | BE37: =MAX(C37-AO37,0) -> 40.05867 | BF37: =MAX(C37-AP37,0) -> 35.174369 | BG37: =MAX(C37-AQ37,0) -> 29.795546 | BH37: =MAX(C37-AR37,0) -> 24.998782 | BI37: =MAX(C37-AS37,0) -> 20.458229 | BJ37: =MAX(C37-AT37,0) -> 15.198361 | BK37: =MAX(C37-AU37,0) -> 9.20539 | BL37: =MAX(C37-AV37,0) -> 4.5097173 | BM37: =MAX(C37-AW37,0) -> 0 | BN37: =MAX(C37-AX37,0) -> 0 | BO37: =MAX(C37-AY37,0) -> 0
A38: 8 | B38: =RAND() -> 0.64819131 | C38: =LOOKUP(B38,$E$12:$E$17,$A$12:$A$17)+LOOKUP(B38,$E$12:$E$17,$D$12:$D$17)*(B38-LOOKUP(B38,$E$12:$E$17))/LOOKUP(B38,$E$12:$E$17,$C$12:$C$17) -> 66.402733 | D38: =RAND() -> 0.330049 | E38: =RAND() -> 0.391025 | F38: =RAND() -> 0.95851958 | G38: =RAND() -> 0.76810449 | H38: =RAND() -> 0.44206649 | I38: =RAND() -> 0.96285594 | J38: =RAND() -> 0.95700215 | K38: =RAND() -> 0.28459864 | ... S38: =RAND() -> 0.66374951 | T38: =LOOKUP(D38,$E$23:$E$26,$A$23:$A$26)+LOOKUP(D38,$E$23:$E$26,$D$23:$D$26)*(D38-LOOKUP(D38,$E$23:$E$26))/LOOKUP(D38,$E$23:$E$26,$C$23:$C$26) -> 4.5375613 | U38: =LOOKUP(E38,$E$23:$E$26,$A$23:$A$26)+LOOKUP(E38,$E$23:$E$26,$D$23:$D$26)*(E38-LOOKUP(E38,$E$23:$E$26))/LOOKUP(E38,$E$23:$E$26,$C$23:$C$26) -> 4.6137813 | V38: =LOOKUP(F38,$E$23:$E$26,$A$23:$A$26)+LOOKUP(F38,$E$23:$E$26,$D$23:$D$26)*(F38-LOOKUP(F38,$E$23:$E$26))/LOOKUP(F38,$E$23:$E$26,$C$23:$C$26) -> 5.7925979 | W38: =LOOKUP(G38,$E$23:$E$26,$A$23:$A$26)+LOOKUP(G38,$E$23:$E$26,$D$23:$D$26)*(G38-LOOKUP(G38,$E$23:$E$26))/LOOKUP(G38,$E$23:$E$26,$C$23:$C$26) -> 5.1702612 | X38: =LOOKUP(H38,$E$23:$E$26,$A$23:$A$26)+LOOKUP(H38,$E$23:$E$26,$D$23:$D$26)*(H38-LOOKUP(H38,$E$23:$E$26))/LOOKUP(H38,$E$23:$E$26,$C$23:$C$26) -> 4.6775831 | Y38: =LOOKUP(I38,$E$23:$E$26,$A$23:$A$26)+LOOKUP(I38,$E$23:$E$26,$D$23:$D$26)*(I38-LOOKUP(I38,$E$23:$E$26))/LOOKUP(I38,$E$23:$E$26,$C$23:$C$26) -> 5.8142797 | Z38: =LOOKUP(J38,$E$23:$E$26,$A$23:$A$26)+LOOKUP(J38,$E$23:$E$26,$D$23:$D$26)*(J38-LOOKUP(J38,$E$23:$E$26))/LOOKUP(J38,$E$23:$E$26,$C$23:$C$26) -> 5.7850108 | AA38: =LOOKUP(K38,$E$23:$E$26,$A$23:$A$26)+LOOKUP(K38,$E$23:$E$26,$D$23:$D$26)*(K38-LOOKUP(K38,$E$23:$E$26))/LOOKUP(K38,$E$23:$E$26,$C$23:$C$26) -> 4.4743311 | ... AI38: =LOOKUP(S38,$E$23:$E$26,$A$23:$A$26)+LOOKUP(S38,$E$23:$E$26,$D$23:$D$26)*(S38-LOOKUP(S38,$E$23:$E$26))/LOOKUP(S38,$E$23:$E$26,$C$23:$C$26) -> 4.9546869 | AJ38: =SUM($T38:T38) -> 4.5375613 | AK38: =SUM($T38:U38) -> 9.1513425 | AL38: =SUM($T38:V38) -> 14.94394 | AM38: =SUM($T38:W38) -> 20.114202 | AN38: =SUM($T38:X38) -> 24.791785 | AO38: =SUM($T38:Y38) -> 30.606064 | AP38: =SUM($T38:Z38) -> 36.391075 | AQ38: =SUM($T38:AA38) -> 40.865406 | ... AY38: =SUM($T38:AI38) -> 77.745529 | AZ38: =MAX(C38-AJ38,0) -> 61.865172 | BA38: =MAX(C38-AK38,0) -> 57.25139 | BB38: =MAX(C38-AL38,0) -> 51.458793 | BC38: =MAX(C38-AM38,0) -> 46.288531 | BD38: =MAX(C38-AN38,0) -> 41.610948 | BE38: =MAX(C38-AO38,0) -> 35.796668 | BF38: =MAX(C38-AP38,0) -> 30.011658 | BG38: =MAX(C38-AQ38,0) -> 25.537327 | BH38: =MAX(C38-AR38,0) -> 20.996759 | BI38: =MAX(C38-AS38,0) -> 16.704386 | BJ38: =MAX(C38-AT38,0) -> 12.184884 | BK38: =MAX(C38-AU38,0) -> 7.4892159 | BL38: =MAX(C38-AV38,0) -> 2.8328056 | BM38: =MAX(C38-AW38,0) -> 0 | BN38: =MAX(C38-AX38,0) -> 0 | BO38: =MAX(C38-AY38,0) -> 0
A39: 9 | B39: =RAND() -> 0.99765927 | C39: =LOOKUP(B39,$E$12:$E$17,$A$12:$A$17)+LOOKUP(B39,$E$12:$E$17,$D$12:$D$17)*(B39-LOOKUP(B39,$E$12:$E$17))/LOOKUP(B39,$E$12:$E$17,$C$12:$C$17) -> 84.414819 | D39: =RAND() -> 0.68064549 | E39: =RAND() -> 0.76880473 | F39: =RAND() -> 0.13457418 | G39: =RAND() -> 0.57758133 | H39: =RAND() -> 0.24523448 | I39: =RAND() -> 0.15145584 | J39: =RAND() -> 0.096942647 | K39: =RAND() -> 0.66153663 | ... S39: =RAND() -> 0.53741363 | T39: =LOOKUP(D39,$E$23:$E$26,$A$23:$A$26)+LOOKUP(D39,$E$23:$E$26,$D$23:$D$26)*(D39-LOOKUP(D39,$E$23:$E$26))/LOOKUP(D39,$E$23:$E$26,$C$23:$C$26) -> 4.9758069 | U39: =LOOKUP(E39,$E$23:$E$26,$A$23:$A$26)+LOOKUP(E39,$E$23:$E$26,$D$23:$D$26)*(E39-LOOKUP(E39,$E$23:$E$26))/LOOKUP(E39,$E$23:$E$26,$C$23:$C$26) -> 5.1720118 | V39: =LOOKUP(F39,$E$23:$E$26,$A$23:$A$26)+LOOKUP(F39,$E$23:$E$26,$D$23:$D$26)*(F39-LOOKUP(F39,$E$23:$E$26))/LOOKUP(F39,$E$23:$E$26,$C$23:$C$26) -> 4.2242903 | W39: =LOOKUP(G39,$E$23:$E$26,$A$23:$A$26)+LOOKUP(G39,$E$23:$E$26,$D$23:$D$26)*(G39-LOOKUP(G39,$E$23:$E$26))/LOOKUP(G39,$E$23:$E$26,$C$23:$C$26) -> 4.8469767 | X39: =LOOKUP(H39,$E$23:$E$26,$A$23:$A$26)+LOOKUP(H39,$E$23:$E$26,$D$23:$D$26)*(H39-LOOKUP(H39,$E$23:$E$26))/LOOKUP(H39,$E$23:$E$26,$C$23:$C$26) -> 4.4087241 | Y39: =LOOKUP(I39,$E$23:$E$26,$A$23:$A$26)+LOOKUP(I39,$E$23:$E$26,$D$23:$D$26)*(I39-LOOKUP(I39,$E$23:$E$26))/LOOKUP(I39,$E$23:$E$26,$C$23:$C$26) -> 4.2524264 | Z39: =LOOKUP(J39,$E$23:$E$26,$A$23:$A$26)+LOOKUP(J39,$E$23:$E$26,$D$23:$D$26)*(J39-LOOKUP(J39,$E$23:$E$26))/LOOKUP(J39,$E$23:$E$26,$C$23:$C$26) -> 4.1615711 | AA39: =LOOKUP(K39,$E$23:$E$26,$A$23:$A$26)+LOOKUP(K39,$E$23:$E$26,$D$23:$D$26)*(K39-LOOKUP(K39,$E$23:$E$26))/LOOKUP(K39,$E$23:$E$26,$C$23:$C$26) -> 4.9519208 | ... AI39: =LOOKUP(S39,$E$23:$E$26,$A$23:$A$26)+LOOKUP(S39,$E$23:$E$26,$D$23:$D$26)*(S39-LOOKUP(S39,$E$23:$E$26))/LOOKUP(S39,$E$23:$E$26,$C$23:$C$26) -> 4.796767 | AJ39: =SUM($T39:T39) -> 4.9758069 | AK39: =SUM($T39:U39) -> 10.147819 | AL39: =SUM($T39:V39) -> 14.372109 | AM39: =SUM($T39:W39) -> 19.219086 | AN39: =SUM($T39:X39) -> 23.62781 | AO39: =SUM($T39:Y39) -> 27.880236 | AP39: =SUM($T39:Z39) -> 32.041807 | AQ39: =SUM($T39:AA39) -> 36.993728 | ... AY39: =SUM($T39:AI39) -> 73.421902 | AZ39: =MAX(C39-AJ39,0) -> 79.439012 | BA39: =MAX(C39-AK39,0) -> 74.267 | BB39: =MAX(C39-AL39,0) -> 70.04271 | BC39: =MAX(C39-AM39,0) -> 65.195733 | BD39: =MAX(C39-AN39,0) -> 60.787009 | BE39: =MAX(C39-AO39,0) -> 56.534582 | BF39: =MAX(C39-AP39,0) -> 52.373011 | BG39: =MAX(C39-AQ39,0) -> 47.421091 | BH39: =MAX(C39-AR39,0) -> 42.673536 | BI39: =MAX(C39-AS39,0) -> 38.600597 | BJ39: =MAX(C39-AT39,0) -> 34.117608 | BK39: =MAX(C39-AU39,0) -> 29.438038 | BL39: =MAX(C39-AV39,0) -> 24.650023 | BM39: =MAX(C39-AW39,0) -> 20.536063 | BN39: =MAX(C39-AX39,0) -> 15.789684 | BO39: =MAX(C39-AY39,0) -> 10.992917
A40: 10 | B40: =RAND() -> 0.66787418 | C40: =LOOKUP(B40,$E$12:$E$17,$A$12:$A$17)+LOOKUP(B40,$E$12:$E$17,$D$12:$D$17)*(B40-LOOKUP(B40,$E$12:$E$17))/LOOKUP(B40,$E$12:$E$17,$C$12:$C$17) -> 66.683917 | D40: =RAND() -> 0.81348809 | E40: =RAND() -> 0.77529568 | F40: =RAND() -> 0.40690839 | G40: =RAND() -> 0.85814383 | H40: =RAND() -> 0.84044402 | I40: =RAND() -> 0.23155261 | J40: =RAND() -> 0.75624473 | K40: =RAND() -> 0.62256229 | ... S40: =RAND() -> 0.28573106 | T40: =LOOKUP(D40,$E$23:$E$26,$A$23:$A$26)+LOOKUP(D40,$E$23:$E$26,$D$23:$D$26)*(D40-LOOKUP(D40,$E$23:$E$26))/LOOKUP(D40,$E$23:$E$26,$C$23:$C$26) -> 5.2837202 | U40: =LOOKUP(E40,$E$23:$E$26,$A$23:$A$26)+LOOKUP(E40,$E$23:$E$26,$D$23:$D$26)*(E40-LOOKUP(E40,$E$23:$E$26))/LOOKUP(E40,$E$23:$E$26,$C$23:$C$26) -> 5.1882392 | V40: =LOOKUP(F40,$E$23:$E$26,$A$23:$A$26)+LOOKUP(F40,$E$23:$E$26,$D$23:$D$26)*(F40-LOOKUP(F40,$E$23:$E$26))/LOOKUP(F40,$E$23:$E$26,$C$23:$C$26) -> 4.6336355 | W40: =LOOKUP(G40,$E$23:$E$26,$A$23:$A$26)+LOOKUP(G40,$E$23:$E$26,$D$23:$D$26)*(G40-LOOKUP(G40,$E$23:$E$26))/LOOKUP(G40,$E$23:$E$26,$C$23:$C$26) -> 5.3953596 | X40: =LOOKUP(H40,$E$23:$E$26,$A$23:$A$26)+LOOKUP(H40,$E$23:$E$26,$D$23:$D$26)*(H40-LOOKUP(H40,$E$23:$E$26))/LOOKUP(H40,$E$23:$E$26,$C$23:$C$26) -> 5.3511101 | Y40: =LOOKUP(I40,$E$23:$E$26,$A$23:$A$26)+LOOKUP(I40,$E$23:$E$26,$D$23:$D$26)*(I40-LOOKUP(I40,$E$23:$E$26))/LOOKUP(I40,$E$23:$E$26,$C$23:$C$26) -> 4.385921 | Z40: =LOOKUP(J40,$E$23:$E$26,$A$23:$A$26)+LOOKUP(J40,$E$23:$E$26,$D$23:$D$26)*(J40-LOOKUP(J40,$E$23:$E$26))/LOOKUP(J40,$E$23:$E$26,$C$23:$C$26) -> 5.1406118 | AA40: =LOOKUP(K40,$E$23:$E$26,$A$23:$A$26)+LOOKUP(K40,$E$23:$E$26,$D$23:$D$26)*(K40-LOOKUP(K40,$E$23:$E$26))/LOOKUP(K40,$E$23:$E$26,$C$23:$C$26) -> 4.9032029 | ... AI40: =LOOKUP(S40,$E$23:$E$26,$A$23:$A$26)+LOOKUP(S40,$E$23:$E$26,$D$23:$D$26)*(S40-LOOKUP(S40,$E$23:$E$26))/LOOKUP(S40,$E$23:$E$26,$C$23:$C$26) -> 4.4762184 | AJ40: =SUM($T40:T40) -> 5.2837202 | AK40: =SUM($T40:U40) -> 10.471959 | AL40: =SUM($T40:V40) -> 15.105595 | AM40: =SUM($T40:W40) -> 20.500954 | AN40: =SUM($T40:X40) -> 25.852065 | AO40: =SUM($T40:Y40) -> 30.237986 | AP40: =SUM($T40:Z40) -> 35.378597 | AQ40: =SUM($T40:AA40) -> 40.2818 | ... AY40: =SUM($T40:AI40) -> 79.784159 | AZ40: =MAX(C40-AJ40,0) -> 61.400197 | BA40: =MAX(C40-AK40,0) -> 56.211957 | BB40: =MAX(C40-AL40,0) -> 51.578322 | BC40: =MAX(C40-AM40,0) -> 46.182962 | BD40: =MAX(C40-AN40,0) -> 40.831852 | BE40: =MAX(C40-AO40,0) -> 36.445931 | BF40: =MAX(C40-AP40,0) -> 31.305319 | BG40: =MAX(C40-AQ40,0) -> 26.402117 | BH40: =MAX(C40-AR40,0) -> 21.376182 | BI40: =MAX(C40-AS40,0) -> 15.6915 | BJ40: =MAX(C40-AT40,0) -> 11.092796 | BK40: =MAX(C40-AU40,0) -> 5.0999424 | BL40: =MAX(C40-AV40,0) -> 1.0106083 | BM40: =MAX(C40-AW40,0) -> 0 | BN40: =MAX(C40-AX40,0) -> 0 | BO40: =MAX(C40-AY40,0) -> 0
A41: 11 | B41: =RAND() -> 0.75929201 | C41: =LOOKUP(B41,$E$12:$E$17,$A$12:$A$17)+LOOKUP(B41,$E$12:$E$17,$D$12:$D$17)*(B41-LOOKUP(B41,$E$12:$E$17))/LOOKUP(B41,$E$12:$E$17,$C$12:$C$17) -> 67.989886 | D41: =RAND() -> 0.3291953 | E41: =RAND() -> 0.3317222 | F41: =RAND() -> 0.4169409 | G41: =RAND() -> 0.87772876 | H41: =RAND() -> 0.14720837 | I41: =RAND() -> 0.008780019 | J41: =RAND() -> 0.42194809 | K41: =RAND() -> 0.70360992 | ... S41: =RAND() -> 0.90932781 | T41: =LOOKUP(D41,$E$23:$E$26,$A$23:$A$26)+LOOKUP(D41,$E$23:$E$26,$D$23:$D$26)*(D41-LOOKUP(D41,$E$23:$E$26))/LOOKUP(D41,$E$23:$E$26,$C$23:$C$26) -> 4.5364941 | U41: =LOOKUP(E41,$E$23:$E$26,$A$23:$A$26)+LOOKUP(E41,$E$23:$E$26,$D$23:$D$26)*(E41-LOOKUP(E41,$E$23:$E$26))/LOOKUP(E41,$E$23:$E$26,$C$23:$C$26) -> 4.5396528 | V41: =LOOKUP(F41,$E$23:$E$26,$A$23:$A$26)+LOOKUP(F41,$E$23:$E$26,$D$23:$D$26)*(F41-LOOKUP(F41,$E$23:$E$26))/LOOKUP(F41,$E$23:$E$26,$C$23:$C$26) -> 4.6461761 | W41: =LOOKUP(G41,$E$23:$E$26,$A$23:$A$26)+LOOKUP(G41,$E$23:$E$26,$D$23:$D$26)*(G41-LOOKUP(G41,$E$23:$E$26))/LOOKUP(G41,$E$23:$E$26,$C$23:$C$26) -> 5.4443219 | X41: =LOOKUP(H41,$E$23:$E$26,$A$23:$A$26)+LOOKUP(H41,$E$23:$E$26,$D$23:$D$26)*(H41-LOOKUP(H41,$E$23:$E$26))/LOOKUP(H41,$E$23:$E$26,$C$23:$C$26) -> 4.2453473 | Y41: =LOOKUP(I41,$E$23:$E$26,$A$23:$A$26)+LOOKUP(I41,$E$23:$E$26,$D$23:$D$26)*(I41-LOOKUP(I41,$E$23:$E$26))/LOOKUP(I41,$E$23:$E$26,$C$23:$C$26) -> 4.0146334 | Z41: =LOOKUP(J41,$E$23:$E$26,$A$23:$A$26)+LOOKUP(J41,$E$23:$E$26,$D$23:$D$26)*(J41-LOOKUP(J41,$E$23:$E$26))/LOOKUP(J41,$E$23:$E$26,$C$23:$C$26) -> 4.6524351 | AA41: =LOOKUP(K41,$E$23:$E$26,$A$23:$A$26)+LOOKUP(K41,$E$23:$E$26,$D$23:$D$26)*(K41-LOOKUP(K41,$E$23:$E$26))/LOOKUP(K41,$E$23:$E$26,$C$23:$C$26) -> 5.0090248 | ... AI41: =LOOKUP(S41,$E$23:$E$26,$A$23:$A$26)+LOOKUP(S41,$E$23:$E$26,$D$23:$D$26)*(S41-LOOKUP(S41,$E$23:$E$26))/LOOKUP(S41,$E$23:$E$26,$C$23:$C$26) -> 5.546639 | AJ41: =SUM($T41:T41) -> 4.5364941 | AK41: =SUM($T41:U41) -> 9.0761469 | AL41: =SUM($T41:V41) -> 13.722323 | AM41: =SUM($T41:W41) -> 19.166645 | AN41: =SUM($T41:X41) -> 23.411992 | AO41: =SUM($T41:Y41) -> 27.426626 | AP41: =SUM($T41:Z41) -> 32.079061 | AQ41: =SUM($T41:AA41) -> 37.088085 | ... AY41: =SUM($T41:AI41) -> 76.593287 | AZ41: =MAX(C41-AJ41,0) -> 63.453392 | BA41: =MAX(C41-AK41,0) -> 58.913739 | BB41: =MAX(C41-AL41,0) -> 54.267563 | BC41: =MAX(C41-AM41,0) -> 48.823241 | BD41: =MAX(C41-AN41,0) -> 44.577894 | BE41: =MAX(C41-AO41,0) -> 40.56326 | BF41: =MAX(C41-AP41,0) -> 35.910825 | BG41: =MAX(C41-AQ41,0) -> 30.9018 | BH41: =MAX(C41-AR41,0) -> 26.431357 | BI41: =MAX(C41-AS41,0) -> 22.205246 | BJ41: =MAX(C41-AT41,0) -> 16.776918 | BK41: =MAX(C41-AU41,0) -> 11.766955 | BL41: =MAX(C41-AV41,0) -> 6.4896211 | BM41: =MAX(C41-AW41,0) -> 2.4453202 | BN41: =MAX(C41-AX41,0) -> 0 | BO41: =MAX(C41-AY41,0) -> 0
A42: 12 | B42: =RAND() -> 0.5041862 | C42: =LOOKUP(B42,$E$12:$E$17,$A$12:$A$17)+LOOKUP(B42,$E$12:$E$17,$D$12:$D$17)*(B42-LOOKUP(B42,$E$12:$E$17))/LOOKUP(B42,$E$12:$E$17,$C$12:$C$17) -> 64.236437 | D42: =RAND() -> 0.77792331 | E42: =RAND() -> 0.76264007 | F42: =RAND() -> 0.084190359 | G42: =RAND() -> 0.92714068 | H42: =RAND() -> 0.24371725 | I42: =RAND() -> 0.95850328 | J42: =RAND() -> 0.79552407 | K42: =RAND() -> 0.80855185 | ... S42: =RAND() -> 0.030082737 | T42: =LOOKUP(D42,$E$23:$E$26,$A$23:$A$26)+LOOKUP(D42,$E$23:$E$26,$D$23:$D$26)*(D42-LOOKUP(D42,$E$23:$E$26))/LOOKUP(D42,$E$23:$E$26,$C$23:$C$26) -> 5.1948083 | U42: =LOOKUP(E42,$E$23:$E$26,$A$23:$A$26)+LOOKUP(E42,$E$23:$E$26,$D$23:$D$26)*(E42-LOOKUP(E42,$E$23:$E$26))/LOOKUP(E42,$E$23:$E$26,$C$23:$C$26) -> 5.1566002 | V42: =LOOKUP(F42,$E$23:$E$26,$A$23:$A$26)+LOOKUP(F42,$E$23:$E$26,$D$23:$D$26)*(F42-LOOKUP(F42,$E$23:$E$26))/LOOKUP(F42,$E$23:$E$26,$C$23:$C$26) -> 4.1403173 | W42: =LOOKUP(G42,$E$23:$E$26,$A$23:$A$26)+LOOKUP(G42,$E$23:$E$26,$D$23:$D$26)*(G42-LOOKUP(G42,$E$23:$E$26))/LOOKUP(G42,$E$23:$E$26,$C$23:$C$26) -> 5.6357034 | X42: =LOOKUP(H42,$E$23:$E$26,$A$23:$A$26)+LOOKUP(H42,$E$23:$E$26,$D$23:$D$26)*(H42-LOOKUP(H42,$E$23:$E$26))/LOOKUP(H42,$E$23:$E$26,$C$23:$C$26) -> 4.4061954 | Y42: =LOOKUP(I42,$E$23:$E$26,$A$23:$A$26)+LOOKUP(I42,$E$23:$E$26,$D$23:$D$26)*(I42-LOOKUP(I42,$E$23:$E$26))/LOOKUP(I42,$E$23:$E$26,$C$23:$C$26) -> 5.7925164 | Z42: =LOOKUP(J42,$E$23:$E$26,$A$23:$A$26)+LOOKUP(J42,$E$23:$E$26,$D$23:$D$26)*(J42-LOOKUP(J42,$E$23:$E$26))/LOOKUP(J42,$E$23:$E$26,$C$23:$C$26) -> 5.2388102 | AA42: =LOOKUP(K42,$E$23:$E$26,$A$23:$A$26)+LOOKUP(K42,$E$23:$E$26,$D$23:$D$26)*(K42-LOOKUP(K42,$E$23:$E$26))/LOOKUP(K42,$E$23:$E$26,$C$23:$C$26) -> 5.2713796 | ... AI42: =LOOKUP(S42,$E$23:$E$26,$A$23:$A$26)+LOOKUP(S42,$E$23:$E$26,$D$23:$D$26)*(S42-LOOKUP(S42,$E$23:$E$26))/LOOKUP(S42,$E$23:$E$26,$C$23:$C$26) -> 4.0501379 | AJ42: =SUM($T42:T42) -> 5.1948083 | AK42: =SUM($T42:U42) -> 10.351408 | AL42: =SUM($T42:V42) -> 14.491726 | AM42: =SUM($T42:W42) -> 20.127429 | AN42: =SUM($T42:X42) -> 24.533625 | AO42: =SUM($T42:Y42) -> 30.326141 | AP42: =SUM($T42:Z42) -> 35.564951 | AQ42: =SUM($T42:AA42) -> 40.836331 | ... AY42: =SUM($T42:AI42) -> 77.991457 | AZ42: =MAX(C42-AJ42,0) -> 59.041628 | BA42: =MAX(C42-AK42,0) -> 53.885028 | BB42: =MAX(C42-AL42,0) -> 49.744711 | BC42: =MAX(C42-AM42,0) -> 44.109008 | BD42: =MAX(C42-AN42,0) -> 39.702812 | BE42: =MAX(C42-AO42,0) -> 33.910296 | BF42: =MAX(C42-AP42,0) -> 28.671486 | BG42: =MAX(C42-AQ42,0) -> 23.400106 | BH42: =MAX(C42-AR42,0) -> 18.811136 | BI42: =MAX(C42-AS42,0) -> 14.336794 | BJ42: =MAX(C42-AT42,0) -> 9.8406014 | BK42: =MAX(C42-AU42,0) -> 4.44054 | BL42: =MAX(C42-AV42,0) -> 0.41135473 | BM42: =MAX(C42-AW42,0) -> 0 | BN42: =MAX(C42-AX42,0) -> 0 | BO42: =MAX(C42-AY42,0) -> 0
... A280: 250 | B280: =RAND() -> 0.34533972 | C280: =LOOKUP(B280,$E$12:$E$17,$A$12:$A$17)+LOOKUP(B280,$E$12:$E$17,$D$12:$D$17)*(B280-LOOKUP(B280,$E$12:$E$17))/LOOKUP(B280,$E$12:$E$17,$C$12:$C$17) -> 61.588995 | D280: =RAND() -> 0.17182434 | E280: =RAND() -> 0.48287825 | F280: =RAND() -> 0.095241845 | G280: =RAND() -> 0.88289425 | H280: =RAND() -> 0.65294939 | I280: =RAND() -> 0.75029273 | J280: =RAND() -> 0.61032566 | K280: =RAND() -> 0.36788741 | ... S280: =RAND() -> 0.85583113 | T280: =LOOKUP(D280,$E$23:$E$26,$A$23:$A$26)+LOOKUP(D280,$E$23:$E$26,$D$23:$D$26)*(D280-LOOKUP(D280,$E$23:$E$26))/LOOKUP(D280,$E$23:$E$26,$C$23:$C$26) -> 4.2863739 | U280: =LOOKUP(E280,$E$23:$E$26,$A$23:$A$26)+LOOKUP(E280,$E$23:$E$26,$D$23:$D$26)*(E280-LOOKUP(E280,$E$23:$E$26))/LOOKUP(E280,$E$23:$E$26,$C$23:$C$26) -> 4.7285978 | V280: =LOOKUP(F280,$E$23:$E$26,$A$23:$A$26)+LOOKUP(F280,$E$23:$E$26,$D$23:$D$26)*(F280-LOOKUP(F280,$E$23:$E$26))/LOOKUP(F280,$E$23:$E$26,$C$23:$C$26) -> 4.1587364 | W280: =LOOKUP(G280,$E$23:$E$26,$A$23:$A$26)+LOOKUP(G280,$E$23:$E$26,$D$23:$D$26)*(G280-LOOKUP(G280,$E$23:$E$26))/LOOKUP(G280,$E$23:$E$26,$C$23:$C$26) -> 5.4572356 | X280: =LOOKUP(H280,$E$23:$E$26,$A$23:$A$26)+LOOKUP(H280,$E$23:$E$26,$D$23:$D$26)*(H280-LOOKUP(H280,$E$23:$E$26))/LOOKUP(H280,$E$23:$E$26,$C$23:$C$26) -> 4.9411867 | Y280: =LOOKUP(I280,$E$23:$E$26,$A$23:$A$26)+LOOKUP(I280,$E$23:$E$26,$D$23:$D$26)*(I280-LOOKUP(I280,$E$23:$E$26))/LOOKUP(I280,$E$23:$E$26,$C$23:$C$26) -> 5.1257318 | Z280: =LOOKUP(J280,$E$23:$E$26,$A$23:$A$26)+LOOKUP(J280,$E$23:$E$26,$D$23:$D$26)*(J280-LOOKUP(J280,$E$23:$E$26))/LOOKUP(J280,$E$23:$E$26,$C$23:$C$26) -> 4.8879071 | AA280: =LOOKUP(K280,$E$23:$E$26,$A$23:$A$26)+LOOKUP(K280,$E$23:$E$26,$D$23:$D$26)*(K280-LOOKUP(K280,$E$23:$E$26))/LOOKUP(K280,$E$23:$E$26,$C$23:$C$26) -> 4.5848593 | ... AI280: =LOOKUP(S280,$E$23:$E$26,$A$23:$A$26)+LOOKUP(S280,$E$23:$E$26,$D$23:$D$26)*(S280-LOOKUP(S280,$E$23:$E$26))/LOOKUP(S280,$E$23:$E$26,$C$23:$C$26) -> 5.3895778 | AJ280: =SUM($T280:T280) -> 4.2863739 | AK280: =SUM($T280:U280) -> 9.0149717 | AL280: =SUM($T280:V280) -> 13.173708 | AM280: =SUM($T280:W280) -> 18.630944 | AN280: =SUM($T280:X280) -> 23.57213 | AO280: =SUM($T280:Y280) -> 28.697862 | AP280: =SUM($T280:Z280) -> 33.585769 | AQ280: =SUM($T280:AA280) -> 38.170629 | ... AY280: =SUM($T280:AI280) -> 76.170632 | AZ280: =MAX(C280-AJ280,0) -> 57.302621 | BA280: =MAX(C280-AK280,0) -> 52.574024 | BB280: =MAX(C280-AL280,0) -> 48.415287 | BC280: =MAX(C280-AM280,0) -> 42.958052 | BD280: =MAX(C280-AN280,0) -> 38.016865 | BE280: =MAX(C280-AO280,0) -> 32.891133 | BF280: =MAX(C280-AP280,0) -> 28.003226 | BG280: =MAX(C280-AQ280,0) -> 23.418367 | BH280: =MAX(C280-AR280,0) -> 19.067719 | BI280: =MAX(C280-AS280,0) -> 14.181291 | BJ280: =MAX(C280-AT280,0) -> 9.8948867 | BK280: =MAX(C280-AU280,0) -> 5.0981594 | BL280: =MAX(C280-AV280,0) -> 0.064646401 | BM280: =MAX(C280-AW280,0) -> 0 | BN280: =MAX(C280-AX280,0) -> 0 | BO280: =MAX(C280-AY280,0) -> 0
A282: Costo anual total según número de camiones (N)
A283: N (camiones) | B283: Toneladas excedentes/año | C283: Costo transporte externo | D283: Costo camiones | E283: Costo total anual
A284: 1 | B284: =SUM(AZ31:AZ280) -> 14871.344 | C284: =B284*$B$5 -> 1487134.4 | D284: =A284*$B$4 -> 100000 | E284: =C284+D284 -> 1587134.4
A285: 2 | B285: =SUM(BA31:BA280) -> 13651.82 | C285: =B285*$B$5 -> 1365182 | D285: =A285*$B$4 -> 200000 | E285: =C285+D285 -> 1565182
A286: 3 | B286: =SUM(BB31:BB280) -> 12447.897 | C286: =B286*$B$5 -> 1244789.7 | D286: =A286*$B$4 -> 300000 | E286: =C286+D286 -> 1544789.7
A287: 4 | B287: =SUM(BC31:BC280) -> 11239.155 | C287: =B287*$B$5 -> 1123915.5 | D287: =A287*$B$4 -> 400000 | E287: =C287+D287 -> 1523915.5
A288: 5 | B288: =SUM(BD31:BD280) -> 10036.648 | C288: =B288*$B$5 -> 1003664.8 | D288: =A288*$B$4 -> 500000 | E288: =C288+D288 -> 1503664.8
A289: 6 | B289: =SUM(BE31:BE280) -> 8845.0608 | C289: =B289*$B$5 -> 884506.08 | D289: =A289*$B$4 -> 600000 | E289: =C289+D289 -> 1484506.1
A290: 7 | B290: =SUM(BF31:BF280) -> 7640.472 | C290: =B290*$B$5 -> 764047.2 | D290: =A290*$B$4 -> 700000 | E290: =C290+D290 -> 1464047.2
A291: 8 | B291: =SUM(BG31:BG280) -> 6434.8706 | C291: =B291*$B$5 -> 643487.06 | D291: =A291*$B$4 -> 800000 | E291: =C291+D291 -> 1443487.1
A292: 9 | B292: =SUM(BH31:BH280) -> 5248.1425 | C292: =B292*$B$5 -> 524814.25 | D292: =A292*$B$4 -> 900000 | E292: =C292+D292 -> 1424814.2
A293: 10 | B293: =SUM(BI31:BI280) -> 4049.2749 | C293: =B293*$B$5 -> 404927.49 | D293: =A293*$B$4 -> 1000000 | E293: =C293+D293 -> 1404927.5
A294: 11 | B294: =SUM(BJ31:BJ280) -> 2879.1259 | C294: =B294*$B$5 -> 287912.59 | D294: =A294*$B$4 -> 1100000 | E294: =C294+D294 -> 1387912.6
A295: 12 | B295: =SUM(BK31:BK280) -> 1810.6662 | C295: =B295*$B$5 -> 181066.62 | D295: =A295*$B$4 -> 1200000 | E295: =C295+D295 -> 1381066.6
A296: 13 | B296: =SUM(BL31:BL280) -> 940.77371 | C296: =B296*$B$5 -> 94077.371 | D296: =A296*$B$4 -> 1300000 | E296: =C296+D296 -> 1394077.4
A297: 14 | B297: =SUM(BM31:BM280) -> 374.34533 | C297: =B297*$B$5 -> 37434.533 | D297: =A297*$B$4 -> 1400000 | E297: =C297+D297 -> 1437434.5
A298: 15 | B298: =SUM(BN31:BN280) -> 187.22638 | C298: =B298*$B$5 -> 18722.638 | D298: =A298*$B$4 -> 1500000 | E298: =C298+D298 -> 1518722.6
A299: 16 | B299: =SUM(BO31:BO280) -> 84.691116 | C299: =B299*$B$5 -> 8469.1116 | D299: =A299*$B$4 -> 1600000 | E299: =C299+D299 -> 1608469.1
A301: Número óptimo de camiones (menor costo total) | B301: =INDEX(A284:A299,MATCH(MIN(E284:E299),E284:E299,0)) -> 12
A302: Costo total anual mínimo | B302: =MIN(E284:E299) -> 1381066.6
