Workbook

Sheet Ejercicio 1 - Trapezoidal V
B1: Ejercicio 1 — Distribución Trapezoidal Método de Composición
B3: Parámetros
B4: a = | C4: 3 | G4: Debe cumplirse: 0 < a < b < c
B5: b = | C5: 7
B6: c = | C6: 10
B7: N° simulaciones = | C7: 1000
B9: Áreas (deducidas en la teoría, Paso 1)
B10: A1 = | C10: =C4/(-C4+C5+C6) -> 0.21428571
B11: A2 = | C11: =(2*C5-2*C4)/(-C4+C5+C6) -> 0.57142857
B12: A3 = | C12: =(C6-C5)/(-C4+C5+C6) -> 0.21428571
B13: Suma = | C13: =C10+C11+C12 -> 1 | F13: Región 1: X = a*√R Región 2: X = a + (b−a)*R Región 3: X = c − (c−b)*√(1−R)
B16: i | C16: R_region | D16: R_valor | E16: Región | F16: X | G16: Fórmula de X según región (Paso 5 de la teoría): Región 1 -> a*SQRT(R_valor) | Región 2 -> a+(b-a)*R_valor | Región 3 -> c-(c-b)*SQRT(1-R_valor)
B17: 1 | C17: =RAND() -> 0.50985324 | D17: =RAND() -> 0.5998261 | E17: =IF(C17<=$C$10,1,IF(C17<=$C$10+$C$11,2,3)) -> 2 | F17: =IF(E17=1,$C$4*SQRT(D17),IF(E17=2,$C$4+($C$5-$C$4)*D17,$C$6-($C$6-$C$5)*SQRT(1-D17))) -> 5.3993044
B18: 2 | C18: =RAND() -> 0.87091636 | D18: =RAND() -> 0.25724521 | E18: =IF(C18<=$C$10,1,IF(C18<=$C$10+$C$11,2,3)) -> 3 | F18: =IF(E18=1,$C$4*SQRT(D18),IF(E18=2,$C$4+($C$5-$C$4)*D18,$C$6-($C$6-$C$5)*SQRT(1-D18))) -> 7.4145033
B19: 3 | C19: =RAND() -> 0.53353241 | D19: =RAND() -> 0.12718183 | E19: =IF(C19<=$C$10,1,IF(C19<=$C$10+$C$11,2,3)) -> 2 | F19: =IF(E19=1,$C$4*SQRT(D19),IF(E19=2,$C$4+($C$5-$C$4)*D19,$C$6-($C$6-$C$5)*SQRT(1-D19))) -> 3.5087273
B20: 4 | C20: =RAND() -> 0.039578797 | D20: =RAND() -> 0.96776714 | E20: =IF(C20<=$C$10,1,IF(C20<=$C$10+$C$11,2,3)) -> 1 | F20: =IF(E20=1,$C$4*SQRT(D20),IF(E20=2,$C$4+($C$5-$C$4)*D20,$C$6-($C$6-$C$5)*SQRT(1-D20))) -> 2.9512547
B21: 5 | C21: =RAND() -> 0.56743481 | D21: =RAND() -> 0.095470759 | E21: =IF(C21<=$C$10,1,IF(C21<=$C$10+$C$11,2,3)) -> 2 | F21: =IF(E21=1,$C$4*SQRT(D21),IF(E21=2,$C$4+($C$5-$C$4)*D21,$C$6-($C$6-$C$5)*SQRT(1-D21))) -> 3.381883
B22: 6 | C22: =RAND() -> 0.45703949 | D22: =RAND() -> 0.41729593 | E22: =IF(C22<=$C$10,1,IF(C22<=$C$10+$C$11,2,3)) -> 2 | F22: =IF(E22=1,$C$4*SQRT(D22),IF(E22=2,$C$4+($C$5-$C$4)*D22,$C$6-($C$6-$C$5)*SQRT(1-D22))) -> 4.6691837
B23: 7 | C23: =RAND() -> 0.59957542 | D23: =RAND() -> 0.68451148 | E23: =IF(C23<=$C$10,1,IF(C23<=$C$10+$C$11,2,3)) -> 2 | F23: =IF(E23=1,$C$4*SQRT(D23),IF(E23=2,$C$4+($C$5-$C$4)*D23,$C$6-($C$6-$C$5)*SQRT(1-D23))) -> 5.7380459
B24: 8 | C24: =RAND() -> 0.12505711 | D24: =RAND() -> 0.82649769 | E24: =IF(C24<=$C$10,1,IF(C24<=$C$10+$C$11,2,3)) -> 1 | F24: =IF(E24=1,$C$4*SQRT(D24),IF(E24=2,$C$4+($C$5-$C$4)*D24,$C$6-($C$6-$C$5)*SQRT(1-D24))) -> 2.7273575
B25: 9 | C25: =RAND() -> 0.7449589 | D25: =RAND() -> 0.77617766 | E25: =IF(C25<=$C$10,1,IF(C25<=$C$10+$C$11,2,3)) -> 2 | F25: =IF(E25=1,$C$4*SQRT(D25),IF(E25=2,$C$4+($C$5-$C$4)*D25,$C$6-($C$6-$C$5)*SQRT(1-D25))) -> 6.1047106
B26: 10 | C26: =RAND() -> 0.29217048 | D26: =RAND() -> 0.31280412 | E26: =IF(C26<=$C$10,1,IF(C26<=$C$10+$C$11,2,3)) -> 2 | F26: =IF(E26=1,$C$4*SQRT(D26),IF(E26=2,$C$4+($C$5-$C$4)*D26,$C$6-($C$6-$C$5)*SQRT(1-D26))) -> 4.2512165
B27: 11 | C27: =RAND() -> 0.03712624 | D27: =RAND() -> 0.21177364 | E27: =IF(C27<=$C$10,1,IF(C27<=$C$10+$C$11,2,3)) -> 1 | F27: =IF(E27=1,$C$4*SQRT(D27),IF(E27=2,$C$4+($C$5-$C$4)*D27,$C$6-($C$6-$C$5)*SQRT(1-D27))) -> 1.3805661
B28: 12 | C28: =RAND() -> 0.94116552 | D28: =RAND() -> 0.86884693 | E28: =IF(C28<=$C$10,1,IF(C28<=$C$10+$C$11,2,3)) -> 3 | F28: =IF(E28=1,$C$4*SQRT(D28),IF(E28=2,$C$4+($C$5-$C$4)*D28,$C$6-($C$6-$C$5)*SQRT(1-D28))) -> 8.9135481
... B1016: 1000 | C1016: =RAND() -> 0.086363534 | D1016: =RAND() -> 0.12037865 | E1016: =IF(C1016<=$C$10,1,IF(C1016<=$C$10+$C$11,2,3)) -> 1 | F1016: =IF(E1016=1,$C$4*SQRT(D1016),IF(E1016=2,$C$4+($C$5-$C$4)*D1016,$C$6-($C$6-$C$5)*SQRT(1-D1016))) -> 1.0408688
B1018: Promedio X = | C1018: =AVERAGE(F17:F1016) -> 4.9110382
B1019: Mínimo X = | C1019: =MIN(F17:F1016) -> 0.052209938
B1020: Máximo X = | C1020: =MAX(F17:F1016) -> 9.7179121
B1023: Histograma vs. densidad teórica (dominio [0, c])
H1024: h (altura meseta) = | I1024: =2/(-C4+C5+C6) -> 0.14285714
B1025: Bin | C1025: Lím. inf. | D1025: Lím. sup. | E1025: Punto medio | F1025: Frecuencia | G1025: Densidad emp. | H1025: Densidad teór.
B1026: 1 | C1026: =($C$6/20)*0 -> 0 | D1026: =($C$6/20)*1 -> 0.5 | E1026: =(C1026+D1026)/2 -> 0.25 | F1026: =COUNTIFS($F$17:$F$1016,">="&C1026,$F$17:$F$1016,"<"&D1026) -> 12 | G1026: =F1026/($C$7*(D1026-C1026)) -> 0.024 | H1026: =IF(E1026<=$C$4,$I$1024*E1026/$C$4,IF(E1026<=$C$5,$I$1024,$I$1024*($C$6-E1026)/($C$6-$C$5))) -> 0.011904762
B1027: 2 | C1027: =($C$6/20)*1 -> 0.5 | D1027: =($C$6/20)*2 -> 1 | E1027: =(C1027+D1027)/2 -> 0.75 | F1027: =COUNTIFS($F$17:$F$1016,">="&C1027,$F$17:$F$1016,"<"&D1027) -> 13 | G1027: =F1027/($C$7*(D1027-C1027)) -> 0.026 | H1027: =IF(E1027<=$C$4,$I$1024*E1027/$C$4,IF(E1027<=$C$5,$I$1024,$I$1024*($C$6-E1027)/($C$6-$C$5))) -> 0.035714286
B1028: 3 | C1028: =($C$6/20)*2 -> 1 | D1028: =($C$6/20)*3 -> 1.5 | E1028: =(C1028+D1028)/2 -> 1.25 | F1028: =COUNTIFS($F$17:$F$1016,">="&C1028,$F$17:$F$1016,"<"&D1028) -> 33 | G1028: =F1028/($C$7*(D1028-C1028)) -> 0.066 | H1028: =IF(E1028<=$C$4,$I$1024*E1028/$C$4,IF(E1028<=$C$5,$I$1024,$I$1024*($C$6-E1028)/($C$6-$C$5))) -> 0.05952381
B1029: 4 | C1029: =($C$6/20)*3 -> 1.5 | D1029: =($C$6/20)*4 -> 2 | E1029: =(C1029+D1029)/2 -> 1.75 | F1029: =COUNTIFS($F$17:$F$1016,">="&C1029,$F$17:$F$1016,"<"&D1029) -> 43 | G1029: =F1029/($C$7*(D1029-C1029)) -> 0.086 | H1029: =IF(E1029<=$C$4,$I$1024*E1029/$C$4,IF(E1029<=$C$5,$I$1024,$I$1024*($C$6-E1029)/($C$6-$C$5))) -> 0.083333333
B1030: 5 | C1030: =($C$6/20)*4 -> 2 | D1030: =($C$6/20)*5 -> 2.5 | E1030: =(C1030+D1030)/2 -> 2.25 | F1030: =COUNTIFS($F$17:$F$1016,">="&C1030,$F$17:$F$1016,"<"&D1030) -> 49 | G1030: =F1030/($C$7*(D1030-C1030)) -> 0.098 | H1030: =IF(E1030<=$C$4,$I$1024*E1030/$C$4,IF(E1030<=$C$5,$I$1024,$I$1024*($C$6-E1030)/($C$6-$C$5))) -> 0.10714286
B1031: 6 | C1031: =($C$6/20)*5 -> 2.5 | D1031: =($C$6/20)*6 -> 3 | E1031: =(C1031+D1031)/2 -> 2.75 | F1031: =COUNTIFS($F$17:$F$1016,">="&C1031,$F$17:$F$1016,"<"&D1031) -> 68 | G1031: =F1031/($C$7*(D1031-C1031)) -> 0.136 | H1031: =IF(E1031<=$C$4,$I$1024*E1031/$C$4,IF(E1031<=$C$5,$I$1024,$I$1024*($C$6-E1031)/($C$6-$C$5))) -> 0.13095238
B1032: 7 | C1032: =($C$6/20)*6 -> 3 | D1032: =($C$6/20)*7 -> 3.5 | E1032: =(C1032+D1032)/2 -> 3.25 | F1032: =COUNTIFS($F$17:$F$1016,">="&C1032,$F$17:$F$1016,"<"&D1032) -> 69 | G1032: =F1032/($C$7*(D1032-C1032)) -> 0.138 | H1032: =IF(E1032<=$C$4,$I$1024*E1032/$C$4,IF(E1032<=$C$5,$I$1024,$I$1024*($C$6-E1032)/($C$6-$C$5))) -> 0.14285714
B1033: 8 | C1033: =($C$6/20)*7 -> 3.5 | D1033: =($C$6/20)*8 -> 4 | E1033: =(C1033+D1033)/2 -> 3.75 | F1033: =COUNTIFS($F$17:$F$1016,">="&C1033,$F$17:$F$1016,"<"&D1033) -> 81 | G1033: =F1033/($C$7*(D1033-C1033)) -> 0.162 | H1033: =IF(E1033<=$C$4,$I$1024*E1033/$C$4,IF(E1033<=$C$5,$I$1024,$I$1024*($C$6-E1033)/($C$6-$C$5))) -> 0.14285714
B1034: 9 | C1034: =($C$6/20)*8 -> 4 | D1034: =($C$6/20)*9 -> 4.5 | E1034: =(C1034+D1034)/2 -> 4.25 | F1034: =COUNTIFS($F$17:$F$1016,">="&C1034,$F$17:$F$1016,"<"&D1034) -> 95 | G1034: =F1034/($C$7*(D1034-C1034)) -> 0.19 | H1034: =IF(E1034<=$C$4,$I$1024*E1034/$C$4,IF(E1034<=$C$5,$I$1024,$I$1024*($C$6-E1034)/($C$6-$C$5))) -> 0.14285714
B1035: 10 | C1035: =($C$6/20)*9 -> 4.5 | D1035: =($C$6/20)*10 -> 5 | E1035: =(C1035+D1035)/2 -> 4.75 | F1035: =COUNTIFS($F$17:$F$1016,">="&C1035,$F$17:$F$1016,"<"&D1035) -> 80 | G1035: =F1035/($C$7*(D1035-C1035)) -> 0.16 | H1035: =IF(E1035<=$C$4,$I$1024*E1035/$C$4,IF(E1035<=$C$5,$I$1024,$I$1024*($C$6-E1035)/($C$6-$C$5))) -> 0.14285714
B1036: 11 | C1036: =($C$6/20)*10 -> 5 | D1036: =($C$6/20)*11 -> 5.5 | E1036: =(C1036+D1036)/2 -> 5.25 | F1036: =COUNTIFS($F$17:$F$1016,">="&C1036,$F$17:$F$1016,"<"&D1036) -> 64 | G1036: =F1036/($C$7*(D1036-C1036)) -> 0.128 | H1036: =IF(E1036<=$C$4,$I$1024*E1036/$C$4,IF(E1036<=$C$5,$I$1024,$I$1024*($C$6-E1036)/($C$6-$C$5))) -> 0.14285714
B1037: 12 | C1037: =($C$6/20)*11 -> 5.5 | D1037: =($C$6/20)*12 -> 6 | E1037: =(C1037+D1037)/2 -> 5.75 | F1037: =COUNTIFS($F$17:$F$1016,">="&C1037,$F$17:$F$1016,"<"&D1037) -> 59 | G1037: =F1037/($C$7*(D1037-C1037)) -> 0.118 | H1037: =IF(E1037<=$C$4,$I$1024*E1037/$C$4,IF(E1037<=$C$5,$I$1024,$I$1024*($C$6-E1037)/($C$6-$C$5))) -> 0.14285714
B1038: 13 | C1038: =($C$6/20)*12 -> 6 | D1038: =($C$6/20)*13 -> 6.5 | E1038: =(C1038+D1038)/2 -> 6.25 | F1038: =COUNTIFS($F$17:$F$1016,">="&C1038,$F$17:$F$1016,"<"&D1038) -> 54 | G1038: =F1038/($C$7*(D1038-C1038)) -> 0.108 | H1038: =IF(E1038<=$C$4,$I$1024*E1038/$C$4,IF(E1038<=$C$5,$I$1024,$I$1024*($C$6-E1038)/($C$6-$C$5))) -> 0.14285714
B1039: 14 | C1039: =($C$6/20)*13 -> 6.5 | D1039: =($C$6/20)*14 -> 7 | E1039: =(C1039+D1039)/2 -> 6.75 | F1039: =COUNTIFS($F$17:$F$1016,">="&C1039,$F$17:$F$1016,"<"&D1039) -> 61 | G1039: =F1039/($C$7*(D1039-C1039)) -> 0.122 | H1039: =IF(E1039<=$C$4,$I$1024*E1039/$C$4,IF(E1039<=$C$5,$I$1024,$I$1024*($C$6-E1039)/($C$6-$C$5))) -> 0.14285714
B1040: 15 | C1040: =($C$6/20)*14 -> 7 | D1040: =($C$6/20)*15 -> 7.5 | E1040: =(C1040+D1040)/2 -> 7.25 | F1040: =COUNTIFS($F$17:$F$1016,">="&C1040,$F$17:$F$1016,"<"&D1040) -> 65 | G1040: =F1040/($C$7*(D1040-C1040)) -> 0.13 | H1040: =IF(E1040<=$C$4,$I$1024*E1040/$C$4,IF(E1040<=$C$5,$I$1024,$I$1024*($C$6-E1040)/($C$6-$C$5))) -> 0.13095238
B1041: 16 | C1041: =($C$6/20)*15 -> 7.5 | D1041: =($C$6/20)*16 -> 8 | E1041: =(C1041+D1041)/2 -> 7.75 | F1041: =COUNTIFS($F$17:$F$1016,">="&C1041,$F$17:$F$1016,"<"&D1041) -> 58 | G1041: =F1041/($C$7*(D1041-C1041)) -> 0.116 | H1041: =IF(E1041<=$C$4,$I$1024*E1041/$C$4,IF(E1041<=$C$5,$I$1024,$I$1024*($C$6-E1041)/($C$6-$C$5))) -> 0.10714286
B1042: 17 | C1042: =($C$6/20)*16 -> 8 | D1042: =($C$6/20)*17 -> 8.5 | E1042: =(C1042+D1042)/2 -> 8.25 | F1042: =COUNTIFS($F$17:$F$1016,">="&C1042,$F$17:$F$1016,"<"&D1042) -> 40 | G1042: =F1042/($C$7*(D1042-C1042)) -> 0.08 | H1042: =IF(E1042<=$C$4,$I$1024*E1042/$C$4,IF(E1042<=$C$5,$I$1024,$I$1024*($C$6-E1042)/($C$6-$C$5))) -> 0.083333333
B1043: 18 | C1043: =($C$6/20)*17 -> 8.5 | D1043: =($C$6/20)*18 -> 9 | E1043: =(C1043+D1043)/2 -> 8.75 | F1043: =COUNTIFS($F$17:$F$1016,">="&C1043,$F$17:$F$1016,"<"&D1043) -> 33 | G1043: =F1043/($C$7*(D1043-C1043)) -> 0.066 | H1043: =IF(E1043<=$C$4,$I$1024*E1043/$C$4,IF(E1043<=$C$5,$I$1024,$I$1024*($C$6-E1043)/($C$6-$C$5))) -> 0.05952381
B1044: 19 | C1044: =($C$6/20)*18 -> 9 | D1044: =($C$6/20)*19 -> 9.5 | E1044: =(C1044+D1044)/2 -> 9.25 | F1044: =COUNTIFS($F$17:$F$1016,">="&C1044,$F$17:$F$1016,"<"&D1044) -> 17 | G1044: =F1044/($C$7*(D1044-C1044)) -> 0.034 | H1044: =IF(E1044<=$C$4,$I$1024*E1044/$C$4,IF(E1044<=$C$5,$I$1024,$I$1024*($C$6-E1044)/($C$6-$C$5))) -> 0.035714286
B1045: 20 | C1045: =($C$6/20)*19 -> 9.5 | D1045: =($C$6/20)*20 -> 10 | E1045: =(C1045+D1045)/2 -> 9.75 | F1045: =COUNTIFS($F$17:$F$1016,">="&C1045,$F$17:$F$1016,"<"&D1045) -> 6 | G1045: =F1045/($C$7*(D1045-C1045)) -> 0.012 | H1045: =IF(E1045<=$C$4,$I$1024*E1045/$C$4,IF(E1045<=$C$5,$I$1024,$I$1024*($C$6-E1045)/($C$6-$C$5))) -> 0.011904762

Sheet Ejercicio 2 - Triangular V
B1: Ejercicio 2 — Distribución Triangular Método de Composición
B3: Parámetros
B4: a (punto 1) = | C4: 8 | G4: Debe cumplirse: a < c < b
B5: c (vértice) = | C5: 9
B6: b (punto 3) = | C6: 10
B7: N° simulaciones = | C7: 1000
B9: Áreas (Paso 1 de la teoría)
B10: A1 = | C10: =(C5-C4)/(C6-C4) -> 0.5
B11: A2 = | C11: =(C6-C5)/(C6-C4) -> 0.5
B12: Suma = | C12: =C10+C11 -> 1
B16: iteracion | C16: R_region | D16: R_valor | E16: Region | F16: X
B17: 1 | C17: =RAND() -> 0.51193726 | D17: =RAND() -> 0.68239737 | E17: =IF(C17<=$C$10,1,2) -> 2 | F17: =IF(E17=1,$C$4+SQRT(D17*($C$6-$C$4)*($C$5-$C$4)),$C$6-SQRT((1-D17)*($C$6-$C$4)*($C$6-$C$5))) -> 9.2030023
B18: 2 | C18: =RAND() -> 0.17642894 | D18: =RAND() -> 0.34367827 | E18: =IF(C18<=$C$10,1,2) -> 1 | F18: =IF(E18=1,$C$4+SQRT(D18*($C$6-$C$4)*($C$5-$C$4)),$C$6-SQRT((1-D18)*($C$6-$C$4)*($C$6-$C$5))) -> 8.8290697
B19: 3 | C19: =RAND() -> 0.62437814 | D19: =RAND() -> 0.4347957 | E19: =IF(C19<=$C$10,1,2) -> 2 | F19: =IF(E19=1,$C$4+SQRT(D19*($C$6-$C$4)*($C$5-$C$4)),$C$6-SQRT((1-D19)*($C$6-$C$4)*($C$6-$C$5))) -> 8.9367932
B20: 4 | C20: =RAND() -> 0.89771039 | D20: =RAND() -> 0.20628556 | E20: =IF(C20<=$C$10,1,2) -> 2 | F20: =IF(E20=1,$C$4+SQRT(D20*($C$6-$C$4)*($C$5-$C$4)),$C$6-SQRT((1-D20)*($C$6-$C$4)*($C$6-$C$5))) -> 8.7400679
B21: 5 | C21: =RAND() -> 0.21259379 | D21: =RAND() -> 0.30154255 | E21: =IF(C21<=$C$10,1,2) -> 1 | F21: =IF(E21=1,$C$4+SQRT(D21*($C$6-$C$4)*($C$5-$C$4)),$C$6-SQRT((1-D21)*($C$6-$C$4)*($C$6-$C$5))) -> 8.7765855
B22: 6 | C22: =RAND() -> 0.89425587 | D22: =RAND() -> 0.20207486 | E22: =IF(C22<=$C$10,1,2) -> 2 | F22: =IF(E22=1,$C$4+SQRT(D22*($C$6-$C$4)*($C$5-$C$4)),$C$6-SQRT((1-D22)*($C$6-$C$4)*($C$6-$C$5))) -> 8.7367303
B23: 7 | C23: =RAND() -> 0.79858053 | D23: =RAND() -> 0.26435538 | E23: =IF(C23<=$C$10,1,2) -> 2 | F23: =IF(E23=1,$C$4+SQRT(D23*($C$6-$C$4)*($C$5-$C$4)),$C$6-SQRT((1-D23)*($C$6-$C$4)*($C$6-$C$5))) -> 8.7870329
B24: 8 | C24: =RAND() -> 0.4767185 | D24: =RAND() -> 0.61853512 | E24: =IF(C24<=$C$10,1,2) -> 1 | F24: =IF(E24=1,$C$4+SQRT(D24*($C$6-$C$4)*($C$5-$C$4)),$C$6-SQRT((1-D24)*($C$6-$C$4)*($C$6-$C$5))) -> 9.1122366
B25: 9 | C25: =RAND() -> 0.026438389 | D25: =RAND() -> 0.76266291 | E25: =IF(C25<=$C$10,1,2) -> 1 | F25: =IF(E25=1,$C$4+SQRT(D25*($C$6-$C$4)*($C$5-$C$4)),$C$6-SQRT((1-D25)*($C$6-$C$4)*($C$6-$C$5))) -> 9.2350408
B26: 10 | C26: =RAND() -> 0.16560435 | D26: =RAND() -> 0.57434596 | E26: =IF(C26<=$C$10,1,2) -> 1 | F26: =IF(E26=1,$C$4+SQRT(D26*($C$6-$C$4)*($C$5-$C$4)),$C$6-SQRT((1-D26)*($C$6-$C$4)*($C$6-$C$5))) -> 9.0717705
B27: 11 | C27: =RAND() -> 0.48269134 | D27: =RAND() -> 0.71878955 | E27: =IF(C27<=$C$10,1,2) -> 1 | F27: =IF(E27=1,$C$4+SQRT(D27*($C$6-$C$4)*($C$5-$C$4)),$C$6-SQRT((1-D27)*($C$6-$C$4)*($C$6-$C$5))) -> 9.1989909
B28: 12 | C28: =RAND() -> 0.67832309 | D28: =RAND() -> 0.35218407 | E28: =IF(C28<=$C$10,1,2) -> 2 | F28: =IF(E28=1,$C$4+SQRT(D28*($C$6-$C$4)*($C$5-$C$4)),$C$6-SQRT((1-D28)*($C$6-$C$4)*($C$6-$C$5))) -> 8.8617417
... B1016: 1000 | C1016: =RAND() -> 0.32997644 | D1016: =RAND() -> 0.74283138 | E1016: =IF(C1016<=$C$10,1,2) -> 1 | F1016: =IF(E1016=1,$C$4+SQRT(D1016*($C$6-$C$4)*($C$5-$C$4)),$C$6-SQRT((1-D1016)*($C$6-$C$4)*($C$6-$C$5))) -> 9.2188777
B1018: Promedio X = | C1018: =AVERAGE(F17:F1016) -> 8.9869469
B1019: Mínimo X = | C1019: =MIN(F17:F1016) -> 8.1166267
B1020: Máximo X = | C1020: =MAX(F17:F1016) -> 9.9418915
B1023: Histograma vs. densidad teórica (dominio [a, b])
B1024: Bin | C1024: Lím. inf. | D1024: Lím. sup. | E1024: Punto medio | F1024: Frecuencia | G1024: Densidad emp. | H1024: Densidad teór.
B1025: 1 | C1025: =$C$4+(($C$6-$C$4)/20)*0 -> 8 | D1025: =$C$4+(($C$6-$C$4)/20)*1 -> 8.1 | E1025: =(C1025+D1025)/2 -> 8.05 | F1025: =COUNTIFS($F$17:$F$1016,">="&C1025,$F$17:$F$1016,"<"&D1025) -> 0 | G1025: =F1025/($C$7*(D1025-C1025)) -> 0 | H1025: =IF(E1025<=$C$5,2*(E1025-$C$4)/(($C$6-$C$4)*($C$5-$C$4)),2*($C$6-E1025)/(($C$6-$C$4)*($C$6-$C$5))) -> 0.05
B1026: 2 | C1026: =$C$4+(($C$6-$C$4)/20)*1 -> 8.1 | D1026: =$C$4+(($C$6-$C$4)/20)*2 -> 8.2 | E1026: =(C1026+D1026)/2 -> 8.15 | F1026: =COUNTIFS($F$17:$F$1016,">="&C1026,$F$17:$F$1016,"<"&D1026) -> 11 | G1026: =F1026/($C$7*(D1026-C1026)) -> 0.11 | H1026: =IF(E1026<=$C$5,2*(E1026-$C$4)/(($C$6-$C$4)*($C$5-$C$4)),2*($C$6-E1026)/(($C$6-$C$4)*($C$6-$C$5))) -> 0.15
B1027: 3 | C1027: =$C$4+(($C$6-$C$4)/20)*2 -> 8.2 | D1027: =$C$4+(($C$6-$C$4)/20)*3 -> 8.3 | E1027: =(C1027+D1027)/2 -> 8.25 | F1027: =COUNTIFS($F$17:$F$1016,">="&C1027,$F$17:$F$1016,"<"&D1027) -> 18 | G1027: =F1027/($C$7*(D1027-C1027)) -> 0.18 | H1027: =IF(E1027<=$C$5,2*(E1027-$C$4)/(($C$6-$C$4)*($C$5-$C$4)),2*($C$6-E1027)/(($C$6-$C$4)*($C$6-$C$5))) -> 0.25
B1028: 4 | C1028: =$C$4+(($C$6-$C$4)/20)*3 -> 8.3 | D1028: =$C$4+(($C$6-$C$4)/20)*4 -> 8.4 | E1028: =(C1028+D1028)/2 -> 8.35 | F1028: =COUNTIFS($F$17:$F$1016,">="&C1028,$F$17:$F$1016,"<"&D1028) -> 16 | G1028: =F1028/($C$7*(D1028-C1028)) -> 0.16 | H1028: =IF(E1028<=$C$5,2*(E1028-$C$4)/(($C$6-$C$4)*($C$5-$C$4)),2*($C$6-E1028)/(($C$6-$C$4)*($C$6-$C$5))) -> 0.35
B1029: 5 | C1029: =$C$4+(($C$6-$C$4)/20)*4 -> 8.4 | D1029: =$C$4+(($C$6-$C$4)/20)*5 -> 8.5 | E1029: =(C1029+D1029)/2 -> 8.45 | F1029: =COUNTIFS($F$17:$F$1016,">="&C1029,$F$17:$F$1016,"<"&D1029) -> 24 | G1029: =F1029/($C$7*(D1029-C1029)) -> 0.24 | H1029: =IF(E1029<=$C$5,2*(E1029-$C$4)/(($C$6-$C$4)*($C$5-$C$4)),2*($C$6-E1029)/(($C$6-$C$4)*($C$6-$C$5))) -> 0.45
B1030: 6 | C1030: =$C$4+(($C$6-$C$4)/20)*5 -> 8.5 | D1030: =$C$4+(($C$6-$C$4)/20)*6 -> 8.6 | E1030: =(C1030+D1030)/2 -> 8.55 | F1030: =COUNTIFS($F$17:$F$1016,">="&C1030,$F$17:$F$1016,"<"&D1030) -> 32 | G1030: =F1030/($C$7*(D1030-C1030)) -> 0.32 | H1030: =IF(E1030<=$C$5,2*(E1030-$C$4)/(($C$6-$C$4)*($C$5-$C$4)),2*($C$6-E1030)/(($C$6-$C$4)*($C$6-$C$5))) -> 0.55
B1031: 7 | C1031: =$C$4+(($C$6-$C$4)/20)*6 -> 8.6 | D1031: =$C$4+(($C$6-$C$4)/20)*7 -> 8.7 | E1031: =(C1031+D1031)/2 -> 8.65 | F1031: =COUNTIFS($F$17:$F$1016,">="&C1031,$F$17:$F$1016,"<"&D1031) -> 97 | G1031: =F1031/($C$7*(D1031-C1031)) -> 0.97 | H1031: =IF(E1031<=$C$5,2*(E1031-$C$4)/(($C$6-$C$4)*($C$5-$C$4)),2*($C$6-E1031)/(($C$6-$C$4)*($C$6-$C$5))) -> 0.65
B1032: 8 | C1032: =$C$4+(($C$6-$C$4)/20)*7 -> 8.7 | D1032: =$C$4+(($C$6-$C$4)/20)*8 -> 8.8 | E1032: =(C1032+D1032)/2 -> 8.75 | F1032: =COUNTIFS($F$17:$F$1016,">="&C1032,$F$17:$F$1016,"<"&D1032) -> 110 | G1032: =F1032/($C$7*(D1032-C1032)) -> 1.1 | H1032: =IF(E1032<=$C$5,2*(E1032-$C$4)/(($C$6-$C$4)*($C$5-$C$4)),2*($C$6-E1032)/(($C$6-$C$4)*($C$6-$C$5))) -> 0.75
B1033: 9 | C1033: =$C$4+(($C$6-$C$4)/20)*8 -> 8.8 | D1033: =$C$4+(($C$6-$C$4)/20)*9 -> 8.9 | E1033: =(C1033+D1033)/2 -> 8.85 | F1033: =COUNTIFS($F$17:$F$1016,">="&C1033,$F$17:$F$1016,"<"&D1033) -> 113 | G1033: =F1033/($C$7*(D1033-C1033)) -> 1.13 | H1033: =IF(E1033<=$C$5,2*(E1033-$C$4)/(($C$6-$C$4)*($C$5-$C$4)),2*($C$6-E1033)/(($C$6-$C$4)*($C$6-$C$5))) -> 0.85
B1034: 10 | C1034: =$C$4+(($C$6-$C$4)/20)*9 -> 8.9 | D1034: =$C$4+(($C$6-$C$4)/20)*10 -> 9 | E1034: =(C1034+D1034)/2 -> 8.95 | F1034: =COUNTIFS($F$17:$F$1016,">="&C1034,$F$17:$F$1016,"<"&D1034) -> 84 | G1034: =F1034/($C$7*(D1034-C1034)) -> 0.84 | H1034: =IF(E1034<=$C$5,2*(E1034-$C$4)/(($C$6-$C$4)*($C$5-$C$4)),2*($C$6-E1034)/(($C$6-$C$4)*($C$6-$C$5))) -> 0.95
B1035: 11 | C1035: =$C$4+(($C$6-$C$4)/20)*10 -> 9 | D1035: =$C$4+(($C$6-$C$4)/20)*11 -> 9.1 | E1035: =(C1035+D1035)/2 -> 9.05 | F1035: =COUNTIFS($F$17:$F$1016,">="&C1035,$F$17:$F$1016,"<"&D1035) -> 106 | G1035: =F1035/($C$7*(D1035-C1035)) -> 1.06 | H1035: =IF(E1035<=$C$5,2*(E1035-$C$4)/(($C$6-$C$4)*($C$5-$C$4)),2*($C$6-E1035)/(($C$6-$C$4)*($C$6-$C$5))) -> 0.95
B1036: 12 | C1036: =$C$4+(($C$6-$C$4)/20)*11 -> 9.1 | D1036: =$C$4+(($C$6-$C$4)/20)*12 -> 9.2 | E1036: =(C1036+D1036)/2 -> 9.15 | F1036: =COUNTIFS($F$17:$F$1016,">="&C1036,$F$17:$F$1016,"<"&D1036) -> 99 | G1036: =F1036/($C$7*(D1036-C1036)) -> 0.99 | H1036: =IF(E1036<=$C$5,2*(E1036-$C$4)/(($C$6-$C$4)*($C$5-$C$4)),2*($C$6-E1036)/(($C$6-$C$4)*($C$6-$C$5))) -> 0.85
B1037: 13 | C1037: =$C$4+(($C$6-$C$4)/20)*12 -> 9.2 | D1037: =$C$4+(($C$6-$C$4)/20)*13 -> 9.3 | E1037: =(C1037+D1037)/2 -> 9.25 | F1037: =COUNTIFS($F$17:$F$1016,">="&C1037,$F$17:$F$1016,"<"&D1037) -> 102 | G1037: =F1037/($C$7*(D1037-C1037)) -> 1.02 | H1037: =IF(E1037<=$C$5,2*(E1037-$C$4)/(($C$6-$C$4)*($C$5-$C$4)),2*($C$6-E1037)/(($C$6-$C$4)*($C$6-$C$5))) -> 0.75
B1038: 14 | C1038: =$C$4+(($C$6-$C$4)/20)*13 -> 9.3 | D1038: =$C$4+(($C$6-$C$4)/20)*14 -> 9.4 | E1038: =(C1038+D1038)/2 -> 9.35 | F1038: =COUNTIFS($F$17:$F$1016,">="&C1038,$F$17:$F$1016,"<"&D1038) -> 101 | G1038: =F1038/($C$7*(D1038-C1038)) -> 1.01 | H1038: =IF(E1038<=$C$5,2*(E1038-$C$4)/(($C$6-$C$4)*($C$5-$C$4)),2*($C$6-E1038)/(($C$6-$C$4)*($C$6-$C$5))) -> 0.65
B1039: 15 | C1039: =$C$4+(($C$6-$C$4)/20)*14 -> 9.4 | D1039: =$C$4+(($C$6-$C$4)/20)*15 -> 9.5 | E1039: =(C1039+D1039)/2 -> 9.45 | F1039: =COUNTIFS($F$17:$F$1016,">="&C1039,$F$17:$F$1016,"<"&D1039) -> 30 | G1039: =F1039/($C$7*(D1039-C1039)) -> 0.3 | H1039: =IF(E1039<=$C$5,2*(E1039-$C$4)/(($C$6-$C$4)*($C$5-$C$4)),2*($C$6-E1039)/(($C$6-$C$4)*($C$6-$C$5))) -> 0.55
B1040: 16 | C1040: =$C$4+(($C$6-$C$4)/20)*15 -> 9.5 | D1040: =$C$4+(($C$6-$C$4)/20)*16 -> 9.6 | E1040: =(C1040+D1040)/2 -> 9.55 | F1040: =COUNTIFS($F$17:$F$1016,">="&C1040,$F$17:$F$1016,"<"&D1040) -> 22 | G1040: =F1040/($C$7*(D1040-C1040)) -> 0.22 | H1040: =IF(E1040<=$C$5,2*(E1040-$C$4)/(($C$6-$C$4)*($C$5-$C$4)),2*($C$6-E1040)/(($C$6-$C$4)*($C$6-$C$5))) -> 0.45
B1041: 17 | C1041: =$C$4+(($C$6-$C$4)/20)*16 -> 9.6 | D1041: =$C$4+(($C$6-$C$4)/20)*17 -> 9.7 | E1041: =(C1041+D1041)/2 -> 9.65 | F1041: =COUNTIFS($F$17:$F$1016,">="&C1041,$F$17:$F$1016,"<"&D1041) -> 23 | G1041: =F1041/($C$7*(D1041-C1041)) -> 0.23 | H1041: =IF(E1041<=$C$5,2*(E1041-$C$4)/(($C$6-$C$4)*($C$5-$C$4)),2*($C$6-E1041)/(($C$6-$C$4)*($C$6-$C$5))) -> 0.35
B1042: 18 | C1042: =$C$4+(($C$6-$C$4)/20)*17 -> 9.7 | D1042: =$C$4+(($C$6-$C$4)/20)*18 -> 9.8 | E1042: =(C1042+D1042)/2 -> 9.75 | F1042: =COUNTIFS($F$17:$F$1016,">="&C1042,$F$17:$F$1016,"<"&D1042) -> 4 | G1042: =F1042/($C$7*(D1042-C1042)) -> 0.04 | H1042: =IF(E1042<=$C$5,2*(E1042-$C$4)/(($C$6-$C$4)*($C$5-$C$4)),2*($C$6-E1042)/(($C$6-$C$4)*($C$6-$C$5))) -> 0.25
B1043: 19 | C1043: =$C$4+(($C$6-$C$4)/20)*18 -> 9.8 | D1043: =$C$4+(($C$6-$C$4)/20)*19 -> 9.9 | E1043: =(C1043+D1043)/2 -> 9.85 | F1043: =COUNTIFS($F$17:$F$1016,">="&C1043,$F$17:$F$1016,"<"&D1043) -> 6 | G1043: =F1043/($C$7*(D1043-C1043)) -> 0.06 | H1043: =IF(E1043<=$C$5,2*(E1043-$C$4)/(($C$6-$C$4)*($C$5-$C$4)),2*($C$6-E1043)/(($C$6-$C$4)*($C$6-$C$5))) -> 0.15
B1044: 20 | C1044: =$C$4+(($C$6-$C$4)/20)*19 -> 9.9 | D1044: =$C$4+(($C$6-$C$4)/20)*20 -> 10 | E1044: =(C1044+D1044)/2 -> 9.95 | F1044: =COUNTIFS($F$17:$F$1016,">="&C1044,$F$17:$F$1016,"<"&D1044) -> 2 | G1044: =F1044/($C$7*(D1044-C1044)) -> 0.02 | H1044: =IF(E1044<=$C$5,2*(E1044-$C$4)/(($C$6-$C$4)*($C$5-$C$4)),2*($C$6-E1044)/(($C$6-$C$4)*($C$6-$C$5))) -> 0.05

Sheet Ejercicio 3 - TIR
B2: EJERCICIO 3 TIR del proyecto Compañía X
B4: Parámetros generales
B5: Tasa de impuestos (T) | D5: 0.5
B6: TREMA | D6: 0.15
B7: Vida fiscal del activo (años) | D7: 5
B8: Umbral de aceptación Prob(TIR>TREMA) | D8: 0.9
B9: Número de simulaciones | D9: 1000
B11: Activo fijo y activo circulante inicial (distribución triangular)
B12: Variable | C12: a (mínimo / optimista) | D12: b (moda / más probable) | E12: c (máximo / pesimista)
B13: Activo fijo inicial (AF) | C13: 60000 | D13: 70000 | E13: 100000
B14: Activo circulante inicial (AC) | C14: 25000 | D14: 30000 | E14: 40000
B16: Flujo de efectivo antes de impuestos, por año (triangular, igual los 5 años)
B17: Variable | C17: a (mínimo / optimista) | D17: b (moda / más probable) | E17: c (máximo / pesimista)
B18: Flujo antes de impuestos (x) | C18: 30000 | D18: 40000 | E18: 45000
B20: Tasas de inflación, por año (triangular)
B21: Año | C21: a (mínimo / optimista) | D21: b (moda / más probable) | E21: c (máximo / pesimista)
B22: 1 | C22: 0.12 | D22: 0.15 | E22: 0.18
B23: 2 | C23: 0.12 | D23: 0.15 | E23: 0.18
B24: 3 | C24: 0.15 | D24: 0.18 | E24: 0.22
B25: 4 | C25: 0.18 | D25: 0.2 | E25: 0.25
B26: 5 | C26: 0.19 | D26: 0.22 | E26: 0.28
B29: Extremos teóricos
B30: TIR mínima (todo pesimista) | D30: -0.031
B31: TIR máxima (todo optimista) | D31: 0.1991
B34: ── Resultados de la simulación ──
B35: Tabla de frecuencia acumulada de la TIR simulada (Pasos 3, 8 y 9)
B36: Intervalo # | C36: Límite inferior (%) | D36: Límite superior (%) | E36: Frecuencia | F36: Fracción | G36: Fracción acumulada
B37: 1 | C37: =$D$30*100 -> -3.1 | D37: =$D$30*100+($D$31*100-$D$30*100)/20*1 -> -1.9495 | E37: =COUNTIFS('Ejercicio 3 - Simulacion'!$BV$2:$BV$1001,">="&C37,'Ejercicio 3 - Simulacion'!$BV$2:$BV$1001,"<="&D37) -> 0 | F37: =E37/$D$9 -> 0 | G37: =F37 -> 0
B38: 2 | C38: =D37 -> -1.9495 | D38: =$D$30*100+($D$31*100-$D$30*100)/20*2 -> -0.799 | E38: =COUNTIFS('Ejercicio 3 - Simulacion'!$BV$2:$BV$1001,">"&C38,'Ejercicio 3 - Simulacion'!$BV$2:$BV$1001,"<="&D38) -> 0 | F38: =E38/$D$9 -> 0 | G38: =G37+F38 -> 0
B39: 3 | C39: =D38 -> -0.799 | D39: =$D$30*100+($D$31*100-$D$30*100)/20*3 -> 0.3515 | E39: =COUNTIFS('Ejercicio 3 - Simulacion'!$BV$2:$BV$1001,">"&C39,'Ejercicio 3 - Simulacion'!$BV$2:$BV$1001,"<="&D39) -> 0 | F39: =E39/$D$9 -> 0 | G39: =G38+F39 -> 0
B40: 4 | C40: =D39 -> 0.3515 | D40: =$D$30*100+($D$31*100-$D$30*100)/20*4 -> 1.502 | E40: =COUNTIFS('Ejercicio 3 - Simulacion'!$BV$2:$BV$1001,">"&C40,'Ejercicio 3 - Simulacion'!$BV$2:$BV$1001,"<="&D40) -> 0 | F40: =E40/$D$9 -> 0 | G40: =G39+F40 -> 0
B41: 5 | C41: =D40 -> 1.502 | D41: =$D$30*100+($D$31*100-$D$30*100)/20*5 -> 2.6525 | E41: =COUNTIFS('Ejercicio 3 - Simulacion'!$BV$2:$BV$1001,">"&C41,'Ejercicio 3 - Simulacion'!$BV$2:$BV$1001,"<="&D41) -> 3 | F41: =E41/$D$9 -> 0.003 | G41: =G40+F41 -> 0.003
B42: 6 | C42: =D41 -> 2.6525 | D42: =$D$30*100+($D$31*100-$D$30*100)/20*6 -> 3.803 | E42: =COUNTIFS('Ejercicio 3 - Simulacion'!$BV$2:$BV$1001,">"&C42,'Ejercicio 3 - Simulacion'!$BV$2:$BV$1001,"<="&D42) -> 30 | F42: =E42/$D$9 -> 0.03 | G42: =G41+F42 -> 0.033
B43: 7 | C43: =D42 -> 3.803 | D43: =$D$30*100+($D$31*100-$D$30*100)/20*7 -> 4.9535 | E43: =COUNTIFS('Ejercicio 3 - Simulacion'!$BV$2:$BV$1001,">"&C43,'Ejercicio 3 - Simulacion'!$BV$2:$BV$1001,"<="&D43) -> 74 | F43: =E43/$D$9 -> 0.074 | G43: =G42+F43 -> 0.107
B44: 8 | C44: =D43 -> 4.9535 | D44: =$D$30*100+($D$31*100-$D$30*100)/20*8 -> 6.104 | E44: =COUNTIFS('Ejercicio 3 - Simulacion'!$BV$2:$BV$1001,">"&C44,'Ejercicio 3 - Simulacion'!$BV$2:$BV$1001,"<="&D44) -> 146 | F44: =E44/$D$9 -> 0.146 | G44: =G43+F44 -> 0.253
B45: 9 | C45: =D44 -> 6.104 | D45: =$D$30*100+($D$31*100-$D$30*100)/20*9 -> 7.2545 | E45: =COUNTIFS('Ejercicio 3 - Simulacion'!$BV$2:$BV$1001,">"&C45,'Ejercicio 3 - Simulacion'!$BV$2:$BV$1001,"<="&D45) -> 176 | F45: =E45/$D$9 -> 0.176 | G45: =G44+F45 -> 0.429
B46: 10 | C46: =D45 -> 7.2545 | D46: =$D$30*100+($D$31*100-$D$30*100)/20*10 -> 8.405 | E46: =COUNTIFS('Ejercicio 3 - Simulacion'!$BV$2:$BV$1001,">"&C46,'Ejercicio 3 - Simulacion'!$BV$2:$BV$1001,"<="&D46) -> 193 | F46: =E46/$D$9 -> 0.193 | G46: =G45+F46 -> 0.622
B47: 11 | C47: =D46 -> 8.405 | D47: =$D$30*100+($D$31*100-$D$30*100)/20*11 -> 9.5555 | E47: =COUNTIFS('Ejercicio 3 - Simulacion'!$BV$2:$BV$1001,">"&C47,'Ejercicio 3 - Simulacion'!$BV$2:$BV$1001,"<="&D47) -> 187 | F47: =E47/$D$9 -> 0.187 | G47: =G46+F47 -> 0.809
B48: 12 | C48: =D47 -> 9.5555 | D48: =$D$30*100+($D$31*100-$D$30*100)/20*12 -> 10.706 | E48: =COUNTIFS('Ejercicio 3 - Simulacion'!$BV$2:$BV$1001,">"&C48,'Ejercicio 3 - Simulacion'!$BV$2:$BV$1001,"<="&D48) -> 112 | F48: =E48/$D$9 -> 0.112 | G48: =G47+F48 -> 0.921
B49: 13 | C49: =D48 -> 10.706 | D49: =$D$30*100+($D$31*100-$D$30*100)/20*13 -> 11.8565 | E49: =COUNTIFS('Ejercicio 3 - Simulacion'!$BV$2:$BV$1001,">"&C49,'Ejercicio 3 - Simulacion'!$BV$2:$BV$1001,"<="&D49) -> 52 | F49: =E49/$D$9 -> 0.052 | G49: =G48+F49 -> 0.973
B50: 14 | C50: =D49 -> 11.8565 | D50: =$D$30*100+($D$31*100-$D$30*100)/20*14 -> 13.007 | E50: =COUNTIFS('Ejercicio 3 - Simulacion'!$BV$2:$BV$1001,">"&C50,'Ejercicio 3 - Simulacion'!$BV$2:$BV$1001,"<="&D50) -> 20 | F50: =E50/$D$9 -> 0.02 | G50: =G49+F50 -> 0.993
B51: 15 | C51: =D50 -> 13.007 | D51: =$D$30*100+($D$31*100-$D$30*100)/20*15 -> 14.1575 | E51: =COUNTIFS('Ejercicio 3 - Simulacion'!$BV$2:$BV$1001,">"&C51,'Ejercicio 3 - Simulacion'!$BV$2:$BV$1001,"<="&D51) -> 6 | F51: =E51/$D$9 -> 0.006 | G51: =G50+F51 -> 0.999
B52: 16 | C52: =D51 -> 14.1575 | D52: =$D$30*100+($D$31*100-$D$30*100)/20*16 -> 15.308 | E52: =COUNTIFS('Ejercicio 3 - Simulacion'!$BV$2:$BV$1001,">"&C52,'Ejercicio 3 - Simulacion'!$BV$2:$BV$1001,"<="&D52) -> 1 | F52: =E52/$D$9 -> 0.001 | G52: =G51+F52 -> 1
B53: 17 | C53: =D52 -> 15.308 | D53: =$D$30*100+($D$31*100-$D$30*100)/20*17 -> 16.4585 | E53: =COUNTIFS('Ejercicio 3 - Simulacion'!$BV$2:$BV$1001,">"&C53,'Ejercicio 3 - Simulacion'!$BV$2:$BV$1001,"<="&D53) -> 0 | F53: =E53/$D$9 -> 0 | G53: =G52+F53 -> 1
B54: 18 | C54: =D53 -> 16.4585 | D54: =$D$30*100+($D$31*100-$D$30*100)/20*18 -> 17.609 | E54: =COUNTIFS('Ejercicio 3 - Simulacion'!$BV$2:$BV$1001,">"&C54,'Ejercicio 3 - Simulacion'!$BV$2:$BV$1001,"<="&D54) -> 0 | F54: =E54/$D$9 -> 0 | G54: =G53+F54 -> 1
B55: 19 | C55: =D54 -> 17.609 | D55: =$D$30*100+($D$31*100-$D$30*100)/20*19 -> 18.7595 | E55: =COUNTIFS('Ejercicio 3 - Simulacion'!$BV$2:$BV$1001,">"&C55,'Ejercicio 3 - Simulacion'!$BV$2:$BV$1001,"<="&D55) -> 0 | F55: =E55/$D$9 -> 0 | G55: =G54+F55 -> 1
B56: 20 | C56: =D55 -> 18.7595 | D56: =$D$30*100+($D$31*100-$D$30*100)/20*20 -> 19.91 | E56: =COUNTIFS('Ejercicio 3 - Simulacion'!$BV$2:$BV$1001,">"&C56,'Ejercicio 3 - Simulacion'!$BV$2:$BV$1001,"<="&D56) -> 0 | F56: =E56/$D$9 -> 0 | G56: =G55+F56 -> 1
B59: Resultado principal
B60: Prob(TIR > TREMA) | D60: =COUNTIF('Ejercicio 3 - Simulacion'!$BV$2:$BV$1001,">"&($D$6*100))/$D$9 -> 0
B61: Umbral requerido por la administración | D61: =$D$8 -> 0.9
B62: Decisión | D62: =IF(D60>=D61,"ACEPTAR el proyecto","RECHAZAR el proyecto") -> RECHAZAR el proyecto
B65: Comparación y validación de resultados (Teórico / Excel / Java)
B66: Método | C66: Prob(TIR > TREMA) | D66: Decisión
B67: Teórico (libro, Tabla 5.6) | C67: 0 | D67: Rechazar
B68: Excel (esta simulación) | C68: =D60 -> 0 | D68: =D62 -> RECHAZAR el proyecto
B69: Java (completar con tu programa)

Sheet Ejercicio 3 - Simulacion
A1: N° sim | B1: R (AF) | C1: AF simulado | D1: R (AC) | E1: AC simulado | F1: R (x año 1) | G1: x año 1 | H1: R (x año 2) | I1: x año 2 | J1: R (x año 3) | K1: x año 3 | L1: R (x año 4) | M1: x año 4 | N1: R (x año 5) | O1: x año 5 | P1: R (i año 1) | Q1: i año 1 | R1: R (i año 2) | S1: i año 2 | T1: R (i año 3) | U1: i año 3 | V1: R (i año 4) | W1: i año 4 | X1: R (i año 5) | Y1: i año 5 | Z1: Inflación acum. año 1 | AA1: Inflación acum. año 2 | AB1: Inflación acum. año 3 | AC1: Inflación acum. año 4 | AD1: Inflación acum. año 5 | AE1: Inv. adicional AC año 1 | AF1: Inv. adicional AC año 2 | AG1: Inv. adicional AC año 3 | AH1: Inv. adicional AC año 4 | AI1: Inv. adicional AC año 5 | AJ1: Flujo antes imp. año 1 (corriente) | AK1: Flujo antes imp. año 2 (corriente) | AL1: Flujo antes imp. año 3 (corriente) | AM1: Flujo antes imp. año 4 (corriente) | AN1: Flujo antes imp. año 5 (corriente) | AO1: Depreciación (fija) | AP1: Ingreso gravable año 1 | AQ1: Ingreso gravable año 2 | AR1: Ingreso gravable año 3 | AS1: Ingreso gravable año 4 | AT1: Ingreso gravable año 5 | AU1: Impuestos año 1 | AV1: Impuestos año 2 | AW1: Impuestos año 3 | AX1: Impuestos año 4 | AY1: Impuestos año 5 | AZ1: Flujo desp. imp. año 1 (corriente) | BA1: Flujo desp. imp. año 2 (corriente) | BB1: Flujo desp. imp. año 3 (corriente) | BC1: Flujo desp. imp. año 4 (corriente) | BD1: Flujo desp. imp. año 5 (corriente) | BE1: Flujo desp. imp. año 1 (constante) | BF1: Flujo desp. imp. año 2 (constante) | BG1: Flujo desp. imp. año 3 (constante) | BH1: Flujo desp. imp. año 4 (constante) | BI1: Flujo desp. imp. año 5 (constante) | BJ1: VR: AC recuperado (nominal) | BK1: VR: 20% AF recuperado (nominal) | BL1: VR antes de impuestos | BM1: VR impuestos | BN1: VR pesos corrientes | BO1: VR pesos constantes | BP1: Flujo año 0 | BQ1: Flujo año 1 | BR1: Flujo año 2 | BS1: Flujo año 3 | BT1: Flujo año 4 | BU1: Flujo año 5 | BV1: TIR simulada
A2: 1 | B2: =RAND() -> 0.77641167 | C2: =IF(B2<=('Ejercicio 3 - TIR'!$D$13-'Ejercicio 3 - TIR'!$C$13)/('Ejercicio 3 - TIR'!$E$13-'Ejercicio 3 - TIR'!$C$13),'Ejercicio 3 - TIR'!$C$13+SQRT(('Ejercicio 3 - TIR'!$E$13-'Ejercicio 3 - TIR'!$C$13)*('Ejercicio 3 - TIR'!$D$13-'Ejercicio 3 - TIR'!$C$13)*B2),'Ejercicio 3 - TIR'!$E$13-SQRT(('Ejercicio 3 - TIR'!$E$13-'Ejercicio 3 - TIR'!$C$13)*('Ejercicio 3 - TIR'!$E$13-'Ejercicio 3 - TIR'!$D$13)*(1-B2))) -> 83619.951 | D2: =RAND() -> 0.93080842 | E2: =IF(D2<=('Ejercicio 3 - TIR'!$D$14-'Ejercicio 3 - TIR'!$C$14)/('Ejercicio 3 - TIR'!$E$14-'Ejercicio 3 - TIR'!$C$14),'Ejercicio 3 - TIR'!$C$14+SQRT(('Ejercicio 3 - TIR'!$E$14-'Ejercicio 3 - TIR'!$C$14)*('Ejercicio 3 - TIR'!$D$14-'Ejercicio 3 - TIR'!$C$14)*D2),'Ejercicio 3 - TIR'!$E$14-SQRT(('Ejercicio 3 - TIR'!$E$14-'Ejercicio 3 - TIR'!$C$14)*('Ejercicio 3 - TIR'!$E$14-'Ejercicio 3 - TIR'!$D$14)*(1-D2))) -> 36778.395 | F2: =RAND() -> 0.21999643 | G2: =IF(F2<=('Ejercicio 3 - TIR'!$D$18-'Ejercicio 3 - TIR'!$C$18)/('Ejercicio 3 - TIR'!$E$18-'Ejercicio 3 - TIR'!$C$18),'Ejercicio 3 - TIR'!$C$18+SQRT(('Ejercicio 3 - TIR'!$E$18-'Ejercicio 3 - TIR'!$C$18)*('Ejercicio 3 - TIR'!$D$18-'Ejercicio 3 - TIR'!$C$18)*F2),'Ejercicio 3 - TIR'!$E$18-SQRT(('Ejercicio 3 - TIR'!$E$18-'Ejercicio 3 - TIR'!$C$18)*('Ejercicio 3 - TIR'!$E$18-'Ejercicio 3 - TIR'!$D$18)*(1-F2))) -> 35744.516 | H2: =RAND() -> 0.044823029 | I2: =IF(H2<=('Ejercicio 3 - TIR'!$D$18-'Ejercicio 3 - TIR'!$C$18)/('Ejercicio 3 - TIR'!$E$18-'Ejercicio 3 - TIR'!$C$18),'Ejercicio 3 - TIR'!$C$18+SQRT(('Ejercicio 3 - TIR'!$E$18-'Ejercicio 3 - TIR'!$C$18)*('Ejercicio 3 - TIR'!$D$18-'Ejercicio 3 - TIR'!$C$18)*H2),'Ejercicio 3 - TIR'!$E$18-SQRT(('Ejercicio 3 - TIR'!$E$18-'Ejercicio 3 - TIR'!$C$18)*('Ejercicio 3 - TIR'!$E$18-'Ejercicio 3 - TIR'!$D$18)*(1-H2))) -> 32592.962 | J2: =RAND() -> 0.25378243 | K2: =IF(J2<=('Ejercicio 3 - TIR'!$D$18-'Ejercicio 3 - TIR'!$C$18)/('Ejercicio 3 - TIR'!$E$18-'Ejercicio 3 - TIR'!$C$18),'Ejercicio 3 - TIR'!$C$18+SQRT(('Ejercicio 3 - TIR'!$E$18-'Ejercicio 3 - TIR'!$C$18)*('Ejercicio 3 - TIR'!$D$18-'Ejercicio 3 - TIR'!$C$18)*J2),'Ejercicio 3 - TIR'!$E$18-SQRT(('Ejercicio 3 - TIR'!$E$18-'Ejercicio 3 - TIR'!$C$18)*('Ejercicio 3 - TIR'!$E$18-'Ejercicio 3 - TIR'!$D$18)*(1-J2))) -> 36169.876 | L2: =RAND() -> 0.3962191 | M2: =IF(L2<=('Ejercicio 3 - TIR'!$D$18-'Ejercicio 3 - TIR'!$C$18)/('Ejercicio 3 - TIR'!$E$18-'Ejercicio 3 - TIR'!$C$18),'Ejercicio 3 - TIR'!$C$18+SQRT(('Ejercicio 3 - TIR'!$E$18-'Ejercicio 3 - TIR'!$C$18)*('Ejercicio 3 - TIR'!$D$18-'Ejercicio 3 - TIR'!$C$18)*L2),'Ejercicio 3 - TIR'!$E$18-SQRT(('Ejercicio 3 - TIR'!$E$18-'Ejercicio 3 - TIR'!$C$18)*('Ejercicio 3 - TIR'!$E$18-'Ejercicio 3 - TIR'!$D$18)*(1-L2))) -> 37709.271 | N2: =RAND() -> 0.93415073 | O2: =IF(N2<=('Ejercicio 3 - TIR'!$D$18-'Ejercicio 3 - TIR'!$C$18)/('Ejercicio 3 - TIR'!$E$18-'Ejercicio 3 - TIR'!$C$18),'Ejercicio 3 - TIR'!$C$18+SQRT(('Ejercicio 3 - TIR'!$E$18-'Ejercicio 3 - TIR'!$C$18)*('Ejercicio 3 - TIR'!$D$18-'Ejercicio 3 - TIR'!$C$18)*N2),'Ejercicio 3 - TIR'!$E$18-SQRT(('Ejercicio 3 - TIR'!$E$18-'Ejercicio 3 - TIR'!$C$18)*('Ejercicio 3 - TIR'!$E$18-'Ejercicio 3 - TIR'!$D$18)*(1-N2))) -> 42777.682 | P2: =RAND() -> 0.87452574 | Q2: =IF(P2<=('Ejercicio 3 - TIR'!$D$22-'Ejercicio 3 - TIR'!$C$22)/('Ejercicio 3 - TIR'!$E$22-'Ejercicio 3 - TIR'!$C$22),'Ejercicio 3 - TIR'!$C$22+SQRT(('Ejercicio 3 - TIR'!$E$22-'Ejercicio 3 - TIR'!$C$22)*('Ejercicio 3 - TIR'!$D$22-'Ejercicio 3 - TIR'!$C$22)*P2),'Ejercicio 3 - TIR'!$E$22-SQRT(('Ejercicio 3 - TIR'!$E$22-'Ejercicio 3 - TIR'!$C$22)*('Ejercicio 3 - TIR'!$E$22-'Ejercicio 3 - TIR'!$D$22)*(1-P2))) -> 0.16497157 | R2: =RAND() -> 0.7387549 | S2: =IF(R2<=('Ejercicio 3 - TIR'!$D$23-'Ejercicio 3 - TIR'!$C$23)/('Ejercicio 3 - TIR'!$E$23-'Ejercicio 3 - TIR'!$C$23),'Ejercicio 3 - TIR'!$C$23+SQRT(('Ejercicio 3 - TIR'!$E$23-'Ejercicio 3 - TIR'!$C$23)*('Ejercicio 3 - TIR'!$D$23-'Ejercicio 3 - TIR'!$C$23)*R2),'Ejercicio 3 - TIR'!$E$23-SQRT(('Ejercicio 3 - TIR'!$E$23-'Ejercicio 3 - TIR'!$C$23)*('Ejercicio 3 - TIR'!$E$23-'Ejercicio 3 - TIR'!$D$23)*(1-R2))) -> 0.15831495 | T2: =RAND() -> 0.13502568 | U2: =IF(T2<=('Ejercicio 3 - TIR'!$D$24-'Ejercicio 3 - TIR'!$C$24)/('Ejercicio 3 - TIR'!$E$24-'Ejercicio 3 - TIR'!$C$24),'Ejercicio 3 - TIR'!$C$24+SQRT(('Ejercicio 3 - TIR'!$E$24-'Ejercicio 3 - TIR'!$C$24)*('Ejercicio 3 - TIR'!$D$24-'Ejercicio 3 - TIR'!$C$24)*T2),'Ejercicio 3 - TIR'!$E$24-SQRT(('Ejercicio 3 - TIR'!$E$24-'Ejercicio 3 - TIR'!$C$24)*('Ejercicio 3 - TIR'!$E$24-'Ejercicio 3 - TIR'!$D$24)*(1-T2))) -> 0.16683906 | V2: =RAND() -> 0.32444266 | W2: =IF(V2<=('Ejercicio 3 - TIR'!$D$25-'Ejercicio 3 - TIR'!$C$25)/('Ejercicio 3 - TIR'!$E$25-'Ejercicio 3 - TIR'!$C$25),'Ejercicio 3 - TIR'!$C$25+SQRT(('Ejercicio 3 - TIR'!$E$25-'Ejercicio 3 - TIR'!$C$25)*('Ejercicio 3 - TIR'!$D$25-'Ejercicio 3 - TIR'!$C$25)*V2),'Ejercicio 3 - TIR'!$E$25-SQRT(('Ejercicio 3 - TIR'!$E$25-'Ejercicio 3 - TIR'!$C$25)*('Ejercicio 3 - TIR'!$E$25-'Ejercicio 3 - TIR'!$D$25)*(1-V2))) -> 0.20137438 | X2: =RAND() -> 0.83367503 | Y2: =IF(X2<=('Ejercicio 3 - TIR'!$D$26-'Ejercicio 3 - TIR'!$C$26)/('Ejercicio 3 - TIR'!$E$26-'Ejercicio 3 - TIR'!$C$26),'Ejercicio 3 - TIR'!$C$26+SQRT(('Ejercicio 3 - TIR'!$E$26-'Ejercicio 3 - TIR'!$C$26)*('Ejercicio 3 - TIR'!$D$26-'Ejercicio 3 - TIR'!$C$26)*X2),'Ejercicio 3 - TIR'!$E$26-SQRT(('Ejercicio 3 - TIR'!$E$26-'Ejercicio 3 - TIR'!$C$26)*('Ejercicio 3 - TIR'!$E$26-'Ejercicio 3 - TIR'!$D$26)*(1-X2))) -> 0.25003077 | Z2: =(1+Q2) -> 1.1649716 | AA2: =Z2*(1+S2) -> 1.349404 | AB2: =AA2*(1+U2) -> 1.5745373 | AC2: =AB2*(1+W2) -> 1.8916088 | AD2: =AC2*(1+Y2) -> 2.3645692 | AE2: =E2*Q2 -> 6067.3897 | AF2: =AE2*(1+S2) -> 7027.9482 | AG2: =AF2*(1+U2) -> 8200.4844 | AH2: =AG2*(1+W2) -> 9851.8519 | AI2: =AH2*(1+Y2) -> 12315.118 | AJ2: =G2*Z2 -> 41641.345 | AK2: =I2*AA2 -> 43981.074 | AL2: =K2*AB2 -> 56950.818 | AM2: =M2*AC2 -> 71331.188 | AN2: =O2*AD2 -> 101150.79 | AO2: =C2/'Ejercicio 3 - TIR'!$D$7 -> 16723.99 | AP2: =AJ2-AO2 -> 24917.355 | AQ2: =AK2-AO2 -> 27257.083 | AR2: =AL2-AO2 -> 40226.828 | AS2: =AM2-AO2 -> 54607.198 | AT2: =AN2-AO2 -> 84426.798 | AU2: =AP2*'Ejercicio 3 - TIR'!$D$5 -> 12458.677 | AV2: =AQ2*'Ejercicio 3 - TIR'!$D$5 -> 13628.542 | AW2: =AR2*'Ejercicio 3 - TIR'!$D$5 -> 20113.414 | AX2: =AS2*'Ejercicio 3 - TIR'!$D$5 -> 27303.599 | AY2: =AT2*'Ejercicio 3 - TIR'!$D$5 -> 42213.399 | AZ2: =AJ2-AU2-AE2 -> 23115.278 | BA2: =AK2-AV2-AF2 -> 23324.584 | BB2: =AL2-AW2-AG2 -> 28636.92 | BC2: =AM2-AX2-AH2 -> 34175.737 | BD2: =AN2-AY2-AI2 -> 46622.271 | BE2: =AZ2/Z2 -> 19841.925 | BF2: =BA2/AA2 -> 17285.101 | BG2: =BB2/AB2 -> 18187.514 | BH2: =BC2/AC2 -> 18067.022 | BI2: =BD2/AD2 -> 19717.026 | BJ2: =E2*AD2 -> 86965.059 | BK2: =0.2*C2*AD2 -> 39545.031 | BL2: =BJ2+BK2 -> 126510.09 | BM2: =BK2*'Ejercicio 3 - TIR'!$D$5 -> 19772.516 | BN2: =BL2-BM2 -> 106737.57 | BO2: =BN2/AD2 -> 45140.39 | BP2: =-(C2+E2) -> -120398.35 | BQ2: =BE2 -> 19841.925 | BR2: =BF2 -> 17285.101 | BS2: =BG2 -> 18187.514 | BT2: =BH2 -> 18067.022 | BU2: =BI2+BO2 -> 64857.416 | BV2: =IFERROR(IRR(BP2:BU2,0.1),NA())*100 -> 3.898642
A3: 2 | B3: =RAND() -> 0.20991637 | C3: =IF(B3<=('Ejercicio 3 - TIR'!$D$13-'Ejercicio 3 - TIR'!$C$13)/('Ejercicio 3 - TIR'!$E$13-'Ejercicio 3 - TIR'!$C$13),'Ejercicio 3 - TIR'!$C$13+SQRT(('Ejercicio 3 - TIR'!$E$13-'Ejercicio 3 - TIR'!$C$13)*('Ejercicio 3 - TIR'!$D$13-'Ejercicio 3 - TIR'!$C$13)*B3),'Ejercicio 3 - TIR'!$E$13-SQRT(('Ejercicio 3 - TIR'!$E$13-'Ejercicio 3 - TIR'!$C$13)*('Ejercicio 3 - TIR'!$E$13-'Ejercicio 3 - TIR'!$D$13)*(1-B3))) -> 69163.326 | D3: =RAND() -> 0.45181736 | E3: =IF(D3<=('Ejercicio 3 - TIR'!$D$14-'Ejercicio 3 - TIR'!$C$14)/('Ejercicio 3 - TIR'!$E$14-'Ejercicio 3 - TIR'!$C$14),'Ejercicio 3 - TIR'!$C$14+SQRT(('Ejercicio 3 - TIR'!$E$14-'Ejercicio 3 - TIR'!$C$14)*('Ejercicio 3 - TIR'!$D$14-'Ejercicio 3 - TIR'!$C$14)*D3),'Ejercicio 3 - TIR'!$E$14-SQRT(('Ejercicio 3 - TIR'!$E$14-'Ejercicio 3 - TIR'!$C$14)*('Ejercicio 3 - TIR'!$E$14-'Ejercicio 3 - TIR'!$D$14)*(1-D3))) -> 30932.068 | F3: =RAND() -> 0.52966332 | G3: =IF(F3<=('Ejercicio 3 - TIR'!$D$18-'Ejercicio 3 - TIR'!$C$18)/('Ejercicio 3 - TIR'!$E$18-'Ejercicio 3 - TIR'!$C$18),'Ejercicio 3 - TIR'!$C$18+SQRT(('Ejercicio 3 - TIR'!$E$18-'Ejercicio 3 - TIR'!$C$18)*('Ejercicio 3 - TIR'!$D$18-'Ejercicio 3 - TIR'!$C$18)*F3),'Ejercicio 3 - TIR'!$E$18-SQRT(('Ejercicio 3 - TIR'!$E$18-'Ejercicio 3 - TIR'!$C$18)*('Ejercicio 3 - TIR'!$E$18-'Ejercicio 3 - TIR'!$D$18)*(1-F3))) -> 38913.445 | H3: =RAND() -> 0.54846966 | I3: =IF(H3<=('Ejercicio 3 - TIR'!$D$18-'Ejercicio 3 - TIR'!$C$18)/('Ejercicio 3 - TIR'!$E$18-'Ejercicio 3 - TIR'!$C$18),'Ejercicio 3 - TIR'!$C$18+SQRT(('Ejercicio 3 - TIR'!$E$18-'Ejercicio 3 - TIR'!$C$18)*('Ejercicio 3 - TIR'!$D$18-'Ejercicio 3 - TIR'!$C$18)*H3),'Ejercicio 3 - TIR'!$E$18-SQRT(('Ejercicio 3 - TIR'!$E$18-'Ejercicio 3 - TIR'!$C$18)*('Ejercicio 3 - TIR'!$E$18-'Ejercicio 3 - TIR'!$D$18)*(1-H3))) -> 39070.306 | J3: =RAND() -> 0.45751991 | K3: =IF(J3<=('Ejercicio 3 - TIR'!$D$18-'Ejercicio 3 - TIR'!$C$18)/('Ejercicio 3 - TIR'!$E$18-'Ejercicio 3 - TIR'!$C$18),'Ejercicio 3 - TIR'!$C$18+SQRT(('Ejercicio 3 - TIR'!$E$18-'Ejercicio 3 - TIR'!$C$18)*('Ejercicio 3 - TIR'!$D$18-'Ejercicio 3 - TIR'!$C$18)*J3),'Ejercicio 3 - TIR'!$E$18-SQRT(('Ejercicio 3 - TIR'!$E$18-'Ejercicio 3 - TIR'!$C$18)*('Ejercicio 3 - TIR'!$E$18-'Ejercicio 3 - TIR'!$D$18)*(1-J3))) -> 38284.201 | L3: =RAND() -> 0.87288181 | M3: =IF(L3<=('Ejercicio 3 - TIR'!$D$18-'Ejercicio 3 - TIR'!$C$18)/('Ejercicio 3 - TIR'!$E$18-'Ejercicio 3 - TIR'!$C$18),'Ejercicio 3 - TIR'!$C$18+SQRT(('Ejercicio 3 - TIR'!$E$18-'Ejercicio 3 - TIR'!$C$18)*('Ejercicio 3 - TIR'!$D$18-'Ejercicio 3 - TIR'!$C$18)*L3),'Ejercicio 3 - TIR'!$E$18-SQRT(('Ejercicio 3 - TIR'!$E$18-'Ejercicio 3 - TIR'!$C$18)*('Ejercicio 3 - TIR'!$E$18-'Ejercicio 3 - TIR'!$D$18)*(1-L3))) -> 41912.304 | N3: =RAND() -> 0.21634229 | O3: =IF(N3<=('Ejercicio 3 - TIR'!$D$18-'Ejercicio 3 - TIR'!$C$18)/('Ejercicio 3 - TIR'!$E$18-'Ejercicio 3 - TIR'!$C$18),'Ejercicio 3 - TIR'!$C$18+SQRT(('Ejercicio 3 - TIR'!$E$18-'Ejercicio 3 - TIR'!$C$18)*('Ejercicio 3 - TIR'!$D$18-'Ejercicio 3 - TIR'!$C$18)*N3),'Ejercicio 3 - TIR'!$E$18-SQRT(('Ejercicio 3 - TIR'!$E$18-'Ejercicio 3 - TIR'!$C$18)*('Ejercicio 3 - TIR'!$E$18-'Ejercicio 3 - TIR'!$D$18)*(1-N3))) -> 35696.608 | P3: =RAND() -> 0.13961279 | Q3: =IF(P3<=('Ejercicio 3 - TIR'!$D$22-'Ejercicio 3 - TIR'!$C$22)/('Ejercicio 3 - TIR'!$E$22-'Ejercicio 3 - TIR'!$C$22),'Ejercicio 3 - TIR'!$C$22+SQRT(('Ejercicio 3 - TIR'!$E$22-'Ejercicio 3 - TIR'!$C$22)*('Ejercicio 3 - TIR'!$D$22-'Ejercicio 3 - TIR'!$C$22)*P3),'Ejercicio 3 - TIR'!$E$22-SQRT(('Ejercicio 3 - TIR'!$E$22-'Ejercicio 3 - TIR'!$C$22)*('Ejercicio 3 - TIR'!$E$22-'Ejercicio 3 - TIR'!$D$22)*(1-P3))) -> 0.13585254 | R3: =RAND() -> 0.15944188 | S3: =IF(R3<=('Ejercicio 3 - TIR'!$D$23-'Ejercicio 3 - TIR'!$C$23)/('Ejercicio 3 - TIR'!$E$23-'Ejercicio 3 - TIR'!$C$23),'Ejercicio 3 - TIR'!$C$23+SQRT(('Ejercicio 3 - TIR'!$E$23-'Ejercicio 3 - TIR'!$C$23)*('Ejercicio 3 - TIR'!$D$23-'Ejercicio 3 - TIR'!$C$23)*R3),'Ejercicio 3 - TIR'!$E$23-SQRT(('Ejercicio 3 - TIR'!$E$23-'Ejercicio 3 - TIR'!$C$23)*('Ejercicio 3 - TIR'!$E$23-'Ejercicio 3 - TIR'!$D$23)*(1-R3))) -> 0.13694094 | T3: =RAND() -> 0.22346911 | U3: =IF(T3<=('Ejercicio 3 - TIR'!$D$24-'Ejercicio 3 - TIR'!$C$24)/('Ejercicio 3 - TIR'!$E$24-'Ejercicio 3 - TIR'!$C$24),'Ejercicio 3 - TIR'!$C$24+SQRT(('Ejercicio 3 - TIR'!$E$24-'Ejercicio 3 - TIR'!$C$24)*('Ejercicio 3 - TIR'!$D$24-'Ejercicio 3 - TIR'!$C$24)*T3),'Ejercicio 3 - TIR'!$E$24-SQRT(('Ejercicio 3 - TIR'!$E$24-'Ejercicio 3 - TIR'!$C$24)*('Ejercicio 3 - TIR'!$E$24-'Ejercicio 3 - TIR'!$D$24)*(1-T3))) -> 0.17166299 | V3: =RAND() -> 0.037469736 | W3: =IF(V3<=('Ejercicio 3 - TIR'!$D$25-'Ejercicio 3 - TIR'!$C$25)/('Ejercicio 3 - TIR'!$E$25-'Ejercicio 3 - TIR'!$C$25),'Ejercicio 3 - TIR'!$C$25+SQRT(('Ejercicio 3 - TIR'!$E$25-'Ejercicio 3 - TIR'!$C$25)*('Ejercicio 3 - TIR'!$D$25-'Ejercicio 3 - TIR'!$C$25)*V3),'Ejercicio 3 - TIR'!$E$25-SQRT(('Ejercicio 3 - TIR'!$E$25-'Ejercicio 3 - TIR'!$C$25)*('Ejercicio 3 - TIR'!$E$25-'Ejercicio 3 - TIR'!$D$25)*(1-V3))) -> 0.18724276 | X3: =RAND() -> 0.00097366396 | Y3: =IF(X3<=('Ejercicio 3 - TIR'!$D$26-'Ejercicio 3 - TIR'!$C$26)/('Ejercicio 3 - TIR'!$E$26-'Ejercicio 3 - TIR'!$C$26),'Ejercicio 3 - TIR'!$C$26+SQRT(('Ejercicio 3 - TIR'!$E$26-'Ejercicio 3 - TIR'!$C$26)*('Ejercicio 3 - TIR'!$D$26-'Ejercicio 3 - TIR'!$C$26)*X3),'Ejercicio 3 - TIR'!$E$26-SQRT(('Ejercicio 3 - TIR'!$E$26-'Ejercicio 3 - TIR'!$C$26)*('Ejercicio 3 - TIR'!$E$26-'Ejercicio 3 - TIR'!$D$26)*(1-X3))) -> 0.19162139 | Z3: =(1+Q3) -> 1.1358525 | AA3: =Z3*(1+S3) -> 1.2913973 | AB3: =AA3*(1+U3) -> 1.5130824 | AC3: =AB3*(1+W3) -> 1.7963961 | AD3: =AC3*(1+Y3) -> 2.140624 | AE3: =E3*Q3 -> 4202.2 | AF3: =AE3*(1+S3) -> 4777.6532 | AG3: =AF3*(1+U3) -> 5597.7994 | AH3: =AG3*(1+W3) -> 6645.9468 | AI3: =AH3*(1+Y3) -> 7919.4524 | AJ3: =G3*Z3 -> 44199.935 | AK3: =I3*AA3 -> 50455.286 | AL3: =K3*AB3 -> 57927.149 | AM3: =M3*AC3 -> 75291.1 | AN3: =O3*AD3 -> 76413.016 | AO3: =C3/'Ejercicio 3 - TIR'!$D$7 -> 13832.665 | AP3: =AJ3-AO3 -> 30367.27 | AQ3: =AK3-AO3 -> 36622.62 | AR3: =AL3-AO3 -> 44094.484 | AS3: =AM3-AO3 -> 61458.434 | AT3: =AN3-AO3 -> 62580.351 | AU3: =AP3*'Ejercicio 3 - TIR'!$D$5 -> 15183.635 | AV3: =AQ3*'Ejercicio 3 - TIR'!$D$5 -> 18311.31 | AW3: =AR3*'Ejercicio 3 - TIR'!$D$5 -> 22047.242 | AX3: =AS3*'Ejercicio 3 - TIR'!$D$5 -> 30729.217 | AY3: =AT3*'Ejercicio 3 - TIR'!$D$5 -> 31290.175 | AZ3: =AJ3-AU3-AE3 -> 24814.1 | BA3: =AK3-AV3-AF3 -> 27366.322 | BB3: =AL3-AW3-AG3 -> 30282.108 | BC3: =AM3-AX3-AH3 -> 37915.936 | BD3: =AN3-AY3-AI3 -> 37203.388 | BE3: =AZ3/Z3 -> 21846.234 | BF3: =BA3/AA3 -> 21191.25 | BG3: =BB3/AB3 -> 20013.522 | BH3: =BC3/AC3 -> 21106.668 | BI3: =BD3/AD3 -> 17379.693 | BJ3: =E3*AD3 -> 66213.927 | BK3: =0.2*C3*AD3 -> 29610.535 | BL3: =BJ3+BK3 -> 95824.462 | BM3: =BK3*'Ejercicio 3 - TIR'!$D$5 -> 14805.268 | BN3: =BL3-BM3 -> 81019.194 | BO3: =BN3/AD3 -> 37848.4 | BP3: =-(C3+E3) -> -100095.39 | BQ3: =BE3 -> 21846.234 | BR3: =BF3 -> 21191.25 | BS3: =BG3 -> 20013.522 | BT3: =BH3 -> 21106.668 | BU3: =BI3+BO3 -> 55228.093 | BV3: =IFERROR(IRR(BP3:BU3,0.1),NA())*100 -> 10.344633
A4: 3 | B4: =RAND() -> 0.91224235 | C4: =IF(B4<=('Ejercicio 3 - TIR'!$D$13-'Ejercicio 3 - TIR'!$C$13)/('Ejercicio 3 - TIR'!$E$13-'Ejercicio 3 - TIR'!$C$13),'Ejercicio 3 - TIR'!$C$13+SQRT(('Ejercicio 3 - TIR'!$E$13-'Ejercicio 3 - TIR'!$C$13)*('Ejercicio 3 - TIR'!$D$13-'Ejercicio 3 - TIR'!$C$13)*B4),'Ejercicio 3 - TIR'!$E$13-SQRT(('Ejercicio 3 - TIR'!$E$13-'Ejercicio 3 - TIR'!$C$13)*('Ejercicio 3 - TIR'!$E$13-'Ejercicio 3 - TIR'!$D$13)*(1-B4))) -> 89737.974 | D4: =RAND() -> 0.70715225 | E4: =IF(D4<=('Ejercicio 3 - TIR'!$D$14-'Ejercicio 3 - TIR'!$C$14)/('Ejercicio 3 - TIR'!$E$14-'Ejercicio 3 - TIR'!$C$14),'Ejercicio 3 - TIR'!$C$14+SQRT(('Ejercicio 3 - TIR'!$E$14-'Ejercicio 3 - TIR'!$C$14)*('Ejercicio 3 - TIR'!$D$14-'Ejercicio 3 - TIR'!$C$14)*D4),'Ejercicio 3 - TIR'!$E$14-SQRT(('Ejercicio 3 - TIR'!$E$14-'Ejercicio 3 - TIR'!$C$14)*('Ejercicio 3 - TIR'!$E$14-'Ejercicio 3 - TIR'!$D$14)*(1-D4))) -> 33372.243 | F4: =RAND() -> 0.11336018 | G4: =IF(F4<=('Ejercicio 3 - TIR'!$D$18-'Ejercicio 3 - TIR'!$C$18)/('Ejercicio 3 - TIR'!$E$18-'Ejercicio 3 - TIR'!$C$18),'Ejercicio 3 - TIR'!$C$18+SQRT(('Ejercicio 3 - TIR'!$E$18-'Ejercicio 3 - TIR'!$C$18)*('Ejercicio 3 - TIR'!$D$18-'Ejercicio 3 - TIR'!$C$18)*F4),'Ejercicio 3 - TIR'!$E$18-SQRT(('Ejercicio 3 - TIR'!$E$18-'Ejercicio 3 - TIR'!$C$18)*('Ejercicio 3 - TIR'!$E$18-'Ejercicio 3 - TIR'!$D$18)*(1-F4))) -> 34123.594 | H4: =RAND() -> 0.44365394 | I4: =IF(H4<=('Ejercicio 3 - TIR'!$D$18-'Ejercicio 3 - TIR'!$C$18)/('Ejercicio 3 - TIR'!$E$18-'Ejercicio 3 - TIR'!$C$18),'Ejercicio 3 - TIR'!$C$18+SQRT(('Ejercicio 3 - TIR'!$E$18-'Ejercicio 3 - TIR'!$C$18)*('Ejercicio 3 - TIR'!$D$18-'Ejercicio 3 - TIR'!$C$18)*H4),'Ejercicio 3 - TIR'!$E$18-SQRT(('Ejercicio 3 - TIR'!$E$18-'Ejercicio 3 - TIR'!$C$18)*('Ejercicio 3 - TIR'!$E$18-'Ejercicio 3 - TIR'!$D$18)*(1-H4))) -> 38157.701 | J4: =RAND() -> 0.66856365 | K4: =IF(J4<=('Ejercicio 3 - TIR'!$D$18-'Ejercicio 3 - TIR'!$C$18)/('Ejercicio 3 - TIR'!$E$18-'Ejercicio 3 - TIR'!$C$18),'Ejercicio 3 - TIR'!$C$18+SQRT(('Ejercicio 3 - TIR'!$E$18-'Ejercicio 3 - TIR'!$C$18)*('Ejercicio 3 - TIR'!$D$18-'Ejercicio 3 - TIR'!$C$18)*J4),'Ejercicio 3 - TIR'!$E$18-SQRT(('Ejercicio 3 - TIR'!$E$18-'Ejercicio 3 - TIR'!$C$18)*('Ejercicio 3 - TIR'!$E$18-'Ejercicio 3 - TIR'!$D$18)*(1-J4))) -> 40014.248 | L4: =RAND() -> 0.55123902 | M4: =IF(L4<=('Ejercicio 3 - TIR'!$D$18-'Ejercicio 3 - TIR'!$C$18)/('Ejercicio 3 - TIR'!$E$18-'Ejercicio 3 - TIR'!$C$18),'Ejercicio 3 - TIR'!$C$18+SQRT(('Ejercicio 3 - TIR'!$E$18-'Ejercicio 3 - TIR'!$C$18)*('Ejercicio 3 - TIR'!$D$18-'Ejercicio 3 - TIR'!$C$18)*L4),'Ejercicio 3 - TIR'!$E$18-SQRT(('Ejercicio 3 - TIR'!$E$18-'Ejercicio 3 - TIR'!$C$18)*('Ejercicio 3 - TIR'!$E$18-'Ejercicio 3 - TIR'!$D$18)*(1-L4))) -> 39093.176 | N4: =RAND() -> 0.98830406 | O4: =IF(N4<=('Ejercicio 3 - TIR'!$D$18-'Ejercicio 3 - TIR'!$C$18)/('Ejercicio 3 - TIR'!$E$18-'Ejercicio 3 - TIR'!$C$18),'Ejercicio 3 - TIR'!$C$18+SQRT(('Ejercicio 3 - TIR'!$E$18-'Ejercicio 3 - TIR'!$C$18)*('Ejercicio 3 - TIR'!$D$18-'Ejercicio 3 - TIR'!$C$18)*N4),'Ejercicio 3 - TIR'!$E$18-SQRT(('Ejercicio 3 - TIR'!$E$18-'Ejercicio 3 - TIR'!$C$18)*('Ejercicio 3 - TIR'!$E$18-'Ejercicio 3 - TIR'!$D$18)*(1-N4))) -> 44063.413 | P4: =RAND() -> 0.64108511 | Q4: =IF(P4<=('Ejercicio 3 - TIR'!$D$22-'Ejercicio 3 - TIR'!$C$22)/('Ejercicio 3 - TIR'!$E$22-'Ejercicio 3 - TIR'!$C$22),'Ejercicio 3 - TIR'!$C$22+SQRT(('Ejercicio 3 - TIR'!$E$22-'Ejercicio 3 - TIR'!$C$22)*('Ejercicio 3 - TIR'!$D$22-'Ejercicio 3 - TIR'!$C$22)*P4),'Ejercicio 3 - TIR'!$E$22-SQRT(('Ejercicio 3 - TIR'!$E$22-'Ejercicio 3 - TIR'!$C$22)*('Ejercicio 3 - TIR'!$E$22-'Ejercicio 3 - TIR'!$D$22)*(1-P4))) -> 0.15458255 | R4: =RAND() -> 0.039168953 | S4: =IF(R4<=('Ejercicio 3 - TIR'!$D$23-'Ejercicio 3 - TIR'!$C$23)/('Ejercicio 3 - TIR'!$E$23-'Ejercicio 3 - TIR'!$C$23),'Ejercicio 3 - TIR'!$C$23+SQRT(('Ejercicio 3 - TIR'!$E$23-'Ejercicio 3 - TIR'!$C$23)*('Ejercicio 3 - TIR'!$D$23-'Ejercicio 3 - TIR'!$C$23)*R4),'Ejercicio 3 - TIR'!$E$23-SQRT(('Ejercicio 3 - TIR'!$E$23-'Ejercicio 3 - TIR'!$C$23)*('Ejercicio 3 - TIR'!$E$23-'Ejercicio 3 - TIR'!$D$23)*(1-R4))) -> 0.12839667 | T4: =RAND() -> 0.50551714 | U4: =IF(T4<=('Ejercicio 3 - TIR'!$D$24-'Ejercicio 3 - TIR'!$C$24)/('Ejercicio 3 - TIR'!$E$24-'Ejercicio 3 - TIR'!$C$24),'Ejercicio 3 - TIR'!$C$24+SQRT(('Ejercicio 3 - TIR'!$E$24-'Ejercicio 3 - TIR'!$C$24)*('Ejercicio 3 - TIR'!$D$24-'Ejercicio 3 - TIR'!$C$24)*T4),'Ejercicio 3 - TIR'!$E$24-SQRT(('Ejercicio 3 - TIR'!$E$24-'Ejercicio 3 - TIR'!$C$24)*('Ejercicio 3 - TIR'!$E$24-'Ejercicio 3 - TIR'!$D$24)*(1-T4))) -> 0.18279043 | V4: =RAND() -> 0.53482972 | W4: =IF(V4<=('Ejercicio 3 - TIR'!$D$25-'Ejercicio 3 - TIR'!$C$25)/('Ejercicio 3 - TIR'!$E$25-'Ejercicio 3 - TIR'!$C$25),'Ejercicio 3 - TIR'!$C$25+SQRT(('Ejercicio 3 - TIR'!$E$25-'Ejercicio 3 - TIR'!$C$25)*('Ejercicio 3 - TIR'!$D$25-'Ejercicio 3 - TIR'!$C$25)*V4),'Ejercicio 3 - TIR'!$E$25-SQRT(('Ejercicio 3 - TIR'!$E$25-'Ejercicio 3 - TIR'!$C$25)*('Ejercicio 3 - TIR'!$E$25-'Ejercicio 3 - TIR'!$D$25)*(1-V4))) -> 0.20965033 | X4: =RAND() -> 0.63112144 | Y4: =IF(X4<=('Ejercicio 3 - TIR'!$D$26-'Ejercicio 3 - TIR'!$C$26)/('Ejercicio 3 - TIR'!$E$26-'Ejercicio 3 - TIR'!$C$26),'Ejercicio 3 - TIR'!$C$26+SQRT(('Ejercicio 3 - TIR'!$E$26-'Ejercicio 3 - TIR'!$C$26)*('Ejercicio 3 - TIR'!$D$26-'Ejercicio 3 - TIR'!$C$26)*X4),'Ejercicio 3 - TIR'!$E$26-SQRT(('Ejercicio 3 - TIR'!$E$26-'Ejercicio 3 - TIR'!$C$26)*('Ejercicio 3 - TIR'!$E$26-'Ejercicio 3 - TIR'!$D$26)*(1-X4))) -> 0.2353688 | Z4: =(1+Q4) -> 1.1545825 | AA4: =Z4*(1+S4) -> 1.3028271 | AB4: =AA4*(1+U4) -> 1.5409714 | AC4: =AB4*(1+W4) -> 1.8640366 | AD4: =AC4*(1+Y4) -> 2.3027727 | AE4: =E4*Q4 -> 5158.7664 | AF4: =AE4*(1+S4) -> 5821.1348 | AG4: =AF4*(1+U4) -> 6885.1826 | AH4: =AG4*(1+W4) -> 8328.6634 | AI4: =AH4*(1+Y4) -> 10288.971 | AJ4: =G4*Z4 -> 39398.506 | AK4: =I4*AA4 -> 49712.888 | AL4: =K4*AB4 -> 61660.813 | AM4: =M4*AC4 -> 72871.111 | AN4: =O4*AD4 -> 101468.02 | AO4: =C4/'Ejercicio 3 - TIR'!$D$7 -> 17947.595 | AP4: =AJ4-AO4 -> 21450.911 | AQ4: =AK4-AO4 -> 31765.293 | AR4: =AL4-AO4 -> 43713.218 | AS4: =AM4-AO4 -> 54923.517 | AT4: =AN4-AO4 -> 83520.428 | AU4: =AP4*'Ejercicio 3 - TIR'!$D$5 -> 10725.456 | AV4: =AQ4*'Ejercicio 3 - TIR'!$D$5 -> 15882.646 | AW4: =AR4*'Ejercicio 3 - TIR'!$D$5 -> 21856.609 | AX4: =AS4*'Ejercicio 3 - TIR'!$D$5 -> 27461.758 | AY4: =AT4*'Ejercicio 3 - TIR'!$D$5 -> 41760.214 | AZ4: =AJ4-AU4-AE4 -> 23514.284 | BA4: =AK4-AV4-AF4 -> 28009.106 | BB4: =AL4-AW4-AG4 -> 32919.021 | BC4: =AM4-AX4-AH4 -> 37080.69 | BD4: =AN4-AY4-AI4 -> 49418.838 | BE4: =AZ4/Z4 -> 20366.048 | BF4: =BA4/AA4 -> 21498.713 | BG4: =BB4/AB4 -> 21362.512 | BH4: =BC4/AC4 -> 19892.683 | BI4: =BD4/AD4 -> 21460.58 | BJ4: =E4*AD4 -> 76848.689 | BK4: =0.2*C4*AD4 -> 41329.231 | BL4: =BJ4+BK4 -> 118177.92 | BM4: =BK4*'Ejercicio 3 - TIR'!$D$5 -> 20664.615 | BN4: =BL4-BM4 -> 97513.304 | BO4: =BN4/AD4 -> 42346.04 | BP4: =-(C4+E4) -> -123110.22 | BQ4: =BE4 -> 20366.048 | BR4: =BF4 -> 21498.713 | BS4: =BG4 -> 21362.512 | BT4: =BH4 -> 19892.683 | BU4: =BI4+BO4 -> 63806.621 | BV4: =IFERROR(IRR(BP4:BU4,0.1),NA())*100 -> 5.1472293
A5: 4 | B5: =RAND() -> 0.54810799 | C5: =IF(B5<=('Ejercicio 3 - TIR'!$D$13-'Ejercicio 3 - TIR'!$C$13)/('Ejercicio 3 - TIR'!$E$13-'Ejercicio 3 - TIR'!$C$13),'Ejercicio 3 - TIR'!$C$13+SQRT(('Ejercicio 3 - TIR'!$E$13-'Ejercicio 3 - TIR'!$C$13)*('Ejercicio 3 - TIR'!$D$13-'Ejercicio 3 - TIR'!$C$13)*B5),'Ejercicio 3 - TIR'!$E$13-SQRT(('Ejercicio 3 - TIR'!$E$13-'Ejercicio 3 - TIR'!$C$13)*('Ejercicio 3 - TIR'!$E$13-'Ejercicio 3 - TIR'!$D$13)*(1-B5))) -> 76713.3 | D5: =RAND() -> 0.55845588 | E5: =IF(D5<=('Ejercicio 3 - TIR'!$D$14-'Ejercicio 3 - TIR'!$C$14)/('Ejercicio 3 - TIR'!$E$14-'Ejercicio 3 - TIR'!$C$14),'Ejercicio 3 - TIR'!$C$14+SQRT(('Ejercicio 3 - TIR'!$E$14-'Ejercicio 3 - TIR'!$C$14)*('Ejercicio 3 - TIR'!$D$14-'Ejercicio 3 - TIR'!$C$14)*D5),'Ejercicio 3 - TIR'!$E$14-SQRT(('Ejercicio 3 - TIR'!$E$14-'Ejercicio 3 - TIR'!$C$14)*('Ejercicio 3 - TIR'!$E$14-'Ejercicio 3 - TIR'!$D$14)*(1-D5))) -> 31861.719 | F5: =RAND() -> 0.021106608 | G5: =IF(F5<=('Ejercicio 3 - TIR'!$D$18-'Ejercicio 3 - TIR'!$C$18)/('Ejercicio 3 - TIR'!$E$18-'Ejercicio 3 - TIR'!$C$18),'Ejercicio 3 - TIR'!$C$18+SQRT(('Ejercicio 3 - TIR'!$E$18-'Ejercicio 3 - TIR'!$C$18)*('Ejercicio 3 - TIR'!$D$18-'Ejercicio 3 - TIR'!$C$18)*F5),'Ejercicio 3 - TIR'!$E$18-SQRT(('Ejercicio 3 - TIR'!$E$18-'Ejercicio 3 - TIR'!$C$18)*('Ejercicio 3 - TIR'!$E$18-'Ejercicio 3 - TIR'!$D$18)*(1-F5))) -> 31779.323 | H5: =RAND() -> 0.2822403 | I5: =IF(H5<=('Ejercicio 3 - TIR'!$D$18-'Ejercicio 3 - TIR'!$C$18)/('Ejercicio 3 - TIR'!$E$18-'Ejercicio 3 - TIR'!$C$18),'Ejercicio 3 - TIR'!$C$18+SQRT(('Ejercicio 3 - TIR'!$E$18-'Ejercicio 3 - TIR'!$C$18)*('Ejercicio 3 - TIR'!$D$18-'Ejercicio 3 - TIR'!$C$18)*H5),'Ejercicio 3 - TIR'!$E$18-SQRT(('Ejercicio 3 - TIR'!$E$18-'Ejercicio 3 - TIR'!$C$18)*('Ejercicio 3 - TIR'!$E$18-'Ejercicio 3 - TIR'!$D$18)*(1-H5))) -> 36506.616 | J5: =RAND() -> 0.17418071 | K5: =IF(J5<=('Ejercicio 3 - TIR'!$D$18-'Ejercicio 3 - TIR'!$C$18)/('Ejercicio 3 - TIR'!$E$18-'Ejercicio 3 - TIR'!$C$18),'Ejercicio 3 - TIR'!$C$18+SQRT(('Ejercicio 3 - TIR'!$E$18-'Ejercicio 3 - TIR'!$C$18)*('Ejercicio 3 - TIR'!$D$18-'Ejercicio 3 - TIR'!$C$18)*J5),'Ejercicio 3 - TIR'!$E$18-SQRT(('Ejercicio 3 - TIR'!$E$18-'Ejercicio 3 - TIR'!$C$18)*('Ejercicio 3 - TIR'!$E$18-'Ejercicio 3 - TIR'!$D$18)*(1-J5))) -> 35111.468 | L5: =RAND() -> 0.60446073 | M5: =IF(L5<=('Ejercicio 3 - TIR'!$D$18-'Ejercicio 3 - TIR'!$C$18)/('Ejercicio 3 - TIR'!$E$18-'Ejercicio 3 - TIR'!$C$18),'Ejercicio 3 - TIR'!$C$18+SQRT(('Ejercicio 3 - TIR'!$E$18-'Ejercicio 3 - TIR'!$C$18)*('Ejercicio 3 - TIR'!$D$18-'Ejercicio 3 - TIR'!$C$18)*L5),'Ejercicio 3 - TIR'!$E$18-SQRT(('Ejercicio 3 - TIR'!$E$18-'Ejercicio 3 - TIR'!$C$18)*('Ejercicio 3 - TIR'!$E$18-'Ejercicio 3 - TIR'!$D$18)*(1-L5))) -> 39522.033 | N5: =RAND() -> 0.86205715 | O5: =IF(N5<=('Ejercicio 3 - TIR'!$D$18-'Ejercicio 3 - TIR'!$C$18)/('Ejercicio 3 - TIR'!$E$18-'Ejercicio 3 - TIR'!$C$18),'Ejercicio 3 - TIR'!$C$18+SQRT(('Ejercicio 3 - TIR'!$E$18-'Ejercicio 3 - TIR'!$C$18)*('Ejercicio 3 - TIR'!$D$18-'Ejercicio 3 - TIR'!$C$18)*N5),'Ejercicio 3 - TIR'!$E$18-SQRT(('Ejercicio 3 - TIR'!$E$18-'Ejercicio 3 - TIR'!$C$18)*('Ejercicio 3 - TIR'!$E$18-'Ejercicio 3 - TIR'!$D$18)*(1-N5))) -> 41783.525 | P5: =RAND() -> 0.28659078 | Q5: =IF(P5<=('Ejercicio 3 - TIR'!$D$22-'Ejercicio 3 - TIR'!$C$22)/('Ejercicio 3 - TIR'!$E$22-'Ejercicio 3 - TIR'!$C$22),'Ejercicio 3 - TIR'!$C$22+SQRT(('Ejercicio 3 - TIR'!$E$22-'Ejercicio 3 - TIR'!$C$22)*('Ejercicio 3 - TIR'!$D$22-'Ejercicio 3 - TIR'!$C$22)*P5),'Ejercicio 3 - TIR'!$E$22-SQRT(('Ejercicio 3 - TIR'!$E$22-'Ejercicio 3 - TIR'!$C$22)*('Ejercicio 3 - TIR'!$E$22-'Ejercicio 3 - TIR'!$D$22)*(1-P5))) -> 0.14271263 | R5: =RAND() -> 0.53401304 | S5: =IF(R5<=('Ejercicio 3 - TIR'!$D$23-'Ejercicio 3 - TIR'!$C$23)/('Ejercicio 3 - TIR'!$E$23-'Ejercicio 3 - TIR'!$C$23),'Ejercicio 3 - TIR'!$C$23+SQRT(('Ejercicio 3 - TIR'!$E$23-'Ejercicio 3 - TIR'!$C$23)*('Ejercicio 3 - TIR'!$D$23-'Ejercicio 3 - TIR'!$C$23)*R5),'Ejercicio 3 - TIR'!$E$23-SQRT(('Ejercicio 3 - TIR'!$E$23-'Ejercicio 3 - TIR'!$C$23)*('Ejercicio 3 - TIR'!$E$23-'Ejercicio 3 - TIR'!$D$23)*(1-R5))) -> 0.15103836 | T5: =RAND() -> 0.34205846 | U5: =IF(T5<=('Ejercicio 3 - TIR'!$D$24-'Ejercicio 3 - TIR'!$C$24)/('Ejercicio 3 - TIR'!$E$24-'Ejercicio 3 - TIR'!$C$24),'Ejercicio 3 - TIR'!$C$24+SQRT(('Ejercicio 3 - TIR'!$E$24-'Ejercicio 3 - TIR'!$C$24)*('Ejercicio 3 - TIR'!$D$24-'Ejercicio 3 - TIR'!$C$24)*T5),'Ejercicio 3 - TIR'!$E$24-SQRT(('Ejercicio 3 - TIR'!$E$24-'Ejercicio 3 - TIR'!$C$24)*('Ejercicio 3 - TIR'!$E$24-'Ejercicio 3 - TIR'!$D$24)*(1-T5))) -> 0.17680154 | V5: =RAND() -> 0.16898323 | W5: =IF(V5<=('Ejercicio 3 - TIR'!$D$25-'Ejercicio 3 - TIR'!$C$25)/('Ejercicio 3 - TIR'!$E$25-'Ejercicio 3 - TIR'!$C$25),'Ejercicio 3 - TIR'!$C$25+SQRT(('Ejercicio 3 - TIR'!$E$25-'Ejercicio 3 - TIR'!$C$25)*('Ejercicio 3 - TIR'!$D$25-'Ejercicio 3 - TIR'!$C$25)*V5),'Ejercicio 3 - TIR'!$E$25-SQRT(('Ejercicio 3 - TIR'!$E$25-'Ejercicio 3 - TIR'!$C$25)*('Ejercicio 3 - TIR'!$E$25-'Ejercicio 3 - TIR'!$D$25)*(1-V5))) -> 0.19538104 | X5: =RAND() -> 0.50662536 | Y5: =IF(X5<=('Ejercicio 3 - TIR'!$D$26-'Ejercicio 3 - TIR'!$C$26)/('Ejercicio 3 - TIR'!$E$26-'Ejercicio 3 - TIR'!$C$26),'Ejercicio 3 - TIR'!$C$26+SQRT(('Ejercicio 3 - TIR'!$E$26-'Ejercicio 3 - TIR'!$C$26)*('Ejercicio 3 - TIR'!$D$26-'Ejercicio 3 - TIR'!$C$26)*X5),'Ejercicio 3 - TIR'!$E$26-SQRT(('Ejercicio 3 - TIR'!$E$26-'Ejercicio 3 - TIR'!$C$26)*('Ejercicio 3 - TIR'!$E$26-'Ejercicio 3 - TIR'!$D$26)*(1-X5))) -> 0.22838389 | Z5: =(1+Q5) -> 1.1427126 | AA5: =Z5*(1+S5) -> 1.3153061 | AB5: =AA5*(1+U5) -> 1.5478542 | AC5: =AB5*(1+W5) -> 1.8502756 | AD5: =AC5*(1+Y5) -> 2.2728487 | AE5: =E5*Q5 -> 4547.0696 | AF5: =AE5*(1+S5) -> 5233.8515 | AG5: =AF5*(1+U5) -> 6159.2046 | AH5: =AG5*(1+W5) -> 7362.5964 | AI5: =AH5*(1+Y5) -> 9044.0948 | AJ5: =G5*Z5 -> 36314.634 | AK5: =I5*AA5 -> 48017.373 | AL5: =K5*AB5 -> 54347.434 | AM5: =M5*AC5 -> 73126.652 | AN5: =O5*AD5 -> 94967.63 | AO5: =C5/'Ejercicio 3 - TIR'!$D$7 -> 15342.66 | AP5: =AJ5-AO5 -> 20971.974 | AQ5: =AK5-AO5 -> 32674.713 | AR5: =AL5-AO5 -> 39004.774 | AS5: =AM5-AO5 -> 57783.993 | AT5: =AN5-AO5 -> 79624.97 | AU5: =AP5*'Ejercicio 3 - TIR'!$D$5 -> 10485.987 | AV5: =AQ5*'Ejercicio 3 - TIR'!$D$5 -> 16337.356 | AW5: =AR5*'Ejercicio 3 - TIR'!$D$5 -> 19502.387 | AX5: =AS5*'Ejercicio 3 - TIR'!$D$5 -> 28891.996 | AY5: =AT5*'Ejercicio 3 - TIR'!$D$5 -> 39812.485 | AZ5: =AJ5-AU5-AE5 -> 21281.577 | BA5: =AK5-AV5-AF5 -> 26446.165 | BB5: =AL5-AW5-AG5 -> 28685.842 | BC5: =AM5-AX5-AH5 -> 36872.06 | BD5: =AN5-AY5-AI5 -> 46111.05 | BE5: =AZ5/Z5 -> 18623.735 | BF5: =BA5/AA5 -> 20106.472 | BG5: =BB5/AB5 -> 18532.651 | BH5: =BC5/AC5 -> 19927.875 | BI5: =BD5/AD5 -> 20287.778 | BJ5: =E5*AD5 -> 72416.867 | BK5: =0.2*C5*AD5 -> 34871.545 | BL5: =BJ5+BK5 -> 107288.41 | BM5: =BK5*'Ejercicio 3 - TIR'!$D$5 -> 17435.772 | BN5: =BL5-BM5 -> 89852.639 | BO5: =BN5/AD5 -> 39533.049 | BP5: =-(C5+E5) -> -108575.02 | BQ5: =BE5 -> 18623.735 | BR5: =BF5 -> 20106.472 | BS5: =BG5 -> 18532.651 | BT5: =BH5 -> 19927.875 | BU5: =BI5+BO5 -> 59820.827 | BV5: =IFERROR(IRR(BP5:BU5,0.1),NA())*100 -> 6.8208697
A6: 5 | B6: =RAND() -> 0.091627714 | C6: =IF(B6<=('Ejercicio 3 - TIR'!$D$13-'Ejercicio 3 - TIR'!$C$13)/('Ejercicio 3 - TIR'!$E$13-'Ejercicio 3 - TIR'!$C$13),'Ejercicio 3 - TIR'!$C$13+SQRT(('Ejercicio 3 - TIR'!$E$13-'Ejercicio 3 - TIR'!$C$13)*('Ejercicio 3 - TIR'!$D$13-'Ejercicio 3 - TIR'!$C$13)*B6),'Ejercicio 3 - TIR'!$E$13-SQRT(('Ejercicio 3 - TIR'!$E$13-'Ejercicio 3 - TIR'!$C$13)*('Ejercicio 3 - TIR'!$E$13-'Ejercicio 3 - TIR'!$D$13)*(1-B6))) -> 66054.014 | D6: =RAND() -> 0.26604877 | E6: =IF(D6<=('Ejercicio 3 - TIR'!$D$14-'Ejercicio 3 - TIR'!$C$14)/('Ejercicio 3 - TIR'!$E$14-'Ejercicio 3 - TIR'!$C$14),'Ejercicio 3 - TIR'!$C$14+SQRT(('Ejercicio 3 - TIR'!$E$14-'Ejercicio 3 - TIR'!$C$14)*('Ejercicio 3 - TIR'!$D$14-'Ejercicio 3 - TIR'!$C$14)*D6),'Ejercicio 3 - TIR'!$E$14-SQRT(('Ejercicio 3 - TIR'!$E$14-'Ejercicio 3 - TIR'!$C$14)*('Ejercicio 3 - TIR'!$E$14-'Ejercicio 3 - TIR'!$D$14)*(1-D6))) -> 29466.952 | F6: =RAND() -> 0.85567868 | G6: =IF(F6<=('Ejercicio 3 - TIR'!$D$18-'Ejercicio 3 - TIR'!$C$18)/('Ejercicio 3 - TIR'!$E$18-'Ejercicio 3 - TIR'!$C$18),'Ejercicio 3 - TIR'!$C$18+SQRT(('Ejercicio 3 - TIR'!$E$18-'Ejercicio 3 - TIR'!$C$18)*('Ejercicio 3 - TIR'!$D$18-'Ejercicio 3 - TIR'!$C$18)*F6),'Ejercicio 3 - TIR'!$E$18-SQRT(('Ejercicio 3 - TIR'!$E$18-'Ejercicio 3 - TIR'!$C$18)*('Ejercicio 3 - TIR'!$E$18-'Ejercicio 3 - TIR'!$D$18)*(1-F6))) -> 41710 | H6: =RAND() -> 0.83634117 | I6: =IF(H6<=('Ejercicio 3 - TIR'!$D$18-'Ejercicio 3 - TIR'!$C$18)/('Ejercicio 3 - TIR'!$E$18-'Ejercicio 3 - TIR'!$C$18),'Ejercicio 3 - TIR'!$C$18+SQRT(('Ejercicio 3 - TIR'!$E$18-'Ejercicio 3 - TIR'!$C$18)*('Ejercicio 3 - TIR'!$D$18-'Ejercicio 3 - TIR'!$C$18)*H6),'Ejercicio 3 - TIR'!$E$18-SQRT(('Ejercicio 3 - TIR'!$E$18-'Ejercicio 3 - TIR'!$C$18)*('Ejercicio 3 - TIR'!$E$18-'Ejercicio 3 - TIR'!$D$18)*(1-H6))) -> 41496.514 | J6: =RAND() -> 0.43190898 | K6: =IF(J6<=('Ejercicio 3 - TIR'!$D$18-'Ejercicio 3 - TIR'!$C$18)/('Ejercicio 3 - TIR'!$E$18-'Ejercicio 3 - TIR'!$C$18),'Ejercicio 3 - TIR'!$C$18+SQRT(('Ejercicio 3 - TIR'!$E$18-'Ejercicio 3 - TIR'!$C$18)*('Ejercicio 3 - TIR'!$D$18-'Ejercicio 3 - TIR'!$C$18)*J6),'Ejercicio 3 - TIR'!$E$18-SQRT(('Ejercicio 3 - TIR'!$E$18-'Ejercicio 3 - TIR'!$C$18)*('Ejercicio 3 - TIR'!$E$18-'Ejercicio 3 - TIR'!$D$18)*(1-J6))) -> 38048.997 | L6: =RAND() -> 0.62223274 | M6: =IF(L6<=('Ejercicio 3 - TIR'!$D$18-'Ejercicio 3 - TIR'!$C$18)/('Ejercicio 3 - TIR'!$E$18-'Ejercicio 3 - TIR'!$C$18),'Ejercicio 3 - TIR'!$C$18+SQRT(('Ejercicio 3 - TIR'!$E$18-'Ejercicio 3 - TIR'!$C$18)*('Ejercicio 3 - TIR'!$D$18-'Ejercicio 3 - TIR'!$C$18)*L6),'Ejercicio 3 - TIR'!$E$18-SQRT(('Ejercicio 3 - TIR'!$E$18-'Ejercicio 3 - TIR'!$C$18)*('Ejercicio 3 - TIR'!$E$18-'Ejercicio 3 - TIR'!$D$18)*(1-L6))) -> 39661 | N6: =RAND() -> 0.41563681 | O6: =IF(N6<=('Ejercicio 3 - TIR'!$D$18-'Ejercicio 3 - TIR'!$C$18)/('Ejercicio 3 - TIR'!$E$18-'Ejercicio 3 - TIR'!$C$18),'Ejercicio 3 - TIR'!$C$18+SQRT(('Ejercicio 3 - TIR'!$E$18-'Ejercicio 3 - TIR'!$C$18)*('Ejercicio 3 - TIR'!$D$18-'Ejercicio 3 - TIR'!$C$18)*N6),'Ejercicio 3 - TIR'!$E$18-SQRT(('Ejercicio 3 - TIR'!$E$18-'Ejercicio 3 - TIR'!$C$18)*('Ejercicio 3 - TIR'!$E$18-'Ejercicio 3 - TIR'!$D$18)*(1-N6))) -> 37895.918 | P6: =RAND() -> 0.12678853 | Q6: =IF(P6<=('Ejercicio 3 - TIR'!$D$22-'Ejercicio 3 - TIR'!$C$22)/('Ejercicio 3 - TIR'!$E$22-'Ejercicio 3 - TIR'!$C$22),'Ejercicio 3 - TIR'!$C$22+SQRT(('Ejercicio 3 - TIR'!$E$22-'Ejercicio 3 - TIR'!$C$22)*('Ejercicio 3 - TIR'!$D$22-'Ejercicio 3 - TIR'!$C$22)*P6),'Ejercicio 3 - TIR'!$E$22-SQRT(('Ejercicio 3 - TIR'!$E$22-'Ejercicio 3 - TIR'!$C$22)*('Ejercicio 3 - TIR'!$E$22-'Ejercicio 3 - TIR'!$D$22)*(1-P6))) -> 0.13510693 | R6: =RAND() -> 0.0051692551 | S6: =IF(R6<=('Ejercicio 3 - TIR'!$D$23-'Ejercicio 3 - TIR'!$C$23)/('Ejercicio 3 - TIR'!$E$23-'Ejercicio 3 - TIR'!$C$23),'Ejercicio 3 - TIR'!$C$23+SQRT(('Ejercicio 3 - TIR'!$E$23-'Ejercicio 3 - TIR'!$C$23)*('Ejercicio 3 - TIR'!$D$23-'Ejercicio 3 - TIR'!$C$23)*R6),'Ejercicio 3 - TIR'!$E$23-SQRT(('Ejercicio 3 - TIR'!$E$23-'Ejercicio 3 - TIR'!$C$23)*('Ejercicio 3 - TIR'!$E$23-'Ejercicio 3 - TIR'!$D$23)*(1-R6))) -> 0.12305035 | T6: =RAND() -> 0.29772719 | U6: =IF(T6<=('Ejercicio 3 - TIR'!$D$24-'Ejercicio 3 - TIR'!$C$24)/('Ejercicio 3 - TIR'!$E$24-'Ejercicio 3 - TIR'!$C$24),'Ejercicio 3 - TIR'!$C$24+SQRT(('Ejercicio 3 - TIR'!$E$24-'Ejercicio 3 - TIR'!$C$24)*('Ejercicio 3 - TIR'!$D$24-'Ejercicio 3 - TIR'!$C$24)*T6),'Ejercicio 3 - TIR'!$E$24-SQRT(('Ejercicio 3 - TIR'!$E$24-'Ejercicio 3 - TIR'!$C$24)*('Ejercicio 3 - TIR'!$E$24-'Ejercicio 3 - TIR'!$D$24)*(1-T6))) -> 0.17500454 | V6: =RAND() -> 0.19458483 | W6: =IF(V6<=('Ejercicio 3 - TIR'!$D$25-'Ejercicio 3 - TIR'!$C$25)/('Ejercicio 3 - TIR'!$E$25-'Ejercicio 3 - TIR'!$C$25),'Ejercicio 3 - TIR'!$C$25+SQRT(('Ejercicio 3 - TIR'!$E$25-'Ejercicio 3 - TIR'!$C$25)*('Ejercicio 3 - TIR'!$D$25-'Ejercicio 3 - TIR'!$C$25)*V6),'Ejercicio 3 - TIR'!$E$25-SQRT(('Ejercicio 3 - TIR'!$E$25-'Ejercicio 3 - TIR'!$C$25)*('Ejercicio 3 - TIR'!$E$25-'Ejercicio 3 - TIR'!$D$25)*(1-V6))) -> 0.19650511 | X6: =RAND() -> 0.82361611 | Y6: =IF(X6<=('Ejercicio 3 - TIR'!$D$26-'Ejercicio 3 - TIR'!$C$26)/('Ejercicio 3 - TIR'!$E$26-'Ejercicio 3 - TIR'!$C$26),'Ejercicio 3 - TIR'!$C$26+SQRT(('Ejercicio 3 - TIR'!$E$26-'Ejercicio 3 - TIR'!$C$26)*('Ejercicio 3 - TIR'!$D$26-'Ejercicio 3 - TIR'!$C$26)*X6),'Ejercicio 3 - TIR'!$E$26-SQRT(('Ejercicio 3 - TIR'!$E$26-'Ejercicio 3 - TIR'!$C$26)*('Ejercicio 3 - TIR'!$E$26-'Ejercicio 3 - TIR'!$D$26)*(1-X6))) -> 0.24913784 | Z6: =(1+Q6) -> 1.1351069 | AA6: =Z6*(1+S6) -> 1.2747822 | AB6: =AA6*(1+U6) -> 1.4978749 | AC6: =AB6*(1+W6) -> 1.792215 | AD6: =AC6*(1+Y6) -> 2.2387236 | AE6: =E6*Q6 -> 3981.1894 | AF6: =AE6*(1+S6) -> 4471.0762 | AG6: =AF6*(1+U6) -> 5253.5348 | AH6: =AG6*(1+W6) -> 6285.8813 | AI6: =AH6*(1+Y6) -> 7851.9321 | AJ6: =G6*Z6 -> 47345.31 | AK6: =I6*AA6 -> 52899.019 | AL6: =K6*AB6 -> 56992.638 | AM6: =M6*AC6 -> 71081.038 | AN6: =O6*AD6 -> 84838.485 | AO6: =C6/'Ejercicio 3 - TIR'!$D$7 -> 13210.803 | AP6: =AJ6-AO6 -> 34134.507 | AQ6: =AK6-AO6 -> 39688.217 | AR6: =AL6-AO6 -> 43781.835 | AS6: =AM6-AO6 -> 57870.236 | AT6: =AN6-AO6 -> 71627.682 | AU6: =AP6*'Ejercicio 3 - TIR'!$D$5 -> 17067.254 | AV6: =AQ6*'Ejercicio 3 - TIR'!$D$5 -> 19844.108 | AW6: =AR6*'Ejercicio 3 - TIR'!$D$5 -> 21890.917 | AX6: =AS6*'Ejercicio 3 - TIR'!$D$5 -> 28935.118 | AY6: =AT6*'Ejercicio 3 - TIR'!$D$5 -> 35813.841 | AZ6: =AJ6-AU6-AE6 -> 26296.867 | BA6: =AK6-AV6-AF6 -> 28583.835 | BB6: =AL6-AW6-AG6 -> 29848.185 | BC6: =AM6-AX6-AH6 -> 35860.039 | BD6: =AN6-AY6-AI6 -> 41172.712 | BE6: =AZ6/Z6 -> 23166.863 | BF6: =BA6/AA6 -> 22422.524 | BG6: =BB6/AB6 -> 19927.021 | BH6: =BC6/AC6 -> 20008.782 | BI6: =BD6/AD6 -> 18391.155 | BJ6: =E6*AD6 -> 65968.36 | BK6: =0.2*C6*AD6 -> 29575.336 | BL6: =BJ6+BK6 -> 95543.695 | BM6: =BK6*'Ejercicio 3 - TIR'!$D$5 -> 14787.668 | BN6: =BL6-BM6 -> 80756.027 | BO6: =BN6/AD6 -> 36072.353 | BP6: =-(C6+E6) -> -95520.966 | BQ6: =BE6 -> 23166.863 | BR6: =BF6 -> 22422.524 | BS6: =BG6 -> 19927.021 | BT6: =BH6 -> 20008.782 | BU6: =BI6+BO6 -> 54463.508 | BV6: =IFERROR(IRR(BP6:BU6,0.1),NA())*100 -> 12.312146
A7: 6 | B7: =RAND() -> 0.7786262 | C7: =IF(B7<=('Ejercicio 3 - TIR'!$D$13-'Ejercicio 3 - TIR'!$C$13)/('Ejercicio 3 - TIR'!$E$13-'Ejercicio 3 - TIR'!$C$13),'Ejercicio 3 - TIR'!$C$13+SQRT(('Ejercicio 3 - TIR'!$E$13-'Ejercicio 3 - TIR'!$C$13)*('Ejercicio 3 - TIR'!$D$13-'Ejercicio 3 - TIR'!$C$13)*B7),'Ejercicio 3 - TIR'!$E$13-SQRT(('Ejercicio 3 - TIR'!$E$13-'Ejercicio 3 - TIR'!$C$13)*('Ejercicio 3 - TIR'!$E$13-'Ejercicio 3 - TIR'!$D$13)*(1-B7))) -> 83701.271 | D7: =RAND() -> 0.36155747 | E7: =IF(D7<=('Ejercicio 3 - TIR'!$D$14-'Ejercicio 3 - TIR'!$C$14)/('Ejercicio 3 - TIR'!$E$14-'Ejercicio 3 - TIR'!$C$14),'Ejercicio 3 - TIR'!$C$14+SQRT(('Ejercicio 3 - TIR'!$E$14-'Ejercicio 3 - TIR'!$C$14)*('Ejercicio 3 - TIR'!$D$14-'Ejercicio 3 - TIR'!$C$14)*D7),'Ejercicio 3 - TIR'!$E$14-SQRT(('Ejercicio 3 - TIR'!$E$14-'Ejercicio 3 - TIR'!$C$14)*('Ejercicio 3 - TIR'!$E$14-'Ejercicio 3 - TIR'!$D$14)*(1-D7))) -> 30213.97 | F7: =RAND() -> 0.80895268 | G7: =IF(F7<=('Ejercicio 3 - TIR'!$D$18-'Ejercicio 3 - TIR'!$C$18)/('Ejercicio 3 - TIR'!$E$18-'Ejercicio 3 - TIR'!$C$18),'Ejercicio 3 - TIR'!$C$18+SQRT(('Ejercicio 3 - TIR'!$E$18-'Ejercicio 3 - TIR'!$C$18)*('Ejercicio 3 - TIR'!$D$18-'Ejercicio 3 - TIR'!$C$18)*F7),'Ejercicio 3 - TIR'!$E$18-SQRT(('Ejercicio 3 - TIR'!$E$18-'Ejercicio 3 - TIR'!$C$18)*('Ejercicio 3 - TIR'!$E$18-'Ejercicio 3 - TIR'!$D$18)*(1-F7))) -> 41214.693 | H7: =RAND() -> 0.19605153 | I7: =IF(H7<=('Ejercicio 3 - TIR'!$D$18-'Ejercicio 3 - TIR'!$C$18)/('Ejercicio 3 - TIR'!$E$18-'Ejercicio 3 - TIR'!$C$18),'Ejercicio 3 - TIR'!$C$18+SQRT(('Ejercicio 3 - TIR'!$E$18-'Ejercicio 3 - TIR'!$C$18)*('Ejercicio 3 - TIR'!$D$18-'Ejercicio 3 - TIR'!$C$18)*H7),'Ejercicio 3 - TIR'!$E$18-SQRT(('Ejercicio 3 - TIR'!$E$18-'Ejercicio 3 - TIR'!$C$18)*('Ejercicio 3 - TIR'!$E$18-'Ejercicio 3 - TIR'!$D$18)*(1-H7))) -> 35422.889 | J7: =RAND() -> 0.90808317 | K7: =IF(J7<=('Ejercicio 3 - TIR'!$D$18-'Ejercicio 3 - TIR'!$C$18)/('Ejercicio 3 - TIR'!$E$18-'Ejercicio 3 - TIR'!$C$18),'Ejercicio 3 - TIR'!$C$18+SQRT(('Ejercicio 3 - TIR'!$E$18-'Ejercicio 3 - TIR'!$C$18)*('Ejercicio 3 - TIR'!$D$18-'Ejercicio 3 - TIR'!$C$18)*J7),'Ejercicio 3 - TIR'!$E$18-SQRT(('Ejercicio 3 - TIR'!$E$18-'Ejercicio 3 - TIR'!$C$18)*('Ejercicio 3 - TIR'!$E$18-'Ejercicio 3 - TIR'!$D$18)*(1-J7))) -> 42374.402 | L7: =RAND() -> 0.22723367 | M7: =IF(L7<=('Ejercicio 3 - TIR'!$D$18-'Ejercicio 3 - TIR'!$C$18)/('Ejercicio 3 - TIR'!$E$18-'Ejercicio 3 - TIR'!$C$18),'Ejercicio 3 - TIR'!$C$18+SQRT(('Ejercicio 3 - TIR'!$E$18-'Ejercicio 3 - TIR'!$C$18)*('Ejercicio 3 - TIR'!$D$18-'Ejercicio 3 - TIR'!$C$18)*L7),'Ejercicio 3 - TIR'!$E$18-SQRT(('Ejercicio 3 - TIR'!$E$18-'Ejercicio 3 - TIR'!$C$18)*('Ejercicio 3 - TIR'!$E$18-'Ejercicio 3 - TIR'!$D$18)*(1-L7))) -> 35838.24 | N7: =RAND() -> 0.86305407 | O7: =IF(N7<=('Ejercicio 3 - TIR'!$D$18-'Ejercicio 3 - TIR'!$C$18)/('Ejercicio 3 - TIR'!$E$18-'Ejercicio 3 - TIR'!$C$18),'Ejercicio 3 - TIR'!$C$18+SQRT(('Ejercicio 3 - TIR'!$E$18-'Ejercicio 3 - TIR'!$C$18)*('Ejercicio 3 - TIR'!$D$18-'Ejercicio 3 - TIR'!$C$18)*N7),'Ejercicio 3 - TIR'!$E$18-SQRT(('Ejercicio 3 - TIR'!$E$18-'Ejercicio 3 - TIR'!$C$18)*('Ejercicio 3 - TIR'!$E$18-'Ejercicio 3 - TIR'!$D$18)*(1-N7))) -> 41795.168 | P7: =RAND() -> 0.82372341 | Q7: =IF(P7<=('Ejercicio 3 - TIR'!$D$22-'Ejercicio 3 - TIR'!$C$22)/('Ejercicio 3 - TIR'!$E$22-'Ejercicio 3 - TIR'!$C$22),'Ejercicio 3 - TIR'!$C$22+SQRT(('Ejercicio 3 - TIR'!$E$22-'Ejercicio 3 - TIR'!$C$22)*('Ejercicio 3 - TIR'!$D$22-'Ejercicio 3 - TIR'!$C$22)*P7),'Ejercicio 3 - TIR'!$E$22-SQRT(('Ejercicio 3 - TIR'!$E$22-'Ejercicio 3 - TIR'!$C$22)*('Ejercicio 3 - TIR'!$E$22-'Ejercicio 3 - TIR'!$D$22)*(1-P7))) -> 0.16218714 | R7: =RAND() -> 0.89343462 | S7: =IF(R7<=('Ejercicio 3 - TIR'!$D$23-'Ejercicio 3 - TIR'!$C$23)/('Ejercicio 3 - TIR'!$E$23-'Ejercicio 3 - TIR'!$C$23),'Ejercicio 3 - TIR'!$C$23+SQRT(('Ejercicio 3 - TIR'!$E$23-'Ejercicio 3 - TIR'!$C$23)*('Ejercicio 3 - TIR'!$D$23-'Ejercicio 3 - TIR'!$C$23)*R7),'Ejercicio 3 - TIR'!$E$23-SQRT(('Ejercicio 3 - TIR'!$E$23-'Ejercicio 3 - TIR'!$C$23)*('Ejercicio 3 - TIR'!$E$23-'Ejercicio 3 - TIR'!$D$23)*(1-R7))) -> 0.16615017 | T7: =RAND() -> 0.38027781 | U7: =IF(T7<=('Ejercicio 3 - TIR'!$D$24-'Ejercicio 3 - TIR'!$C$24)/('Ejercicio 3 - TIR'!$E$24-'Ejercicio 3 - TIR'!$C$24),'Ejercicio 3 - TIR'!$C$24+SQRT(('Ejercicio 3 - TIR'!$E$24-'Ejercicio 3 - TIR'!$C$24)*('Ejercicio 3 - TIR'!$D$24-'Ejercicio 3 - TIR'!$C$24)*T7),'Ejercicio 3 - TIR'!$E$24-SQRT(('Ejercicio 3 - TIR'!$E$24-'Ejercicio 3 - TIR'!$C$24)*('Ejercicio 3 - TIR'!$E$24-'Ejercicio 3 - TIR'!$D$24)*(1-T7))) -> 0.17825922 | V7: =RAND() -> 0.70934986 | W7: =IF(V7<=('Ejercicio 3 - TIR'!$D$25-'Ejercicio 3 - TIR'!$C$25)/('Ejercicio 3 - TIR'!$E$25-'Ejercicio 3 - TIR'!$C$25),'Ejercicio 3 - TIR'!$C$25+SQRT(('Ejercicio 3 - TIR'!$E$25-'Ejercicio 3 - TIR'!$C$25)*('Ejercicio 3 - TIR'!$D$25-'Ejercicio 3 - TIR'!$C$25)*V7),'Ejercicio 3 - TIR'!$E$25-SQRT(('Ejercicio 3 - TIR'!$E$25-'Ejercicio 3 - TIR'!$C$25)*('Ejercicio 3 - TIR'!$E$25-'Ejercicio 3 - TIR'!$D$25)*(1-V7))) -> 0.21810524 | X7: =RAND() -> 0.22695412 | Y7: =IF(X7<=('Ejercicio 3 - TIR'!$D$26-'Ejercicio 3 - TIR'!$C$26)/('Ejercicio 3 - TIR'!$E$26-'Ejercicio 3 - TIR'!$C$26),'Ejercicio 3 - TIR'!$C$26+SQRT(('Ejercicio 3 - TIR'!$E$26-'Ejercicio 3 - TIR'!$C$26)*('Ejercicio 3 - TIR'!$D$26-'Ejercicio 3 - TIR'!$C$26)*X7),'Ejercicio 3 - TIR'!$E$26-SQRT(('Ejercicio 3 - TIR'!$E$26-'Ejercicio 3 - TIR'!$C$26)*('Ejercicio 3 - TIR'!$E$26-'Ejercicio 3 - TIR'!$D$26)*(1-X7))) -> 0.21475432 | Z7: =(1+Q7) -> 1.1621871 | AA7: =Z7*(1+S7) -> 1.3552847 | AB7: =AA7*(1+U7) -> 1.5968767 | AC7: =AB7*(1+W7) -> 1.9451639 | AD7: =AC7*(1+Y7) -> 2.3628963 | AE7: =E7*Q7 -> 4900.3175 | AF7: =AE7*(1+S7) -> 5714.5061 | AG7: =AF7*(1+U7) -> 6733.1695 | AH7: =AG7*(1+W7) -> 8201.7091 | AI7: =AH7*(1+Y7) -> 9963.0615 | AJ7: =G7*Z7 -> 47899.186 | AK7: =I7*AA7 -> 48008.101 | AL7: =K7*AB7 -> 67666.697 | AM7: =M7*AC7 -> 69711.252 | AN7: =O7*AD7 -> 98757.648 | AO7: =C7/'Ejercicio 3 - TIR'!$D$7 -> 16740.254 | AP7: =AJ7-AO7 -> 31158.932 | AQ7: =AK7-AO7 -> 31267.847 | AR7: =AL7-AO7 -> 50926.443 | AS7: =AM7-AO7 -> 52970.998 | AT7: =AN7-AO7 -> 82017.394 | AU7: =AP7*'Ejercicio 3 - TIR'!$D$5 -> 15579.466 | AV7: =AQ7*'Ejercicio 3 - TIR'!$D$5 -> 15633.924 | AW7: =AR7*'Ejercicio 3 - TIR'!$D$5 -> 25463.222 | AX7: =AS7*'Ejercicio 3 - TIR'!$D$5 -> 26485.499 | AY7: =AT7*'Ejercicio 3 - TIR'!$D$5 -> 41008.697 | AZ7: =AJ7-AU7-AE7 -> 27419.403 | BA7: =AK7-AV7-AF7 -> 26659.672 | BB7: =AL7-AW7-AG7 -> 35470.306 | BC7: =AM7-AX7-AH7 -> 35024.044 | BD7: =AN7-AY7-AI7 -> 47785.89 | BE7: =AZ7/Z7 -> 23592.932 | BF7: =BA7/AA7 -> 19670.901 | BG7: =BB7/AB7 -> 22212.301 | BH7: =BC7/AC7 -> 18005.703 | BI7: =BD7/AD7 -> 20223.439 | BJ7: =E7*AD7 -> 71392.478 | BK7: =0.2*C7*AD7 -> 39555.484 | BL7: =BJ7+BK7 -> 110947.96 | BM7: =BK7*'Ejercicio 3 - TIR'!$D$5 -> 19777.742 | BN7: =BL7-BM7 -> 91170.22 | BO7: =BN7/AD7 -> 38584.097 | BP7: =-(C7+E7) -> -113915.24 | BQ7: =BE7 -> 23592.932 | BR7: =BF7 -> 19670.901 | BS7: =BG7 -> 22212.301 | BT7: =BH7 -> 18005.703 | BU7: =BI7+BO7 -> 58807.537 | BV7: =IFERROR(IRR(BP7:BU7,0.1),NA())*100 -> 6.7486305
A8: 7 | B8: =RAND() -> 0.42250347 | C8: =IF(B8<=('Ejercicio 3 - TIR'!$D$13-'Ejercicio 3 - TIR'!$C$13)/('Ejercicio 3 - TIR'!$E$13-'Ejercicio 3 - TIR'!$C$13),'Ejercicio 3 - TIR'!$C$13+SQRT(('Ejercicio 3 - TIR'!$E$13-'Ejercicio 3 - TIR'!$C$13)*('Ejercicio 3 - TIR'!$D$13-'Ejercicio 3 - TIR'!$C$13)*B8),'Ejercicio 3 - TIR'!$E$13-SQRT(('Ejercicio 3 - TIR'!$E$13-'Ejercicio 3 - TIR'!$C$13)*('Ejercicio 3 - TIR'!$E$13-'Ejercicio 3 - TIR'!$D$13)*(1-B8))) -> 73675.186 | D8: =RAND() -> 0.33416119 | E8: =IF(D8<=('Ejercicio 3 - TIR'!$D$14-'Ejercicio 3 - TIR'!$C$14)/('Ejercicio 3 - TIR'!$E$14-'Ejercicio 3 - TIR'!$C$14),'Ejercicio 3 - TIR'!$C$14+SQRT(('Ejercicio 3 - TIR'!$E$14-'Ejercicio 3 - TIR'!$C$14)*('Ejercicio 3 - TIR'!$D$14-'Ejercicio 3 - TIR'!$C$14)*D8),'Ejercicio 3 - TIR'!$E$14-SQRT(('Ejercicio 3 - TIR'!$E$14-'Ejercicio 3 - TIR'!$C$14)*('Ejercicio 3 - TIR'!$E$14-'Ejercicio 3 - TIR'!$D$14)*(1-D8))) -> 30006.211 | F8: =RAND() -> 0.84211216 | G8: =IF(F8<=('Ejercicio 3 - TIR'!$D$18-'Ejercicio 3 - TIR'!$C$18)/('Ejercicio 3 - TIR'!$E$18-'Ejercicio 3 - TIR'!$C$18),'Ejercicio 3 - TIR'!$C$18+SQRT(('Ejercicio 3 - TIR'!$E$18-'Ejercicio 3 - TIR'!$C$18)*('Ejercicio 3 - TIR'!$D$18-'Ejercicio 3 - TIR'!$C$18)*F8),'Ejercicio 3 - TIR'!$E$18-SQRT(('Ejercicio 3 - TIR'!$E$18-'Ejercicio 3 - TIR'!$C$18)*('Ejercicio 3 - TIR'!$E$18-'Ejercicio 3 - TIR'!$D$18)*(1-F8))) -> 41558.839 | H8: =RAND() -> 0.5792084 | I8: =IF(H8<=('Ejercicio 3 - TIR'!$D$18-'Ejercicio 3 - TIR'!$C$18)/('Ejercicio 3 - TIR'!$E$18-'Ejercicio 3 - TIR'!$C$18),'Ejercicio 3 - TIR'!$C$18+SQRT(('Ejercicio 3 - TIR'!$E$18-'Ejercicio 3 - TIR'!$C$18)*('Ejercicio 3 - TIR'!$D$18-'Ejercicio 3 - TIR'!$C$18)*H8),'Ejercicio 3 - TIR'!$E$18-SQRT(('Ejercicio 3 - TIR'!$E$18-'Ejercicio 3 - TIR'!$C$18)*('Ejercicio 3 - TIR'!$E$18-'Ejercicio 3 - TIR'!$D$18)*(1-H8))) -> 39321.012 | J8: =RAND() -> 0.23208004 | K8: =IF(J8<=('Ejercicio 3 - TIR'!$D$18-'Ejercicio 3 - TIR'!$C$18)/('Ejercicio 3 - TIR'!$E$18-'Ejercicio 3 - TIR'!$C$18),'Ejercicio 3 - TIR'!$C$18+SQRT(('Ejercicio 3 - TIR'!$E$18-'Ejercicio 3 - TIR'!$C$18)*('Ejercicio 3 - TIR'!$D$18-'Ejercicio 3 - TIR'!$C$18)*J8),'Ejercicio 3 - TIR'!$E$18-SQRT(('Ejercicio 3 - TIR'!$E$18-'Ejercicio 3 - TIR'!$C$18)*('Ejercicio 3 - TIR'!$E$18-'Ejercicio 3 - TIR'!$D$18)*(1-J8))) -> 35900.17 | L8: =RAND() -> 0.50758225 | M8: =IF(L8<=('Ejercicio 3 - TIR'!$D$18-'Ejercicio 3 - TIR'!$C$18)/('Ejercicio 3 - TIR'!$E$18-'Ejercicio 3 - TIR'!$C$18),'Ejercicio 3 - TIR'!$C$18+SQRT(('Ejercicio 3 - TIR'!$E$18-'Ejercicio 3 - TIR'!$C$18)*('Ejercicio 3 - TIR'!$D$18-'Ejercicio 3 - TIR'!$C$18)*L8),'Ejercicio 3 - TIR'!$E$18-SQRT(('Ejercicio 3 - TIR'!$E$18-'Ejercicio 3 - TIR'!$C$18)*('Ejercicio 3 - TIR'!$E$18-'Ejercicio 3 - TIR'!$D$18)*(1-L8))) -> 38725.671 | N8: =RAND() -> 0.87569885 | O8: =IF(N8<=('Ejercicio 3 - TIR'!$D$18-'Ejercicio 3 - TIR'!$C$18)/('Ejercicio 3 - TIR'!$E$18-'Ejercicio 3 - TIR'!$C$18),'Ejercicio 3 - TIR'!$C$18+SQRT(('Ejercicio 3 - TIR'!$E$18-'Ejercicio 3 - TIR'!$C$18)*('Ejercicio 3 - TIR'!$D$18-'Ejercicio 3 - TIR'!$C$18)*N8),'Ejercicio 3 - TIR'!$E$18-SQRT(('Ejercicio 3 - TIR'!$E$18-'Ejercicio 3 - TIR'!$C$18)*('Ejercicio 3 - TIR'!$E$18-'Ejercicio 3 - TIR'!$D$18)*(1-N8))) -> 41946.709 | P8: =RAND() -> 0.35375177 | Q8: =IF(P8<=('Ejercicio 3 - TIR'!$D$22-'Ejercicio 3 - TIR'!$C$22)/('Ejercicio 3 - TIR'!$E$22-'Ejercicio 3 - TIR'!$C$22),'Ejercicio 3 - TIR'!$C$22+SQRT(('Ejercicio 3 - TIR'!$E$22-'Ejercicio 3 - TIR'!$C$22)*('Ejercicio 3 - TIR'!$D$22-'Ejercicio 3 - TIR'!$C$22)*P8),'Ejercicio 3 - TIR'!$E$22-SQRT(('Ejercicio 3 - TIR'!$E$22-'Ejercicio 3 - TIR'!$C$22)*('Ejercicio 3 - TIR'!$E$22-'Ejercicio 3 - TIR'!$D$22)*(1-P8))) -> 0.14523397 | R8: =RAND() -> 0.89718919 | S8: =IF(R8<=('Ejercicio 3 - TIR'!$D$23-'Ejercicio 3 - TIR'!$C$23)/('Ejercicio 3 - TIR'!$E$23-'Ejercicio 3 - TIR'!$C$23),'Ejercicio 3 - TIR'!$C$23+SQRT(('Ejercicio 3 - TIR'!$E$23-'Ejercicio 3 - TIR'!$C$23)*('Ejercicio 3 - TIR'!$D$23-'Ejercicio 3 - TIR'!$C$23)*R8),'Ejercicio 3 - TIR'!$E$23-SQRT(('Ejercicio 3 - TIR'!$E$23-'Ejercicio 3 - TIR'!$C$23)*('Ejercicio 3 - TIR'!$E$23-'Ejercicio 3 - TIR'!$D$23)*(1-R8))) -> 0.16639634 | T8: =RAND() -> 0.095471586 | U8: =IF(T8<=('Ejercicio 3 - TIR'!$D$24-'Ejercicio 3 - TIR'!$C$24)/('Ejercicio 3 - TIR'!$E$24-'Ejercicio 3 - TIR'!$C$24),'Ejercicio 3 - TIR'!$C$24+SQRT(('Ejercicio 3 - TIR'!$E$24-'Ejercicio 3 - TIR'!$C$24)*('Ejercicio 3 - TIR'!$D$24-'Ejercicio 3 - TIR'!$C$24)*T8),'Ejercicio 3 - TIR'!$E$24-SQRT(('Ejercicio 3 - TIR'!$E$24-'Ejercicio 3 - TIR'!$C$24)*('Ejercicio 3 - TIR'!$E$24-'Ejercicio 3 - TIR'!$D$24)*(1-T8))) -> 0.16415946 | V8: =RAND() -> 0.036870829 | W8: =IF(V8<=('Ejercicio 3 - TIR'!$D$25-'Ejercicio 3 - TIR'!$C$25)/('Ejercicio 3 - TIR'!$E$25-'Ejercicio 3 - TIR'!$C$25),'Ejercicio 3 - TIR'!$C$25+SQRT(('Ejercicio 3 - TIR'!$E$25-'Ejercicio 3 - TIR'!$C$25)*('Ejercicio 3 - TIR'!$D$25-'Ejercicio 3 - TIR'!$C$25)*V8),'Ejercicio 3 - TIR'!$E$25-SQRT(('Ejercicio 3 - TIR'!$E$25-'Ejercicio 3 - TIR'!$C$25)*('Ejercicio 3 - TIR'!$E$25-'Ejercicio 3 - TIR'!$D$25)*(1-V8))) -> 0.18718465 | X8: =RAND() -> 0.78360395 | Y8: =IF(X8<=('Ejercicio 3 - TIR'!$D$26-'Ejercicio 3 - TIR'!$C$26)/('Ejercicio 3 - TIR'!$E$26-'Ejercicio 3 - TIR'!$C$26),'Ejercicio 3 - TIR'!$C$26+SQRT(('Ejercicio 3 - TIR'!$E$26-'Ejercicio 3 - TIR'!$C$26)*('Ejercicio 3 - TIR'!$D$26-'Ejercicio 3 - TIR'!$C$26)*X8),'Ejercicio 3 - TIR'!$E$26-SQRT(('Ejercicio 3 - TIR'!$E$26-'Ejercicio 3 - TIR'!$C$26)*('Ejercicio 3 - TIR'!$E$26-'Ejercicio 3 - TIR'!$D$26)*(1-X8))) -> 0.2458161 | Z8: =(1+Q8) -> 1.145234 | AA8: =Z8*(1+S8) -> 1.3357967 | AB8: =AA8*(1+U8) -> 1.5550804 | AC8: =AB8*(1+W8) -> 1.8461676 | AD8: =AC8*(1+Y8) -> 2.2999853 | AE8: =E8*Q8 -> 4357.9211 | AF8: =AE8*(1+S8) -> 5083.0632 | AG8: =AF8*(1+U8) -> 5917.4962 | AH8: =AG8*(1+W8) -> 7025.1606 | AI8: =AH8*(1+Y8) -> 8752.0582 | AJ8: =G8*Z8 -> 47594.594 | AK8: =I8*AA8 -> 52524.878 | AL8: =K8*AB8 -> 55827.65 | AM8: =M8*AC8 -> 71494.078 | AN8: =O8*AD8 -> 96476.813 | AO8: =C8/'Ejercicio 3 - TIR'!$D$7 -> 14735.037 | AP8: =AJ8-AO8 -> 32859.557 | AQ8: =AK8-AO8 -> 37789.841 | AR8: =AL8-AO8 -> 41092.613 | AS8: =AM8-AO8 -> 56759.04 | AT8: =AN8-AO8 -> 81741.776 | AU8: =AP8*'Ejercicio 3 - TIR'!$D$5 -> 16429.779 | AV8: =AQ8*'Ejercicio 3 - TIR'!$D$5 -> 18894.921 | AW8: =AR8*'Ejercicio 3 - TIR'!$D$5 -> 20546.306 | AX8: =AS8*'Ejercicio 3 - TIR'!$D$5 -> 28379.52 | AY8: =AT8*'Ejercicio 3 - TIR'!$D$5 -> 40870.888 | AZ8: =AJ8-AU8-AE8 -> 26806.895 | BA8: =AK8-AV8-AF8 -> 28546.895 | BB8: =AL8-AW8-AG8 -> 29363.847 | BC8: =AM8-AX8-AH8 -> 36089.397 | BD8: =AN8-AY8-AI8 -> 46853.867 | BE8: =AZ8/Z8 -> 23407.352 | BF8: =BA8/AA8 -> 21370.688 | BG8: =BB8/AB8 -> 18882.527 | BH8: =BC8/AC8 -> 19548.278 | BI8: =BD8/AD8 -> 20371.377 | BJ8: =E8*AD8 -> 69013.843 | BK8: =0.2*C8*AD8 -> 33890.369 | BL8: =BJ8+BK8 -> 102904.21 | BM8: =BK8*'Ejercicio 3 - TIR'!$D$5 -> 16945.184 | BN8: =BL8-BM8 -> 85959.027 | BO8: =BN8/AD8 -> 37373.729 | BP8: =-(C8+E8) -> -103681.4 | BQ8: =BE8 -> 23407.352 | BR8: =BF8 -> 21370.688 | BS8: =BG8 -> 18882.527 | BT8: =BH8 -> 19548.278 | BU8: =BI8+BO8 -> 57745.106 | BV8: =IFERROR(IRR(BP8:BU8,0.1),NA())*100 -> 9.558101
A9: 8 | B9: =RAND() -> 0.2810776 | C9: =IF(B9<=('Ejercicio 3 - TIR'!$D$13-'Ejercicio 3 - TIR'!$C$13)/('Ejercicio 3 - TIR'!$E$13-'Ejercicio 3 - TIR'!$C$13),'Ejercicio 3 - TIR'!$C$13+SQRT(('Ejercicio 3 - TIR'!$E$13-'Ejercicio 3 - TIR'!$C$13)*('Ejercicio 3 - TIR'!$D$13-'Ejercicio 3 - TIR'!$C$13)*B9),'Ejercicio 3 - TIR'!$E$13-SQRT(('Ejercicio 3 - TIR'!$E$13-'Ejercicio 3 - TIR'!$C$13)*('Ejercicio 3 - TIR'!$E$13-'Ejercicio 3 - TIR'!$D$13)*(1-B9))) -> 70628.128 | D9: =RAND() -> 0.59689451 | E9: =IF(D9<=('Ejercicio 3 - TIR'!$D$14-'Ejercicio 3 - TIR'!$C$14)/('Ejercicio 3 - TIR'!$E$14-'Ejercicio 3 - TIR'!$C$14),'Ejercicio 3 - TIR'!$C$14+SQRT(('Ejercicio 3 - TIR'!$E$14-'Ejercicio 3 - TIR'!$C$14)*('Ejercicio 3 - TIR'!$D$14-'Ejercicio 3 - TIR'!$C$14)*D9),'Ejercicio 3 - TIR'!$E$14-SQRT(('Ejercicio 3 - TIR'!$E$14-'Ejercicio 3 - TIR'!$C$14)*('Ejercicio 3 - TIR'!$E$14-'Ejercicio 3 - TIR'!$D$14)*(1-D9))) -> 32224.023 | F9: =RAND() -> 0.73325033 | G9: =IF(F9<=('Ejercicio 3 - TIR'!$D$18-'Ejercicio 3 - TIR'!$C$18)/('Ejercicio 3 - TIR'!$E$18-'Ejercicio 3 - TIR'!$C$18),'Ejercicio 3 - TIR'!$C$18+SQRT(('Ejercicio 3 - TIR'!$E$18-'Ejercicio 3 - TIR'!$C$18)*('Ejercicio 3 - TIR'!$D$18-'Ejercicio 3 - TIR'!$C$18)*F9),'Ejercicio 3 - TIR'!$E$18-SQRT(('Ejercicio 3 - TIR'!$E$18-'Ejercicio 3 - TIR'!$C$18)*('Ejercicio 3 - TIR'!$E$18-'Ejercicio 3 - TIR'!$D$18)*(1-F9))) -> 40527.168 | H9: =RAND() -> 0.4768917 | I9: =IF(H9<=('Ejercicio 3 - TIR'!$D$18-'Ejercicio 3 - TIR'!$C$18)/('Ejercicio 3 - TIR'!$E$18-'Ejercicio 3 - TIR'!$C$18),'Ejercicio 3 - TIR'!$C$18+SQRT(('Ejercicio 3 - TIR'!$E$18-'Ejercicio 3 - TIR'!$C$18)*('Ejercicio 3 - TIR'!$D$18-'Ejercicio 3 - TIR'!$C$18)*H9),'Ejercicio 3 - TIR'!$E$18-SQRT(('Ejercicio 3 - TIR'!$E$18-'Ejercicio 3 - TIR'!$C$18)*('Ejercicio 3 - TIR'!$E$18-'Ejercicio 3 - TIR'!$D$18)*(1-H9))) -> 38457.763 | J9: =RAND() -> 0.023458729 | K9: =IF(J9<=('Ejercicio 3 - TIR'!$D$18-'Ejercicio 3 - TIR'!$C$18)/('Ejercicio 3 - TIR'!$E$18-'Ejercicio 3 - TIR'!$C$18),'Ejercicio 3 - TIR'!$C$18+SQRT(('Ejercicio 3 - TIR'!$E$18-'Ejercicio 3 - TIR'!$C$18)*('Ejercicio 3 - TIR'!$D$18-'Ejercicio 3 - TIR'!$C$18)*J9),'Ejercicio 3 - TIR'!$E$18-SQRT(('Ejercicio 3 - TIR'!$E$18-'Ejercicio 3 - TIR'!$C$18)*('Ejercicio 3 - TIR'!$E$18-'Ejercicio 3 - TIR'!$D$18)*(1-J9))) -> 31875.849 | L9: =RAND() -> 0.96583407 | M9: =IF(L9<=('Ejercicio 3 - TIR'!$D$18-'Ejercicio 3 - TIR'!$C$18)/('Ejercicio 3 - TIR'!$E$18-'Ejercicio 3 - TIR'!$C$18),'Ejercicio 3 - TIR'!$C$18+SQRT(('Ejercicio 3 - TIR'!$E$18-'Ejercicio 3 - TIR'!$C$18)*('Ejercicio 3 - TIR'!$D$18-'Ejercicio 3 - TIR'!$C$18)*L9),'Ejercicio 3 - TIR'!$E$18-SQRT(('Ejercicio 3 - TIR'!$E$18-'Ejercicio 3 - TIR'!$C$18)*('Ejercicio 3 - TIR'!$E$18-'Ejercicio 3 - TIR'!$D$18)*(1-L9))) -> 43399.236 | N9: =RAND() -> 0.93192038 | O9: =IF(N9<=('Ejercicio 3 - TIR'!$D$18-'Ejercicio 3 - TIR'!$C$18)/('Ejercicio 3 - TIR'!$E$18-'Ejercicio 3 - TIR'!$C$18),'Ejercicio 3 - TIR'!$C$18+SQRT(('Ejercicio 3 - TIR'!$E$18-'Ejercicio 3 - TIR'!$C$18)*('Ejercicio 3 - TIR'!$D$18-'Ejercicio 3 - TIR'!$C$18)*N9),'Ejercicio 3 - TIR'!$E$18-SQRT(('Ejercicio 3 - TIR'!$E$18-'Ejercicio 3 - TIR'!$C$18)*('Ejercicio 3 - TIR'!$E$18-'Ejercicio 3 - TIR'!$D$18)*(1-N9))) -> 42740.36 | P9: =RAND() -> 0.40734454 | Q9: =IF(P9<=('Ejercicio 3 - TIR'!$D$22-'Ejercicio 3 - TIR'!$C$22)/('Ejercicio 3 - TIR'!$E$22-'Ejercicio 3 - TIR'!$C$22),'Ejercicio 3 - TIR'!$C$22+SQRT(('Ejercicio 3 - TIR'!$E$22-'Ejercicio 3 - TIR'!$C$22)*('Ejercicio 3 - TIR'!$D$22-'Ejercicio 3 - TIR'!$C$22)*P9),'Ejercicio 3 - TIR'!$E$22-SQRT(('Ejercicio 3 - TIR'!$E$22-'Ejercicio 3 - TIR'!$C$22)*('Ejercicio 3 - TIR'!$E$22-'Ejercicio 3 - TIR'!$D$22)*(1-P9))) -> 0.14707804 | R9: =RAND() -> 0.69432502 | S9: =IF(R9<=('Ejercicio 3 - TIR'!$D$23-'Ejercicio 3 - TIR'!$C$23)/('Ejercicio 3 - TIR'!$E$23-'Ejercicio 3 - TIR'!$C$23),'Ejercicio 3 - TIR'!$C$23+SQRT(('Ejercicio 3 - TIR'!$E$23-'Ejercicio 3 - TIR'!$C$23)*('Ejercicio 3 - TIR'!$D$23-'Ejercicio 3 - TIR'!$C$23)*R9),'Ejercicio 3 - TIR'!$E$23-SQRT(('Ejercicio 3 - TIR'!$E$23-'Ejercicio 3 - TIR'!$C$23)*('Ejercicio 3 - TIR'!$E$23-'Ejercicio 3 - TIR'!$D$23)*(1-R9))) -> 0.15654334 | T9: =RAND() -> 0.086764382 | U9: =IF(T9<=('Ejercicio 3 - TIR'!$D$24-'Ejercicio 3 - TIR'!$C$24)/('Ejercicio 3 - TIR'!$E$24-'Ejercicio 3 - TIR'!$C$24),'Ejercicio 3 - TIR'!$C$24+SQRT(('Ejercicio 3 - TIR'!$E$24-'Ejercicio 3 - TIR'!$C$24)*('Ejercicio 3 - TIR'!$D$24-'Ejercicio 3 - TIR'!$C$24)*T9),'Ejercicio 3 - TIR'!$E$24-SQRT(('Ejercicio 3 - TIR'!$E$24-'Ejercicio 3 - TIR'!$C$24)*('Ejercicio 3 - TIR'!$E$24-'Ejercicio 3 - TIR'!$D$24)*(1-T9))) -> 0.16349834 | V9: =RAND() -> 0.75413647 | W9: =IF(V9<=('Ejercicio 3 - TIR'!$D$25-'Ejercicio 3 - TIR'!$C$25)/('Ejercicio 3 - TIR'!$E$25-'Ejercicio 3 - TIR'!$C$25),'Ejercicio 3 - TIR'!$C$25+SQRT(('Ejercicio 3 - TIR'!$E$25-'Ejercicio 3 - TIR'!$C$25)*('Ejercicio 3 - TIR'!$D$25-'Ejercicio 3 - TIR'!$C$25)*V9),'Ejercicio 3 - TIR'!$E$25-SQRT(('Ejercicio 3 - TIR'!$E$25-'Ejercicio 3 - TIR'!$C$25)*('Ejercicio 3 - TIR'!$E$25-'Ejercicio 3 - TIR'!$D$25)*(1-V9))) -> 0.22066534 | X9: =RAND() -> 0.016122429 | Y9: =IF(X9<=('Ejercicio 3 - TIR'!$D$26-'Ejercicio 3 - TIR'!$C$26)/('Ejercicio 3 - TIR'!$E$26-'Ejercicio 3 - TIR'!$C$26),'Ejercicio 3 - TIR'!$C$26+SQRT(('Ejercicio 3 - TIR'!$E$26-'Ejercicio 3 - TIR'!$C$26)*('Ejercicio 3 - TIR'!$D$26-'Ejercicio 3 - TIR'!$C$26)*X9),'Ejercicio 3 - TIR'!$E$26-SQRT(('Ejercicio 3 - TIR'!$E$26-'Ejercicio 3 - TIR'!$C$26)*('Ejercicio 3 - TIR'!$E$26-'Ejercicio 3 - TIR'!$D$26)*(1-X9))) -> 0.19659777 | Z9: =(1+Q9) -> 1.147078 | AA9: =Z9*(1+S9) -> 1.3266455 | AB9: =AA9*(1+U9) -> 1.5435498 | AC9: =AB9*(1+W9) -> 1.8841577 | AD9: =AC9*(1+Y9) -> 2.2545789 | AE9: =E9*Q9 -> 4739.446 | AF9: =AE9*(1+S9) -> 5481.3747 | AG9: =AF9*(1+U9) -> 6377.5704 | AH9: =AG9*(1+W9) -> 7784.8792 | AI9: =AH9*(1+Y9) -> 9315.369 | AJ9: =G9*Z9 -> 46487.824 | AK9: =I9*AA9 -> 51019.817 | AL9: =K9*AB9 -> 49201.96 | AM9: =M9*AC9 -> 81771.007 | AN9: =O9*AD9 -> 96361.516 | AO9: =C9/'Ejercicio 3 - TIR'!$D$7 -> 14125.626 | AP9: =AJ9-AO9 -> 32362.199 | AQ9: =AK9-AO9 -> 36894.191 | AR9: =AL9-AO9 -> 35076.335 | AS9: =AM9-AO9 -> 67645.381 | AT9: =AN9-AO9 -> 82235.891 | AU9: =AP9*'Ejercicio 3 - TIR'!$D$5 -> 16181.099 | AV9: =AQ9*'Ejercicio 3 - TIR'!$D$5 -> 18447.096 | AW9: =AR9*'Ejercicio 3 - TIR'!$D$5 -> 17538.167 | AX9: =AS9*'Ejercicio 3 - TIR'!$D$5 -> 33822.691 | AY9: =AT9*'Ejercicio 3 - TIR'!$D$5 -> 41117.945 | AZ9: =AJ9-AU9-AE9 -> 25567.279 | BA9: =AK9-AV9-AF9 -> 27091.346 | BB9: =AL9-AW9-AG9 -> 25286.222 | BC9: =AM9-AX9-AH9 -> 40163.437 | BD9: =AN9-AY9-AI9 -> 45928.202 | BE9: =AZ9/Z9 -> 22289.049 | BF9: =BA9/AA9 -> 20420.939 | BG9: =BB9/AB9 -> 16381.864 | BH9: =BC9/AC9 -> 21316.388 | BI9: =BD9/AD9 -> 20371.077 | BJ9: =E9*AD9 -> 72651.603 | BK9: =0.2*C9*AD9 -> 31847.338 | BL9: =BJ9+BK9 -> 104498.94 | BM9: =BK9*'Ejercicio 3 - TIR'!$D$5 -> 15923.669 | BN9: =BL9-BM9 -> 88575.272 | BO9: =BN9/AD9 -> 39286.835 | BP9: =-(C9+E9) -> -102852.15 | BQ9: =BE9 -> 22289.049 | BR9: =BF9 -> 20420.939 | BS9: =BG9 -> 16381.864 | BT9: =BH9 -> 21316.388 | BU9: =BI9+BO9 -> 59657.913 | BV9: =IFERROR(IRR(BP9:BU9,0.1),NA())*100 -> 9.4150562
A10: 9 | B10: =RAND() -> 0.48500981 | C10: =IF(B10<=('Ejercicio 3 - TIR'!$D$13-'Ejercicio 3 - TIR'!$C$13)/('Ejercicio 3 - TIR'!$E$13-'Ejercicio 3 - TIR'!$C$13),'Ejercicio 3 - TIR'!$C$13+SQRT(('Ejercicio 3 - TIR'!$E$13-'Ejercicio 3 - TIR'!$C$13)*('Ejercicio 3 - TIR'!$D$13-'Ejercicio 3 - TIR'!$C$13)*B10),'Ejercicio 3 - TIR'!$E$13-SQRT(('Ejercicio 3 - TIR'!$E$13-'Ejercicio 3 - TIR'!$C$13)*('Ejercicio 3 - TIR'!$E$13-'Ejercicio 3 - TIR'!$D$13)*(1-B10))) -> 75140.631 | D10: =RAND() -> 0.71968374 | E10: =IF(D10<=('Ejercicio 3 - TIR'!$D$14-'Ejercicio 3 - TIR'!$C$14)/('Ejercicio 3 - TIR'!$E$14-'Ejercicio 3 - TIR'!$C$14),'Ejercicio 3 - TIR'!$C$14+SQRT(('Ejercicio 3 - TIR'!$E$14-'Ejercicio 3 - TIR'!$C$14)*('Ejercicio 3 - TIR'!$D$14-'Ejercicio 3 - TIR'!$C$14)*D10),'Ejercicio 3 - TIR'!$E$14-SQRT(('Ejercicio 3 - TIR'!$E$14-'Ejercicio 3 - TIR'!$C$14)*('Ejercicio 3 - TIR'!$E$14-'Ejercicio 3 - TIR'!$D$14)*(1-D10))) -> 33515.6 | F10: =RAND() -> 0.222095 | G10: =IF(F10<=('Ejercicio 3 - TIR'!$D$18-'Ejercicio 3 - TIR'!$C$18)/('Ejercicio 3 - TIR'!$E$18-'Ejercicio 3 - TIR'!$C$18),'Ejercicio 3 - TIR'!$C$18+SQRT(('Ejercicio 3 - TIR'!$E$18-'Ejercicio 3 - TIR'!$C$18)*('Ejercicio 3 - TIR'!$D$18-'Ejercicio 3 - TIR'!$C$18)*F10),'Ejercicio 3 - TIR'!$E$18-SQRT(('Ejercicio 3 - TIR'!$E$18-'Ejercicio 3 - TIR'!$C$18)*('Ejercicio 3 - TIR'!$E$18-'Ejercicio 3 - TIR'!$D$18)*(1-F10))) -> 35771.85 | H10: =RAND() -> 0.63741707 | I10: =IF(H10<=('Ejercicio 3 - TIR'!$D$18-'Ejercicio 3 - TIR'!$C$18)/('Ejercicio 3 - TIR'!$E$18-'Ejercicio 3 - TIR'!$C$18),'Ejercicio 3 - TIR'!$C$18+SQRT(('Ejercicio 3 - TIR'!$E$18-'Ejercicio 3 - TIR'!$C$18)*('Ejercicio 3 - TIR'!$D$18-'Ejercicio 3 - TIR'!$C$18)*H10),'Ejercicio 3 - TIR'!$E$18-SQRT(('Ejercicio 3 - TIR'!$E$18-'Ejercicio 3 - TIR'!$C$18)*('Ejercicio 3 - TIR'!$E$18-'Ejercicio 3 - TIR'!$D$18)*(1-H10))) -> 39778.168 | J10: =RAND() -> 0.58152411 | K10: =IF(J10<=('Ejercicio 3 - TIR'!$D$18-'Ejercicio 3 - TIR'!$C$18)/('Ejercicio 3 - TIR'!$E$18-'Ejercicio 3 - TIR'!$C$18),'Ejercicio 3 - TIR'!$C$18+SQRT(('Ejercicio 3 - TIR'!$E$18-'Ejercicio 3 - TIR'!$C$18)*('Ejercicio 3 - TIR'!$D$18-'Ejercicio 3 - TIR'!$C$18)*J10),'Ejercicio 3 - TIR'!$E$18-SQRT(('Ejercicio 3 - TIR'!$E$18-'Ejercicio 3 - TIR'!$C$18)*('Ejercicio 3 - TIR'!$E$18-'Ejercicio 3 - TIR'!$D$18)*(1-J10))) -> 39339.626 | L10: =RAND() -> 0.90611469 | M10: =IF(L10<=('Ejercicio 3 - TIR'!$D$18-'Ejercicio 3 - TIR'!$C$18)/('Ejercicio 3 - TIR'!$E$18-'Ejercicio 3 - TIR'!$C$18),'Ejercicio 3 - TIR'!$C$18+SQRT(('Ejercicio 3 - TIR'!$E$18-'Ejercicio 3 - TIR'!$C$18)*('Ejercicio 3 - TIR'!$D$18-'Ejercicio 3 - TIR'!$C$18)*L10),'Ejercicio 3 - TIR'!$E$18-SQRT(('Ejercicio 3 - TIR'!$E$18-'Ejercicio 3 - TIR'!$C$18)*('Ejercicio 3 - TIR'!$E$18-'Ejercicio 3 - TIR'!$D$18)*(1-L10))) -> 42346.437 | N10: =RAND() -> 0.75144717 | O10: =IF(N10<=('Ejercicio 3 - TIR'!$D$18-'Ejercicio 3 - TIR'!$C$18)/('Ejercicio 3 - TIR'!$E$18-'Ejercicio 3 - TIR'!$C$18),'Ejercicio 3 - TIR'!$C$18+SQRT(('Ejercicio 3 - TIR'!$E$18-'Ejercicio 3 - TIR'!$C$18)*('Ejercicio 3 - TIR'!$D$18-'Ejercicio 3 - TIR'!$C$18)*N10),'Ejercicio 3 - TIR'!$E$18-SQRT(('Ejercicio 3 - TIR'!$E$18-'Ejercicio 3 - TIR'!$C$18)*('Ejercicio 3 - TIR'!$E$18-'Ejercicio 3 - TIR'!$D$18)*(1-N10))) -> 40682.424 | P10: =RAND() -> 0.25704007 | Q10: =IF(P10<=('Ejercicio 3 - TIR'!$D$22-'Ejercicio 3 - TIR'!$C$22)/('Ejercicio 3 - TIR'!$E$22-'Ejercicio 3 - TIR'!$C$22),'Ejercicio 3 - TIR'!$C$22+SQRT(('Ejercicio 3 - TIR'!$E$22-'Ejercicio 3 - TIR'!$C$22)*('Ejercicio 3 - TIR'!$D$22-'Ejercicio 3 - TIR'!$C$22)*P10),'Ejercicio 3 - TIR'!$E$22-SQRT(('Ejercicio 3 - TIR'!$E$22-'Ejercicio 3 - TIR'!$C$22)*('Ejercicio 3 - TIR'!$E$22-'Ejercicio 3 - TIR'!$D$22)*(1-P10))) -> 0.14150981 | R10: =RAND() -> 0.15445647 | S10: =IF(R10<=('Ejercicio 3 - TIR'!$D$23-'Ejercicio 3 - TIR'!$C$23)/('Ejercicio 3 - TIR'!$E$23-'Ejercicio 3 - TIR'!$C$23),'Ejercicio 3 - TIR'!$C$23+SQRT(('Ejercicio 3 - TIR'!$E$23-'Ejercicio 3 - TIR'!$C$23)*('Ejercicio 3 - TIR'!$D$23-'Ejercicio 3 - TIR'!$C$23)*R10),'Ejercicio 3 - TIR'!$E$23-SQRT(('Ejercicio 3 - TIR'!$E$23-'Ejercicio 3 - TIR'!$C$23)*('Ejercicio 3 - TIR'!$E$23-'Ejercicio 3 - TIR'!$D$23)*(1-R10))) -> 0.13667398 | T10: =RAND() -> 0.22608998 | U10: =IF(T10<=('Ejercicio 3 - TIR'!$D$24-'Ejercicio 3 - TIR'!$C$24)/('Ejercicio 3 - TIR'!$E$24-'Ejercicio 3 - TIR'!$C$24),'Ejercicio 3 - TIR'!$C$24+SQRT(('Ejercicio 3 - TIR'!$E$24-'Ejercicio 3 - TIR'!$C$24)*('Ejercicio 3 - TIR'!$D$24-'Ejercicio 3 - TIR'!$C$24)*T10),'Ejercicio 3 - TIR'!$E$24-SQRT(('Ejercicio 3 - TIR'!$E$24-'Ejercicio 3 - TIR'!$C$24)*('Ejercicio 3 - TIR'!$E$24-'Ejercicio 3 - TIR'!$D$24)*(1-T10))) -> 0.17178965 | V10: =RAND() -> 0.90462726 | W10: =IF(V10<=('Ejercicio 3 - TIR'!$D$25-'Ejercicio 3 - TIR'!$C$25)/('Ejercicio 3 - TIR'!$E$25-'Ejercicio 3 - TIR'!$C$25),'Ejercicio 3 - TIR'!$C$25+SQRT(('Ejercicio 3 - TIR'!$E$25-'Ejercicio 3 - TIR'!$C$25)*('Ejercicio 3 - TIR'!$D$25-'Ejercicio 3 - TIR'!$C$25)*V10),'Ejercicio 3 - TIR'!$E$25-SQRT(('Ejercicio 3 - TIR'!$E$25-'Ejercicio 3 - TIR'!$C$25)*('Ejercicio 3 - TIR'!$E$25-'Ejercicio 3 - TIR'!$D$25)*(1-V10))) -> 0.23172968 | X10: =RAND() -> 0.96317778 | Y10: =IF(X10<=('Ejercicio 3 - TIR'!$D$26-'Ejercicio 3 - TIR'!$C$26)/('Ejercicio 3 - TIR'!$E$26-'Ejercicio 3 - TIR'!$C$26),'Ejercicio 3 - TIR'!$C$26+SQRT(('Ejercicio 3 - TIR'!$E$26-'Ejercicio 3 - TIR'!$C$26)*('Ejercicio 3 - TIR'!$D$26-'Ejercicio 3 - TIR'!$C$26)*X10),'Ejercicio 3 - TIR'!$E$26-SQRT(('Ejercicio 3 - TIR'!$E$26-'Ejercicio 3 - TIR'!$C$26)*('Ejercicio 3 - TIR'!$E$26-'Ejercicio 3 - TIR'!$D$26)*(1-X10))) -> 0.26589894 | Z10: =(1+Q10) -> 1.1415098 | AA10: =Z10*(1+S10) -> 1.2975245 | AB10: =AA10*(1+U10) -> 1.5204258 | AC10: =AB10*(1+W10) -> 1.8727536 | AD10: =AC10*(1+Y10) -> 2.3707168 | AE10: =E10*Q10 -> 4742.7864 | AF10: =AE10*(1+S10) -> 5391.0019 | AG10: =AF10*(1+U10) -> 6317.1202 | AH10: =AG10*(1+W10) -> 7780.9845 | AI10: =AH10*(1+Y10) -> 9849.94 | AJ10: =G10*Z10 -> 40833.918 | AK10: =I10*AA10 -> 51613.147 | AL10: =K10*AB10 -> 59812.982 | AM10: =M10*AC10 -> 79304.441 | AN10: =O10*AD10 -> 96446.504 | AO10: =C10/'Ejercicio 3 - TIR'!$D$7 -> 15028.126 | AP10: =AJ10-AO10 -> 25805.791 | AQ10: =AK10-AO10 -> 36585.021 | AR10: =AL10-AO10 -> 44784.856 | AS10: =AM10-AO10 -> 64276.314 | AT10: =AN10-AO10 -> 81418.378 | AU10: =AP10*'Ejercicio 3 - TIR'!$D$5 -> 12902.896 | AV10: =AQ10*'Ejercicio 3 - TIR'!$D$5 -> 18292.51 | AW10: =AR10*'Ejercicio 3 - TIR'!$D$5 -> 22392.428 | AX10: =AS10*'Ejercicio 3 - TIR'!$D$5 -> 32138.157 | AY10: =AT10*'Ejercicio 3 - TIR'!$D$5 -> 40709.189 | AZ10: =AJ10-AU10-AE10 -> 23188.236 | BA10: =AK10-AV10-AF10 -> 27929.635 | BB10: =AL10-AW10-AG10 -> 31103.434 | BC10: =AM10-AX10-AH10 -> 39385.299 | BD10: =AN10-AY10-AI10 -> 45887.375 | BE10: =AZ10/Z10 -> 20313.654 | BF10: =BA10/AA10 -> 21525.324 | BG10: =BB10/AB10 -> 20457.055 | BH10: =BC10/AC10 -> 21030.69 | BI10: =BD10/AD10 -> 19355.908 | BJ10: =E10*AD10 -> 79455.995 | BK10: =0.2*C10*AD10 -> 35627.431 | BL10: =BJ10+BK10 -> 115083.43 | BM10: =BK10*'Ejercicio 3 - TIR'!$D$5 -> 17813.715 | BN10: =BL10-BM10 -> 97269.711 | BO10: =BN10/AD10 -> 41029.664 | BP10: =-(C10+E10) -> -108656.23 | BQ10: =BE10 -> 20313.654 | BR10: =BF10 -> 21525.324 | BS10: =BG10 -> 20457.055 | BT10: =BH10 -> 21030.69 | BU10: =BI10+BO10 -> 60385.571 | BV10: =IFERROR(IRR(BP10:BU10,0.1),NA())*100 -> 8.4113158
A11: 10 | B11: =RAND() -> 0.63302908 | C11: =IF(B11<=('Ejercicio 3 - TIR'!$D$13-'Ejercicio 3 - TIR'!$C$13)/('Ejercicio 3 - TIR'!$E$13-'Ejercicio 3 - TIR'!$C$13),'Ejercicio 3 - TIR'!$C$13+SQRT(('Ejercicio 3 - TIR'!$E$13-'Ejercicio 3 - TIR'!$C$13)*('Ejercicio 3 - TIR'!$D$13-'Ejercicio 3 - TIR'!$C$13)*B11),'Ejercicio 3 - TIR'!$E$13-SQRT(('Ejercicio 3 - TIR'!$E$13-'Ejercicio 3 - TIR'!$C$13)*('Ejercicio 3 - TIR'!$E$13-'Ejercicio 3 - TIR'!$D$13)*(1-B11))) -> 79015.122 | D11: =RAND() -> 0.80985979 | E11: =IF(D11<=('Ejercicio 3 - TIR'!$D$14-'Ejercicio 3 - TIR'!$C$14)/('Ejercicio 3 - TIR'!$E$14-'Ejercicio 3 - TIR'!$C$14),'Ejercicio 3 - TIR'!$C$14+SQRT(('Ejercicio 3 - TIR'!$E$14-'Ejercicio 3 - TIR'!$C$14)*('Ejercicio 3 - TIR'!$D$14-'Ejercicio 3 - TIR'!$C$14)*D11),'Ejercicio 3 - TIR'!$E$14-SQRT(('Ejercicio 3 - TIR'!$E$14-'Ejercicio 3 - TIR'!$C$14)*('Ejercicio 3 - TIR'!$E$14-'Ejercicio 3 - TIR'!$D$14)*(1-D11))) -> 34659.491 | F11: =RAND() -> 0.5629416 | G11: =IF(F11<=('Ejercicio 3 - TIR'!$D$18-'Ejercicio 3 - TIR'!$C$18)/('Ejercicio 3 - TIR'!$E$18-'Ejercicio 3 - TIR'!$C$18),'Ejercicio 3 - TIR'!$C$18+SQRT(('Ejercicio 3 - TIR'!$E$18-'Ejercicio 3 - TIR'!$C$18)*('Ejercicio 3 - TIR'!$D$18-'Ejercicio 3 - TIR'!$C$18)*F11),'Ejercicio 3 - TIR'!$E$18-SQRT(('Ejercicio 3 - TIR'!$E$18-'Ejercicio 3 - TIR'!$C$18)*('Ejercicio 3 - TIR'!$E$18-'Ejercicio 3 - TIR'!$D$18)*(1-F11))) -> 39189.191 | H11: =RAND() -> 0.62905848 | I11: =IF(H11<=('Ejercicio 3 - TIR'!$D$18-'Ejercicio 3 - TIR'!$C$18)/('Ejercicio 3 - TIR'!$E$18-'Ejercicio 3 - TIR'!$C$18),'Ejercicio 3 - TIR'!$C$18+SQRT(('Ejercicio 3 - TIR'!$E$18-'Ejercicio 3 - TIR'!$C$18)*('Ejercicio 3 - TIR'!$D$18-'Ejercicio 3 - TIR'!$C$18)*H11),'Ejercicio 3 - TIR'!$E$18-SQRT(('Ejercicio 3 - TIR'!$E$18-'Ejercicio 3 - TIR'!$C$18)*('Ejercicio 3 - TIR'!$E$18-'Ejercicio 3 - TIR'!$D$18)*(1-H11))) -> 39713.844 | J11: =RAND() -> 0.095252508 | K11: =IF(J11<=('Ejercicio 3 - TIR'!$D$18-'Ejercicio 3 - TIR'!$C$18)/('Ejercicio 3 - TIR'!$E$18-'Ejercicio 3 - TIR'!$C$18),'Ejercicio 3 - TIR'!$C$18+SQRT(('Ejercicio 3 - TIR'!$E$18-'Ejercicio 3 - TIR'!$C$18)*('Ejercicio 3 - TIR'!$D$18-'Ejercicio 3 - TIR'!$C$18)*J11),'Ejercicio 3 - TIR'!$E$18-SQRT(('Ejercicio 3 - TIR'!$E$18-'Ejercicio 3 - TIR'!$C$18)*('Ejercicio 3 - TIR'!$E$18-'Ejercicio 3 - TIR'!$D$18)*(1-J11))) -> 33779.931 | L11: =RAND() -> 0.73917195 | M11: =IF(L11<=('Ejercicio 3 - TIR'!$D$18-'Ejercicio 3 - TIR'!$C$18)/('Ejercicio 3 - TIR'!$E$18-'Ejercicio 3 - TIR'!$C$18),'Ejercicio 3 - TIR'!$C$18+SQRT(('Ejercicio 3 - TIR'!$E$18-'Ejercicio 3 - TIR'!$C$18)*('Ejercicio 3 - TIR'!$D$18-'Ejercicio 3 - TIR'!$C$18)*L11),'Ejercicio 3 - TIR'!$E$18-SQRT(('Ejercicio 3 - TIR'!$E$18-'Ejercicio 3 - TIR'!$C$18)*('Ejercicio 3 - TIR'!$E$18-'Ejercicio 3 - TIR'!$D$18)*(1-L11))) -> 40577.093 | N11: =RAND() -> 0.98924697 | O11: =IF(N11<=('Ejercicio 3 - TIR'!$D$18-'Ejercicio 3 - TIR'!$C$18)/('Ejercicio 3 - TIR'!$E$18-'Ejercicio 3 - TIR'!$C$18),'Ejercicio 3 - TIR'!$C$18+SQRT(('Ejercicio 3 - TIR'!$E$18-'Ejercicio 3 - TIR'!$C$18)*('Ejercicio 3 - TIR'!$D$18-'Ejercicio 3 - TIR'!$C$18)*N11),'Ejercicio 3 - TIR'!$E$18-SQRT(('Ejercicio 3 - TIR'!$E$18-'Ejercicio 3 - TIR'!$C$18)*('Ejercicio 3 - TIR'!$E$18-'Ejercicio 3 - TIR'!$D$18)*(1-N11))) -> 44101.959 | P11: =RAND() -> 0.53450213 | Q11: =IF(P11<=('Ejercicio 3 - TIR'!$D$22-'Ejercicio 3 - TIR'!$C$22)/('Ejercicio 3 - TIR'!$E$22-'Ejercicio 3 - TIR'!$C$22),'Ejercicio 3 - TIR'!$C$22+SQRT(('Ejercicio 3 - TIR'!$E$22-'Ejercicio 3 - TIR'!$C$22)*('Ejercicio 3 - TIR'!$D$22-'Ejercicio 3 - TIR'!$C$22)*P11),'Ejercicio 3 - TIR'!$E$22-SQRT(('Ejercicio 3 - TIR'!$E$22-'Ejercicio 3 - TIR'!$C$22)*('Ejercicio 3 - TIR'!$E$22-'Ejercicio 3 - TIR'!$D$22)*(1-P11))) -> 0.15105356 | R11: =RAND() -> 0.231097 | S11: =IF(R11<=('Ejercicio 3 - TIR'!$D$23-'Ejercicio 3 - TIR'!$C$23)/('Ejercicio 3 - TIR'!$E$23-'Ejercicio 3 - TIR'!$C$23),'Ejercicio 3 - TIR'!$C$23+SQRT(('Ejercicio 3 - TIR'!$E$23-'Ejercicio 3 - TIR'!$C$23)*('Ejercicio 3 - TIR'!$D$23-'Ejercicio 3 - TIR'!$C$23)*R11),'Ejercicio 3 - TIR'!$E$23-SQRT(('Ejercicio 3 - TIR'!$E$23-'Ejercicio 3 - TIR'!$C$23)*('Ejercicio 3 - TIR'!$E$23-'Ejercicio 3 - TIR'!$D$23)*(1-R11))) -> 0.14039546 | T11: =RAND() -> 0.8613957 | U11: =IF(T11<=('Ejercicio 3 - TIR'!$D$24-'Ejercicio 3 - TIR'!$C$24)/('Ejercicio 3 - TIR'!$E$24-'Ejercicio 3 - TIR'!$C$24),'Ejercicio 3 - TIR'!$C$24+SQRT(('Ejercicio 3 - TIR'!$E$24-'Ejercicio 3 - TIR'!$C$24)*('Ejercicio 3 - TIR'!$D$24-'Ejercicio 3 - TIR'!$C$24)*T11),'Ejercicio 3 - TIR'!$E$24-SQRT(('Ejercicio 3 - TIR'!$E$24-'Ejercicio 3 - TIR'!$C$24)*('Ejercicio 3 - TIR'!$E$24-'Ejercicio 3 - TIR'!$D$24)*(1-T11))) -> 0.20029995 | V11: =RAND() -> 0.72325385 | W11: =IF(V11<=('Ejercicio 3 - TIR'!$D$25-'Ejercicio 3 - TIR'!$C$25)/('Ejercicio 3 - TIR'!$E$25-'Ejercicio 3 - TIR'!$C$25),'Ejercicio 3 - TIR'!$C$25+SQRT(('Ejercicio 3 - TIR'!$E$25-'Ejercicio 3 - TIR'!$C$25)*('Ejercicio 3 - TIR'!$D$25-'Ejercicio 3 - TIR'!$C$25)*V11),'Ejercicio 3 - TIR'!$E$25-SQRT(('Ejercicio 3 - TIR'!$E$25-'Ejercicio 3 - TIR'!$C$25)*('Ejercicio 3 - TIR'!$E$25-'Ejercicio 3 - TIR'!$D$25)*(1-V11))) -> 0.21887748 | X11: =RAND() -> 0.1158294 | Y11: =IF(X11<=('Ejercicio 3 - TIR'!$D$26-'Ejercicio 3 - TIR'!$C$26)/('Ejercicio 3 - TIR'!$E$26-'Ejercicio 3 - TIR'!$C$26),'Ejercicio 3 - TIR'!$C$26+SQRT(('Ejercicio 3 - TIR'!$E$26-'Ejercicio 3 - TIR'!$C$26)*('Ejercicio 3 - TIR'!$D$26-'Ejercicio 3 - TIR'!$C$26)*X11),'Ejercicio 3 - TIR'!$E$26-SQRT(('Ejercicio 3 - TIR'!$E$26-'Ejercicio 3 - TIR'!$C$26)*('Ejercicio 3 - TIR'!$E$26-'Ejercicio 3 - TIR'!$D$26)*(1-X11))) -> 0.20768444 | Z11: =(1+Q11) -> 1.1510536 | AA11: =Z11*(1+S11) -> 1.3126563 | AB11: =AA11*(1+U11) -> 1.5755812 | AC11: =AB11*(1+W11) -> 1.9204405 | AD11: =AC11*(1+Y11) -> 2.3192861 | AE11: =E11*Q11 -> 5235.4397 | AF11: =AE11*(1+S11) -> 5970.4716 | AG11: =AF11*(1+U11) -> 7166.3568 | AH11: =AG11*(1+W11) -> 8734.9109 | AI11: =AH11*(1+Y11) -> 10549.016 | AJ11: =G11*Z11 -> 45108.859 | AK11: =I11*AA11 -> 52130.626 | AL11: =K11*AB11 -> 53223.025 | AM11: =M11*AC11 -> 77925.892 | AN11: =O11*AD11 -> 102285.06 | AO11: =C11/'Ejercicio 3 - TIR'!$D$7 -> 15803.024 | AP11: =AJ11-AO11 -> 29305.834 | AQ11: =AK11-AO11 -> 36327.602 | AR11: =AL11-AO11 -> 37420 | AS11: =AM11-AO11 -> 62122.868 | AT11: =AN11-AO11 -> 86482.036 | AU11: =AP11*'Ejercicio 3 - TIR'!$D$5 -> 14652.917 | AV11: =AQ11*'Ejercicio 3 - TIR'!$D$5 -> 18163.801 | AW11: =AR11*'Ejercicio 3 - TIR'!$D$5 -> 18710 | AX11: =AS11*'Ejercicio 3 - TIR'!$D$5 -> 31061.434 | AY11: =AT11*'Ejercicio 3 - TIR'!$D$5 -> 43241.018 | AZ11: =AJ11-AU11-AE11 -> 25220.502 | BA11: =AK11-AV11-AF11 -> 27996.354 | BB11: =AL11-AW11-AG11 -> 27346.668 | BC11: =AM11-AX11-AH11 -> 38129.547 | BD11: =AN11-AY11-AI11 -> 48495.026 | BE11: =AZ11/Z11 -> 21910.798 | BF11: =BA11/AA11 -> 21328.016 | BG11: =BB11/AB11 -> 17356.558 | BH11: =BC11/AC11 -> 19854.584 | BI11: =BD11/AD11 -> 20909.463 | BJ11: =E11*AD11 -> 80385.276 | BK11: =0.2*C11*AD11 -> 36651.735 | BL11: =BJ11+BK11 -> 117037.01 | BM11: =BK11*'Ejercicio 3 - TIR'!$D$5 -> 18325.867 | BN11: =BL11-BM11 -> 98711.143 | BO11: =BN11/AD11 -> 42561.004 | BP11: =-(C11+E11) -> -113674.61 | BQ11: =BE11 -> 21910.798 | BR11: =BF11 -> 21328.016 | BS11: =BG11 -> 17356.558 | BT11: =BH11 -> 19854.584 | BU11: =BI11+BO11 -> 63470.467 | BV11: =IFERROR(IRR(BP11:BU11,0.1),NA())*100 -> 7.000038
A12: 11 | B12: =RAND() -> 0.85197602 | C12: =IF(B12<=('Ejercicio 3 - TIR'!$D$13-'Ejercicio 3 - TIR'!$C$13)/('Ejercicio 3 - TIR'!$E$13-'Ejercicio 3 - TIR'!$C$13),'Ejercicio 3 - TIR'!$C$13+SQRT(('Ejercicio 3 - TIR'!$E$13-'Ejercicio 3 - TIR'!$C$13)*('Ejercicio 3 - TIR'!$D$13-'Ejercicio 3 - TIR'!$C$13)*B12),'Ejercicio 3 - TIR'!$E$13-SQRT(('Ejercicio 3 - TIR'!$E$13-'Ejercicio 3 - TIR'!$C$13)*('Ejercicio 3 - TIR'!$E$13-'Ejercicio 3 - TIR'!$D$13)*(1-B12))) -> 86672.255 | D12: =RAND() -> 0.49971506 | E12: =IF(D12<=('Ejercicio 3 - TIR'!$D$14-'Ejercicio 3 - TIR'!$C$14)/('Ejercicio 3 - TIR'!$E$14-'Ejercicio 3 - TIR'!$C$14),'Ejercicio 3 - TIR'!$C$14+SQRT(('Ejercicio 3 - TIR'!$E$14-'Ejercicio 3 - TIR'!$C$14)*('Ejercicio 3 - TIR'!$D$14-'Ejercicio 3 - TIR'!$C$14)*D12),'Ejercicio 3 - TIR'!$E$14-SQRT(('Ejercicio 3 - TIR'!$E$14-'Ejercicio 3 - TIR'!$C$14)*('Ejercicio 3 - TIR'!$E$14-'Ejercicio 3 - TIR'!$D$14)*(1-D12))) -> 31337.279 | F12: =RAND() -> 0.34570301 | G12: =IF(F12<=('Ejercicio 3 - TIR'!$D$18-'Ejercicio 3 - TIR'!$C$18)/('Ejercicio 3 - TIR'!$E$18-'Ejercicio 3 - TIR'!$C$18),'Ejercicio 3 - TIR'!$C$18+SQRT(('Ejercicio 3 - TIR'!$E$18-'Ejercicio 3 - TIR'!$C$18)*('Ejercicio 3 - TIR'!$D$18-'Ejercicio 3 - TIR'!$C$18)*F12),'Ejercicio 3 - TIR'!$E$18-SQRT(('Ejercicio 3 - TIR'!$E$18-'Ejercicio 3 - TIR'!$C$18)*('Ejercicio 3 - TIR'!$E$18-'Ejercicio 3 - TIR'!$D$18)*(1-F12))) -> 37201.073 | H12: =RAND() -> 0.3279295 | I12: =IF(H12<=('Ejercicio 3 - TIR'!$D$18-'Ejercicio 3 - TIR'!$C$18)/('Ejercicio 3 - TIR'!$E$18-'Ejercicio 3 - TIR'!$C$18),'Ejercicio 3 - TIR'!$C$18+SQRT(('Ejercicio 3 - TIR'!$E$18-'Ejercicio 3 - TIR'!$C$18)*('Ejercicio 3 - TIR'!$D$18-'Ejercicio 3 - TIR'!$C$18)*H12),'Ejercicio 3 - TIR'!$E$18-SQRT(('Ejercicio 3 - TIR'!$E$18-'Ejercicio 3 - TIR'!$C$18)*('Ejercicio 3 - TIR'!$E$18-'Ejercicio 3 - TIR'!$D$18)*(1-H12))) -> 37013.517 | J12: =RAND() -> 0.6000625 | K12: =IF(J12<=('Ejercicio 3 - TIR'!$D$18-'Ejercicio 3 - TIR'!$C$18)/('Ejercicio 3 - TIR'!$E$18-'Ejercicio 3 - TIR'!$C$18),'Ejercicio 3 - TIR'!$C$18+SQRT(('Ejercicio 3 - TIR'!$E$18-'Ejercicio 3 - TIR'!$C$18)*('Ejercicio 3 - TIR'!$D$18-'Ejercicio 3 - TIR'!$C$18)*J12),'Ejercicio 3 - TIR'!$E$18-SQRT(('Ejercicio 3 - TIR'!$E$18-'Ejercicio 3 - TIR'!$C$18)*('Ejercicio 3 - TIR'!$E$18-'Ejercicio 3 - TIR'!$D$18)*(1-J12))) -> 39487.327 | L12: =RAND() -> 0.73046128 | M12: =IF(L12<=('Ejercicio 3 - TIR'!$D$18-'Ejercicio 3 - TIR'!$C$18)/('Ejercicio 3 - TIR'!$E$18-'Ejercicio 3 - TIR'!$C$18),'Ejercicio 3 - TIR'!$C$18+SQRT(('Ejercicio 3 - TIR'!$E$18-'Ejercicio 3 - TIR'!$C$18)*('Ejercicio 3 - TIR'!$D$18-'Ejercicio 3 - TIR'!$C$18)*L12),'Ejercicio 3 - TIR'!$E$18-SQRT(('Ejercicio 3 - TIR'!$E$18-'Ejercicio 3 - TIR'!$C$18)*('Ejercicio 3 - TIR'!$E$18-'Ejercicio 3 - TIR'!$D$18)*(1-L12))) -> 40503.846 | N12: =RAND() -> 0.7648605 | O12: =IF(N12<=('Ejercicio 3 - TIR'!$D$18-'Ejercicio 3 - TIR'!$C$18)/('Ejercicio 3 - TIR'!$E$18-'Ejercicio 3 - TIR'!$C$18),'Ejercicio 3 - TIR'!$C$18+SQRT(('Ejercicio 3 - TIR'!$E$18-'Ejercicio 3 - TIR'!$C$18)*('Ejercicio 3 - TIR'!$D$18-'Ejercicio 3 - TIR'!$C$18)*N12),'Ejercicio 3 - TIR'!$E$18-SQRT(('Ejercicio 3 - TIR'!$E$18-'Ejercicio 3 - TIR'!$C$18)*('Ejercicio 3 - TIR'!$E$18-'Ejercicio 3 - TIR'!$D$18)*(1-N12))) -> 40800.54 | P12: =RAND() -> 0.74801186 | Q12: =IF(P12<=('Ejercicio 3 - TIR'!$D$22-'Ejercicio 3 - TIR'!$C$22)/('Ejercicio 3 - TIR'!$E$22-'Ejercicio 3 - TIR'!$C$22),'Ejercicio 3 - TIR'!$C$22+SQRT(('Ejercicio 3 - TIR'!$E$22-'Ejercicio 3 - TIR'!$C$22)*('Ejercicio 3 - TIR'!$D$22-'Ejercicio 3 - TIR'!$C$22)*P12),'Ejercicio 3 - TIR'!$E$22-SQRT(('Ejercicio 3 - TIR'!$E$22-'Ejercicio 3 - TIR'!$C$22)*('Ejercicio 3 - TIR'!$E$22-'Ejercicio 3 - TIR'!$D$22)*(1-P12))) -> 0.15870261 | R12: =RAND() -> 0.61996231 | S12: =IF(R12<=('Ejercicio 3 - TIR'!$D$23-'Ejercicio 3 - TIR'!$C$23)/('Ejercicio 3 - TIR'!$E$23-'Ejercicio 3 - TIR'!$C$23),'Ejercicio 3 - TIR'!$C$23+SQRT(('Ejercicio 3 - TIR'!$E$23-'Ejercicio 3 - TIR'!$C$23)*('Ejercicio 3 - TIR'!$D$23-'Ejercicio 3 - TIR'!$C$23)*R12),'Ejercicio 3 - TIR'!$E$23-SQRT(('Ejercicio 3 - TIR'!$E$23-'Ejercicio 3 - TIR'!$C$23)*('Ejercicio 3 - TIR'!$E$23-'Ejercicio 3 - TIR'!$D$23)*(1-R12))) -> 0.15384531 | T12: =RAND() -> 0.70989994 | U12: =IF(T12<=('Ejercicio 3 - TIR'!$D$24-'Ejercicio 3 - TIR'!$C$24)/('Ejercicio 3 - TIR'!$E$24-'Ejercicio 3 - TIR'!$C$24),'Ejercicio 3 - TIR'!$C$24+SQRT(('Ejercicio 3 - TIR'!$E$24-'Ejercicio 3 - TIR'!$C$24)*('Ejercicio 3 - TIR'!$D$24-'Ejercicio 3 - TIR'!$C$24)*T12),'Ejercicio 3 - TIR'!$E$24-SQRT(('Ejercicio 3 - TIR'!$E$24-'Ejercicio 3 - TIR'!$C$24)*('Ejercicio 3 - TIR'!$E$24-'Ejercicio 3 - TIR'!$D$24)*(1-T12))) -> 0.19149947 | V12: =RAND() -> 0.6364609 | W12: =IF(V12<=('Ejercicio 3 - TIR'!$D$25-'Ejercicio 3 - TIR'!$C$25)/('Ejercicio 3 - TIR'!$E$25-'Ejercicio 3 - TIR'!$C$25),'Ejercicio 3 - TIR'!$C$25+SQRT(('Ejercicio 3 - TIR'!$E$25-'Ejercicio 3 - TIR'!$C$25)*('Ejercicio 3 - TIR'!$D$25-'Ejercicio 3 - TIR'!$C$25)*V12),'Ejercicio 3 - TIR'!$E$25-SQRT(('Ejercicio 3 - TIR'!$E$25-'Ejercicio 3 - TIR'!$C$25)*('Ejercicio 3 - TIR'!$E$25-'Ejercicio 3 - TIR'!$D$25)*(1-V12))) -> 0.21432947 | X12: =RAND() -> 0.48486015 | Y12: =IF(X12<=('Ejercicio 3 - TIR'!$D$26-'Ejercicio 3 - TIR'!$C$26)/('Ejercicio 3 - TIR'!$E$26-'Ejercicio 3 - TIR'!$C$26),'Ejercicio 3 - TIR'!$C$26+SQRT(('Ejercicio 3 - TIR'!$E$26-'Ejercicio 3 - TIR'!$C$26)*('Ejercicio 3 - TIR'!$D$26-'Ejercicio 3 - TIR'!$C$26)*X12),'Ejercicio 3 - TIR'!$E$26-SQRT(('Ejercicio 3 - TIR'!$E$26-'Ejercicio 3 - TIR'!$C$26)*('Ejercicio 3 - TIR'!$E$26-'Ejercicio 3 - TIR'!$D$26)*(1-X12))) -> 0.22725765 | Z12: =(1+Q12) -> 1.1587026 | AA12: =Z12*(1+S12) -> 1.3369636 | AB12: =AA12*(1+U12) -> 1.5929914 | AC12: =AB12*(1+W12) -> 1.9344164 | AD12: =AC12*(1+Y12) -> 2.3740273 | AE12: =E12*Q12 -> 4973.308 | AF12: =AE12*(1+S12) -> 5738.4282 | AG12: =AF12*(1+U12) -> 6837.3341 | AH12: =AG12*(1+W12) -> 8302.7763 | AI12: =AH12*(1+Y12) -> 10189.646 | AJ12: =G12*Z12 -> 43104.98 | AK12: =I12*AA12 -> 49485.725 | AL12: =K12*AB12 -> 62902.972 | AM12: =M12*AC12 -> 78351.303 | AN12: =O12*AD12 -> 96861.597 | AO12: =C12/'Ejercicio 3 - TIR'!$D$7 -> 17334.451 | AP12: =AJ12-AO12 -> 25770.529 | AQ12: =AK12-AO12 -> 32151.273 | AR12: =AL12-AO12 -> 45568.521 | AS12: =AM12-AO12 -> 61016.852 | AT12: =AN12-AO12 -> 79527.146 | AU12: =AP12*'Ejercicio 3 - TIR'!$D$5 -> 12885.265 | AV12: =AQ12*'Ejercicio 3 - TIR'!$D$5 -> 16075.637 | AW12: =AR12*'Ejercicio 3 - TIR'!$D$5 -> 22784.261 | AX12: =AS12*'Ejercicio 3 - TIR'!$D$5 -> 30508.426 | AY12: =AT12*'Ejercicio 3 - TIR'!$D$5 -> 39763.573 | AZ12: =AJ12-AU12-AE12 -> 25246.408 | BA12: =AK12-AV12-AF12 -> 27671.66 | BB12: =AL12-AW12-AG12 -> 33281.378 | BC12: =AM12-AX12-AH12 -> 39540.101 | BD12: =AN12-AY12-AI12 -> 46908.378 | BE12: =AZ12/Z12 -> 21788.514 | BF12: =BA12/AA12 -> 20697.392 | BG12: =BB12/AB12 -> 20892.377 | BH12: =BC12/AC12 -> 20440.326 | BI12: =BD12/AD12 -> 19758.988 | BJ12: =E12*AD12 -> 74395.556 | BK12: =0.2*C12*AD12 -> 41152.46 | BL12: =BJ12+BK12 -> 115548.02 | BM12: =BK12*'Ejercicio 3 - TIR'!$D$5 -> 20576.23 | BN12: =BL12-BM12 -> 94971.786 | BO12: =BN12/AD12 -> 40004.504 | BP12: =-(C12+E12) -> -118009.53 | BQ12: =BE12 -> 21788.514 | BR12: =BF12 -> 20697.392 | BS12: =BG12 -> 20892.377 | BT12: =BH12 -> 20440.326 | BU12: =BI12+BO12 -> 59763.493 | BV12: =IFERROR(IRR(BP12:BU12,0.1),NA())*100 -> 5.8295688
A13: 12 | B13: =RAND() -> 0.80414858 | C13: =IF(B13<=('Ejercicio 3 - TIR'!$D$13-'Ejercicio 3 - TIR'!$C$13)/('Ejercicio 3 - TIR'!$E$13-'Ejercicio 3 - TIR'!$C$13),'Ejercicio 3 - TIR'!$C$13+SQRT(('Ejercicio 3 - TIR'!$E$13-'Ejercicio 3 - TIR'!$C$13)*('Ejercicio 3 - TIR'!$D$13-'Ejercicio 3 - TIR'!$C$13)*B13),'Ejercicio 3 - TIR'!$E$13-SQRT(('Ejercicio 3 - TIR'!$E$13-'Ejercicio 3 - TIR'!$C$13)*('Ejercicio 3 - TIR'!$E$13-'Ejercicio 3 - TIR'!$D$13)*(1-B13))) -> 84669.582 | D13: =RAND() -> 0.59048217 | E13: =IF(D13<=('Ejercicio 3 - TIR'!$D$14-'Ejercicio 3 - TIR'!$C$14)/('Ejercicio 3 - TIR'!$E$14-'Ejercicio 3 - TIR'!$C$14),'Ejercicio 3 - TIR'!$C$14+SQRT(('Ejercicio 3 - TIR'!$E$14-'Ejercicio 3 - TIR'!$C$14)*('Ejercicio 3 - TIR'!$D$14-'Ejercicio 3 - TIR'!$C$14)*D13),'Ejercicio 3 - TIR'!$E$14-SQRT(('Ejercicio 3 - TIR'!$E$14-'Ejercicio 3 - TIR'!$C$14)*('Ejercicio 3 - TIR'!$E$14-'Ejercicio 3 - TIR'!$D$14)*(1-D13))) -> 32162.419 | F13: =RAND() -> 0.15915653 | G13: =IF(F13<=('Ejercicio 3 - TIR'!$D$18-'Ejercicio 3 - TIR'!$C$18)/('Ejercicio 3 - TIR'!$E$18-'Ejercicio 3 - TIR'!$C$18),'Ejercicio 3 - TIR'!$C$18+SQRT(('Ejercicio 3 - TIR'!$E$18-'Ejercicio 3 - TIR'!$C$18)*('Ejercicio 3 - TIR'!$D$18-'Ejercicio 3 - TIR'!$C$18)*F13),'Ejercicio 3 - TIR'!$E$18-SQRT(('Ejercicio 3 - TIR'!$E$18-'Ejercicio 3 - TIR'!$C$18)*('Ejercicio 3 - TIR'!$E$18-'Ejercicio 3 - TIR'!$D$18)*(1-F13))) -> 34886.049 | H13: =RAND() -> 0.51621855 | I13: =IF(H13<=('Ejercicio 3 - TIR'!$D$18-'Ejercicio 3 - TIR'!$C$18)/('Ejercicio 3 - TIR'!$E$18-'Ejercicio 3 - TIR'!$C$18),'Ejercicio 3 - TIR'!$C$18+SQRT(('Ejercicio 3 - TIR'!$E$18-'Ejercicio 3 - TIR'!$C$18)*('Ejercicio 3 - TIR'!$D$18-'Ejercicio 3 - TIR'!$C$18)*H13),'Ejercicio 3 - TIR'!$E$18-SQRT(('Ejercicio 3 - TIR'!$E$18-'Ejercicio 3 - TIR'!$C$18)*('Ejercicio 3 - TIR'!$E$18-'Ejercicio 3 - TIR'!$D$18)*(1-H13))) -> 38799.59 | J13: =RAND() -> 0.53238542 | K13: =IF(J13<=('Ejercicio 3 - TIR'!$D$18-'Ejercicio 3 - TIR'!$C$18)/('Ejercicio 3 - TIR'!$E$18-'Ejercicio 3 - TIR'!$C$18),'Ejercicio 3 - TIR'!$C$18+SQRT(('Ejercicio 3 - TIR'!$E$18-'Ejercicio 3 - TIR'!$C$18)*('Ejercicio 3 - TIR'!$D$18-'Ejercicio 3 - TIR'!$C$18)*J13),'Ejercicio 3 - TIR'!$E$18-SQRT(('Ejercicio 3 - TIR'!$E$18-'Ejercicio 3 - TIR'!$C$18)*('Ejercicio 3 - TIR'!$E$18-'Ejercicio 3 - TIR'!$D$18)*(1-J13))) -> 38936.32 | L13: =RAND() -> 0.31561178 | M13: =IF(L13<=('Ejercicio 3 - TIR'!$D$18-'Ejercicio 3 - TIR'!$C$18)/('Ejercicio 3 - TIR'!$E$18-'Ejercicio 3 - TIR'!$C$18),'Ejercicio 3 - TIR'!$C$18+SQRT(('Ejercicio 3 - TIR'!$E$18-'Ejercicio 3 - TIR'!$C$18)*('Ejercicio 3 - TIR'!$D$18-'Ejercicio 3 - TIR'!$C$18)*L13),'Ejercicio 3 - TIR'!$E$18-SQRT(('Ejercicio 3 - TIR'!$E$18-'Ejercicio 3 - TIR'!$C$18)*('Ejercicio 3 - TIR'!$E$18-'Ejercicio 3 - TIR'!$D$18)*(1-L13))) -> 36880.535 | N13: =RAND() -> 0.41980015 | O13: =IF(N13<=('Ejercicio 3 - TIR'!$D$18-'Ejercicio 3 - TIR'!$C$18)/('Ejercicio 3 - TIR'!$E$18-'Ejercicio 3 - TIR'!$C$18),'Ejercicio 3 - TIR'!$C$18+SQRT(('Ejercicio 3 - TIR'!$E$18-'Ejercicio 3 - TIR'!$C$18)*('Ejercicio 3 - TIR'!$D$18-'Ejercicio 3 - TIR'!$C$18)*N13),'Ejercicio 3 - TIR'!$E$18-SQRT(('Ejercicio 3 - TIR'!$E$18-'Ejercicio 3 - TIR'!$C$18)*('Ejercicio 3 - TIR'!$E$18-'Ejercicio 3 - TIR'!$D$18)*(1-N13))) -> 37935.365 | P13: =RAND() -> 0.88846772 | Q13: =IF(P13<=('Ejercicio 3 - TIR'!$D$22-'Ejercicio 3 - TIR'!$C$22)/('Ejercicio 3 - TIR'!$E$22-'Ejercicio 3 - TIR'!$C$22),'Ejercicio 3 - TIR'!$C$22+SQRT(('Ejercicio 3 - TIR'!$E$22-'Ejercicio 3 - TIR'!$C$22)*('Ejercicio 3 - TIR'!$D$22-'Ejercicio 3 - TIR'!$C$22)*P13),'Ejercicio 3 - TIR'!$E$22-SQRT(('Ejercicio 3 - TIR'!$E$22-'Ejercicio 3 - TIR'!$C$22)*('Ejercicio 3 - TIR'!$E$22-'Ejercicio 3 - TIR'!$D$22)*(1-P13))) -> 0.16583109 | R13: =RAND() -> 0.69989759 | S13: =IF(R13<=('Ejercicio 3 - TIR'!$D$23-'Ejercicio 3 - TIR'!$C$23)/('Ejercicio 3 - TIR'!$E$23-'Ejercicio 3 - TIR'!$C$23),'Ejercicio 3 - TIR'!$C$23+SQRT(('Ejercicio 3 - TIR'!$E$23-'Ejercicio 3 - TIR'!$C$23)*('Ejercicio 3 - TIR'!$D$23-'Ejercicio 3 - TIR'!$C$23)*R13),'Ejercicio 3 - TIR'!$E$23-SQRT(('Ejercicio 3 - TIR'!$E$23-'Ejercicio 3 - TIR'!$C$23)*('Ejercicio 3 - TIR'!$E$23-'Ejercicio 3 - TIR'!$D$23)*(1-R13))) -> 0.15675813 | T13: =RAND() -> 0.87518491 | U13: =IF(T13<=('Ejercicio 3 - TIR'!$D$24-'Ejercicio 3 - TIR'!$C$24)/('Ejercicio 3 - TIR'!$E$24-'Ejercicio 3 - TIR'!$C$24),'Ejercicio 3 - TIR'!$C$24+SQRT(('Ejercicio 3 - TIR'!$E$24-'Ejercicio 3 - TIR'!$C$24)*('Ejercicio 3 - TIR'!$D$24-'Ejercicio 3 - TIR'!$C$24)*T13),'Ejercicio 3 - TIR'!$E$24-SQRT(('Ejercicio 3 - TIR'!$E$24-'Ejercicio 3 - TIR'!$C$24)*('Ejercicio 3 - TIR'!$E$24-'Ejercicio 3 - TIR'!$D$24)*(1-T13))) -> 0.20130556 | V13: =RAND() -> 0.28169159 | W13: =IF(V13<=('Ejercicio 3 - TIR'!$D$25-'Ejercicio 3 - TIR'!$C$25)/('Ejercicio 3 - TIR'!$E$25-'Ejercicio 3 - TIR'!$C$25),'Ejercicio 3 - TIR'!$C$25+SQRT(('Ejercicio 3 - TIR'!$E$25-'Ejercicio 3 - TIR'!$C$25)*('Ejercicio 3 - TIR'!$D$25-'Ejercicio 3 - TIR'!$C$25)*V13),'Ejercicio 3 - TIR'!$E$25-SQRT(('Ejercicio 3 - TIR'!$E$25-'Ejercicio 3 - TIR'!$C$25)*('Ejercicio 3 - TIR'!$E$25-'Ejercicio 3 - TIR'!$D$25)*(1-V13))) -> 0.19985871 | X13: =RAND() -> 0.63607175 | Y13: =IF(X13<=('Ejercicio 3 - TIR'!$D$26-'Ejercicio 3 - TIR'!$C$26)/('Ejercicio 3 - TIR'!$E$26-'Ejercicio 3 - TIR'!$C$26),'Ejercicio 3 - TIR'!$C$26+SQRT(('Ejercicio 3 - TIR'!$E$26-'Ejercicio 3 - TIR'!$C$26)*('Ejercicio 3 - TIR'!$D$26-'Ejercicio 3 - TIR'!$C$26)*X13),'Ejercicio 3 - TIR'!$E$26-SQRT(('Ejercicio 3 - TIR'!$E$26-'Ejercicio 3 - TIR'!$C$26)*('Ejercicio 3 - TIR'!$E$26-'Ejercicio 3 - TIR'!$D$26)*(1-X13))) -> 0.23566928 | Z13: =(1+Q13) -> 1.1658311 | AA13: =Z13*(1+S13) -> 1.3485846 | AB13: =AA13*(1+U13) -> 1.6200622 | AC13: =AB13*(1+W13) -> 1.9438457 | AD13: =AC13*(1+Y13) -> 2.4019504 | AE13: =E13*Q13 -> 5333.5289 | AF13: =AE13*(1+S13) -> 6169.603 | AG13: =AF13*(1+U13) -> 7411.5783 | AH13: =AG13*(1+W13) -> 8892.8468 | AI13: =AH13*(1+Y13) -> 10988.618 | AJ13: =G13*Z13 -> 40671.241 | AK13: =I13*AA13 -> 52324.529 | AL13: =K13*AB13 -> 63079.259 | AM13: =M13*AC13 -> 71690.07 | AN13: =O13*AD13 -> 91118.866 | AO13: =C13/'Ejercicio 3 - TIR'!$D$7 -> 16933.916 | AP13: =AJ13-AO13 -> 23737.324 | AQ13: =AK13-AO13 -> 35390.613 | AR13: =AL13-AO13 -> 46145.342 | AS13: =AM13-AO13 -> 54756.153 | AT13: =AN13-AO13 -> 74184.95 | AU13: =AP13*'Ejercicio 3 - TIR'!$D$5 -> 11868.662 | AV13: =AQ13*'Ejercicio 3 - TIR'!$D$5 -> 17695.306 | AW13: =AR13*'Ejercicio 3 - TIR'!$D$5 -> 23072.671 | AX13: =AS13*'Ejercicio 3 - TIR'!$D$5 -> 27378.077 | AY13: =AT13*'Ejercicio 3 - TIR'!$D$5 -> 37092.475 | AZ13: =AJ13-AU13-AE13 -> 23469.05 | BA13: =AK13-AV13-AF13 -> 28459.62 | BB13: =AL13-AW13-AG13 -> 32595.009 | BC13: =AM13-AX13-AH13 -> 35419.146 | BD13: =AN13-AY13-AI13 -> 43037.774 | BE13: =AZ13/Z13 -> 20130.746 | BF13: =BA13/AA13 -> 21103.326 | BG13: =BB13/AB13 -> 20119.604 | BH13: =BC13/AC13 -> 18221.172 | BI13: =BD13/AD13 -> 17917.844 | BJ13: =E13*AD13 -> 77252.536 | BK13: =0.2*C13*AD13 -> 40674.428 | BL13: =BJ13+BK13 -> 117926.96 | BM13: =BK13*'Ejercicio 3 - TIR'!$D$5 -> 20337.214 | BN13: =BL13-BM13 -> 97589.75 | BO13: =BN13/AD13 -> 40629.377 | BP13: =-(C13+E13) -> -116832 | BQ13: =BE13 -> 20130.746 | BR13: =BF13 -> 21103.326 | BS13: =BG13 -> 20119.604 | BT13: =BH13 -> 18221.172 | BU13: =BI13+BO13 -> 58547.222 | BV13: =IFERROR(IRR(BP13:BU13,0.1),NA())*100 -> 4.9278578
... A1001: 1000 | B1001: =RAND() -> 0.10757143 | C1001: =IF(B1001<=('Ejercicio 3 - TIR'!$D$13-'Ejercicio 3 - TIR'!$C$13)/('Ejercicio 3 - TIR'!$E$13-'Ejercicio 3 - TIR'!$C$13),'Ejercicio 3 - TIR'!$C$13+SQRT(('Ejercicio 3 - TIR'!$E$13-'Ejercicio 3 - TIR'!$C$13)*('Ejercicio 3 - TIR'!$D$13-'Ejercicio 3 - TIR'!$C$13)*B1001),'Ejercicio 3 - TIR'!$E$13-SQRT(('Ejercicio 3 - TIR'!$E$13-'Ejercicio 3 - TIR'!$C$13)*('Ejercicio 3 - TIR'!$E$13-'Ejercicio 3 - TIR'!$D$13)*(1-B1001))) -> 66559.617 | D1001: =RAND() -> 0.52955829 | E1001: =IF(D1001<=('Ejercicio 3 - TIR'!$D$14-'Ejercicio 3 - TIR'!$C$14)/('Ejercicio 3 - TIR'!$E$14-'Ejercicio 3 - TIR'!$C$14),'Ejercicio 3 - TIR'!$C$14+SQRT(('Ejercicio 3 - TIR'!$E$14-'Ejercicio 3 - TIR'!$C$14)*('Ejercicio 3 - TIR'!$D$14-'Ejercicio 3 - TIR'!$C$14)*D1001),'Ejercicio 3 - TIR'!$E$14-SQRT(('Ejercicio 3 - TIR'!$E$14-'Ejercicio 3 - TIR'!$C$14)*('Ejercicio 3 - TIR'!$E$14-'Ejercicio 3 - TIR'!$D$14)*(1-D1001))) -> 31599.628 | F1001: =RAND() -> 0.58556713 | G1001: =IF(F1001<=('Ejercicio 3 - TIR'!$D$18-'Ejercicio 3 - TIR'!$C$18)/('Ejercicio 3 - TIR'!$E$18-'Ejercicio 3 - TIR'!$C$18),'Ejercicio 3 - TIR'!$C$18+SQRT(('Ejercicio 3 - TIR'!$E$18-'Ejercicio 3 - TIR'!$C$18)*('Ejercicio 3 - TIR'!$D$18-'Ejercicio 3 - TIR'!$C$18)*F1001),'Ejercicio 3 - TIR'!$E$18-SQRT(('Ejercicio 3 - TIR'!$E$18-'Ejercicio 3 - TIR'!$C$18)*('Ejercicio 3 - TIR'!$E$18-'Ejercicio 3 - TIR'!$D$18)*(1-F1001))) -> 39372.037 | H1001: =RAND() -> 0.30671228 | I1001: =IF(H1001<=('Ejercicio 3 - TIR'!$D$18-'Ejercicio 3 - TIR'!$C$18)/('Ejercicio 3 - TIR'!$E$18-'Ejercicio 3 - TIR'!$C$18),'Ejercicio 3 - TIR'!$C$18+SQRT(('Ejercicio 3 - TIR'!$E$18-'Ejercicio 3 - TIR'!$C$18)*('Ejercicio 3 - TIR'!$D$18-'Ejercicio 3 - TIR'!$C$18)*H1001),'Ejercicio 3 - TIR'!$E$18-SQRT(('Ejercicio 3 - TIR'!$E$18-'Ejercicio 3 - TIR'!$C$18)*('Ejercicio 3 - TIR'!$E$18-'Ejercicio 3 - TIR'!$D$18)*(1-H1001))) -> 36782.834 | J1001: =RAND() -> 0.50294084 | K1001: =IF(J1001<=('Ejercicio 3 - TIR'!$D$18-'Ejercicio 3 - TIR'!$C$18)/('Ejercicio 3 - TIR'!$E$18-'Ejercicio 3 - TIR'!$C$18),'Ejercicio 3 - TIR'!$C$18+SQRT(('Ejercicio 3 - TIR'!$E$18-'Ejercicio 3 - TIR'!$C$18)*('Ejercicio 3 - TIR'!$D$18-'Ejercicio 3 - TIR'!$C$18)*J1001),'Ejercicio 3 - TIR'!$E$18-SQRT(('Ejercicio 3 - TIR'!$E$18-'Ejercicio 3 - TIR'!$C$18)*('Ejercicio 3 - TIR'!$E$18-'Ejercicio 3 - TIR'!$D$18)*(1-J1001))) -> 38685.685 | L1001: =RAND() -> 0.12210508 | M1001: =IF(L1001<=('Ejercicio 3 - TIR'!$D$18-'Ejercicio 3 - TIR'!$C$18)/('Ejercicio 3 - TIR'!$E$18-'Ejercicio 3 - TIR'!$C$18),'Ejercicio 3 - TIR'!$C$18+SQRT(('Ejercicio 3 - TIR'!$E$18-'Ejercicio 3 - TIR'!$C$18)*('Ejercicio 3 - TIR'!$D$18-'Ejercicio 3 - TIR'!$C$18)*L1001),'Ejercicio 3 - TIR'!$E$18-SQRT(('Ejercicio 3 - TIR'!$E$18-'Ejercicio 3 - TIR'!$C$18)*('Ejercicio 3 - TIR'!$E$18-'Ejercicio 3 - TIR'!$D$18)*(1-L1001))) -> 34279.692 | N1001: =RAND() -> 0.87866792 | O1001: =IF(N1001<=('Ejercicio 3 - TIR'!$D$18-'Ejercicio 3 - TIR'!$C$18)/('Ejercicio 3 - TIR'!$E$18-'Ejercicio 3 - TIR'!$C$18),'Ejercicio 3 - TIR'!$C$18+SQRT(('Ejercicio 3 - TIR'!$E$18-'Ejercicio 3 - TIR'!$C$18)*('Ejercicio 3 - TIR'!$D$18-'Ejercicio 3 - TIR'!$C$18)*N1001),'Ejercicio 3 - TIR'!$E$18-SQRT(('Ejercicio 3 - TIR'!$E$18-'Ejercicio 3 - TIR'!$C$18)*('Ejercicio 3 - TIR'!$E$18-'Ejercicio 3 - TIR'!$D$18)*(1-N1001))) -> 41983.395 | P1001: =RAND() -> 0.25661364 | Q1001: =IF(P1001<=('Ejercicio 3 - TIR'!$D$22-'Ejercicio 3 - TIR'!$C$22)/('Ejercicio 3 - TIR'!$E$22-'Ejercicio 3 - TIR'!$C$22),'Ejercicio 3 - TIR'!$C$22+SQRT(('Ejercicio 3 - TIR'!$E$22-'Ejercicio 3 - TIR'!$C$22)*('Ejercicio 3 - TIR'!$D$22-'Ejercicio 3 - TIR'!$C$22)*P1001),'Ejercicio 3 - TIR'!$E$22-SQRT(('Ejercicio 3 - TIR'!$E$22-'Ejercicio 3 - TIR'!$C$22)*('Ejercicio 3 - TIR'!$E$22-'Ejercicio 3 - TIR'!$D$22)*(1-P1001))) -> 0.14149196 | R1001: =RAND() -> 0.14194111 | S1001: =IF(R1001<=('Ejercicio 3 - TIR'!$D$23-'Ejercicio 3 - TIR'!$C$23)/('Ejercicio 3 - TIR'!$E$23-'Ejercicio 3 - TIR'!$C$23),'Ejercicio 3 - TIR'!$C$23+SQRT(('Ejercicio 3 - TIR'!$E$23-'Ejercicio 3 - TIR'!$C$23)*('Ejercicio 3 - TIR'!$D$23-'Ejercicio 3 - TIR'!$C$23)*R1001),'Ejercicio 3 - TIR'!$E$23-SQRT(('Ejercicio 3 - TIR'!$E$23-'Ejercicio 3 - TIR'!$C$23)*('Ejercicio 3 - TIR'!$E$23-'Ejercicio 3 - TIR'!$D$23)*(1-R1001))) -> 0.13598418 | T1001: =RAND() -> 0.42958348 | U1001: =IF(T1001<=('Ejercicio 3 - TIR'!$D$24-'Ejercicio 3 - TIR'!$C$24)/('Ejercicio 3 - TIR'!$E$24-'Ejercicio 3 - TIR'!$C$24),'Ejercicio 3 - TIR'!$C$24+SQRT(('Ejercicio 3 - TIR'!$E$24-'Ejercicio 3 - TIR'!$C$24)*('Ejercicio 3 - TIR'!$D$24-'Ejercicio 3 - TIR'!$C$24)*T1001),'Ejercicio 3 - TIR'!$E$24-SQRT(('Ejercicio 3 - TIR'!$E$24-'Ejercicio 3 - TIR'!$C$24)*('Ejercicio 3 - TIR'!$E$24-'Ejercicio 3 - TIR'!$D$24)*(1-T1001))) -> 0.18003544 | V1001: =RAND() -> 0.27028349 | W1001: =IF(V1001<=('Ejercicio 3 - TIR'!$D$25-'Ejercicio 3 - TIR'!$C$25)/('Ejercicio 3 - TIR'!$E$25-'Ejercicio 3 - TIR'!$C$25),'Ejercicio 3 - TIR'!$C$25+SQRT(('Ejercicio 3 - TIR'!$E$25-'Ejercicio 3 - TIR'!$C$25)*('Ejercicio 3 - TIR'!$D$25-'Ejercicio 3 - TIR'!$C$25)*V1001),'Ejercicio 3 - TIR'!$E$25-SQRT(('Ejercicio 3 - TIR'!$E$25-'Ejercicio 3 - TIR'!$C$25)*('Ejercicio 3 - TIR'!$E$25-'Ejercicio 3 - TIR'!$D$25)*(1-V1001))) -> 0.19945243 | X1001: =RAND() -> 0.38416745 | Y1001: =IF(X1001<=('Ejercicio 3 - TIR'!$D$26-'Ejercicio 3 - TIR'!$C$26)/('Ejercicio 3 - TIR'!$E$26-'Ejercicio 3 - TIR'!$C$26),'Ejercicio 3 - TIR'!$C$26+SQRT(('Ejercicio 3 - TIR'!$E$26-'Ejercicio 3 - TIR'!$C$26)*('Ejercicio 3 - TIR'!$D$26-'Ejercicio 3 - TIR'!$C$26)*X1001),'Ejercicio 3 - TIR'!$E$26-SQRT(('Ejercicio 3 - TIR'!$E$26-'Ejercicio 3 - TIR'!$C$26)*('Ejercicio 3 - TIR'!$E$26-'Ejercicio 3 - TIR'!$D$26)*(1-X1001))) -> 0.22233289 | Z1001: =(1+Q1001) -> 1.141492 | AA1001: =Z1001*(1+S1001) -> 1.2967168 | AB1001: =AA1001*(1+U1001) -> 1.5301718 | AC1001: =AB1001*(1+W1001) -> 1.8353683 | AD1001: =AC1001*(1+Y1001) -> 2.243431 | AE1001: =E1001*Q1001 -> 4471.0934 | AF1001: =AE1001*(1+S1001) -> 5079.0914 | AG1001: =AF1001*(1+U1001) -> 5993.5078 | AH1001: =AG1001*(1+W1001) -> 7188.9275 | AI1001: =AH1001*(1+Y1001) -> 8787.2625 | AJ1001: =G1001*Z1001 -> 44942.863 | AK1001: =I1001*AA1001 -> 47696.92 | AL1001: =K1001*AB1001 -> 59195.744 | AM1001: =M1001*AC1001 -> 62915.858 | AN1001: =O1001*AD1001 -> 94186.85 | AO1001: =C1001/'Ejercicio 3 - TIR'!$D$7 -> 13311.923 | AP1001: =AJ1001-AO1001 -> 31630.94 | AQ1001: =AK1001-AO1001 -> 34384.996 | AR1001: =AL1001-AO1001 -> 45883.821 | AS1001: =AM1001-AO1001 -> 49603.935 | AT1001: =AN1001-AO1001 -> 80874.926 | AU1001: =AP1001*'Ejercicio 3 - TIR'!$D$5 -> 15815.47 | AV1001: =AQ1001*'Ejercicio 3 - TIR'!$D$5 -> 17192.498 | AW1001: =AR1001*'Ejercicio 3 - TIR'!$D$5 -> 22941.91 | AX1001: =AS1001*'Ejercicio 3 - TIR'!$D$5 -> 24801.968 | AY1001: =AT1001*'Ejercicio 3 - TIR'!$D$5 -> 40437.463 | AZ1001: =AJ1001-AU1001-AE1001 -> 24656.3 | BA1001: =AK1001-AV1001-AF1001 -> 25425.33 | BB1001: =AL1001-AW1001-AG1001 -> 30260.326 | BC1001: =AM1001-AX1001-AH1001 -> 30924.963 | BD1001: =AN1001-AY1001-AI1001 -> 44962.124 | BE1001: =AZ1001/Z1001 -> 21600.064 | BF1001: =BA1001/AA1001 -> 19607.466 | BG1001: =BB1001/AB1001 -> 19775.77 | BH1001: =BC1001/AC1001 -> 16849.46 | BI1001: =BD1001/AD1001 -> 20041.679 | BJ1001: =E1001*AD1001 -> 70891.584 | BK1001: =0.2*C1001*AD1001 -> 29864.382 | BL1001: =BJ1001+BK1001 -> 100755.97 | BM1001: =BK1001*'Ejercicio 3 - TIR'!$D$5 -> 14932.191 | BN1001: =BL1001-BM1001 -> 85823.775 | BO1001: =BN1001/AD1001 -> 38255.589 | BP1001: =-(C1001+E1001) -> -98159.244 | BQ1001: =BE1001 -> 21600.064 | BR1001: =BF1001 -> 19607.466 | BS1001: =BG1001 -> 19775.77 | BT1001: =BH1001 -> 16849.46 | BU1001: =BI1001+BO1001 -> 58297.268 | BV1001: =IFERROR(IRR(BP1001:BU1001,0.1),NA())*100 -> 10.083754

Sheet Ejercicio 4 - Camiones V
A1: Ejercicio 4 — Número óptimo de camiones (distribución empírica agrupada)
A3: Nº camiones a comprar (B1): | B3: 12 | D3: <- cambia este valor y presiona F9 para recalcular
A5: Tabla de Producción Diaria (toneladas) | J5: Tabla de Capacidad por Camión (ton/día)
F6: Prob. acumulada (F) | G6: Lím. inf. ton (G) | H6: Lím. sup. ton (H) | K6: Prob. acum. (K) | L6: Lím. inf. ton (L) | M6: Lím. sup. ton (M)
F7: 0 | G7: 50 | H7: 55 | K7: 0 | L7: 4 | M7: 4.5
F8: 0.1 | G8: 55 | H8: 60 | K8: 0.3 | L8: 4.5 | M8: 5
F9: 0.25 | G9: 60 | H9: 65 | K9: 0.7 | L9: 5 | M9: 5.5
F10: 0.55 | G10: 65 | H10: 70 | K10: 0.9 | L10: 5.5 | M10: 6
F11: 0.9 | G11: 75 | H11: 80
F12: 0.98 | G12: 80 | H12: 85
A14: Día | B14: R_Producción | C14: Producción del Día | D14: R_Camión | E14: Capacidad Prom. x Camión | F14: Capacidad Flotilla Total | G14: Excedente (Ton) | H14: Costo Flete Externo
A15: 1 | B15: =RAND() -> 0.71455878 | C15: =VLOOKUP(B15,$F$7:$H$12,2,TRUE())+(RAND()*(VLOOKUP(B15,$F$7:$H$12,3,TRUE())-VLOOKUP(B15,$F$7:$H$12,2,TRUE()))) -> 69.319129 | D15: =RAND() -> 0.14008373 | E15: =VLOOKUP(D15,$K$7:$M$10,2,TRUE())+(RAND()*(VLOOKUP(D15,$K$7:$M$10,3,TRUE())-VLOOKUP(D15,$K$7:$M$10,2,TRUE()))) -> 4.0229987 | F15: =E15*$B$3 -> 48.275985 | G15: =MAX(C15-F15,0) -> 21.043145 | H15: =G15*100 -> 2104.3145
A16: =A15+1 -> 2 | B16: =RAND() -> 0.17777768 | C16: =VLOOKUP(B16,$F$7:$H$12,2,TRUE())+(RAND()*(VLOOKUP(B16,$F$7:$H$12,3,TRUE())-VLOOKUP(B16,$F$7:$H$12,2,TRUE()))) -> 58.129465 | D16: =RAND() -> 0.90864614 | E16: =VLOOKUP(D16,$K$7:$M$10,2,TRUE())+(RAND()*(VLOOKUP(D16,$K$7:$M$10,3,TRUE())-VLOOKUP(D16,$K$7:$M$10,2,TRUE()))) -> 5.9661235 | F16: =E16*$B$3 -> 71.593482 | G16: =MAX(C16-F16,0) -> 0 | H16: =G16*100 -> 0
A17: =A16+1 -> 3 | B17: =RAND() -> 0.93259249 | C17: =VLOOKUP(B17,$F$7:$H$12,2,TRUE())+(RAND()*(VLOOKUP(B17,$F$7:$H$12,3,TRUE())-VLOOKUP(B17,$F$7:$H$12,2,TRUE()))) -> 76.087324 | D17: =RAND() -> 0.82140598 | E17: =VLOOKUP(D17,$K$7:$M$10,2,TRUE())+(RAND()*(VLOOKUP(D17,$K$7:$M$10,3,TRUE())-VLOOKUP(D17,$K$7:$M$10,2,TRUE()))) -> 5.4129789 | F17: =E17*$B$3 -> 64.955747 | G17: =MAX(C17-F17,0) -> 11.131577 | H17: =G17*100 -> 1113.1577
A18: =A17+1 -> 4 | B18: =RAND() -> 0.65617459 | C18: =VLOOKUP(B18,$F$7:$H$12,2,TRUE())+(RAND()*(VLOOKUP(B18,$F$7:$H$12,3,TRUE())-VLOOKUP(B18,$F$7:$H$12,2,TRUE()))) -> 66.191994 | D18: =RAND() -> 0.12376201 | E18: =VLOOKUP(D18,$K$7:$M$10,2,TRUE())+(RAND()*(VLOOKUP(D18,$K$7:$M$10,3,TRUE())-VLOOKUP(D18,$K$7:$M$10,2,TRUE()))) -> 4.2388658 | F18: =E18*$B$3 -> 50.86639 | G18: =MAX(C18-F18,0) -> 15.325604 | H18: =G18*100 -> 1532.5604
A19: =A18+1 -> 5 | B19: =RAND() -> 0.10340378 | C19: =VLOOKUP(B19,$F$7:$H$12,2,TRUE())+(RAND()*(VLOOKUP(B19,$F$7:$H$12,3,TRUE())-VLOOKUP(B19,$F$7:$H$12,2,TRUE()))) -> 59.750604 | D19: =RAND() -> 0.13088229 | E19: =VLOOKUP(D19,$K$7:$M$10,2,TRUE())+(RAND()*(VLOOKUP(D19,$K$7:$M$10,3,TRUE())-VLOOKUP(D19,$K$7:$M$10,2,TRUE()))) -> 4.1532077 | F19: =E19*$B$3 -> 49.838493 | G19: =MAX(C19-F19,0) -> 9.9121108 | H19: =G19*100 -> 991.21108
A20: =A19+1 -> 6 | B20: =RAND() -> 0.84776911 | C20: =VLOOKUP(B20,$F$7:$H$12,2,TRUE())+(RAND()*(VLOOKUP(B20,$F$7:$H$12,3,TRUE())-VLOOKUP(B20,$F$7:$H$12,2,TRUE()))) -> 65.936689 | D20: =RAND() -> 0.67898415 | E20: =VLOOKUP(D20,$K$7:$M$10,2,TRUE())+(RAND()*(VLOOKUP(D20,$K$7:$M$10,3,TRUE())-VLOOKUP(D20,$K$7:$M$10,2,TRUE()))) -> 4.6744788 | F20: =E20*$B$3 -> 56.093746 | G20: =MAX(C20-F20,0) -> 9.8429433 | H20: =G20*100 -> 984.29433
A21: =A20+1 -> 7 | B21: =RAND() -> 0.12567367 | C21: =VLOOKUP(B21,$F$7:$H$12,2,TRUE())+(RAND()*(VLOOKUP(B21,$F$7:$H$12,3,TRUE())-VLOOKUP(B21,$F$7:$H$12,2,TRUE()))) -> 55.379309 | D21: =RAND() -> 0.90276586 | E21: =VLOOKUP(D21,$K$7:$M$10,2,TRUE())+(RAND()*(VLOOKUP(D21,$K$7:$M$10,3,TRUE())-VLOOKUP(D21,$K$7:$M$10,2,TRUE()))) -> 5.8068742 | F21: =E21*$B$3 -> 69.682491 | G21: =MAX(C21-F21,0) -> 0 | H21: =G21*100 -> 0
A22: =A21+1 -> 8 | B22: =RAND() -> 0.20450935 | C22: =VLOOKUP(B22,$F$7:$H$12,2,TRUE())+(RAND()*(VLOOKUP(B22,$F$7:$H$12,3,TRUE())-VLOOKUP(B22,$F$7:$H$12,2,TRUE()))) -> 59.59244 | D22: =RAND() -> 0.044631423 | E22: =VLOOKUP(D22,$K$7:$M$10,2,TRUE())+(RAND()*(VLOOKUP(D22,$K$7:$M$10,3,TRUE())-VLOOKUP(D22,$K$7:$M$10,2,TRUE()))) -> 4.0016899 | F22: =E22*$B$3 -> 48.020279 | G22: =MAX(C22-F22,0) -> 11.572161 | H22: =G22*100 -> 1157.2161
A23: =A22+1 -> 9 | B23: =RAND() -> 0.99067192 | C23: =VLOOKUP(B23,$F$7:$H$12,2,TRUE())+(RAND()*(VLOOKUP(B23,$F$7:$H$12,3,TRUE())-VLOOKUP(B23,$F$7:$H$12,2,TRUE()))) -> 81.174482 | D23: =RAND() -> 0.38388877 | E23: =VLOOKUP(D23,$K$7:$M$10,2,TRUE())+(RAND()*(VLOOKUP(D23,$K$7:$M$10,3,TRUE())-VLOOKUP(D23,$K$7:$M$10,2,TRUE()))) -> 4.7569009 | F23: =E23*$B$3 -> 57.08281 | G23: =MAX(C23-F23,0) -> 24.091672 | H23: =G23*100 -> 2409.1672
A24: =A23+1 -> 10 | B24: =RAND() -> 0.48445474 | C24: =VLOOKUP(B24,$F$7:$H$12,2,TRUE())+(RAND()*(VLOOKUP(B24,$F$7:$H$12,3,TRUE())-VLOOKUP(B24,$F$7:$H$12,2,TRUE()))) -> 60.813301 | D24: =RAND() -> 0.63366787 | E24: =VLOOKUP(D24,$K$7:$M$10,2,TRUE())+(RAND()*(VLOOKUP(D24,$K$7:$M$10,3,TRUE())-VLOOKUP(D24,$K$7:$M$10,2,TRUE()))) -> 4.878138 | F24: =E24*$B$3 -> 58.537656 | G24: =MAX(C24-F24,0) -> 2.2756451 | H24: =G24*100 -> 227.56451
A25: =A24+1 -> 11 | B25: =RAND() -> 0.78532255 | C25: =VLOOKUP(B25,$F$7:$H$12,2,TRUE())+(RAND()*(VLOOKUP(B25,$F$7:$H$12,3,TRUE())-VLOOKUP(B25,$F$7:$H$12,2,TRUE()))) -> 67.538944 | D25: =RAND() -> 0.84880977 | E25: =VLOOKUP(D25,$K$7:$M$10,2,TRUE())+(RAND()*(VLOOKUP(D25,$K$7:$M$10,3,TRUE())-VLOOKUP(D25,$K$7:$M$10,2,TRUE()))) -> 5.4006493 | F25: =E25*$B$3 -> 64.807791 | G25: =MAX(C25-F25,0) -> 2.7311523 | H25: =G25*100 -> 273.11523
A26: =A25+1 -> 12 | B26: =RAND() -> 0.86268933 | C26: =VLOOKUP(B26,$F$7:$H$12,2,TRUE())+(RAND()*(VLOOKUP(B26,$F$7:$H$12,3,TRUE())-VLOOKUP(B26,$F$7:$H$12,2,TRUE()))) -> 68.766388 | D26: =RAND() -> 0.84531885 | E26: =VLOOKUP(D26,$K$7:$M$10,2,TRUE())+(RAND()*(VLOOKUP(D26,$K$7:$M$10,3,TRUE())-VLOOKUP(D26,$K$7:$M$10,2,TRUE()))) -> 5.0203296 | F26: =E26*$B$3 -> 60.243956 | G26: =MAX(C26-F26,0) -> 8.5224328 | H26: =G26*100 -> 852.24328
A27: =A26+1 -> 13 | B27: =RAND() -> 0.45500791 | C27: =VLOOKUP(B27,$F$7:$H$12,2,TRUE())+(RAND()*(VLOOKUP(B27,$F$7:$H$12,3,TRUE())-VLOOKUP(B27,$F$7:$H$12,2,TRUE()))) -> 60.547684 | D27: =RAND() -> 0.25665204 | E27: =VLOOKUP(D27,$K$7:$M$10,2,TRUE())+(RAND()*(VLOOKUP(D27,$K$7:$M$10,3,TRUE())-VLOOKUP(D27,$K$7:$M$10,2,TRUE()))) -> 4.3240523 | F27: =E27*$B$3 -> 51.888628 | G27: =MAX(C27-F27,0) -> 8.6590559 | H27: =G27*100 -> 865.90559
... A264: =A263+1 -> 250 | B264: =RAND() -> 0.57983423 | C264: =VLOOKUP(B264,$F$7:$H$12,2,TRUE())+(RAND()*(VLOOKUP(B264,$F$7:$H$12,3,TRUE())-VLOOKUP(B264,$F$7:$H$12,2,TRUE()))) -> 65.632733 | D264: =RAND() -> 0.065331892 | E264: =VLOOKUP(D264,$K$7:$M$10,2,TRUE())+(RAND()*(VLOOKUP(D264,$K$7:$M$10,3,TRUE())-VLOOKUP(D264,$K$7:$M$10,2,TRUE()))) -> 4.2256008 | F264: =E264*$B$3 -> 50.70721 | G264: =MAX(C264-F264,0) -> 14.925523 | H264: =G264*100 -> 1492.5523
A266: Costo Anual de Camiones = | B266: =$B$3*100000 -> 1200000
A267: Costo Anual Flete Externo = | B267: =SUM(H15:H264) -> 207205.71
A268: COSTO TOTAL = | B268: =B266+B267 -> 1407205.7
A270: Para encontrar el óptimo: cambia B3 (10,11,12,13,14...), presiona F9, y anota el COSTO TOTAL de cada uno.
A273: Tabla de referencia (promedio de 500 corridas de 250 días cada una, calculada aparte para validar):
A274: N° camiones | B274: Costo camiones | C274: Flete externo (prom.) | D274: Costo total (prom.)
A275: 10 | B275: 1000000 | C275: 404778 | D275: 1404778
A276: 11 | B276: 1100000 | C276: 293293 | D276: 1393293
A277: 12 | B277: 1200000 | C277: 194157 | D277: 1394157
A278: 13 | B278: 1300000 | C278: 116862 | D278: 1416862
A279: 14 | B279: 1400000 | C279: 63358 | D279: 1463358
A280: 15 | B280: 1500000 | C280: 30183 | D280: 1530183
A282: Con estos datos, 11 camiones da el menor costo total esperado (muy cerca de 12).
