Workbook

Sheet Ejercicio 1 - Trapezoidal V
B1: Ejercicio 1
B3: Parámetros
B4: a = | C4: 3 | G4: Debe cumplirse: 0 < a < b < c
B5: b = | C5: 7
B6: c = | C6: 10
B7: N° simulaciones = | C7: 1000
B9: Áreas (deducidas en la teoría, Paso 1)
B10: A1 = | C10: =C4/(-C4+C5+C6) -> 0.21428571
B11: A2 = | C11: =(2*C5-2*C4)/(-C4+C5+C6) -> 0.57142857
B12: A3 = | C12: =(C6-C5)/(-C4+C5+C6) -> 0.21428571
B13: Suma = | C13: =C10+C11+C12 -> 1 | F13: Región 1: X = a*√R Región 2: X = a + (b−a)*R Región 3: X = c − (c−b)*√(1−R)
B16: i | C16: R_region | D16: R_valor | E16: Región | F16: X | G16: Fórmula de X según región (Paso 5 de la teoría): Región 1 -> a*SQRT(R_valor) | Región 2 -> a+(b-a)*R_valor | Región 3 -> c-(c-b)*SQRT(1-R_valor)
B17: 1 | C17: =RAND() -> 0.38098408 | D17: =RAND() -> 0.4504255 | E17: =IF(C17<=$C$10,1,IF(C17<=$C$10+$C$11,2,3)) -> 2 | F17: =IF(E17=1,$C$4*SQRT(D17),IF(E17=2,$C$4+($C$5-$C$4)*D17,$C$6-($C$6-$C$5)*SQRT(1-D17))) -> 4.801702
B18: 2 | C18: =RAND() -> 0.99956711 | D18: =RAND() -> 0.55026678 | E18: =IF(C18<=$C$10,1,IF(C18<=$C$10+$C$11,2,3)) -> 3 | F18: =IF(E18=1,$C$4*SQRT(D18),IF(E18=2,$C$4+($C$5-$C$4)*D18,$C$6-($C$6-$C$5)*SQRT(1-D18))) -> 7.9881355
B19: 3 | C19: =RAND() -> 0.21235295 | D19: =RAND() -> 0.13169998 | E19: =IF(C19<=$C$10,1,IF(C19<=$C$10+$C$11,2,3)) -> 1 | F19: =IF(E19=1,$C$4*SQRT(D19),IF(E19=2,$C$4+($C$5-$C$4)*D19,$C$6-($C$6-$C$5)*SQRT(1-D19))) -> 1.0887147
B20: 4 | C20: =RAND() -> 0.58462084 | D20: =RAND() -> 0.036259224 | E20: =IF(C20<=$C$10,1,IF(C20<=$C$10+$C$11,2,3)) -> 2 | F20: =IF(E20=1,$C$4*SQRT(D20),IF(E20=2,$C$4+($C$5-$C$4)*D20,$C$6-($C$6-$C$5)*SQRT(1-D20))) -> 3.1450369
B21: 5 | C21: =RAND() -> 0.34015705 | D21: =RAND() -> 0.40886414 | E21: =IF(C21<=$C$10,1,IF(C21<=$C$10+$C$11,2,3)) -> 2 | F21: =IF(E21=1,$C$4*SQRT(D21),IF(E21=2,$C$4+($C$5-$C$4)*D21,$C$6-($C$6-$C$5)*SQRT(1-D21))) -> 4.6354565
B22: 6 | C22: =RAND() -> 0.6942453 | D22: =RAND() -> 0.697366 | E22: =IF(C22<=$C$10,1,IF(C22<=$C$10+$C$11,2,3)) -> 2 | F22: =IF(E22=1,$C$4*SQRT(D22),IF(E22=2,$C$4+($C$5-$C$4)*D22,$C$6-($C$6-$C$5)*SQRT(1-D22))) -> 5.789464
B23: 7 | C23: =RAND() -> 0.64659635 | D23: =RAND() -> 0.45362541 | E23: =IF(C23<=$C$10,1,IF(C23<=$C$10+$C$11,2,3)) -> 2 | F23: =IF(E23=1,$C$4*SQRT(D23),IF(E23=2,$C$4+($C$5-$C$4)*D23,$C$6-($C$6-$C$5)*SQRT(1-D23))) -> 4.8145016
B24: 8 | C24: =RAND() -> 0.44746 | D24: =RAND() -> 0.36927872 | E24: =IF(C24<=$C$10,1,IF(C24<=$C$10+$C$11,2,3)) -> 2 | F24: =IF(E24=1,$C$4*SQRT(D24),IF(E24=2,$C$4+($C$5-$C$4)*D24,$C$6-($C$6-$C$5)*SQRT(1-D24))) -> 4.4771149
B25: 9 | C25: =RAND() -> 0.025573764 | D25: =RAND() -> 0.65713832 | E25: =IF(C25<=$C$10,1,IF(C25<=$C$10+$C$11,2,3)) -> 1 | F25: =IF(E25=1,$C$4*SQRT(D25),IF(E25=2,$C$4+($C$5-$C$4)*D25,$C$6-($C$6-$C$5)*SQRT(1-D25))) -> 2.431922
B26: 10 | C26: =RAND() -> 0.23219517 | D26: =RAND() -> 0.78676206 | E26: =IF(C26<=$C$10,1,IF(C26<=$C$10+$C$11,2,3)) -> 2 | F26: =IF(E26=1,$C$4*SQRT(D26),IF(E26=2,$C$4+($C$5-$C$4)*D26,$C$6-($C$6-$C$5)*SQRT(1-D26))) -> 6.1470483
B27: 11 | C27: =RAND() -> 0.4023865 | D27: =RAND() -> 0.0039764677 | E27: =IF(C27<=$C$10,1,IF(C27<=$C$10+$C$11,2,3)) -> 2 | F27: =IF(E27=1,$C$4*SQRT(D27),IF(E27=2,$C$4+($C$5-$C$4)*D27,$C$6-($C$6-$C$5)*SQRT(1-D27))) -> 3.0159059
B28: 12 | C28: =RAND() -> 0.87593753 | D28: =RAND() -> 0.78755093 | E28: =IF(C28<=$C$10,1,IF(C28<=$C$10+$C$11,2,3)) -> 3 | F28: =IF(E28=1,$C$4*SQRT(D28),IF(E28=2,$C$4+($C$5-$C$4)*D28,$C$6-($C$6-$C$5)*SQRT(1-D28))) -> 8.6172341
... B1016: 1000 | C1016: =RAND() -> 0.56485633 | D1016: =RAND() -> 0.73735232 | E1016: =IF(C1016<=$C$10,1,IF(C1016<=$C$10+$C$11,2,3)) -> 2 | F1016: =IF(E1016=1,$C$4*SQRT(D1016),IF(E1016=2,$C$4+($C$5-$C$4)*D1016,$C$6-($C$6-$C$5)*SQRT(1-D1016))) -> 5.9494093
B1018: Promedio X = | C1018: =AVERAGE(F17:F1016) -> 5.0035354
B1019: Mínimo X = | C1019: =MIN(F17:F1016) -> 0.053967765
B1020: Máximo X = | C1020: =MAX(F17:F1016) -> 9.8988731
B1023: Histograma vs. densidad teórica (dominio [0, c])
H1024: h (altura meseta) = | I1024: =2/(-C4+C5+C6) -> 0.14285714
B1025: Bin | C1025: Lím. inf. | D1025: Lím. sup. | E1025: Punto medio | F1025: Frecuencia | G1025: Densidad emp. | H1025: Densidad teór.
B1026: 1 | C1026: =($C$6/20)*0 -> 0 | D1026: =($C$6/20)*1 -> 0.5 | E1026: =(C1026+D1026)/2 -> 0.25 | F1026: =COUNTIFS($F$17:$F$1016,">="&C1026,$F$17:$F$1016,"<"&D1026) -> 8 | G1026: =F1026/($C$7*(D1026-C1026)) -> 0.016 | H1026: =IF(E1026<=$C$4,$I$1024*E1026/$C$4,IF(E1026<=$C$5,$I$1024,$I$1024*($C$6-E1026)/($C$6-$C$5))) -> 0.011904762
B1027: 2 | C1027: =($C$6/20)*1 -> 0.5 | D1027: =($C$6/20)*2 -> 1 | E1027: =(C1027+D1027)/2 -> 0.75 | F1027: =COUNTIFS($F$17:$F$1016,">="&C1027,$F$17:$F$1016,"<"&D1027) -> 15 | G1027: =F1027/($C$7*(D1027-C1027)) -> 0.03 | H1027: =IF(E1027<=$C$4,$I$1024*E1027/$C$4,IF(E1027<=$C$5,$I$1024,$I$1024*($C$6-E1027)/($C$6-$C$5))) -> 0.035714286
B1028: 3 | C1028: =($C$6/20)*2 -> 1 | D1028: =($C$6/20)*3 -> 1.5 | E1028: =(C1028+D1028)/2 -> 1.25 | F1028: =COUNTIFS($F$17:$F$1016,">="&C1028,$F$17:$F$1016,"<"&D1028) -> 27 | G1028: =F1028/($C$7*(D1028-C1028)) -> 0.054 | H1028: =IF(E1028<=$C$4,$I$1024*E1028/$C$4,IF(E1028<=$C$5,$I$1024,$I$1024*($C$6-E1028)/($C$6-$C$5))) -> 0.05952381
B1029: 4 | C1029: =($C$6/20)*3 -> 1.5 | D1029: =($C$6/20)*4 -> 2 | E1029: =(C1029+D1029)/2 -> 1.75 | F1029: =COUNTIFS($F$17:$F$1016,">="&C1029,$F$17:$F$1016,"<"&D1029) -> 35 | G1029: =F1029/($C$7*(D1029-C1029)) -> 0.07 | H1029: =IF(E1029<=$C$4,$I$1024*E1029/$C$4,IF(E1029<=$C$5,$I$1024,$I$1024*($C$6-E1029)/($C$6-$C$5))) -> 0.083333333
B1030: 5 | C1030: =($C$6/20)*4 -> 2 | D1030: =($C$6/20)*5 -> 2.5 | E1030: =(C1030+D1030)/2 -> 2.25 | F1030: =COUNTIFS($F$17:$F$1016,">="&C1030,$F$17:$F$1016,"<"&D1030) -> 55 | G1030: =F1030/($C$7*(D1030-C1030)) -> 0.11 | H1030: =IF(E1030<=$C$4,$I$1024*E1030/$C$4,IF(E1030<=$C$5,$I$1024,$I$1024*($C$6-E1030)/($C$6-$C$5))) -> 0.10714286
B1031: 6 | C1031: =($C$6/20)*5 -> 2.5 | D1031: =($C$6/20)*6 -> 3 | E1031: =(C1031+D1031)/2 -> 2.75 | F1031: =COUNTIFS($F$17:$F$1016,">="&C1031,$F$17:$F$1016,"<"&D1031) -> 56 | G1031: =F1031/($C$7*(D1031-C1031)) -> 0.112 | H1031: =IF(E1031<=$C$4,$I$1024*E1031/$C$4,IF(E1031<=$C$5,$I$1024,$I$1024*($C$6-E1031)/($C$6-$C$5))) -> 0.13095238
B1032: 7 | C1032: =($C$6/20)*6 -> 3 | D1032: =($C$6/20)*7 -> 3.5 | E1032: =(C1032+D1032)/2 -> 3.25 | F1032: =COUNTIFS($F$17:$F$1016,">="&C1032,$F$17:$F$1016,"<"&D1032) -> 74 | G1032: =F1032/($C$7*(D1032-C1032)) -> 0.148 | H1032: =IF(E1032<=$C$4,$I$1024*E1032/$C$4,IF(E1032<=$C$5,$I$1024,$I$1024*($C$6-E1032)/($C$6-$C$5))) -> 0.14285714
B1033: 8 | C1033: =($C$6/20)*7 -> 3.5 | D1033: =($C$6/20)*8 -> 4 | E1033: =(C1033+D1033)/2 -> 3.75 | F1033: =COUNTIFS($F$17:$F$1016,">="&C1033,$F$17:$F$1016,"<"&D1033) -> 88 | G1033: =F1033/($C$7*(D1033-C1033)) -> 0.176 | H1033: =IF(E1033<=$C$4,$I$1024*E1033/$C$4,IF(E1033<=$C$5,$I$1024,$I$1024*($C$6-E1033)/($C$6-$C$5))) -> 0.14285714
B1034: 9 | C1034: =($C$6/20)*8 -> 4 | D1034: =($C$6/20)*9 -> 4.5 | E1034: =(C1034+D1034)/2 -> 4.25 | F1034: =COUNTIFS($F$17:$F$1016,">="&C1034,$F$17:$F$1016,"<"&D1034) -> 62 | G1034: =F1034/($C$7*(D1034-C1034)) -> 0.124 | H1034: =IF(E1034<=$C$4,$I$1024*E1034/$C$4,IF(E1034<=$C$5,$I$1024,$I$1024*($C$6-E1034)/($C$6-$C$5))) -> 0.14285714
B1035: 10 | C1035: =($C$6/20)*9 -> 4.5 | D1035: =($C$6/20)*10 -> 5 | E1035: =(C1035+D1035)/2 -> 4.75 | F1035: =COUNTIFS($F$17:$F$1016,">="&C1035,$F$17:$F$1016,"<"&D1035) -> 81 | G1035: =F1035/($C$7*(D1035-C1035)) -> 0.162 | H1035: =IF(E1035<=$C$4,$I$1024*E1035/$C$4,IF(E1035<=$C$5,$I$1024,$I$1024*($C$6-E1035)/($C$6-$C$5))) -> 0.14285714
B1036: 11 | C1036: =($C$6/20)*10 -> 5 | D1036: =($C$6/20)*11 -> 5.5 | E1036: =(C1036+D1036)/2 -> 5.25 | F1036: =COUNTIFS($F$17:$F$1016,">="&C1036,$F$17:$F$1016,"<"&D1036) -> 86 | G1036: =F1036/($C$7*(D1036-C1036)) -> 0.172 | H1036: =IF(E1036<=$C$4,$I$1024*E1036/$C$4,IF(E1036<=$C$5,$I$1024,$I$1024*($C$6-E1036)/($C$6-$C$5))) -> 0.14285714
B1037: 12 | C1037: =($C$6/20)*11 -> 5.5 | D1037: =($C$6/20)*12 -> 6 | E1037: =(C1037+D1037)/2 -> 5.75 | F1037: =COUNTIFS($F$17:$F$1016,">="&C1037,$F$17:$F$1016,"<"&D1037) -> 70 | G1037: =F1037/($C$7*(D1037-C1037)) -> 0.14 | H1037: =IF(E1037<=$C$4,$I$1024*E1037/$C$4,IF(E1037<=$C$5,$I$1024,$I$1024*($C$6-E1037)/($C$6-$C$5))) -> 0.14285714
B1038: 13 | C1038: =($C$6/20)*12 -> 6 | D1038: =($C$6/20)*13 -> 6.5 | E1038: =(C1038+D1038)/2 -> 6.25 | F1038: =COUNTIFS($F$17:$F$1016,">="&C1038,$F$17:$F$1016,"<"&D1038) -> 69 | G1038: =F1038/($C$7*(D1038-C1038)) -> 0.138 | H1038: =IF(E1038<=$C$4,$I$1024*E1038/$C$4,IF(E1038<=$C$5,$I$1024,$I$1024*($C$6-E1038)/($C$6-$C$5))) -> 0.14285714
B1039: 14 | C1039: =($C$6/20)*13 -> 6.5 | D1039: =($C$6/20)*14 -> 7 | E1039: =(C1039+D1039)/2 -> 6.75 | F1039: =COUNTIFS($F$17:$F$1016,">="&C1039,$F$17:$F$1016,"<"&D1039) -> 66 | G1039: =F1039/($C$7*(D1039-C1039)) -> 0.132 | H1039: =IF(E1039<=$C$4,$I$1024*E1039/$C$4,IF(E1039<=$C$5,$I$1024,$I$1024*($C$6-E1039)/($C$6-$C$5))) -> 0.14285714
B1040: 15 | C1040: =($C$6/20)*14 -> 7 | D1040: =($C$6/20)*15 -> 7.5 | E1040: =(C1040+D1040)/2 -> 7.25 | F1040: =COUNTIFS($F$17:$F$1016,">="&C1040,$F$17:$F$1016,"<"&D1040) -> 58 | G1040: =F1040/($C$7*(D1040-C1040)) -> 0.116 | H1040: =IF(E1040<=$C$4,$I$1024*E1040/$C$4,IF(E1040<=$C$5,$I$1024,$I$1024*($C$6-E1040)/($C$6-$C$5))) -> 0.13095238
B1041: 16 | C1041: =($C$6/20)*15 -> 7.5 | D1041: =($C$6/20)*16 -> 8 | E1041: =(C1041+D1041)/2 -> 7.75 | F1041: =COUNTIFS($F$17:$F$1016,">="&C1041,$F$17:$F$1016,"<"&D1041) -> 60 | G1041: =F1041/($C$7*(D1041-C1041)) -> 0.12 | H1041: =IF(E1041<=$C$4,$I$1024*E1041/$C$4,IF(E1041<=$C$5,$I$1024,$I$1024*($C$6-E1041)/($C$6-$C$5))) -> 0.10714286
B1042: 17 | C1042: =($C$6/20)*16 -> 8 | D1042: =($C$6/20)*17 -> 8.5 | E1042: =(C1042+D1042)/2 -> 8.25 | F1042: =COUNTIFS($F$17:$F$1016,">="&C1042,$F$17:$F$1016,"<"&D1042) -> 36 | G1042: =F1042/($C$7*(D1042-C1042)) -> 0.072 | H1042: =IF(E1042<=$C$4,$I$1024*E1042/$C$4,IF(E1042<=$C$5,$I$1024,$I$1024*($C$6-E1042)/($C$6-$C$5))) -> 0.083333333
B1043: 18 | C1043: =($C$6/20)*17 -> 8.5 | D1043: =($C$6/20)*18 -> 9 | E1043: =(C1043+D1043)/2 -> 8.75 | F1043: =COUNTIFS($F$17:$F$1016,">="&C1043,$F$17:$F$1016,"<"&D1043) -> 28 | G1043: =F1043/($C$7*(D1043-C1043)) -> 0.056 | H1043: =IF(E1043<=$C$4,$I$1024*E1043/$C$4,IF(E1043<=$C$5,$I$1024,$I$1024*($C$6-E1043)/($C$6-$C$5))) -> 0.05952381
B1044: 19 | C1044: =($C$6/20)*18 -> 9 | D1044: =($C$6/20)*19 -> 9.5 | E1044: =(C1044+D1044)/2 -> 9.25 | F1044: =COUNTIFS($F$17:$F$1016,">="&C1044,$F$17:$F$1016,"<"&D1044) -> 20 | G1044: =F1044/($C$7*(D1044-C1044)) -> 0.04 | H1044: =IF(E1044<=$C$4,$I$1024*E1044/$C$4,IF(E1044<=$C$5,$I$1024,$I$1024*($C$6-E1044)/($C$6-$C$5))) -> 0.035714286
B1045: 20 | C1045: =($C$6/20)*19 -> 9.5 | D1045: =($C$6/20)*20 -> 10 | E1045: =(C1045+D1045)/2 -> 9.75 | F1045: =COUNTIFS($F$17:$F$1016,">="&C1045,$F$17:$F$1016,"<"&D1045) -> 6 | G1045: =F1045/($C$7*(D1045-C1045)) -> 0.012 | H1045: =IF(E1045<=$C$4,$I$1024*E1045/$C$4,IF(E1045<=$C$5,$I$1024,$I$1024*($C$6-E1045)/($C$6-$C$5))) -> 0.011904762

Sheet Ejercicio 2 - Triangular V
B1: Ejercicio 2
B3: Parámetros
B4: a (punto 1) = | C4: 8 | G4: Debe cumplirse: a < c < b
B5: c (vértice) = | C5: 9
B6: b (punto 3) = | C6: 10
B7: N° simulaciones = | C7: 1000
B9: Áreas (Paso 1 de la teoría)
B10: A1 = | C10: =(C5-C4)/(C6-C4) -> 0.5
B11: A2 = | C11: =(C6-C5)/(C6-C4) -> 0.5
B12: Suma = | C12: =C10+C11 -> 1
B16: iteracion | C16: R_region | D16: R_valor | E16: Region | F16: X
B17: 1 | C17: =RAND() -> 0.43798882 | D17: =RAND() -> 0.8375502 | E17: =IF(C17<=$C$10,1,2) -> 1 | F17: =IF(E17=1,$C$4+SQRT(D17*($C$6-$C$4)*($C$5-$C$4)),$C$6-SQRT((1-D17)*($C$6-$C$4)*($C$6-$C$5))) -> 9.2942567
B18: 2 | C18: =RAND() -> 0.30992138 | D18: =RAND() -> 0.20959272 | E18: =IF(C18<=$C$10,1,2) -> 1 | F18: =IF(E18=1,$C$4+SQRT(D18*($C$6-$C$4)*($C$5-$C$4)),$C$6-SQRT((1-D18)*($C$6-$C$4)*($C$6-$C$5))) -> 8.6474453
B19: 3 | C19: =RAND() -> 0.16697596 | D19: =RAND() -> 0.8691507 | E19: =IF(C19<=$C$10,1,2) -> 1 | F19: =IF(E19=1,$C$4+SQRT(D19*($C$6-$C$4)*($C$5-$C$4)),$C$6-SQRT((1-D19)*($C$6-$C$4)*($C$6-$C$5))) -> 9.3184466
B20: 4 | C20: =RAND() -> 0.16982072 | D20: =RAND() -> 0.72258929 | E20: =IF(C20<=$C$10,1,2) -> 1 | F20: =IF(E20=1,$C$4+SQRT(D20*($C$6-$C$4)*($C$5-$C$4)),$C$6-SQRT((1-D20)*($C$6-$C$4)*($C$6-$C$5))) -> 9.2021558
B21: 5 | C21: =RAND() -> 0.21299243 | D21: =RAND() -> 0.78557649 | E21: =IF(C21<=$C$10,1,2) -> 1 | F21: =IF(E21=1,$C$4+SQRT(D21*($C$6-$C$4)*($C$5-$C$4)),$C$6-SQRT((1-D21)*($C$6-$C$4)*($C$6-$C$5))) -> 9.2534564
B22: 6 | C22: =RAND() -> 0.89389787 | D22: =RAND() -> 0.23784977 | E22: =IF(C22<=$C$10,1,2) -> 2 | F22: =IF(E22=1,$C$4+SQRT(D22*($C$6-$C$4)*($C$5-$C$4)),$C$6-SQRT((1-D22)*($C$6-$C$4)*($C$6-$C$5))) -> 8.7653744
B23: 7 | C23: =RAND() -> 0.77079164 | D23: =RAND() -> 0.63292486 | E23: =IF(C23<=$C$10,1,2) -> 2 | F23: =IF(E23=1,$C$4+SQRT(D23*($C$6-$C$4)*($C$5-$C$4)),$C$6-SQRT((1-D23)*($C$6-$C$4)*($C$6-$C$5))) -> 9.1431743
B24: 8 | C24: =RAND() -> 0.27247167 | D24: =RAND() -> 0.77521819 | E24: =IF(C24<=$C$10,1,2) -> 1 | F24: =IF(E24=1,$C$4+SQRT(D24*($C$6-$C$4)*($C$5-$C$4)),$C$6-SQRT((1-D24)*($C$6-$C$4)*($C$6-$C$5))) -> 9.2451652
B25: 9 | C25: =RAND() -> 0.70952535 | D25: =RAND() -> 0.49954541 | E25: =IF(C25<=$C$10,1,2) -> 2 | F25: =IF(E25=1,$C$4+SQRT(D25*($C$6-$C$4)*($C$5-$C$4)),$C$6-SQRT((1-D25)*($C$6-$C$4)*($C$6-$C$5))) -> 8.9995455
B26: 10 | C26: =RAND() -> 0.53390172 | D26: =RAND() -> 0.61524758 | E26: =IF(C26<=$C$10,1,2) -> 2 | F26: =IF(E26=1,$C$4+SQRT(D26*($C$6-$C$4)*($C$5-$C$4)),$C$6-SQRT((1-D26)*($C$6-$C$4)*($C$6-$C$5))) -> 9.1227857
B27: 11 | C27: =RAND() -> 0.68455095 | D27: =RAND() -> 0.35070772 | E27: =IF(C27<=$C$10,1,2) -> 2 | F27: =IF(E27=1,$C$4+SQRT(D27*($C$6-$C$4)*($C$5-$C$4)),$C$6-SQRT((1-D27)*($C$6-$C$4)*($C$6-$C$5))) -> 8.8604455
B28: 12 | C28: =RAND() -> 0.37921058 | D28: =RAND() -> 0.63241274 | E28: =IF(C28<=$C$10,1,2) -> 1 | F28: =IF(E28=1,$C$4+SQRT(D28*($C$6-$C$4)*($C$5-$C$4)),$C$6-SQRT((1-D28)*($C$6-$C$4)*($C$6-$C$5))) -> 9.1246446
... B1016: 1000 | C1016: =RAND() -> 0.93423704 | D1016: =RAND() -> 0.82588804 | E1016: =IF(C1016<=$C$10,1,2) -> 2 | F1016: =IF(E1016=1,$C$4+SQRT(D1016*($C$6-$C$4)*($C$5-$C$4)),$C$6-SQRT((1-D1016)*($C$6-$C$4)*($C$6-$C$5))) -> 9.409895
B1018: Promedio X = | C1018: =AVERAGE(F17:F1016) -> 9.0061818
B1019: Mínimo X = | C1019: =MIN(F17:F1016) -> 8.0278119
B1020: Máximo X = | C1020: =MAX(F17:F1016) -> 9.9433951
B1023: Histograma vs. densidad teórica (dominio [a, b])
B1024: Bin | C1024: Lím. inf. | D1024: Lím. sup. | E1024: Punto medio | F1024: Frecuencia | G1024: Densidad emp. | H1024: Densidad teór.
B1025: 1 | C1025: =$C$4+(($C$6-$C$4)/20)*0 -> 8 | D1025: =$C$4+(($C$6-$C$4)/20)*1 -> 8.1 | E1025: =(C1025+D1025)/2 -> 8.05 | F1025: =COUNTIFS($F$17:$F$1016,">="&C1025,$F$17:$F$1016,"<"&D1025) -> 4 | G1025: =F1025/($C$7*(D1025-C1025)) -> 0.04 | H1025: =IF(E1025<=$C$5,2*(E1025-$C$4)/(($C$6-$C$4)*($C$5-$C$4)),2*($C$6-E1025)/(($C$6-$C$4)*($C$6-$C$5))) -> 0.05
B1026: 2 | C1026: =$C$4+(($C$6-$C$4)/20)*1 -> 8.1 | D1026: =$C$4+(($C$6-$C$4)/20)*2 -> 8.2 | E1026: =(C1026+D1026)/2 -> 8.15 | F1026: =COUNTIFS($F$17:$F$1016,">="&C1026,$F$17:$F$1016,"<"&D1026) -> 8 | G1026: =F1026/($C$7*(D1026-C1026)) -> 0.08 | H1026: =IF(E1026<=$C$5,2*(E1026-$C$4)/(($C$6-$C$4)*($C$5-$C$4)),2*($C$6-E1026)/(($C$6-$C$4)*($C$6-$C$5))) -> 0.15
B1027: 3 | C1027: =$C$4+(($C$6-$C$4)/20)*2 -> 8.2 | D1027: =$C$4+(($C$6-$C$4)/20)*3 -> 8.3 | E1027: =(C1027+D1027)/2 -> 8.25 | F1027: =COUNTIFS($F$17:$F$1016,">="&C1027,$F$17:$F$1016,"<"&D1027) -> 6 | G1027: =F1027/($C$7*(D1027-C1027)) -> 0.06 | H1027: =IF(E1027<=$C$5,2*(E1027-$C$4)/(($C$6-$C$4)*($C$5-$C$4)),2*($C$6-E1027)/(($C$6-$C$4)*($C$6-$C$5))) -> 0.25
B1028: 4 | C1028: =$C$4+(($C$6-$C$4)/20)*3 -> 8.3 | D1028: =$C$4+(($C$6-$C$4)/20)*4 -> 8.4 | E1028: =(C1028+D1028)/2 -> 8.35 | F1028: =COUNTIFS($F$17:$F$1016,">="&C1028,$F$17:$F$1016,"<"&D1028) -> 15 | G1028: =F1028/($C$7*(D1028-C1028)) -> 0.15 | H1028: =IF(E1028<=$C$5,2*(E1028-$C$4)/(($C$6-$C$4)*($C$5-$C$4)),2*($C$6-E1028)/(($C$6-$C$4)*($C$6-$C$5))) -> 0.35
B1029: 5 | C1029: =$C$4+(($C$6-$C$4)/20)*4 -> 8.4 | D1029: =$C$4+(($C$6-$C$4)/20)*5 -> 8.5 | E1029: =(C1029+D1029)/2 -> 8.45 | F1029: =COUNTIFS($F$17:$F$1016,">="&C1029,$F$17:$F$1016,"<"&D1029) -> 33 | G1029: =F1029/($C$7*(D1029-C1029)) -> 0.33 | H1029: =IF(E1029<=$C$5,2*(E1029-$C$4)/(($C$6-$C$4)*($C$5-$C$4)),2*($C$6-E1029)/(($C$6-$C$4)*($C$6-$C$5))) -> 0.45
B1030: 6 | C1030: =$C$4+(($C$6-$C$4)/20)*5 -> 8.5 | D1030: =$C$4+(($C$6-$C$4)/20)*6 -> 8.6 | E1030: =(C1030+D1030)/2 -> 8.55 | F1030: =COUNTIFS($F$17:$F$1016,">="&C1030,$F$17:$F$1016,"<"&D1030) -> 29 | G1030: =F1030/($C$7*(D1030-C1030)) -> 0.29 | H1030: =IF(E1030<=$C$5,2*(E1030-$C$4)/(($C$6-$C$4)*($C$5-$C$4)),2*($C$6-E1030)/(($C$6-$C$4)*($C$6-$C$5))) -> 0.55
B1031: 7 | C1031: =$C$4+(($C$6-$C$4)/20)*6 -> 8.6 | D1031: =$C$4+(($C$6-$C$4)/20)*7 -> 8.7 | E1031: =(C1031+D1031)/2 -> 8.65 | F1031: =COUNTIFS($F$17:$F$1016,">="&C1031,$F$17:$F$1016,"<"&D1031) -> 105 | G1031: =F1031/($C$7*(D1031-C1031)) -> 1.05 | H1031: =IF(E1031<=$C$5,2*(E1031-$C$4)/(($C$6-$C$4)*($C$5-$C$4)),2*($C$6-E1031)/(($C$6-$C$4)*($C$6-$C$5))) -> 0.65
B1032: 8 | C1032: =$C$4+(($C$6-$C$4)/20)*7 -> 8.7 | D1032: =$C$4+(($C$6-$C$4)/20)*8 -> 8.8 | E1032: =(C1032+D1032)/2 -> 8.75 | F1032: =COUNTIFS($F$17:$F$1016,">="&C1032,$F$17:$F$1016,"<"&D1032) -> 98 | G1032: =F1032/($C$7*(D1032-C1032)) -> 0.98 | H1032: =IF(E1032<=$C$5,2*(E1032-$C$4)/(($C$6-$C$4)*($C$5-$C$4)),2*($C$6-E1032)/(($C$6-$C$4)*($C$6-$C$5))) -> 0.75
B1033: 9 | C1033: =$C$4+(($C$6-$C$4)/20)*8 -> 8.8 | D1033: =$C$4+(($C$6-$C$4)/20)*9 -> 8.9 | E1033: =(C1033+D1033)/2 -> 8.85 | F1033: =COUNTIFS($F$17:$F$1016,">="&C1033,$F$17:$F$1016,"<"&D1033) -> 100 | G1033: =F1033/($C$7*(D1033-C1033)) -> 1 | H1033: =IF(E1033<=$C$5,2*(E1033-$C$4)/(($C$6-$C$4)*($C$5-$C$4)),2*($C$6-E1033)/(($C$6-$C$4)*($C$6-$C$5))) -> 0.85
B1034: 10 | C1034: =$C$4+(($C$6-$C$4)/20)*9 -> 8.9 | D1034: =$C$4+(($C$6-$C$4)/20)*10 -> 9 | E1034: =(C1034+D1034)/2 -> 8.95 | F1034: =COUNTIFS($F$17:$F$1016,">="&C1034,$F$17:$F$1016,"<"&D1034) -> 87 | G1034: =F1034/($C$7*(D1034-C1034)) -> 0.87 | H1034: =IF(E1034<=$C$5,2*(E1034-$C$4)/(($C$6-$C$4)*($C$5-$C$4)),2*($C$6-E1034)/(($C$6-$C$4)*($C$6-$C$5))) -> 0.95
B1035: 11 | C1035: =$C$4+(($C$6-$C$4)/20)*10 -> 9 | D1035: =$C$4+(($C$6-$C$4)/20)*11 -> 9.1 | E1035: =(C1035+D1035)/2 -> 9.05 | F1035: =COUNTIFS($F$17:$F$1016,">="&C1035,$F$17:$F$1016,"<"&D1035) -> 96 | G1035: =F1035/($C$7*(D1035-C1035)) -> 0.96 | H1035: =IF(E1035<=$C$5,2*(E1035-$C$4)/(($C$6-$C$4)*($C$5-$C$4)),2*($C$6-E1035)/(($C$6-$C$4)*($C$6-$C$5))) -> 0.95
B1036: 12 | C1036: =$C$4+(($C$6-$C$4)/20)*11 -> 9.1 | D1036: =$C$4+(($C$6-$C$4)/20)*12 -> 9.2 | E1036: =(C1036+D1036)/2 -> 9.15 | F1036: =COUNTIFS($F$17:$F$1016,">="&C1036,$F$17:$F$1016,"<"&D1036) -> 107 | G1036: =F1036/($C$7*(D1036-C1036)) -> 1.07 | H1036: =IF(E1036<=$C$5,2*(E1036-$C$4)/(($C$6-$C$4)*($C$5-$C$4)),2*($C$6-E1036)/(($C$6-$C$4)*($C$6-$C$5))) -> 0.85
B1037: 13 | C1037: =$C$4+(($C$6-$C$4)/20)*12 -> 9.2 | D1037: =$C$4+(($C$6-$C$4)/20)*13 -> 9.3 | E1037: =(C1037+D1037)/2 -> 9.25 | F1037: =COUNTIFS($F$17:$F$1016,">="&C1037,$F$17:$F$1016,"<"&D1037) -> 101 | G1037: =F1037/($C$7*(D1037-C1037)) -> 1.01 | H1037: =IF(E1037<=$C$5,2*(E1037-$C$4)/(($C$6-$C$4)*($C$5-$C$4)),2*($C$6-E1037)/(($C$6-$C$4)*($C$6-$C$5))) -> 0.75
B1038: 14 | C1038: =$C$4+(($C$6-$C$4)/20)*13 -> 9.3 | D1038: =$C$4+(($C$6-$C$4)/20)*14 -> 9.4 | E1038: =(C1038+D1038)/2 -> 9.35 | F1038: =COUNTIFS($F$17:$F$1016,">="&C1038,$F$17:$F$1016,"<"&D1038) -> 99 | G1038: =F1038/($C$7*(D1038-C1038)) -> 0.99 | H1038: =IF(E1038<=$C$5,2*(E1038-$C$4)/(($C$6-$C$4)*($C$5-$C$4)),2*($C$6-E1038)/(($C$6-$C$4)*($C$6-$C$5))) -> 0.65
B1039: 15 | C1039: =$C$4+(($C$6-$C$4)/20)*14 -> 9.4 | D1039: =$C$4+(($C$6-$C$4)/20)*15 -> 9.5 | E1039: =(C1039+D1039)/2 -> 9.45 | F1039: =COUNTIFS($F$17:$F$1016,">="&C1039,$F$17:$F$1016,"<"&D1039) -> 51 | G1039: =F1039/($C$7*(D1039-C1039)) -> 0.51 | H1039: =IF(E1039<=$C$5,2*(E1039-$C$4)/(($C$6-$C$4)*($C$5-$C$4)),2*($C$6-E1039)/(($C$6-$C$4)*($C$6-$C$5))) -> 0.55
B1040: 16 | C1040: =$C$4+(($C$6-$C$4)/20)*15 -> 9.5 | D1040: =$C$4+(($C$6-$C$4)/20)*16 -> 9.6 | E1040: =(C1040+D1040)/2 -> 9.55 | F1040: =COUNTIFS($F$17:$F$1016,">="&C1040,$F$17:$F$1016,"<"&D1040) -> 22 | G1040: =F1040/($C$7*(D1040-C1040)) -> 0.22 | H1040: =IF(E1040<=$C$5,2*(E1040-$C$4)/(($C$6-$C$4)*($C$5-$C$4)),2*($C$6-E1040)/(($C$6-$C$4)*($C$6-$C$5))) -> 0.45
B1041: 17 | C1041: =$C$4+(($C$6-$C$4)/20)*16 -> 9.6 | D1041: =$C$4+(($C$6-$C$4)/20)*17 -> 9.7 | E1041: =(C1041+D1041)/2 -> 9.65 | F1041: =COUNTIFS($F$17:$F$1016,">="&C1041,$F$17:$F$1016,"<"&D1041) -> 14 | G1041: =F1041/($C$7*(D1041-C1041)) -> 0.14 | H1041: =IF(E1041<=$C$5,2*(E1041-$C$4)/(($C$6-$C$4)*($C$5-$C$4)),2*($C$6-E1041)/(($C$6-$C$4)*($C$6-$C$5))) -> 0.35
B1042: 18 | C1042: =$C$4+(($C$6-$C$4)/20)*17 -> 9.7 | D1042: =$C$4+(($C$6-$C$4)/20)*18 -> 9.8 | E1042: =(C1042+D1042)/2 -> 9.75 | F1042: =COUNTIFS($F$17:$F$1016,">="&C1042,$F$17:$F$1016,"<"&D1042) -> 15 | G1042: =F1042/($C$7*(D1042-C1042)) -> 0.15 | H1042: =IF(E1042<=$C$5,2*(E1042-$C$4)/(($C$6-$C$4)*($C$5-$C$4)),2*($C$6-E1042)/(($C$6-$C$4)*($C$6-$C$5))) -> 0.25
B1043: 19 | C1043: =$C$4+(($C$6-$C$4)/20)*18 -> 9.8 | D1043: =$C$4+(($C$6-$C$4)/20)*19 -> 9.9 | E1043: =(C1043+D1043)/2 -> 9.85 | F1043: =COUNTIFS($F$17:$F$1016,">="&C1043,$F$17:$F$1016,"<"&D1043) -> 8 | G1043: =F1043/($C$7*(D1043-C1043)) -> 0.08 | H1043: =IF(E1043<=$C$5,2*(E1043-$C$4)/(($C$6-$C$4)*($C$5-$C$4)),2*($C$6-E1043)/(($C$6-$C$4)*($C$6-$C$5))) -> 0.15
B1044: 20 | C1044: =$C$4+(($C$6-$C$4)/20)*19 -> 9.9 | D1044: =$C$4+(($C$6-$C$4)/20)*20 -> 10 | E1044: =(C1044+D1044)/2 -> 9.95 | F1044: =COUNTIFS($F$17:$F$1016,">="&C1044,$F$17:$F$1016,"<"&D1044) -> 2 | G1044: =F1044/($C$7*(D1044-C1044)) -> 0.02 | H1044: =IF(E1044<=$C$5,2*(E1044-$C$4)/(($C$6-$C$4)*($C$5-$C$4)),2*($C$6-E1044)/(($C$6-$C$4)*($C$6-$C$5))) -> 0.05

Sheet Ejercicio 3 - TIR
B2: EJERCICIO 3
B4: Parámetros generales
B5: Tasa de impuestos (T) | D5: 0.5
B6: TREMA | D6: 0.15
B7: Vida fiscal del activo (años) | D7: 5
B8: Umbral de aceptación Prob(TIR>TREMA) | D8: 0.9
B9: Número de simulaciones | D9: 1000
B11: Activo fijo y activo circulante inicial (distribución triangular)
B12: Variable | C12: a (mínimo / optimista) | D12: b (moda / más probable) | E12: c (máximo / pesimista)
B13: Activo fijo inicial (AF) | C13: 60000 | D13: 70000 | E13: 100000
B14: Activo circulante inicial (AC) | C14: 25000 | D14: 30000 | E14: 40000
B16: Flujo de efectivo antes de impuestos, por año (triangular, igual los 5 años)
B17: Variable | C17: a (mínimo / optimista) | D17: b (moda / más probable) | E17: c (máximo / pesimista)
B18: Flujo antes de impuestos (x) | C18: 30000 | D18: 40000 | E18: 45000
B20: Tasas de inflación, por año (triangular)
B21: Año | C21: a (mínimo / optimista) | D21: b (moda / más probable) | E21: c (máximo / pesimista)
B22: 1 | C22: 0.12 | D22: 0.15 | E22: 0.18
B23: 2 | C23: 0.12 | D23: 0.15 | E23: 0.18
B24: 3 | C24: 0.15 | D24: 0.18 | E24: 0.22
B25: 4 | C25: 0.18 | D25: 0.2 | E25: 0.25
B26: 5 | C26: 0.19 | D26: 0.22 | E26: 0.28
B29: Extremos teóricos
B30: TIR mínima (todo pesimista) | D30: -0.031
B31: TIR máxima (todo optimista) | D31: 0.1991
B34: ── Resultados de la simulación ──
B35: Tabla de frecuencia acumulada de la TIR simulada (Pasos 3, 8 y 9)
B36: Intervalo # | C36: Límite inferior (%) | D36: Límite superior (%) | E36: Frecuencia | F36: Fracción | G36: Fracción acumulada
B37: 1 | C37: =$D$30*100 -> -3.1 | D37: =$D$30*100+($D$31*100-$D$30*100)/20*1 -> -1.9495 | E37: =COUNTIFS('Ejercicio 3 - Simulacion'!$BV$2:$BV$1001,">="&C37,'Ejercicio 3 - Simulacion'!$BV$2:$BV$1001,"<="&D37) -> 0 | F37: =E37/$D$9 -> 0 | G37: =F37 -> 0
B38: 2 | C38: =D37 -> -1.9495 | D38: =$D$30*100+($D$31*100-$D$30*100)/20*2 -> -0.799 | E38: =COUNTIFS('Ejercicio 3 - Simulacion'!$BV$2:$BV$1001,">"&C38,'Ejercicio 3 - Simulacion'!$BV$2:$BV$1001,"<="&D38) -> 0 | F38: =E38/$D$9 -> 0 | G38: =G37+F38 -> 0
B39: 3 | C39: =D38 -> -0.799 | D39: =$D$30*100+($D$31*100-$D$30*100)/20*3 -> 0.3515 | E39: =COUNTIFS('Ejercicio 3 - Simulacion'!$BV$2:$BV$1001,">"&C39,'Ejercicio 3 - Simulacion'!$BV$2:$BV$1001,"<="&D39) -> 0 | F39: =E39/$D$9 -> 0 | G39: =G38+F39 -> 0
B40: 4 | C40: =D39 -> 0.3515 | D40: =$D$30*100+($D$31*100-$D$30*100)/20*4 -> 1.502 | E40: =COUNTIFS('Ejercicio 3 - Simulacion'!$BV$2:$BV$1001,">"&C40,'Ejercicio 3 - Simulacion'!$BV$2:$BV$1001,"<="&D40) -> 0 | F40: =E40/$D$9 -> 0 | G40: =G39+F40 -> 0
B41: 5 | C41: =D40 -> 1.502 | D41: =$D$30*100+($D$31*100-$D$30*100)/20*5 -> 2.6525 | E41: =COUNTIFS('Ejercicio 3 - Simulacion'!$BV$2:$BV$1001,">"&C41,'Ejercicio 3 - Simulacion'!$BV$2:$BV$1001,"<="&D41) -> 0 | F41: =E41/$D$9 -> 0 | G41: =G40+F41 -> 0
B42: 6 | C42: =D41 -> 2.6525 | D42: =$D$30*100+($D$31*100-$D$30*100)/20*6 -> 3.803 | E42: =COUNTIFS('Ejercicio 3 - Simulacion'!$BV$2:$BV$1001,">"&C42,'Ejercicio 3 - Simulacion'!$BV$2:$BV$1001,"<="&D42) -> 16 | F42: =E42/$D$9 -> 0.016 | G42: =G41+F42 -> 0.016
B43: 7 | C43: =D42 -> 3.803 | D43: =$D$30*100+($D$31*100-$D$30*100)/20*7 -> 4.9535 | E43: =COUNTIFS('Ejercicio 3 - Simulacion'!$BV$2:$BV$1001,">"&C43,'Ejercicio 3 - Simulacion'!$BV$2:$BV$1001,"<="&D43) -> 67 | F43: =E43/$D$9 -> 0.067 | G43: =G42+F43 -> 0.083
B44: 8 | C44: =D43 -> 4.9535 | D44: =$D$30*100+($D$31*100-$D$30*100)/20*8 -> 6.104 | E44: =COUNTIFS('Ejercicio 3 - Simulacion'!$BV$2:$BV$1001,">"&C44,'Ejercicio 3 - Simulacion'!$BV$2:$BV$1001,"<="&D44) -> 119 | F44: =E44/$D$9 -> 0.119 | G44: =G43+F44 -> 0.202
B45: 9 | C45: =D44 -> 6.104 | D45: =$D$30*100+($D$31*100-$D$30*100)/20*9 -> 7.2545 | E45: =COUNTIFS('Ejercicio 3 - Simulacion'!$BV$2:$BV$1001,">"&C45,'Ejercicio 3 - Simulacion'!$BV$2:$BV$1001,"<="&D45) -> 195 | F45: =E45/$D$9 -> 0.195 | G45: =G44+F45 -> 0.397
B46: 10 | C46: =D45 -> 7.2545 | D46: =$D$30*100+($D$31*100-$D$30*100)/20*10 -> 8.405 | E46: =COUNTIFS('Ejercicio 3 - Simulacion'!$BV$2:$BV$1001,">"&C46,'Ejercicio 3 - Simulacion'!$BV$2:$BV$1001,"<="&D46) -> 214 | F46: =E46/$D$9 -> 0.214 | G46: =G45+F46 -> 0.611
B47: 11 | C47: =D46 -> 8.405 | D47: =$D$30*100+($D$31*100-$D$30*100)/20*11 -> 9.5555 | E47: =COUNTIFS('Ejercicio 3 - Simulacion'!$BV$2:$BV$1001,">"&C47,'Ejercicio 3 - Simulacion'!$BV$2:$BV$1001,"<="&D47) -> 189 | F47: =E47/$D$9 -> 0.189 | G47: =G46+F47 -> 0.8
B48: 12 | C48: =D47 -> 9.5555 | D48: =$D$30*100+($D$31*100-$D$30*100)/20*12 -> 10.706 | E48: =COUNTIFS('Ejercicio 3 - Simulacion'!$BV$2:$BV$1001,">"&C48,'Ejercicio 3 - Simulacion'!$BV$2:$BV$1001,"<="&D48) -> 110 | F48: =E48/$D$9 -> 0.11 | G48: =G47+F48 -> 0.91
B49: 13 | C49: =D48 -> 10.706 | D49: =$D$30*100+($D$31*100-$D$30*100)/20*13 -> 11.8565 | E49: =COUNTIFS('Ejercicio 3 - Simulacion'!$BV$2:$BV$1001,">"&C49,'Ejercicio 3 - Simulacion'!$BV$2:$BV$1001,"<="&D49) -> 70 | F49: =E49/$D$9 -> 0.07 | G49: =G48+F49 -> 0.98
B50: 14 | C50: =D49 -> 11.8565 | D50: =$D$30*100+($D$31*100-$D$30*100)/20*14 -> 13.007 | E50: =COUNTIFS('Ejercicio 3 - Simulacion'!$BV$2:$BV$1001,">"&C50,'Ejercicio 3 - Simulacion'!$BV$2:$BV$1001,"<="&D50) -> 19 | F50: =E50/$D$9 -> 0.019 | G50: =G49+F50 -> 0.999
B51: 15 | C51: =D50 -> 13.007 | D51: =$D$30*100+($D$31*100-$D$30*100)/20*15 -> 14.1575 | E51: =COUNTIFS('Ejercicio 3 - Simulacion'!$BV$2:$BV$1001,">"&C51,'Ejercicio 3 - Simulacion'!$BV$2:$BV$1001,"<="&D51) -> 1 | F51: =E51/$D$9 -> 0.001 | G51: =G50+F51 -> 1
B52: 16 | C52: =D51 -> 14.1575 | D52: =$D$30*100+($D$31*100-$D$30*100)/20*16 -> 15.308 | E52: =COUNTIFS('Ejercicio 3 - Simulacion'!$BV$2:$BV$1001,">"&C52,'Ejercicio 3 - Simulacion'!$BV$2:$BV$1001,"<="&D52) -> 0 | F52: =E52/$D$9 -> 0 | G52: =G51+F52 -> 1
B53: 17 | C53: =D52 -> 15.308 | D53: =$D$30*100+($D$31*100-$D$30*100)/20*17 -> 16.4585 | E53: =COUNTIFS('Ejercicio 3 - Simulacion'!$BV$2:$BV$1001,">"&C53,'Ejercicio 3 - Simulacion'!$BV$2:$BV$1001,"<="&D53) -> 0 | F53: =E53/$D$9 -> 0 | G53: =G52+F53 -> 1
B54: 18 | C54: =D53 -> 16.4585 | D54: =$D$30*100+($D$31*100-$D$30*100)/20*18 -> 17.609 | E54: =COUNTIFS('Ejercicio 3 - Simulacion'!$BV$2:$BV$1001,">"&C54,'Ejercicio 3 - Simulacion'!$BV$2:$BV$1001,"<="&D54) -> 0 | F54: =E54/$D$9 -> 0 | G54: =G53+F54 -> 1
B55: 19 | C55: =D54 -> 17.609 | D55: =$D$30*100+($D$31*100-$D$30*100)/20*19 -> 18.7595 | E55: =COUNTIFS('Ejercicio 3 - Simulacion'!$BV$2:$BV$1001,">"&C55,'Ejercicio 3 - Simulacion'!$BV$2:$BV$1001,"<="&D55) -> 0 | F55: =E55/$D$9 -> 0 | G55: =G54+F55 -> 1
B56: 20 | C56: =D55 -> 18.7595 | D56: =$D$30*100+($D$31*100-$D$30*100)/20*20 -> 19.91 | E56: =COUNTIFS('Ejercicio 3 - Simulacion'!$BV$2:$BV$1001,">"&C56,'Ejercicio 3 - Simulacion'!$BV$2:$BV$1001,"<="&D56) -> 0 | F56: =E56/$D$9 -> 0 | G56: =G55+F56 -> 1
B59: Resultado principal
B60: Prob(TIR > TREMA) | D60: =COUNTIF('Ejercicio 3 - Simulacion'!$BV$2:$BV$1001,">"&($D$6*100))/$D$9 -> 0
B61: Umbral requerido por la administración | D61: =$D$8 -> 0.9
B62: Decisión | D62: =IF(D60>=D61,"ACEPTAR el proyecto","RECHAZAR el proyecto") -> RECHAZAR el proyecto

Sheet Ejercicio 3 - Simulacion
A1: N° sim | B1: R (AF) | C1: AF simulado | D1: R (AC) | E1: AC simulado | F1: R (x año 1) | G1: x año 1 | H1: R (x año 2) | I1: x año 2 | J1: R (x año 3) | K1: x año 3 | L1: R (x año 4) | M1: x año 4 | N1: R (x año 5) | O1: x año 5 | P1: R (i año 1) | Q1: i año 1 | R1: R (i año 2) | S1: i año 2 | T1: R (i año 3) | U1: i año 3 | V1: R (i año 4) | W1: i año 4 | X1: R (i año 5) | Y1: i año 5 | Z1: Inflación acum. año 1 | AA1: Inflación acum. año 2 | AB1: Inflación acum. año 3 | AC1: Inflación acum. año 4 | AD1: Inflación acum. año 5 | AE1: Inv. adicional AC año 1 | AF1: Inv. adicional AC año 2 | AG1: Inv. adicional AC año 3 | AH1: Inv. adicional AC año 4 | AI1: Inv. adicional AC año 5 | AJ1: Flujo antes imp. año 1 (corriente) | AK1: Flujo antes imp. año 2 (corriente) | AL1: Flujo antes imp. año 3 (corriente) | AM1: Flujo antes imp. año 4 (corriente) | AN1: Flujo antes imp. año 5 (corriente) | AO1: Depreciación (fija) | AP1: Ingreso gravable año 1 | AQ1: Ingreso gravable año 2 | AR1: Ingreso gravable año 3 | AS1: Ingreso gravable año 4 | AT1: Ingreso gravable año 5 | AU1: Impuestos año 1 | AV1: Impuestos año 2 | AW1: Impuestos año 3 | AX1: Impuestos año 4 | AY1: Impuestos año 5 | AZ1: Flujo desp. imp. año 1 (corriente) | BA1: Flujo desp. imp. año 2 (corriente) | BB1: Flujo desp. imp. año 3 (corriente) | BC1: Flujo desp. imp. año 4 (corriente) | BD1: Flujo desp. imp. año 5 (corriente) | BE1: Flujo desp. imp. año 1 (constante) | BF1: Flujo desp. imp. año 2 (constante) | BG1: Flujo desp. imp. año 3 (constante) | BH1: Flujo desp. imp. año 4 (constante) | BI1: Flujo desp. imp. año 5 (constante) | BJ1: VR: AC recuperado (nominal) | BK1: VR: 20% AF recuperado (nominal) | BL1: VR antes de impuestos | BM1: VR impuestos | BN1: VR pesos corrientes | BO1: VR pesos constantes | BP1: Flujo año 0 | BQ1: Flujo año 1 | BR1: Flujo año 2 | BS1: Flujo año 3 | BT1: Flujo año 4 | BU1: Flujo año 5 | BV1: TIR simulada
A2: 1 | B2: =RAND() -> 0.17604283 | C2: =IF(B2<=('Ejercicio 3 - TIR'!$D$13-'Ejercicio 3 - TIR'!$C$13)/('Ejercicio 3 - TIR'!$E$13-'Ejercicio 3 - TIR'!$C$13),'Ejercicio 3 - TIR'!$C$13+SQRT(('Ejercicio 3 - TIR'!$E$13-'Ejercicio 3 - TIR'!$C$13)*('Ejercicio 3 - TIR'!$D$13-'Ejercicio 3 - TIR'!$C$13)*B2),'Ejercicio 3 - TIR'!$E$13-SQRT(('Ejercicio 3 - TIR'!$E$13-'Ejercicio 3 - TIR'!$C$13)*('Ejercicio 3 - TIR'!$E$13-'Ejercicio 3 - TIR'!$D$13)*(1-B2))) -> 68391.492 | D2: =RAND() -> 0.43599568 | E2: =IF(D2<=('Ejercicio 3 - TIR'!$D$14-'Ejercicio 3 - TIR'!$C$14)/('Ejercicio 3 - TIR'!$E$14-'Ejercicio 3 - TIR'!$C$14),'Ejercicio 3 - TIR'!$C$14+SQRT(('Ejercicio 3 - TIR'!$E$14-'Ejercicio 3 - TIR'!$C$14)*('Ejercicio 3 - TIR'!$D$14-'Ejercicio 3 - TIR'!$C$14)*D2),'Ejercicio 3 - TIR'!$E$14-SQRT(('Ejercicio 3 - TIR'!$E$14-'Ejercicio 3 - TIR'!$C$14)*('Ejercicio 3 - TIR'!$E$14-'Ejercicio 3 - TIR'!$D$14)*(1-D2))) -> 30802.139 | F2: =RAND() -> 0.74322412 | G2: =IF(F2<=('Ejercicio 3 - TIR'!$D$18-'Ejercicio 3 - TIR'!$C$18)/('Ejercicio 3 - TIR'!$E$18-'Ejercicio 3 - TIR'!$C$18),'Ejercicio 3 - TIR'!$C$18+SQRT(('Ejercicio 3 - TIR'!$E$18-'Ejercicio 3 - TIR'!$C$18)*('Ejercicio 3 - TIR'!$D$18-'Ejercicio 3 - TIR'!$C$18)*F2),'Ejercicio 3 - TIR'!$E$18-SQRT(('Ejercicio 3 - TIR'!$E$18-'Ejercicio 3 - TIR'!$C$18)*('Ejercicio 3 - TIR'!$E$18-'Ejercicio 3 - TIR'!$D$18)*(1-F2))) -> 40611.584 | H2: =RAND() -> 0.11371915 | I2: =IF(H2<=('Ejercicio 3 - TIR'!$D$18-'Ejercicio 3 - TIR'!$C$18)/('Ejercicio 3 - TIR'!$E$18-'Ejercicio 3 - TIR'!$C$18),'Ejercicio 3 - TIR'!$C$18+SQRT(('Ejercicio 3 - TIR'!$E$18-'Ejercicio 3 - TIR'!$C$18)*('Ejercicio 3 - TIR'!$D$18-'Ejercicio 3 - TIR'!$C$18)*H2),'Ejercicio 3 - TIR'!$E$18-SQRT(('Ejercicio 3 - TIR'!$E$18-'Ejercicio 3 - TIR'!$C$18)*('Ejercicio 3 - TIR'!$E$18-'Ejercicio 3 - TIR'!$D$18)*(1-H2))) -> 34130.118 | J2: =RAND() -> 0.57794757 | K2: =IF(J2<=('Ejercicio 3 - TIR'!$D$18-'Ejercicio 3 - TIR'!$C$18)/('Ejercicio 3 - TIR'!$E$18-'Ejercicio 3 - TIR'!$C$18),'Ejercicio 3 - TIR'!$C$18+SQRT(('Ejercicio 3 - TIR'!$E$18-'Ejercicio 3 - TIR'!$C$18)*('Ejercicio 3 - TIR'!$D$18-'Ejercicio 3 - TIR'!$C$18)*J2),'Ejercicio 3 - TIR'!$E$18-SQRT(('Ejercicio 3 - TIR'!$E$18-'Ejercicio 3 - TIR'!$C$18)*('Ejercicio 3 - TIR'!$E$18-'Ejercicio 3 - TIR'!$D$18)*(1-J2))) -> 39310.861 | L2: =RAND() -> 0.23226942 | M2: =IF(L2<=('Ejercicio 3 - TIR'!$D$18-'Ejercicio 3 - TIR'!$C$18)/('Ejercicio 3 - TIR'!$E$18-'Ejercicio 3 - TIR'!$C$18),'Ejercicio 3 - TIR'!$C$18+SQRT(('Ejercicio 3 - TIR'!$E$18-'Ejercicio 3 - TIR'!$C$18)*('Ejercicio 3 - TIR'!$D$18-'Ejercicio 3 - TIR'!$C$18)*L2),'Ejercicio 3 - TIR'!$E$18-SQRT(('Ejercicio 3 - TIR'!$E$18-'Ejercicio 3 - TIR'!$C$18)*('Ejercicio 3 - TIR'!$E$18-'Ejercicio 3 - TIR'!$D$18)*(1-L2))) -> 35902.577 | N2: =RAND() -> 0.6200061 | O2: =IF(N2<=('Ejercicio 3 - TIR'!$D$18-'Ejercicio 3 - TIR'!$C$18)/('Ejercicio 3 - TIR'!$E$18-'Ejercicio 3 - TIR'!$C$18),'Ejercicio 3 - TIR'!$C$18+SQRT(('Ejercicio 3 - TIR'!$E$18-'Ejercicio 3 - TIR'!$C$18)*('Ejercicio 3 - TIR'!$D$18-'Ejercicio 3 - TIR'!$C$18)*N2),'Ejercicio 3 - TIR'!$E$18-SQRT(('Ejercicio 3 - TIR'!$E$18-'Ejercicio 3 - TIR'!$C$18)*('Ejercicio 3 - TIR'!$E$18-'Ejercicio 3 - TIR'!$D$18)*(1-N2))) -> 39643.698 | P2: =RAND() -> 0.32887827 | Q2: =IF(P2<=('Ejercicio 3 - TIR'!$D$22-'Ejercicio 3 - TIR'!$C$22)/('Ejercicio 3 - TIR'!$E$22-'Ejercicio 3 - TIR'!$C$22),'Ejercicio 3 - TIR'!$C$22+SQRT(('Ejercicio 3 - TIR'!$E$22-'Ejercicio 3 - TIR'!$C$22)*('Ejercicio 3 - TIR'!$D$22-'Ejercicio 3 - TIR'!$C$22)*P2),'Ejercicio 3 - TIR'!$E$22-SQRT(('Ejercicio 3 - TIR'!$E$22-'Ejercicio 3 - TIR'!$C$22)*('Ejercicio 3 - TIR'!$E$22-'Ejercicio 3 - TIR'!$D$22)*(1-P2))) -> 0.14433066 | R2: =RAND() -> 0.94153219 | S2: =IF(R2<=('Ejercicio 3 - TIR'!$D$23-'Ejercicio 3 - TIR'!$C$23)/('Ejercicio 3 - TIR'!$E$23-'Ejercicio 3 - TIR'!$C$23),'Ejercicio 3 - TIR'!$C$23+SQRT(('Ejercicio 3 - TIR'!$E$23-'Ejercicio 3 - TIR'!$C$23)*('Ejercicio 3 - TIR'!$D$23-'Ejercicio 3 - TIR'!$C$23)*R2),'Ejercicio 3 - TIR'!$E$23-SQRT(('Ejercicio 3 - TIR'!$E$23-'Ejercicio 3 - TIR'!$C$23)*('Ejercicio 3 - TIR'!$E$23-'Ejercicio 3 - TIR'!$D$23)*(1-R2))) -> 0.16974124 | T2: =RAND() -> 0.72587293 | U2: =IF(T2<=('Ejercicio 3 - TIR'!$D$24-'Ejercicio 3 - TIR'!$C$24)/('Ejercicio 3 - TIR'!$E$24-'Ejercicio 3 - TIR'!$C$24),'Ejercicio 3 - TIR'!$C$24+SQRT(('Ejercicio 3 - TIR'!$E$24-'Ejercicio 3 - TIR'!$C$24)*('Ejercicio 3 - TIR'!$D$24-'Ejercicio 3 - TIR'!$C$24)*T2),'Ejercicio 3 - TIR'!$E$24-SQRT(('Ejercicio 3 - TIR'!$E$24-'Ejercicio 3 - TIR'!$C$24)*('Ejercicio 3 - TIR'!$E$24-'Ejercicio 3 - TIR'!$D$24)*(1-T2))) -> 0.1922952 | V2: =RAND() -> 0.70192371 | W2: =IF(V2<=('Ejercicio 3 - TIR'!$D$25-'Ejercicio 3 - TIR'!$C$25)/('Ejercicio 3 - TIR'!$E$25-'Ejercicio 3 - TIR'!$C$25),'Ejercicio 3 - TIR'!$C$25+SQRT(('Ejercicio 3 - TIR'!$E$25-'Ejercicio 3 - TIR'!$C$25)*('Ejercicio 3 - TIR'!$D$25-'Ejercicio 3 - TIR'!$C$25)*V2),'Ejercicio 3 - TIR'!$E$25-SQRT(('Ejercicio 3 - TIR'!$E$25-'Ejercicio 3 - TIR'!$C$25)*('Ejercicio 3 - TIR'!$E$25-'Ejercicio 3 - TIR'!$D$25)*(1-V2))) -> 0.21770036 | X2: =RAND() -> 0.97192974 | Y2: =IF(X2<=('Ejercicio 3 - TIR'!$D$26-'Ejercicio 3 - TIR'!$C$26)/('Ejercicio 3 - TIR'!$E$26-'Ejercicio 3 - TIR'!$C$26),'Ejercicio 3 - TIR'!$C$26+SQRT(('Ejercicio 3 - TIR'!$E$26-'Ejercicio 3 - TIR'!$C$26)*('Ejercicio 3 - TIR'!$D$26-'Ejercicio 3 - TIR'!$C$26)*X2),'Ejercicio 3 - TIR'!$E$26-SQRT(('Ejercicio 3 - TIR'!$E$26-'Ejercicio 3 - TIR'!$C$26)*('Ejercicio 3 - TIR'!$E$26-'Ejercicio 3 - TIR'!$D$26)*(1-X2))) -> 0.26768824 | Z2: =(1+Q2) -> 1.1443307 | AA2: =Z2*(1+S2) -> 1.3385708 | AB2: =AA2*(1+U2) -> 1.5959715 | AC2: =AB2*(1+W2) -> 1.9434151 | AD2: =AC2*(1+Y2) -> 2.4636444 | AE2: =E2*Q2 -> 4445.693 | AF2: =AE2*(1+S2) -> 5200.3104 | AG2: =AF2*(1+U2) -> 6200.3052 | AH2: =AG2*(1+W2) -> 7550.1138 | AI2: =AH2*(1+Y2) -> 9571.1905 | AJ2: =G2*Z2 -> 46473.081 | AK2: =I2*AA2 -> 45685.578 | AL2: =K2*AB2 -> 62739.014 | AM2: =M2*AC2 -> 69773.609 | AN2: =O2*AD2 -> 97667.976 | AO2: =C2/'Ejercicio 3 - TIR'!$D$7 -> 13678.298 | AP2: =AJ2-AO2 -> 32794.783 | AQ2: =AK2-AO2 -> 32007.279 | AR2: =AL2-AO2 -> 49060.716 | AS2: =AM2-AO2 -> 56095.31 | AT2: =AN2-AO2 -> 83989.678 | AU2: =AP2*'Ejercicio 3 - TIR'!$D$5 -> 16397.391 | AV2: =AQ2*'Ejercicio 3 - TIR'!$D$5 -> 16003.64 | AW2: =AR2*'Ejercicio 3 - TIR'!$D$5 -> 24530.358 | AX2: =AS2*'Ejercicio 3 - TIR'!$D$5 -> 28047.655 | AY2: =AT2*'Ejercicio 3 - TIR'!$D$5 -> 41994.839 | AZ2: =AJ2-AU2-AE2 -> 25629.997 | BA2: =AK2-AV2-AF2 -> 24481.628 | BB2: =AL2-AW2-AG2 -> 32008.351 | BC2: =AM2-AX2-AH2 -> 34175.84 | BD2: =AN2-AY2-AI2 -> 46101.947 | BE2: =AZ2/Z2 -> 22397.37 | BF2: =BA2/AA2 -> 18289.379 | BG2: =BB2/AB2 -> 20055.716 | BH2: =BC2/AC2 -> 17585.456 | BI2: =BD2/AD2 -> 18712.906 | BJ2: =E2*AD2 -> 75885.518 | BK2: =0.2*C2*AD2 -> 33698.464 | BL2: =BJ2+BK2 -> 109583.98 | BM2: =BK2*'Ejercicio 3 - TIR'!$D$5 -> 16849.232 | BN2: =BL2-BM2 -> 92734.75 | BO2: =BN2/AD2 -> 37641.288 | BP2: =-(C2+E2) -> -99193.631 | BQ2: =BE2 -> 22397.37 | BR2: =BF2 -> 18289.379 | BS2: =BG2 -> 20055.716 | BT2: =BH2 -> 17585.456 | BU2: =BI2+BO2 -> 56354.194 | BV2: =IFERROR(IRR(BP2:BU2,0.1),NA())*100 -> 9.4391741
A3: 2 | B3: =RAND() -> 0.79830747 | C3: =IF(B3<=('Ejercicio 3 - TIR'!$D$13-'Ejercicio 3 - TIR'!$C$13)/('Ejercicio 3 - TIR'!$E$13-'Ejercicio 3 - TIR'!$C$13),'Ejercicio 3 - TIR'!$C$13+SQRT(('Ejercicio 3 - TIR'!$E$13-'Ejercicio 3 - TIR'!$C$13)*('Ejercicio 3 - TIR'!$D$13-'Ejercicio 3 - TIR'!$C$13)*B3),'Ejercicio 3 - TIR'!$E$13-SQRT(('Ejercicio 3 - TIR'!$E$13-'Ejercicio 3 - TIR'!$C$13)*('Ejercicio 3 - TIR'!$E$13-'Ejercicio 3 - TIR'!$D$13)*(1-B3))) -> 84442.653 | D3: =RAND() -> 0.51342874 | E3: =IF(D3<=('Ejercicio 3 - TIR'!$D$14-'Ejercicio 3 - TIR'!$C$14)/('Ejercicio 3 - TIR'!$E$14-'Ejercicio 3 - TIR'!$C$14),'Ejercicio 3 - TIR'!$C$14+SQRT(('Ejercicio 3 - TIR'!$E$14-'Ejercicio 3 - TIR'!$C$14)*('Ejercicio 3 - TIR'!$D$14-'Ejercicio 3 - TIR'!$C$14)*D3),'Ejercicio 3 - TIR'!$E$14-SQRT(('Ejercicio 3 - TIR'!$E$14-'Ejercicio 3 - TIR'!$C$14)*('Ejercicio 3 - TIR'!$E$14-'Ejercicio 3 - TIR'!$D$14)*(1-D3))) -> 31456.834 | F3: =RAND() -> 0.50048557 | G3: =IF(F3<=('Ejercicio 3 - TIR'!$D$18-'Ejercicio 3 - TIR'!$C$18)/('Ejercicio 3 - TIR'!$E$18-'Ejercicio 3 - TIR'!$C$18),'Ejercicio 3 - TIR'!$C$18+SQRT(('Ejercicio 3 - TIR'!$E$18-'Ejercicio 3 - TIR'!$C$18)*('Ejercicio 3 - TIR'!$D$18-'Ejercicio 3 - TIR'!$C$18)*F3),'Ejercicio 3 - TIR'!$E$18-SQRT(('Ejercicio 3 - TIR'!$E$18-'Ejercicio 3 - TIR'!$C$18)*('Ejercicio 3 - TIR'!$E$18-'Ejercicio 3 - TIR'!$D$18)*(1-F3))) -> 38664.458 | H3: =RAND() -> 0.26263857 | I3: =IF(H3<=('Ejercicio 3 - TIR'!$D$18-'Ejercicio 3 - TIR'!$C$18)/('Ejercicio 3 - TIR'!$E$18-'Ejercicio 3 - TIR'!$C$18),'Ejercicio 3 - TIR'!$C$18+SQRT(('Ejercicio 3 - TIR'!$E$18-'Ejercicio 3 - TIR'!$C$18)*('Ejercicio 3 - TIR'!$D$18-'Ejercicio 3 - TIR'!$C$18)*H3),'Ejercicio 3 - TIR'!$E$18-SQRT(('Ejercicio 3 - TIR'!$E$18-'Ejercicio 3 - TIR'!$C$18)*('Ejercicio 3 - TIR'!$E$18-'Ejercicio 3 - TIR'!$D$18)*(1-H3))) -> 36276.606 | J3: =RAND() -> 0.97490481 | K3: =IF(J3<=('Ejercicio 3 - TIR'!$D$18-'Ejercicio 3 - TIR'!$C$18)/('Ejercicio 3 - TIR'!$E$18-'Ejercicio 3 - TIR'!$C$18),'Ejercicio 3 - TIR'!$C$18+SQRT(('Ejercicio 3 - TIR'!$E$18-'Ejercicio 3 - TIR'!$C$18)*('Ejercicio 3 - TIR'!$D$18-'Ejercicio 3 - TIR'!$C$18)*J3),'Ejercicio 3 - TIR'!$E$18-SQRT(('Ejercicio 3 - TIR'!$E$18-'Ejercicio 3 - TIR'!$C$18)*('Ejercicio 3 - TIR'!$E$18-'Ejercicio 3 - TIR'!$D$18)*(1-J3))) -> 43628.089 | L3: =RAND() -> 0.51139775 | M3: =IF(L3<=('Ejercicio 3 - TIR'!$D$18-'Ejercicio 3 - TIR'!$C$18)/('Ejercicio 3 - TIR'!$E$18-'Ejercicio 3 - TIR'!$C$18),'Ejercicio 3 - TIR'!$C$18+SQRT(('Ejercicio 3 - TIR'!$E$18-'Ejercicio 3 - TIR'!$C$18)*('Ejercicio 3 - TIR'!$D$18-'Ejercicio 3 - TIR'!$C$18)*L3),'Ejercicio 3 - TIR'!$E$18-SQRT(('Ejercicio 3 - TIR'!$E$18-'Ejercicio 3 - TIR'!$C$18)*('Ejercicio 3 - TIR'!$E$18-'Ejercicio 3 - TIR'!$D$18)*(1-L3))) -> 38758.405 | N3: =RAND() -> 0.99215931 | O3: =IF(N3<=('Ejercicio 3 - TIR'!$D$18-'Ejercicio 3 - TIR'!$C$18)/('Ejercicio 3 - TIR'!$E$18-'Ejercicio 3 - TIR'!$C$18),'Ejercicio 3 - TIR'!$C$18+SQRT(('Ejercicio 3 - TIR'!$E$18-'Ejercicio 3 - TIR'!$C$18)*('Ejercicio 3 - TIR'!$D$18-'Ejercicio 3 - TIR'!$C$18)*N3),'Ejercicio 3 - TIR'!$E$18-SQRT(('Ejercicio 3 - TIR'!$E$18-'Ejercicio 3 - TIR'!$C$18)*('Ejercicio 3 - TIR'!$E$18-'Ejercicio 3 - TIR'!$D$18)*(1-N3))) -> 44233.155 | P3: =RAND() -> 0.9550529 | Q3: =IF(P3<=('Ejercicio 3 - TIR'!$D$22-'Ejercicio 3 - TIR'!$C$22)/('Ejercicio 3 - TIR'!$E$22-'Ejercicio 3 - TIR'!$C$22),'Ejercicio 3 - TIR'!$C$22+SQRT(('Ejercicio 3 - TIR'!$E$22-'Ejercicio 3 - TIR'!$C$22)*('Ejercicio 3 - TIR'!$D$22-'Ejercicio 3 - TIR'!$C$22)*P3),'Ejercicio 3 - TIR'!$E$22-SQRT(('Ejercicio 3 - TIR'!$E$22-'Ejercicio 3 - TIR'!$C$22)*('Ejercicio 3 - TIR'!$E$22-'Ejercicio 3 - TIR'!$D$22)*(1-P3))) -> 0.17100529 | R3: =RAND() -> 0.50818638 | S3: =IF(R3<=('Ejercicio 3 - TIR'!$D$23-'Ejercicio 3 - TIR'!$C$23)/('Ejercicio 3 - TIR'!$E$23-'Ejercicio 3 - TIR'!$C$23),'Ejercicio 3 - TIR'!$C$23+SQRT(('Ejercicio 3 - TIR'!$E$23-'Ejercicio 3 - TIR'!$C$23)*('Ejercicio 3 - TIR'!$D$23-'Ejercicio 3 - TIR'!$C$23)*R3),'Ejercicio 3 - TIR'!$E$23-SQRT(('Ejercicio 3 - TIR'!$E$23-'Ejercicio 3 - TIR'!$C$23)*('Ejercicio 3 - TIR'!$E$23-'Ejercicio 3 - TIR'!$D$23)*(1-R3))) -> 0.15024661 | T3: =RAND() -> 0.068333505 | U3: =IF(T3<=('Ejercicio 3 - TIR'!$D$24-'Ejercicio 3 - TIR'!$C$24)/('Ejercicio 3 - TIR'!$E$24-'Ejercicio 3 - TIR'!$C$24),'Ejercicio 3 - TIR'!$C$24+SQRT(('Ejercicio 3 - TIR'!$E$24-'Ejercicio 3 - TIR'!$C$24)*('Ejercicio 3 - TIR'!$D$24-'Ejercicio 3 - TIR'!$C$24)*T3),'Ejercicio 3 - TIR'!$E$24-SQRT(('Ejercicio 3 - TIR'!$E$24-'Ejercicio 3 - TIR'!$C$24)*('Ejercicio 3 - TIR'!$E$24-'Ejercicio 3 - TIR'!$D$24)*(1-T3))) -> 0.16197916 | V3: =RAND() -> 0.54082263 | W3: =IF(V3<=('Ejercicio 3 - TIR'!$D$25-'Ejercicio 3 - TIR'!$C$25)/('Ejercicio 3 - TIR'!$E$25-'Ejercicio 3 - TIR'!$C$25),'Ejercicio 3 - TIR'!$C$25+SQRT(('Ejercicio 3 - TIR'!$E$25-'Ejercicio 3 - TIR'!$C$25)*('Ejercicio 3 - TIR'!$D$25-'Ejercicio 3 - TIR'!$C$25)*V3),'Ejercicio 3 - TIR'!$E$25-SQRT(('Ejercicio 3 - TIR'!$E$25-'Ejercicio 3 - TIR'!$C$25)*('Ejercicio 3 - TIR'!$E$25-'Ejercicio 3 - TIR'!$D$25)*(1-V3))) -> 0.20991109 | X3: =RAND() -> 0.046361504 | Y3: =IF(X3<=('Ejercicio 3 - TIR'!$D$26-'Ejercicio 3 - TIR'!$C$26)/('Ejercicio 3 - TIR'!$E$26-'Ejercicio 3 - TIR'!$C$26),'Ejercicio 3 - TIR'!$C$26+SQRT(('Ejercicio 3 - TIR'!$E$26-'Ejercicio 3 - TIR'!$C$26)*('Ejercicio 3 - TIR'!$D$26-'Ejercicio 3 - TIR'!$C$26)*X3),'Ejercicio 3 - TIR'!$E$26-SQRT(('Ejercicio 3 - TIR'!$E$26-'Ejercicio 3 - TIR'!$C$26)*('Ejercicio 3 - TIR'!$E$26-'Ejercicio 3 - TIR'!$D$26)*(1-X3))) -> 0.20118821 | Z3: =(1+Q3) -> 1.1710053 | AA3: =Z3*(1+S3) -> 1.3469449 | AB3: =AA3*(1+U3) -> 1.5651219 | AC3: =AB3*(1+W3) -> 1.8936583 | AD3: =AC3*(1+Y3) -> 2.27464 | AE3: =E3*Q3 -> 5379.2851 | AF3: =AE3*(1+S3) -> 6187.5044 | AG3: =AF3*(1+U3) -> 7189.7512 | AH3: =AG3*(1+W3) -> 8698.9596 | AI3: =AH3*(1+Y3) -> 10449.088 | AJ3: =G3*Z3 -> 45276.285 | AK3: =I3*AA3 -> 48862.588 | AL3: =K3*AB3 -> 68283.276 | AM3: =M3*AC3 -> 73395.176 | AN3: =O3*AD3 -> 100614.5 | AO3: =C3/'Ejercicio 3 - TIR'!$D$7 -> 16888.531 | AP3: =AJ3-AO3 -> 28387.754 | AQ3: =AK3-AO3 -> 31974.058 | AR3: =AL3-AO3 -> 51394.745 | AS3: =AM3-AO3 -> 56506.645 | AT3: =AN3-AO3 -> 83725.973 | AU3: =AP3*'Ejercicio 3 - TIR'!$D$5 -> 14193.877 | AV3: =AQ3*'Ejercicio 3 - TIR'!$D$5 -> 15987.029 | AW3: =AR3*'Ejercicio 3 - TIR'!$D$5 -> 25697.373 | AX3: =AS3*'Ejercicio 3 - TIR'!$D$5 -> 28253.323 | AY3: =AT3*'Ejercicio 3 - TIR'!$D$5 -> 41862.987 | AZ3: =AJ3-AU3-AE3 -> 25703.123 | BA3: =AK3-AV3-AF3 -> 26688.055 | BB3: =AL3-AW3-AG3 -> 35396.152 | BC3: =AM3-AX3-AH3 -> 36442.894 | BD3: =AN3-AY3-AI3 -> 48302.429 | BE3: =AZ3/Z3 -> 21949.621 | BF3: =BA3/AA3 -> 19813.77 | BG3: =BB3/AB3 -> 22615.589 | BH3: =BC3/AC3 -> 19244.704 | BI3: =BD3/AD3 -> 21235.197 | BJ3: =E3*AD3 -> 71552.973 | BK3: =0.2*C3*AD3 -> 38415.328 | BL3: =BJ3+BK3 -> 109968.3 | BM3: =BK3*'Ejercicio 3 - TIR'!$D$5 -> 19207.664 | BN3: =BL3-BM3 -> 90760.637 | BO3: =BN3/AD3 -> 39901.099 | BP3: =-(C3+E3) -> -115899.49 | BQ3: =BE3 -> 21949.621 | BR3: =BF3 -> 19813.77 | BS3: =BG3 -> 22615.589 | BT3: =BH3 -> 19244.704 | BU3: =BI3+BO3 -> 61136.296 | BV3: =IFERROR(IRR(BP3:BU3,0.1),NA())*100 -> 6.6308369
A4: 3 | B4: =RAND() -> 0.57055546 | C4: =IF(B4<=('Ejercicio 3 - TIR'!$D$13-'Ejercicio 3 - TIR'!$C$13)/('Ejercicio 3 - TIR'!$E$13-'Ejercicio 3 - TIR'!$C$13),'Ejercicio 3 - TIR'!$C$13+SQRT(('Ejercicio 3 - TIR'!$E$13-'Ejercicio 3 - TIR'!$C$13)*('Ejercicio 3 - TIR'!$D$13-'Ejercicio 3 - TIR'!$C$13)*B4),'Ejercicio 3 - TIR'!$E$13-SQRT(('Ejercicio 3 - TIR'!$E$13-'Ejercicio 3 - TIR'!$C$13)*('Ejercicio 3 - TIR'!$E$13-'Ejercicio 3 - TIR'!$D$13)*(1-B4))) -> 77299.043 | D4: =RAND() -> 0.4011356 | E4: =IF(D4<=('Ejercicio 3 - TIR'!$D$14-'Ejercicio 3 - TIR'!$C$14)/('Ejercicio 3 - TIR'!$E$14-'Ejercicio 3 - TIR'!$C$14),'Ejercicio 3 - TIR'!$C$14+SQRT(('Ejercicio 3 - TIR'!$E$14-'Ejercicio 3 - TIR'!$C$14)*('Ejercicio 3 - TIR'!$D$14-'Ejercicio 3 - TIR'!$C$14)*D4),'Ejercicio 3 - TIR'!$E$14-SQRT(('Ejercicio 3 - TIR'!$E$14-'Ejercicio 3 - TIR'!$C$14)*('Ejercicio 3 - TIR'!$E$14-'Ejercicio 3 - TIR'!$D$14)*(1-D4))) -> 30522.149 | F4: =RAND() -> 0.62274308 | G4: =IF(F4<=('Ejercicio 3 - TIR'!$D$18-'Ejercicio 3 - TIR'!$C$18)/('Ejercicio 3 - TIR'!$E$18-'Ejercicio 3 - TIR'!$C$18),'Ejercicio 3 - TIR'!$C$18+SQRT(('Ejercicio 3 - TIR'!$E$18-'Ejercicio 3 - TIR'!$C$18)*('Ejercicio 3 - TIR'!$D$18-'Ejercicio 3 - TIR'!$C$18)*F4),'Ejercicio 3 - TIR'!$E$18-SQRT(('Ejercicio 3 - TIR'!$E$18-'Ejercicio 3 - TIR'!$C$18)*('Ejercicio 3 - TIR'!$E$18-'Ejercicio 3 - TIR'!$D$18)*(1-F4))) -> 39664.961 | H4: =RAND() -> 0.56507133 | I4: =IF(H4<=('Ejercicio 3 - TIR'!$D$18-'Ejercicio 3 - TIR'!$C$18)/('Ejercicio 3 - TIR'!$E$18-'Ejercicio 3 - TIR'!$C$18),'Ejercicio 3 - TIR'!$C$18+SQRT(('Ejercicio 3 - TIR'!$E$18-'Ejercicio 3 - TIR'!$C$18)*('Ejercicio 3 - TIR'!$D$18-'Ejercicio 3 - TIR'!$C$18)*H4),'Ejercicio 3 - TIR'!$E$18-SQRT(('Ejercicio 3 - TIR'!$E$18-'Ejercicio 3 - TIR'!$C$18)*('Ejercicio 3 - TIR'!$E$18-'Ejercicio 3 - TIR'!$D$18)*(1-H4))) -> 39206.557 | J4: =RAND() -> 0.89923617 | K4: =IF(J4<=('Ejercicio 3 - TIR'!$D$18-'Ejercicio 3 - TIR'!$C$18)/('Ejercicio 3 - TIR'!$E$18-'Ejercicio 3 - TIR'!$C$18),'Ejercicio 3 - TIR'!$C$18+SQRT(('Ejercicio 3 - TIR'!$E$18-'Ejercicio 3 - TIR'!$C$18)*('Ejercicio 3 - TIR'!$D$18-'Ejercicio 3 - TIR'!$C$18)*J4),'Ejercicio 3 - TIR'!$E$18-SQRT(('Ejercicio 3 - TIR'!$E$18-'Ejercicio 3 - TIR'!$C$18)*('Ejercicio 3 - TIR'!$E$18-'Ejercicio 3 - TIR'!$D$18)*(1-J4))) -> 42250.948 | L4: =RAND() -> 0.23184138 | M4: =IF(L4<=('Ejercicio 3 - TIR'!$D$18-'Ejercicio 3 - TIR'!$C$18)/('Ejercicio 3 - TIR'!$E$18-'Ejercicio 3 - TIR'!$C$18),'Ejercicio 3 - TIR'!$C$18+SQRT(('Ejercicio 3 - TIR'!$E$18-'Ejercicio 3 - TIR'!$C$18)*('Ejercicio 3 - TIR'!$D$18-'Ejercicio 3 - TIR'!$C$18)*L4),'Ejercicio 3 - TIR'!$E$18-SQRT(('Ejercicio 3 - TIR'!$E$18-'Ejercicio 3 - TIR'!$C$18)*('Ejercicio 3 - TIR'!$E$18-'Ejercicio 3 - TIR'!$D$18)*(1-L4))) -> 35897.135 | N4: =RAND() -> 0.41248435 | O4: =IF(N4<=('Ejercicio 3 - TIR'!$D$18-'Ejercicio 3 - TIR'!$C$18)/('Ejercicio 3 - TIR'!$E$18-'Ejercicio 3 - TIR'!$C$18),'Ejercicio 3 - TIR'!$C$18+SQRT(('Ejercicio 3 - TIR'!$E$18-'Ejercicio 3 - TIR'!$C$18)*('Ejercicio 3 - TIR'!$D$18-'Ejercicio 3 - TIR'!$C$18)*N4),'Ejercicio 3 - TIR'!$E$18-SQRT(('Ejercicio 3 - TIR'!$E$18-'Ejercicio 3 - TIR'!$C$18)*('Ejercicio 3 - TIR'!$E$18-'Ejercicio 3 - TIR'!$D$18)*(1-N4))) -> 37865.917 | P4: =RAND() -> 0.62892038 | Q4: =IF(P4<=('Ejercicio 3 - TIR'!$D$22-'Ejercicio 3 - TIR'!$C$22)/('Ejercicio 3 - TIR'!$E$22-'Ejercicio 3 - TIR'!$C$22),'Ejercicio 3 - TIR'!$C$22+SQRT(('Ejercicio 3 - TIR'!$E$22-'Ejercicio 3 - TIR'!$C$22)*('Ejercicio 3 - TIR'!$D$22-'Ejercicio 3 - TIR'!$C$22)*P4),'Ejercicio 3 - TIR'!$E$22-SQRT(('Ejercicio 3 - TIR'!$E$22-'Ejercicio 3 - TIR'!$C$22)*('Ejercicio 3 - TIR'!$E$22-'Ejercicio 3 - TIR'!$D$22)*(1-P4))) -> 0.1541554 | R4: =RAND() -> 0.61410445 | S4: =IF(R4<=('Ejercicio 3 - TIR'!$D$23-'Ejercicio 3 - TIR'!$C$23)/('Ejercicio 3 - TIR'!$E$23-'Ejercicio 3 - TIR'!$C$23),'Ejercicio 3 - TIR'!$C$23+SQRT(('Ejercicio 3 - TIR'!$E$23-'Ejercicio 3 - TIR'!$C$23)*('Ejercicio 3 - TIR'!$D$23-'Ejercicio 3 - TIR'!$C$23)*R4),'Ejercicio 3 - TIR'!$E$23-SQRT(('Ejercicio 3 - TIR'!$E$23-'Ejercicio 3 - TIR'!$C$23)*('Ejercicio 3 - TIR'!$E$23-'Ejercicio 3 - TIR'!$D$23)*(1-R4))) -> 0.15364451 | T4: =RAND() -> 0.53932903 | U4: =IF(T4<=('Ejercicio 3 - TIR'!$D$24-'Ejercicio 3 - TIR'!$C$24)/('Ejercicio 3 - TIR'!$E$24-'Ejercicio 3 - TIR'!$C$24),'Ejercicio 3 - TIR'!$C$24+SQRT(('Ejercicio 3 - TIR'!$E$24-'Ejercicio 3 - TIR'!$C$24)*('Ejercicio 3 - TIR'!$D$24-'Ejercicio 3 - TIR'!$C$24)*T4),'Ejercicio 3 - TIR'!$E$24-SQRT(('Ejercicio 3 - TIR'!$E$24-'Ejercicio 3 - TIR'!$C$24)*('Ejercicio 3 - TIR'!$E$24-'Ejercicio 3 - TIR'!$D$24)*(1-T4))) -> 0.18408512 | V4: =RAND() -> 0.41767713 | W4: =IF(V4<=('Ejercicio 3 - TIR'!$D$25-'Ejercicio 3 - TIR'!$C$25)/('Ejercicio 3 - TIR'!$E$25-'Ejercicio 3 - TIR'!$C$25),'Ejercicio 3 - TIR'!$C$25+SQRT(('Ejercicio 3 - TIR'!$E$25-'Ejercicio 3 - TIR'!$C$25)*('Ejercicio 3 - TIR'!$D$25-'Ejercicio 3 - TIR'!$C$25)*V4),'Ejercicio 3 - TIR'!$E$25-SQRT(('Ejercicio 3 - TIR'!$E$25-'Ejercicio 3 - TIR'!$C$25)*('Ejercicio 3 - TIR'!$E$25-'Ejercicio 3 - TIR'!$D$25)*(1-V4))) -> 0.20485435 | X4: =RAND() -> 0.092008793 | Y4: =IF(X4<=('Ejercicio 3 - TIR'!$D$26-'Ejercicio 3 - TIR'!$C$26)/('Ejercicio 3 - TIR'!$E$26-'Ejercicio 3 - TIR'!$C$26),'Ejercicio 3 - TIR'!$C$26+SQRT(('Ejercicio 3 - TIR'!$E$26-'Ejercicio 3 - TIR'!$C$26)*('Ejercicio 3 - TIR'!$D$26-'Ejercicio 3 - TIR'!$C$26)*X4),'Ejercicio 3 - TIR'!$E$26-SQRT(('Ejercicio 3 - TIR'!$E$26-'Ejercicio 3 - TIR'!$C$26)*('Ejercicio 3 - TIR'!$E$26-'Ejercicio 3 - TIR'!$D$26)*(1-X4))) -> 0.20576146 | Z4: =(1+Q4) -> 1.1541554 | AA4: =Z4*(1+S4) -> 1.331485 | AB4: =AA4*(1+U4) -> 1.5765916 | AC4: =AB4*(1+W4) -> 1.8995633 | AD4: =AC4*(1+Y4) -> 2.2904202 | AE4: =E4*Q4 -> 4705.1541 | AF4: =AE4*(1+S4) -> 5428.0752 | AG4: =AF4*(1+U4) -> 6427.3031 | AH4: =AG4*(1+W4) -> 7743.964 | AI4: =AH4*(1+Y4) -> 9337.3734 | AJ4: =G4*Z4 -> 45779.528 | AK4: =I4*AA4 -> 52202.945 | AL4: =K4*AB4 -> 66612.491 | AM4: =M4*AC4 -> 68188.88 | AN4: =O4*AD4 -> 86728.861 | AO4: =C4/'Ejercicio 3 - TIR'!$D$7 -> 15459.809 | AP4: =AJ4-AO4 -> 30319.72 | AQ4: =AK4-AO4 -> 36743.136 | AR4: =AL4-AO4 -> 51152.682 | AS4: =AM4-AO4 -> 52729.071 | AT4: =AN4-AO4 -> 71269.052 | AU4: =AP4*'Ejercicio 3 - TIR'!$D$5 -> 15159.86 | AV4: =AQ4*'Ejercicio 3 - TIR'!$D$5 -> 18371.568 | AW4: =AR4*'Ejercicio 3 - TIR'!$D$5 -> 25576.341 | AX4: =AS4*'Ejercicio 3 - TIR'!$D$5 -> 26364.536 | AY4: =AT4*'Ejercicio 3 - TIR'!$D$5 -> 35634.526 | AZ4: =AJ4-AU4-AE4 -> 25914.514 | BA4: =AK4-AV4-AF4 -> 28403.301 | BB4: =AL4-AW4-AG4 -> 34608.847 | BC4: =AM4-AX4-AH4 -> 34080.38 | BD4: =AN4-AY4-AI4 -> 41756.961 | BE4: =AZ4/Z4 -> 22453.228 | BF4: =BA4/AA4 -> 21332.047 | BG4: =BB4/AB4 -> 21951.687 | BH4: =BC4/AC4 -> 17941.166 | BI4: =BD4/AD4 -> 18231.136 | BJ4: =E4*AD4 -> 69908.546 | BK4: =0.2*C4*AD4 -> 35409.458 | BL4: =BJ4+BK4 -> 105318 | BM4: =BK4*'Ejercicio 3 - TIR'!$D$5 -> 17704.729 | BN4: =BL4-BM4 -> 87613.275 | BO4: =BN4/AD4 -> 38252.053 | BP4: =-(C4+E4) -> -107821.19 | BQ4: =BE4 -> 22453.228 | BR4: =BF4 -> 21332.047 | BS4: =BG4 -> 21951.687 | BT4: =BH4 -> 17941.166 | BU4: =BI4+BO4 -> 56483.189 | BV4: =IFERROR(IRR(BP4:BU4,0.1),NA())*100 -> 8.0953527
A5: 4 | B5: =RAND() -> 0.3502263 | C5: =IF(B5<=('Ejercicio 3 - TIR'!$D$13-'Ejercicio 3 - TIR'!$C$13)/('Ejercicio 3 - TIR'!$E$13-'Ejercicio 3 - TIR'!$C$13),'Ejercicio 3 - TIR'!$C$13+SQRT(('Ejercicio 3 - TIR'!$E$13-'Ejercicio 3 - TIR'!$C$13)*('Ejercicio 3 - TIR'!$D$13-'Ejercicio 3 - TIR'!$C$13)*B5),'Ejercicio 3 - TIR'!$E$13-SQRT(('Ejercicio 3 - TIR'!$E$13-'Ejercicio 3 - TIR'!$C$13)*('Ejercicio 3 - TIR'!$E$13-'Ejercicio 3 - TIR'!$D$13)*(1-B5))) -> 72076.382 | D5: =RAND() -> 0.89972942 | E5: =IF(D5<=('Ejercicio 3 - TIR'!$D$14-'Ejercicio 3 - TIR'!$C$14)/('Ejercicio 3 - TIR'!$E$14-'Ejercicio 3 - TIR'!$C$14),'Ejercicio 3 - TIR'!$C$14+SQRT(('Ejercicio 3 - TIR'!$E$14-'Ejercicio 3 - TIR'!$C$14)*('Ejercicio 3 - TIR'!$D$14-'Ejercicio 3 - TIR'!$C$14)*D5),'Ejercicio 3 - TIR'!$E$14-SQRT(('Ejercicio 3 - TIR'!$E$14-'Ejercicio 3 - TIR'!$C$14)*('Ejercicio 3 - TIR'!$E$14-'Ejercicio 3 - TIR'!$D$14)*(1-D5))) -> 36121.78 | F5: =RAND() -> 0.098215042 | G5: =IF(F5<=('Ejercicio 3 - TIR'!$D$18-'Ejercicio 3 - TIR'!$C$18)/('Ejercicio 3 - TIR'!$E$18-'Ejercicio 3 - TIR'!$C$18),'Ejercicio 3 - TIR'!$C$18+SQRT(('Ejercicio 3 - TIR'!$E$18-'Ejercicio 3 - TIR'!$C$18)*('Ejercicio 3 - TIR'!$D$18-'Ejercicio 3 - TIR'!$C$18)*F5),'Ejercicio 3 - TIR'!$E$18-SQRT(('Ejercicio 3 - TIR'!$E$18-'Ejercicio 3 - TIR'!$C$18)*('Ejercicio 3 - TIR'!$E$18-'Ejercicio 3 - TIR'!$D$18)*(1-F5))) -> 33838.262 | H5: =RAND() -> 0.53625286 | I5: =IF(H5<=('Ejercicio 3 - TIR'!$D$18-'Ejercicio 3 - TIR'!$C$18)/('Ejercicio 3 - TIR'!$E$18-'Ejercicio 3 - TIR'!$C$18),'Ejercicio 3 - TIR'!$C$18+SQRT(('Ejercicio 3 - TIR'!$E$18-'Ejercicio 3 - TIR'!$C$18)*('Ejercicio 3 - TIR'!$D$18-'Ejercicio 3 - TIR'!$C$18)*H5),'Ejercicio 3 - TIR'!$E$18-SQRT(('Ejercicio 3 - TIR'!$E$18-'Ejercicio 3 - TIR'!$C$18)*('Ejercicio 3 - TIR'!$E$18-'Ejercicio 3 - TIR'!$D$18)*(1-H5))) -> 38968.719 | J5: =RAND() -> 0.28868354 | K5: =IF(J5<=('Ejercicio 3 - TIR'!$D$18-'Ejercicio 3 - TIR'!$C$18)/('Ejercicio 3 - TIR'!$E$18-'Ejercicio 3 - TIR'!$C$18),'Ejercicio 3 - TIR'!$C$18+SQRT(('Ejercicio 3 - TIR'!$E$18-'Ejercicio 3 - TIR'!$C$18)*('Ejercicio 3 - TIR'!$D$18-'Ejercicio 3 - TIR'!$C$18)*J5),'Ejercicio 3 - TIR'!$E$18-SQRT(('Ejercicio 3 - TIR'!$E$18-'Ejercicio 3 - TIR'!$C$18)*('Ejercicio 3 - TIR'!$E$18-'Ejercicio 3 - TIR'!$D$18)*(1-J5))) -> 36580.466 | L5: =RAND() -> 0.099619092 | M5: =IF(L5<=('Ejercicio 3 - TIR'!$D$18-'Ejercicio 3 - TIR'!$C$18)/('Ejercicio 3 - TIR'!$E$18-'Ejercicio 3 - TIR'!$C$18),'Ejercicio 3 - TIR'!$C$18+SQRT(('Ejercicio 3 - TIR'!$E$18-'Ejercicio 3 - TIR'!$C$18)*('Ejercicio 3 - TIR'!$D$18-'Ejercicio 3 - TIR'!$C$18)*L5),'Ejercicio 3 - TIR'!$E$18-SQRT(('Ejercicio 3 - TIR'!$E$18-'Ejercicio 3 - TIR'!$C$18)*('Ejercicio 3 - TIR'!$E$18-'Ejercicio 3 - TIR'!$D$18)*(1-L5))) -> 33865.6 | N5: =RAND() -> 0.88488717 | O5: =IF(N5<=('Ejercicio 3 - TIR'!$D$18-'Ejercicio 3 - TIR'!$C$18)/('Ejercicio 3 - TIR'!$E$18-'Ejercicio 3 - TIR'!$C$18),'Ejercicio 3 - TIR'!$C$18+SQRT(('Ejercicio 3 - TIR'!$E$18-'Ejercicio 3 - TIR'!$C$18)*('Ejercicio 3 - TIR'!$D$18-'Ejercicio 3 - TIR'!$C$18)*N5),'Ejercicio 3 - TIR'!$E$18-SQRT(('Ejercicio 3 - TIR'!$E$18-'Ejercicio 3 - TIR'!$C$18)*('Ejercicio 3 - TIR'!$E$18-'Ejercicio 3 - TIR'!$D$18)*(1-N5))) -> 42061.725 | P5: =RAND() -> 0.34488789 | Q5: =IF(P5<=('Ejercicio 3 - TIR'!$D$22-'Ejercicio 3 - TIR'!$C$22)/('Ejercicio 3 - TIR'!$E$22-'Ejercicio 3 - TIR'!$C$22),'Ejercicio 3 - TIR'!$C$22+SQRT(('Ejercicio 3 - TIR'!$E$22-'Ejercicio 3 - TIR'!$C$22)*('Ejercicio 3 - TIR'!$D$22-'Ejercicio 3 - TIR'!$C$22)*P5),'Ejercicio 3 - TIR'!$E$22-SQRT(('Ejercicio 3 - TIR'!$E$22-'Ejercicio 3 - TIR'!$C$22)*('Ejercicio 3 - TIR'!$E$22-'Ejercicio 3 - TIR'!$D$22)*(1-P5))) -> 0.14491582 | R5: =RAND() -> 0.73083214 | S5: =IF(R5<=('Ejercicio 3 - TIR'!$D$23-'Ejercicio 3 - TIR'!$C$23)/('Ejercicio 3 - TIR'!$E$23-'Ejercicio 3 - TIR'!$C$23),'Ejercicio 3 - TIR'!$C$23+SQRT(('Ejercicio 3 - TIR'!$E$23-'Ejercicio 3 - TIR'!$C$23)*('Ejercicio 3 - TIR'!$D$23-'Ejercicio 3 - TIR'!$C$23)*R5),'Ejercicio 3 - TIR'!$E$23-SQRT(('Ejercicio 3 - TIR'!$E$23-'Ejercicio 3 - TIR'!$C$23)*('Ejercicio 3 - TIR'!$E$23-'Ejercicio 3 - TIR'!$D$23)*(1-R5))) -> 0.15798859 | T5: =RAND() -> 0.057329767 | U5: =IF(T5<=('Ejercicio 3 - TIR'!$D$24-'Ejercicio 3 - TIR'!$C$24)/('Ejercicio 3 - TIR'!$E$24-'Ejercicio 3 - TIR'!$C$24),'Ejercicio 3 - TIR'!$C$24+SQRT(('Ejercicio 3 - TIR'!$E$24-'Ejercicio 3 - TIR'!$C$24)*('Ejercicio 3 - TIR'!$D$24-'Ejercicio 3 - TIR'!$C$24)*T5),'Ejercicio 3 - TIR'!$E$24-SQRT(('Ejercicio 3 - TIR'!$E$24-'Ejercicio 3 - TIR'!$C$24)*('Ejercicio 3 - TIR'!$E$24-'Ejercicio 3 - TIR'!$D$24)*(1-T5))) -> 0.16097235 | V5: =RAND() -> 0.30429683 | W5: =IF(V5<=('Ejercicio 3 - TIR'!$D$25-'Ejercicio 3 - TIR'!$C$25)/('Ejercicio 3 - TIR'!$E$25-'Ejercicio 3 - TIR'!$C$25),'Ejercicio 3 - TIR'!$C$25+SQRT(('Ejercicio 3 - TIR'!$E$25-'Ejercicio 3 - TIR'!$C$25)*('Ejercicio 3 - TIR'!$D$25-'Ejercicio 3 - TIR'!$C$25)*V5),'Ejercicio 3 - TIR'!$E$25-SQRT(('Ejercicio 3 - TIR'!$E$25-'Ejercicio 3 - TIR'!$C$25)*('Ejercicio 3 - TIR'!$E$25-'Ejercicio 3 - TIR'!$D$25)*(1-V5))) -> 0.20065467 | X5: =RAND() -> 0.40115031 | Y5: =IF(X5<=('Ejercicio 3 - TIR'!$D$26-'Ejercicio 3 - TIR'!$C$26)/('Ejercicio 3 - TIR'!$E$26-'Ejercicio 3 - TIR'!$C$26),'Ejercicio 3 - TIR'!$C$26+SQRT(('Ejercicio 3 - TIR'!$E$26-'Ejercicio 3 - TIR'!$C$26)*('Ejercicio 3 - TIR'!$D$26-'Ejercicio 3 - TIR'!$C$26)*X5),'Ejercicio 3 - TIR'!$E$26-SQRT(('Ejercicio 3 - TIR'!$E$26-'Ejercicio 3 - TIR'!$C$26)*('Ejercicio 3 - TIR'!$E$26-'Ejercicio 3 - TIR'!$D$26)*(1-X5))) -> 0.22313359 | Z5: =(1+Q5) -> 1.1449158 | AA5: =Z5*(1+S5) -> 1.3257995 | AB5: =AA5*(1+U5) -> 1.5392165 | AC5: =AB5*(1+W5) -> 1.8480675 | AD5: =AC5*(1+Y5) -> 2.2604334 | AE5: =E5*Q5 -> 5234.6175 | AF5: =AE5*(1+S5) -> 6061.6274 | AG5: =AF5*(1+U5) -> 7037.3818 | AH5: =AG5*(1+W5) -> 8449.4653 | AI5: =AH5*(1+Y5) -> 10334.825 | AJ5: =G5*Z5 -> 38741.962 | AK5: =I5*AA5 -> 51664.707 | AL5: =K5*AB5 -> 56305.257 | AM5: =M5*AC5 -> 62585.915 | AN5: =O5*AD5 -> 95077.729 | AO5: =C5/'Ejercicio 3 - TIR'!$D$7 -> 14415.276 | AP5: =AJ5-AO5 -> 24326.685 | AQ5: =AK5-AO5 -> 37249.431 | AR5: =AL5-AO5 -> 41889.981 | AS5: =AM5-AO5 -> 48170.639 | AT5: =AN5-AO5 -> 80662.453 | AU5: =AP5*'Ejercicio 3 - TIR'!$D$5 -> 12163.343 | AV5: =AQ5*'Ejercicio 3 - TIR'!$D$5 -> 18624.715 | AW5: =AR5*'Ejercicio 3 - TIR'!$D$5 -> 20944.99 | AX5: =AS5*'Ejercicio 3 - TIR'!$D$5 -> 24085.319 | AY5: =AT5*'Ejercicio 3 - TIR'!$D$5 -> 40331.226 | AZ5: =AJ5-AU5-AE5 -> 21344.002 | BA5: =AK5-AV5-AF5 -> 26978.364 | BB5: =AL5-AW5-AG5 -> 28322.885 | BC5: =AM5-AX5-AH5 -> 30051.13 | BD5: =AN5-AY5-AI5 -> 44411.678 | BE5: =AZ5/Z5 -> 18642.42 | BF5: =BA5/AA5 -> 20348.752 | BG5: =BB5/AB5 -> 18400.845 | BH5: =BC5/AC5 -> 16260.84 | BI5: =BD5/AD5 -> 19647.417 | BJ5: =E5*AD5 -> 81650.881 | BK5: =0.2*C5*AD5 -> 32584.773 | BL5: =BJ5+BK5 -> 114235.65 | BM5: =BK5*'Ejercicio 3 - TIR'!$D$5 -> 16292.386 | BN5: =BL5-BM5 -> 97943.267 | BO5: =BN5/AD5 -> 43329.419 | BP5: =-(C5+E5) -> -108198.16 | BQ5: =BE5 -> 18642.42 | BR5: =BF5 -> 20348.752 | BS5: =BG5 -> 18400.845 | BT5: =BH5 -> 16260.84 | BU5: =BI5+BO5 -> 62976.835 | BV5: =IFERROR(IRR(BP5:BU5,0.1),NA())*100 -> 6.8069886
A6: 5 | B6: =RAND() -> 0.34982436 | C6: =IF(B6<=('Ejercicio 3 - TIR'!$D$13-'Ejercicio 3 - TIR'!$C$13)/('Ejercicio 3 - TIR'!$E$13-'Ejercicio 3 - TIR'!$C$13),'Ejercicio 3 - TIR'!$C$13+SQRT(('Ejercicio 3 - TIR'!$E$13-'Ejercicio 3 - TIR'!$C$13)*('Ejercicio 3 - TIR'!$D$13-'Ejercicio 3 - TIR'!$C$13)*B6),'Ejercicio 3 - TIR'!$E$13-SQRT(('Ejercicio 3 - TIR'!$E$13-'Ejercicio 3 - TIR'!$C$13)*('Ejercicio 3 - TIR'!$E$13-'Ejercicio 3 - TIR'!$D$13)*(1-B6))) -> 72067.747 | D6: =RAND() -> 0.99969213 | E6: =IF(D6<=('Ejercicio 3 - TIR'!$D$14-'Ejercicio 3 - TIR'!$C$14)/('Ejercicio 3 - TIR'!$E$14-'Ejercicio 3 - TIR'!$C$14),'Ejercicio 3 - TIR'!$C$14+SQRT(('Ejercicio 3 - TIR'!$E$14-'Ejercicio 3 - TIR'!$C$14)*('Ejercicio 3 - TIR'!$D$14-'Ejercicio 3 - TIR'!$C$14)*D6),'Ejercicio 3 - TIR'!$E$14-SQRT(('Ejercicio 3 - TIR'!$E$14-'Ejercicio 3 - TIR'!$C$14)*('Ejercicio 3 - TIR'!$E$14-'Ejercicio 3 - TIR'!$D$14)*(1-D6))) -> 39785.104 | F6: =RAND() -> 0.57028463 | G6: =IF(F6<=('Ejercicio 3 - TIR'!$D$18-'Ejercicio 3 - TIR'!$C$18)/('Ejercicio 3 - TIR'!$E$18-'Ejercicio 3 - TIR'!$C$18),'Ejercicio 3 - TIR'!$C$18+SQRT(('Ejercicio 3 - TIR'!$E$18-'Ejercicio 3 - TIR'!$C$18)*('Ejercicio 3 - TIR'!$D$18-'Ejercicio 3 - TIR'!$C$18)*F6),'Ejercicio 3 - TIR'!$E$18-SQRT(('Ejercicio 3 - TIR'!$E$18-'Ejercicio 3 - TIR'!$C$18)*('Ejercicio 3 - TIR'!$E$18-'Ejercicio 3 - TIR'!$D$18)*(1-F6))) -> 39248.929 | H6: =RAND() -> 0.7194127 | I6: =IF(H6<=('Ejercicio 3 - TIR'!$D$18-'Ejercicio 3 - TIR'!$C$18)/('Ejercicio 3 - TIR'!$E$18-'Ejercicio 3 - TIR'!$C$18),'Ejercicio 3 - TIR'!$C$18+SQRT(('Ejercicio 3 - TIR'!$E$18-'Ejercicio 3 - TIR'!$C$18)*('Ejercicio 3 - TIR'!$D$18-'Ejercicio 3 - TIR'!$C$18)*H6),'Ejercicio 3 - TIR'!$E$18-SQRT(('Ejercicio 3 - TIR'!$E$18-'Ejercicio 3 - TIR'!$C$18)*('Ejercicio 3 - TIR'!$E$18-'Ejercicio 3 - TIR'!$D$18)*(1-H6))) -> 40412.621 | J6: =RAND() -> 0.030706232 | K6: =IF(J6<=('Ejercicio 3 - TIR'!$D$18-'Ejercicio 3 - TIR'!$C$18)/('Ejercicio 3 - TIR'!$E$18-'Ejercicio 3 - TIR'!$C$18),'Ejercicio 3 - TIR'!$C$18+SQRT(('Ejercicio 3 - TIR'!$E$18-'Ejercicio 3 - TIR'!$C$18)*('Ejercicio 3 - TIR'!$D$18-'Ejercicio 3 - TIR'!$C$18)*J6),'Ejercicio 3 - TIR'!$E$18-SQRT(('Ejercicio 3 - TIR'!$E$18-'Ejercicio 3 - TIR'!$C$18)*('Ejercicio 3 - TIR'!$E$18-'Ejercicio 3 - TIR'!$D$18)*(1-J6))) -> 32146.144 | L6: =RAND() -> 0.039732221 | M6: =IF(L6<=('Ejercicio 3 - TIR'!$D$18-'Ejercicio 3 - TIR'!$C$18)/('Ejercicio 3 - TIR'!$E$18-'Ejercicio 3 - TIR'!$C$18),'Ejercicio 3 - TIR'!$C$18+SQRT(('Ejercicio 3 - TIR'!$E$18-'Ejercicio 3 - TIR'!$C$18)*('Ejercicio 3 - TIR'!$D$18-'Ejercicio 3 - TIR'!$C$18)*L6),'Ejercicio 3 - TIR'!$E$18-SQRT(('Ejercicio 3 - TIR'!$E$18-'Ejercicio 3 - TIR'!$C$18)*('Ejercicio 3 - TIR'!$E$18-'Ejercicio 3 - TIR'!$D$18)*(1-L6))) -> 32441.277 | N6: =RAND() -> 0.24796723 | O6: =IF(N6<=('Ejercicio 3 - TIR'!$D$18-'Ejercicio 3 - TIR'!$C$18)/('Ejercicio 3 - TIR'!$E$18-'Ejercicio 3 - TIR'!$C$18),'Ejercicio 3 - TIR'!$C$18+SQRT(('Ejercicio 3 - TIR'!$E$18-'Ejercicio 3 - TIR'!$C$18)*('Ejercicio 3 - TIR'!$D$18-'Ejercicio 3 - TIR'!$C$18)*N6),'Ejercicio 3 - TIR'!$E$18-SQRT(('Ejercicio 3 - TIR'!$E$18-'Ejercicio 3 - TIR'!$C$18)*('Ejercicio 3 - TIR'!$E$18-'Ejercicio 3 - TIR'!$D$18)*(1-N6))) -> 36098.777 | P6: =RAND() -> 0.38634233 | Q6: =IF(P6<=('Ejercicio 3 - TIR'!$D$22-'Ejercicio 3 - TIR'!$C$22)/('Ejercicio 3 - TIR'!$E$22-'Ejercicio 3 - TIR'!$C$22),'Ejercicio 3 - TIR'!$C$22+SQRT(('Ejercicio 3 - TIR'!$E$22-'Ejercicio 3 - TIR'!$C$22)*('Ejercicio 3 - TIR'!$D$22-'Ejercicio 3 - TIR'!$C$22)*P6),'Ejercicio 3 - TIR'!$E$22-SQRT(('Ejercicio 3 - TIR'!$E$22-'Ejercicio 3 - TIR'!$C$22)*('Ejercicio 3 - TIR'!$E$22-'Ejercicio 3 - TIR'!$D$22)*(1-P6))) -> 0.14637074 | R6: =RAND() -> 0.44007963 | S6: =IF(R6<=('Ejercicio 3 - TIR'!$D$23-'Ejercicio 3 - TIR'!$C$23)/('Ejercicio 3 - TIR'!$E$23-'Ejercicio 3 - TIR'!$C$23),'Ejercicio 3 - TIR'!$C$23+SQRT(('Ejercicio 3 - TIR'!$E$23-'Ejercicio 3 - TIR'!$C$23)*('Ejercicio 3 - TIR'!$D$23-'Ejercicio 3 - TIR'!$C$23)*R6),'Ejercicio 3 - TIR'!$E$23-SQRT(('Ejercicio 3 - TIR'!$E$23-'Ejercicio 3 - TIR'!$C$23)*('Ejercicio 3 - TIR'!$E$23-'Ejercicio 3 - TIR'!$D$23)*(1-R6))) -> 0.14814504 | T6: =RAND() -> 0.1965392 | U6: =IF(T6<=('Ejercicio 3 - TIR'!$D$24-'Ejercicio 3 - TIR'!$C$24)/('Ejercicio 3 - TIR'!$E$24-'Ejercicio 3 - TIR'!$C$24),'Ejercicio 3 - TIR'!$C$24+SQRT(('Ejercicio 3 - TIR'!$E$24-'Ejercicio 3 - TIR'!$C$24)*('Ejercicio 3 - TIR'!$D$24-'Ejercicio 3 - TIR'!$C$24)*T6),'Ejercicio 3 - TIR'!$E$24-SQRT(('Ejercicio 3 - TIR'!$E$24-'Ejercicio 3 - TIR'!$C$24)*('Ejercicio 3 - TIR'!$E$24-'Ejercicio 3 - TIR'!$D$24)*(1-T6))) -> 0.17031581 | V6: =RAND() -> 0.32779464 | W6: =IF(V6<=('Ejercicio 3 - TIR'!$D$25-'Ejercicio 3 - TIR'!$C$25)/('Ejercicio 3 - TIR'!$E$25-'Ejercicio 3 - TIR'!$C$25),'Ejercicio 3 - TIR'!$C$25+SQRT(('Ejercicio 3 - TIR'!$E$25-'Ejercicio 3 - TIR'!$C$25)*('Ejercicio 3 - TIR'!$D$25-'Ejercicio 3 - TIR'!$C$25)*V6),'Ejercicio 3 - TIR'!$E$25-SQRT(('Ejercicio 3 - TIR'!$E$25-'Ejercicio 3 - TIR'!$C$25)*('Ejercicio 3 - TIR'!$E$25-'Ejercicio 3 - TIR'!$D$25)*(1-V6))) -> 0.20149517 | X6: =RAND() -> 0.2696569 | Y6: =IF(X6<=('Ejercicio 3 - TIR'!$D$26-'Ejercicio 3 - TIR'!$C$26)/('Ejercicio 3 - TIR'!$E$26-'Ejercicio 3 - TIR'!$C$26),'Ejercicio 3 - TIR'!$C$26+SQRT(('Ejercicio 3 - TIR'!$E$26-'Ejercicio 3 - TIR'!$C$26)*('Ejercicio 3 - TIR'!$D$26-'Ejercicio 3 - TIR'!$C$26)*X6),'Ejercicio 3 - TIR'!$E$26-SQRT(('Ejercicio 3 - TIR'!$E$26-'Ejercicio 3 - TIR'!$C$26)*('Ejercicio 3 - TIR'!$E$26-'Ejercicio 3 - TIR'!$D$26)*(1-X6))) -> 0.21698284 | Z6: =(1+Q6) -> 1.1463707 | AA6: =Z6*(1+S6) -> 1.3161999 | AB6: =AA6*(1+U6) -> 1.5403695 | AC6: =AB6*(1+W6) -> 1.8507466 | AD6: =AC6*(1+Y6) -> 2.2523268 | AE6: =E6*Q6 -> 5823.3753 | AF6: =AE6*(1+S6) -> 6686.0794 | AG6: =AF6*(1+U6) -> 7824.8245 | AH6: =AG6*(1+W6) -> 9401.4888 | AI6: =AH6*(1+Y6) -> 11441.451 | AJ6: =G6*Z6 -> 44993.824 | AK6: =I6*AA6 -> 53191.087 | AL6: =K6*AB6 -> 49516.941 | AM6: =M6*AC6 -> 60040.582 | AN6: =O6*AD6 -> 81306.244 | AO6: =C6/'Ejercicio 3 - TIR'!$D$7 -> 14413.549 | AP6: =AJ6-AO6 -> 30580.275 | AQ6: =AK6-AO6 -> 38777.538 | AR6: =AL6-AO6 -> 35103.392 | AS6: =AM6-AO6 -> 45627.032 | AT6: =AN6-AO6 -> 66892.694 | AU6: =AP6*'Ejercicio 3 - TIR'!$D$5 -> 15290.138 | AV6: =AQ6*'Ejercicio 3 - TIR'!$D$5 -> 19388.769 | AW6: =AR6*'Ejercicio 3 - TIR'!$D$5 -> 17551.696 | AX6: =AS6*'Ejercicio 3 - TIR'!$D$5 -> 22813.516 | AY6: =AT6*'Ejercicio 3 - TIR'!$D$5 -> 33446.347 | AZ6: =AJ6-AU6-AE6 -> 23880.312 | BA6: =AK6-AV6-AF6 -> 27116.239 | BB6: =AL6-AW6-AG6 -> 24140.421 | BC6: =AM6-AX6-AH6 -> 27825.577 | BD6: =AN6-AY6-AI6 -> 36418.446 | BE6: =AZ6/Z6 -> 20831.229 | BF6: =BA6/AA6 -> 20601.915 | BG6: =BB6/AB6 -> 15671.837 | BH6: =BC6/AC6 -> 15034.785 | BI6: =BD6/AD6 -> 16169.255 | BJ6: =E6*AD6 -> 89609.056 | BK6: =0.2*C6*AD6 -> 32464.024 | BL6: =BJ6+BK6 -> 122073.08 | BM6: =BK6*'Ejercicio 3 - TIR'!$D$5 -> 16232.012 | BN6: =BL6-BM6 -> 105841.07 | BO6: =BN6/AD6 -> 46991.878 | BP6: =-(C6+E6) -> -111852.85 | BQ6: =BE6 -> 20831.229 | BR6: =BF6 -> 20601.915 | BS6: =BG6 -> 15671.837 | BT6: =BH6 -> 15034.785 | BU6: =BI6+BO6 -> 63161.133 | BV6: =IFERROR(IRR(BP6:BU6,0.1),NA())*100 -> 5.5577863
A7: 6 | B7: =RAND() -> 0.14848031 | C7: =IF(B7<=('Ejercicio 3 - TIR'!$D$13-'Ejercicio 3 - TIR'!$C$13)/('Ejercicio 3 - TIR'!$E$13-'Ejercicio 3 - TIR'!$C$13),'Ejercicio 3 - TIR'!$C$13+SQRT(('Ejercicio 3 - TIR'!$E$13-'Ejercicio 3 - TIR'!$C$13)*('Ejercicio 3 - TIR'!$D$13-'Ejercicio 3 - TIR'!$C$13)*B7),'Ejercicio 3 - TIR'!$E$13-SQRT(('Ejercicio 3 - TIR'!$E$13-'Ejercicio 3 - TIR'!$C$13)*('Ejercicio 3 - TIR'!$E$13-'Ejercicio 3 - TIR'!$D$13)*(1-B7))) -> 67706.629 | D7: =RAND() -> 0.9749385 | E7: =IF(D7<=('Ejercicio 3 - TIR'!$D$14-'Ejercicio 3 - TIR'!$C$14)/('Ejercicio 3 - TIR'!$E$14-'Ejercicio 3 - TIR'!$C$14),'Ejercicio 3 - TIR'!$C$14+SQRT(('Ejercicio 3 - TIR'!$E$14-'Ejercicio 3 - TIR'!$C$14)*('Ejercicio 3 - TIR'!$D$14-'Ejercicio 3 - TIR'!$C$14)*D7),'Ejercicio 3 - TIR'!$E$14-SQRT(('Ejercicio 3 - TIR'!$E$14-'Ejercicio 3 - TIR'!$C$14)*('Ejercicio 3 - TIR'!$E$14-'Ejercicio 3 - TIR'!$D$14)*(1-D7))) -> 38061.128 | F7: =RAND() -> 0.48778699 | G7: =IF(F7<=('Ejercicio 3 - TIR'!$D$18-'Ejercicio 3 - TIR'!$C$18)/('Ejercicio 3 - TIR'!$E$18-'Ejercicio 3 - TIR'!$C$18),'Ejercicio 3 - TIR'!$C$18+SQRT(('Ejercicio 3 - TIR'!$E$18-'Ejercicio 3 - TIR'!$C$18)*('Ejercicio 3 - TIR'!$D$18-'Ejercicio 3 - TIR'!$C$18)*F7),'Ejercicio 3 - TIR'!$E$18-SQRT(('Ejercicio 3 - TIR'!$E$18-'Ejercicio 3 - TIR'!$C$18)*('Ejercicio 3 - TIR'!$E$18-'Ejercicio 3 - TIR'!$D$18)*(1-F7))) -> 38553.832 | H7: =RAND() -> 0.90588929 | I7: =IF(H7<=('Ejercicio 3 - TIR'!$D$18-'Ejercicio 3 - TIR'!$C$18)/('Ejercicio 3 - TIR'!$E$18-'Ejercicio 3 - TIR'!$C$18),'Ejercicio 3 - TIR'!$C$18+SQRT(('Ejercicio 3 - TIR'!$E$18-'Ejercicio 3 - TIR'!$C$18)*('Ejercicio 3 - TIR'!$D$18-'Ejercicio 3 - TIR'!$C$18)*H7),'Ejercicio 3 - TIR'!$E$18-SQRT(('Ejercicio 3 - TIR'!$E$18-'Ejercicio 3 - TIR'!$C$18)*('Ejercicio 3 - TIR'!$E$18-'Ejercicio 3 - TIR'!$D$18)*(1-H7))) -> 42343.253 | J7: =RAND() -> 0.84932076 | K7: =IF(J7<=('Ejercicio 3 - TIR'!$D$18-'Ejercicio 3 - TIR'!$C$18)/('Ejercicio 3 - TIR'!$E$18-'Ejercicio 3 - TIR'!$C$18),'Ejercicio 3 - TIR'!$C$18+SQRT(('Ejercicio 3 - TIR'!$E$18-'Ejercicio 3 - TIR'!$C$18)*('Ejercicio 3 - TIR'!$D$18-'Ejercicio 3 - TIR'!$C$18)*J7),'Ejercicio 3 - TIR'!$E$18-SQRT(('Ejercicio 3 - TIR'!$E$18-'Ejercicio 3 - TIR'!$C$18)*('Ejercicio 3 - TIR'!$E$18-'Ejercicio 3 - TIR'!$D$18)*(1-J7))) -> 41638.313 | L7: =RAND() -> 0.94458087 | M7: =IF(L7<=('Ejercicio 3 - TIR'!$D$18-'Ejercicio 3 - TIR'!$C$18)/('Ejercicio 3 - TIR'!$E$18-'Ejercicio 3 - TIR'!$C$18),'Ejercicio 3 - TIR'!$C$18+SQRT(('Ejercicio 3 - TIR'!$E$18-'Ejercicio 3 - TIR'!$C$18)*('Ejercicio 3 - TIR'!$D$18-'Ejercicio 3 - TIR'!$C$18)*L7),'Ejercicio 3 - TIR'!$E$18-SQRT(('Ejercicio 3 - TIR'!$E$18-'Ejercicio 3 - TIR'!$C$18)*('Ejercicio 3 - TIR'!$E$18-'Ejercicio 3 - TIR'!$D$18)*(1-L7))) -> 42961.266 | N7: =RAND() -> 0.060725792 | O7: =IF(N7<=('Ejercicio 3 - TIR'!$D$18-'Ejercicio 3 - TIR'!$C$18)/('Ejercicio 3 - TIR'!$E$18-'Ejercicio 3 - TIR'!$C$18),'Ejercicio 3 - TIR'!$C$18+SQRT(('Ejercicio 3 - TIR'!$E$18-'Ejercicio 3 - TIR'!$C$18)*('Ejercicio 3 - TIR'!$D$18-'Ejercicio 3 - TIR'!$C$18)*N7),'Ejercicio 3 - TIR'!$E$18-SQRT(('Ejercicio 3 - TIR'!$E$18-'Ejercicio 3 - TIR'!$C$18)*('Ejercicio 3 - TIR'!$E$18-'Ejercicio 3 - TIR'!$D$18)*(1-N7))) -> 33018.09 | P7: =RAND() -> 0.65689012 | Q7: =IF(P7<=('Ejercicio 3 - TIR'!$D$22-'Ejercicio 3 - TIR'!$C$22)/('Ejercicio 3 - TIR'!$E$22-'Ejercicio 3 - TIR'!$C$22),'Ejercicio 3 - TIR'!$C$22+SQRT(('Ejercicio 3 - TIR'!$E$22-'Ejercicio 3 - TIR'!$C$22)*('Ejercicio 3 - TIR'!$D$22-'Ejercicio 3 - TIR'!$C$22)*P7),'Ejercicio 3 - TIR'!$E$22-SQRT(('Ejercicio 3 - TIR'!$E$22-'Ejercicio 3 - TIR'!$C$22)*('Ejercicio 3 - TIR'!$E$22-'Ejercicio 3 - TIR'!$D$22)*(1-P7))) -> 0.15514849 | R7: =RAND() -> 0.97166675 | S7: =IF(R7<=('Ejercicio 3 - TIR'!$D$23-'Ejercicio 3 - TIR'!$C$23)/('Ejercicio 3 - TIR'!$E$23-'Ejercicio 3 - TIR'!$C$23),'Ejercicio 3 - TIR'!$C$23+SQRT(('Ejercicio 3 - TIR'!$E$23-'Ejercicio 3 - TIR'!$C$23)*('Ejercicio 3 - TIR'!$D$23-'Ejercicio 3 - TIR'!$C$23)*R7),'Ejercicio 3 - TIR'!$E$23-SQRT(('Ejercicio 3 - TIR'!$E$23-'Ejercicio 3 - TIR'!$C$23)*('Ejercicio 3 - TIR'!$E$23-'Ejercicio 3 - TIR'!$D$23)*(1-R7))) -> 0.17285858 | T7: =RAND() -> 0.034812998 | U7: =IF(T7<=('Ejercicio 3 - TIR'!$D$24-'Ejercicio 3 - TIR'!$C$24)/('Ejercicio 3 - TIR'!$E$24-'Ejercicio 3 - TIR'!$C$24),'Ejercicio 3 - TIR'!$C$24+SQRT(('Ejercicio 3 - TIR'!$E$24-'Ejercicio 3 - TIR'!$C$24)*('Ejercicio 3 - TIR'!$D$24-'Ejercicio 3 - TIR'!$C$24)*T7),'Ejercicio 3 - TIR'!$E$24-SQRT(('Ejercicio 3 - TIR'!$E$24-'Ejercicio 3 - TIR'!$C$24)*('Ejercicio 3 - TIR'!$E$24-'Ejercicio 3 - TIR'!$D$24)*(1-T7))) -> 0.15855028 | V7: =RAND() -> 0.73175252 | W7: =IF(V7<=('Ejercicio 3 - TIR'!$D$25-'Ejercicio 3 - TIR'!$C$25)/('Ejercicio 3 - TIR'!$E$25-'Ejercicio 3 - TIR'!$C$25),'Ejercicio 3 - TIR'!$C$25+SQRT(('Ejercicio 3 - TIR'!$E$25-'Ejercicio 3 - TIR'!$C$25)*('Ejercicio 3 - TIR'!$D$25-'Ejercicio 3 - TIR'!$C$25)*V7),'Ejercicio 3 - TIR'!$E$25-SQRT(('Ejercicio 3 - TIR'!$E$25-'Ejercicio 3 - TIR'!$C$25)*('Ejercicio 3 - TIR'!$E$25-'Ejercicio 3 - TIR'!$D$25)*(1-V7))) -> 0.21935908 | X7: =RAND() -> 0.40134122 | Y7: =IF(X7<=('Ejercicio 3 - TIR'!$D$26-'Ejercicio 3 - TIR'!$C$26)/('Ejercicio 3 - TIR'!$E$26-'Ejercicio 3 - TIR'!$C$26),'Ejercicio 3 - TIR'!$C$26+SQRT(('Ejercicio 3 - TIR'!$E$26-'Ejercicio 3 - TIR'!$C$26)*('Ejercicio 3 - TIR'!$D$26-'Ejercicio 3 - TIR'!$C$26)*X7),'Ejercicio 3 - TIR'!$E$26-SQRT(('Ejercicio 3 - TIR'!$E$26-'Ejercicio 3 - TIR'!$C$26)*('Ejercicio 3 - TIR'!$E$26-'Ejercicio 3 - TIR'!$D$26)*(1-X7))) -> 0.22314266 | Z7: =(1+Q7) -> 1.1551485 | AA7: =Z7*(1+S7) -> 1.3548258 | AB7: =AA7*(1+U7) -> 1.5696338 | AC7: =AB7*(1+W7) -> 1.9139473 | AD7: =AC7*(1+Y7) -> 2.3410305 | AE7: =E7*Q7 -> 5905.1263 | AF7: =AE7*(1+S7) -> 6925.8781 | AG7: =AF7*(1+U7) -> 8023.978 | AH7: =AG7*(1+W7) -> 9784.1104 | AI7: =AH7*(1+Y7) -> 11967.363 | AJ7: =G7*Z7 -> 44535.401 | AK7: =I7*AA7 -> 57367.733 | AL7: =K7*AB7 -> 65356.904 | AM7: =M7*AC7 -> 82225.598 | AN7: =O7*AD7 -> 77296.357 | AO7: =C7/'Ejercicio 3 - TIR'!$D$7 -> 13541.326 | AP7: =AJ7-AO7 -> 30994.075 | AQ7: =AK7-AO7 -> 43826.407 | AR7: =AL7-AO7 -> 51815.578 | AS7: =AM7-AO7 -> 68684.272 | AT7: =AN7-AO7 -> 63755.032 | AU7: =AP7*'Ejercicio 3 - TIR'!$D$5 -> 15497.038 | AV7: =AQ7*'Ejercicio 3 - TIR'!$D$5 -> 21913.203 | AW7: =AR7*'Ejercicio 3 - TIR'!$D$5 -> 25907.789 | AX7: =AS7*'Ejercicio 3 - TIR'!$D$5 -> 34342.136 | AY7: =AT7*'Ejercicio 3 - TIR'!$D$5 -> 31877.516 | AZ7: =AJ7-AU7-AE7 -> 23133.237 | BA7: =AK7-AV7-AF7 -> 28528.651 | BB7: =AL7-AW7-AG7 -> 31425.137 | BC7: =AM7-AX7-AH7 -> 38099.351 | BD7: =AN7-AY7-AI7 -> 33451.479 | BE7: =AZ7/Z7 -> 20026.202 | BF7: =BA7/AA7 -> 21057.062 | BG7: =BB7/AB7 -> 20020.68 | BH7: =BC7/AC7 -> 19906.166 | BI7: =BD7/AD7 -> 14289.211 | BJ7: =E7*AD7 -> 89102.262 | BK7: =0.2*C7*AD7 -> 31700.657 | BL7: =BJ7+BK7 -> 120802.92 | BM7: =BK7*'Ejercicio 3 - TIR'!$D$5 -> 15850.328 | BN7: =BL7-BM7 -> 104952.59 | BO7: =BN7/AD7 -> 44831.791 | BP7: =-(C7+E7) -> -105767.76 | BQ7: =BE7 -> 20026.202 | BR7: =BF7 -> 21057.062 | BS7: =BG7 -> 20020.68 | BT7: =BH7 -> 19906.166 | BU7: =BI7+BO7 -> 59121.001 | BV7: =IFERROR(IRR(BP7:BU7,0.1),NA())*100 -> 8.4795151
A8: 7 | B8: =RAND() -> 0.65396627 | C8: =IF(B8<=('Ejercicio 3 - TIR'!$D$13-'Ejercicio 3 - TIR'!$C$13)/('Ejercicio 3 - TIR'!$E$13-'Ejercicio 3 - TIR'!$C$13),'Ejercicio 3 - TIR'!$C$13+SQRT(('Ejercicio 3 - TIR'!$E$13-'Ejercicio 3 - TIR'!$C$13)*('Ejercicio 3 - TIR'!$D$13-'Ejercicio 3 - TIR'!$C$13)*B8),'Ejercicio 3 - TIR'!$E$13-SQRT(('Ejercicio 3 - TIR'!$E$13-'Ejercicio 3 - TIR'!$C$13)*('Ejercicio 3 - TIR'!$E$13-'Ejercicio 3 - TIR'!$D$13)*(1-B8))) -> 79622.55 | D8: =RAND() -> 0.24514241 | E8: =IF(D8<=('Ejercicio 3 - TIR'!$D$14-'Ejercicio 3 - TIR'!$C$14)/('Ejercicio 3 - TIR'!$E$14-'Ejercicio 3 - TIR'!$C$14),'Ejercicio 3 - TIR'!$C$14+SQRT(('Ejercicio 3 - TIR'!$E$14-'Ejercicio 3 - TIR'!$C$14)*('Ejercicio 3 - TIR'!$D$14-'Ejercicio 3 - TIR'!$C$14)*D8),'Ejercicio 3 - TIR'!$E$14-SQRT(('Ejercicio 3 - TIR'!$E$14-'Ejercicio 3 - TIR'!$C$14)*('Ejercicio 3 - TIR'!$E$14-'Ejercicio 3 - TIR'!$D$14)*(1-D8))) -> 29287.853 | F8: =RAND() -> 0.24803863 | G8: =IF(F8<=('Ejercicio 3 - TIR'!$D$18-'Ejercicio 3 - TIR'!$C$18)/('Ejercicio 3 - TIR'!$E$18-'Ejercicio 3 - TIR'!$C$18),'Ejercicio 3 - TIR'!$C$18+SQRT(('Ejercicio 3 - TIR'!$E$18-'Ejercicio 3 - TIR'!$C$18)*('Ejercicio 3 - TIR'!$D$18-'Ejercicio 3 - TIR'!$C$18)*F8),'Ejercicio 3 - TIR'!$E$18-SQRT(('Ejercicio 3 - TIR'!$E$18-'Ejercicio 3 - TIR'!$C$18)*('Ejercicio 3 - TIR'!$E$18-'Ejercicio 3 - TIR'!$D$18)*(1-F8))) -> 36099.655 | H8: =RAND() -> 0.2312384 | I8: =IF(H8<=('Ejercicio 3 - TIR'!$D$18-'Ejercicio 3 - TIR'!$C$18)/('Ejercicio 3 - TIR'!$E$18-'Ejercicio 3 - TIR'!$C$18),'Ejercicio 3 - TIR'!$C$18+SQRT(('Ejercicio 3 - TIR'!$E$18-'Ejercicio 3 - TIR'!$C$18)*('Ejercicio 3 - TIR'!$D$18-'Ejercicio 3 - TIR'!$C$18)*H8),'Ejercicio 3 - TIR'!$E$18-SQRT(('Ejercicio 3 - TIR'!$E$18-'Ejercicio 3 - TIR'!$C$18)*('Ejercicio 3 - TIR'!$E$18-'Ejercicio 3 - TIR'!$D$18)*(1-H8))) -> 35889.462 | J8: =RAND() -> 0.83671594 | K8: =IF(J8<=('Ejercicio 3 - TIR'!$D$18-'Ejercicio 3 - TIR'!$C$18)/('Ejercicio 3 - TIR'!$E$18-'Ejercicio 3 - TIR'!$C$18),'Ejercicio 3 - TIR'!$C$18+SQRT(('Ejercicio 3 - TIR'!$E$18-'Ejercicio 3 - TIR'!$C$18)*('Ejercicio 3 - TIR'!$D$18-'Ejercicio 3 - TIR'!$C$18)*J8),'Ejercicio 3 - TIR'!$E$18-SQRT(('Ejercicio 3 - TIR'!$E$18-'Ejercicio 3 - TIR'!$C$18)*('Ejercicio 3 - TIR'!$E$18-'Ejercicio 3 - TIR'!$D$18)*(1-J8))) -> 41500.528 | L8: =RAND() -> 0.67038013 | M8: =IF(L8<=('Ejercicio 3 - TIR'!$D$18-'Ejercicio 3 - TIR'!$C$18)/('Ejercicio 3 - TIR'!$E$18-'Ejercicio 3 - TIR'!$C$18),'Ejercicio 3 - TIR'!$C$18+SQRT(('Ejercicio 3 - TIR'!$E$18-'Ejercicio 3 - TIR'!$C$18)*('Ejercicio 3 - TIR'!$D$18-'Ejercicio 3 - TIR'!$C$18)*L8),'Ejercicio 3 - TIR'!$E$18-SQRT(('Ejercicio 3 - TIR'!$E$18-'Ejercicio 3 - TIR'!$C$18)*('Ejercicio 3 - TIR'!$E$18-'Ejercicio 3 - TIR'!$D$18)*(1-L8))) -> 40027.929 | N8: =RAND() -> 0.59551151 | O8: =IF(N8<=('Ejercicio 3 - TIR'!$D$18-'Ejercicio 3 - TIR'!$C$18)/('Ejercicio 3 - TIR'!$E$18-'Ejercicio 3 - TIR'!$C$18),'Ejercicio 3 - TIR'!$C$18+SQRT(('Ejercicio 3 - TIR'!$E$18-'Ejercicio 3 - TIR'!$C$18)*('Ejercicio 3 - TIR'!$D$18-'Ejercicio 3 - TIR'!$C$18)*N8),'Ejercicio 3 - TIR'!$E$18-SQRT(('Ejercicio 3 - TIR'!$E$18-'Ejercicio 3 - TIR'!$C$18)*('Ejercicio 3 - TIR'!$E$18-'Ejercicio 3 - TIR'!$D$18)*(1-N8))) -> 39451.282 | P8: =RAND() -> 0.87831114 | Q8: =IF(P8<=('Ejercicio 3 - TIR'!$D$22-'Ejercicio 3 - TIR'!$C$22)/('Ejercicio 3 - TIR'!$E$22-'Ejercicio 3 - TIR'!$C$22),'Ejercicio 3 - TIR'!$C$22+SQRT(('Ejercicio 3 - TIR'!$E$22-'Ejercicio 3 - TIR'!$C$22)*('Ejercicio 3 - TIR'!$D$22-'Ejercicio 3 - TIR'!$C$22)*P8),'Ejercicio 3 - TIR'!$E$22-SQRT(('Ejercicio 3 - TIR'!$E$22-'Ejercicio 3 - TIR'!$C$22)*('Ejercicio 3 - TIR'!$E$22-'Ejercicio 3 - TIR'!$D$22)*(1-P8))) -> 0.1652 | R8: =RAND() -> 0.88477997 | S8: =IF(R8<=('Ejercicio 3 - TIR'!$D$23-'Ejercicio 3 - TIR'!$C$23)/('Ejercicio 3 - TIR'!$E$23-'Ejercicio 3 - TIR'!$C$23),'Ejercicio 3 - TIR'!$C$23+SQRT(('Ejercicio 3 - TIR'!$E$23-'Ejercicio 3 - TIR'!$C$23)*('Ejercicio 3 - TIR'!$D$23-'Ejercicio 3 - TIR'!$C$23)*R8),'Ejercicio 3 - TIR'!$E$23-SQRT(('Ejercicio 3 - TIR'!$E$23-'Ejercicio 3 - TIR'!$C$23)*('Ejercicio 3 - TIR'!$E$23-'Ejercicio 3 - TIR'!$D$23)*(1-R8))) -> 0.16559875 | T8: =RAND() -> 0.27814753 | U8: =IF(T8<=('Ejercicio 3 - TIR'!$D$24-'Ejercicio 3 - TIR'!$C$24)/('Ejercicio 3 - TIR'!$E$24-'Ejercicio 3 - TIR'!$C$24),'Ejercicio 3 - TIR'!$C$24+SQRT(('Ejercicio 3 - TIR'!$E$24-'Ejercicio 3 - TIR'!$C$24)*('Ejercicio 3 - TIR'!$D$24-'Ejercicio 3 - TIR'!$C$24)*T8),'Ejercicio 3 - TIR'!$E$24-SQRT(('Ejercicio 3 - TIR'!$E$24-'Ejercicio 3 - TIR'!$C$24)*('Ejercicio 3 - TIR'!$E$24-'Ejercicio 3 - TIR'!$D$24)*(1-T8))) -> 0.17416836 | V8: =RAND() -> 0.91606872 | W8: =IF(V8<=('Ejercicio 3 - TIR'!$D$25-'Ejercicio 3 - TIR'!$C$25)/('Ejercicio 3 - TIR'!$E$25-'Ejercicio 3 - TIR'!$C$25),'Ejercicio 3 - TIR'!$C$25+SQRT(('Ejercicio 3 - TIR'!$E$25-'Ejercicio 3 - TIR'!$C$25)*('Ejercicio 3 - TIR'!$D$25-'Ejercicio 3 - TIR'!$C$25)*V8),'Ejercicio 3 - TIR'!$E$25-SQRT(('Ejercicio 3 - TIR'!$E$25-'Ejercicio 3 - TIR'!$C$25)*('Ejercicio 3 - TIR'!$E$25-'Ejercicio 3 - TIR'!$D$25)*(1-V8))) -> 0.23286059 | X8: =RAND() -> 0.89680736 | Y8: =IF(X8<=('Ejercicio 3 - TIR'!$D$26-'Ejercicio 3 - TIR'!$C$26)/('Ejercicio 3 - TIR'!$E$26-'Ejercicio 3 - TIR'!$C$26),'Ejercicio 3 - TIR'!$C$26+SQRT(('Ejercicio 3 - TIR'!$E$26-'Ejercicio 3 - TIR'!$C$26)*('Ejercicio 3 - TIR'!$D$26-'Ejercicio 3 - TIR'!$C$26)*X8),'Ejercicio 3 - TIR'!$E$26-SQRT(('Ejercicio 3 - TIR'!$E$26-'Ejercicio 3 - TIR'!$C$26)*('Ejercicio 3 - TIR'!$E$26-'Ejercicio 3 - TIR'!$D$26)*(1-X8))) -> 0.25639406 | Z8: =(1+Q8) -> 1.1652 | AA8: =Z8*(1+S8) -> 1.3581557 | AB8: =AA8*(1+U8) -> 1.5947034 | AC8: =AB8*(1+W8) -> 1.966047 | AD8: =AC8*(1+Y8) -> 2.4701298 | AE8: =E8*Q8 -> 4838.3533 | AF8: =AE8*(1+S8) -> 5639.5786 | AG8: =AF8*(1+U8) -> 6621.8148 | AH8: =AG8*(1+W8) -> 8163.7744 | AI8: =AH8*(1+Y8) -> 10256.918 | AJ8: =G8*Z8 -> 42063.318 | AK8: =I8*AA8 -> 48743.476 | AL8: =K8*AB8 -> 66181.034 | AM8: =M8*AC8 -> 78696.789 | AN8: =O8*AD8 -> 97449.785 | AO8: =C8/'Ejercicio 3 - TIR'!$D$7 -> 15924.51 | AP8: =AJ8-AO8 -> 26138.808 | AQ8: =AK8-AO8 -> 32818.966 | AR8: =AL8-AO8 -> 50256.524 | AS8: =AM8-AO8 -> 62772.279 | AT8: =AN8-AO8 -> 81525.275 | AU8: =AP8*'Ejercicio 3 - TIR'!$D$5 -> 13069.404 | AV8: =AQ8*'Ejercicio 3 - TIR'!$D$5 -> 16409.483 | AW8: =AR8*'Ejercicio 3 - TIR'!$D$5 -> 25128.262 | AX8: =AS8*'Ejercicio 3 - TIR'!$D$5 -> 31386.14 | AY8: =AT8*'Ejercicio 3 - TIR'!$D$5 -> 40762.638 | AZ8: =AJ8-AU8-AE8 -> 24155.561 | BA8: =AK8-AV8-AF8 -> 26694.414 | BB8: =AL8-AW8-AG8 -> 34430.957 | BC8: =AM8-AX8-AH8 -> 39146.875 | BD8: =AN8-AY8-AI8 -> 46430.23 | BE8: =AZ8/Z8 -> 20730.828 | BF8: =BA8/AA8 -> 19654.9 | BG8: =BB8/AB8 -> 21590.822 | BH8: =BC8/AC8 -> 19911.465 | BI8: =BD8/AD8 -> 18796.676 | BJ8: =E8*AD8 -> 72344.797 | BK8: =0.2*C8*AD8 -> 39335.606 | BL8: =BJ8+BK8 -> 111680.4 | BM8: =BK8*'Ejercicio 3 - TIR'!$D$5 -> 19667.803 | BN8: =BL8-BM8 -> 92012.6 | BO8: =BN8/AD8 -> 37250.108 | BP8: =-(C8+E8) -> -108910.4 | BQ8: =BE8 -> 20730.828 | BR8: =BF8 -> 19654.9 | BS8: =BG8 -> 21590.822 | BT8: =BH8 -> 19911.465 | BU8: =BI8+BO8 -> 56046.784 | BV8: =IFERROR(IRR(BP8:BU8,0.1),NA())*100 -> 7.1189596
A9: 8 | B9: =RAND() -> 0.80255248 | C9: =IF(B9<=('Ejercicio 3 - TIR'!$D$13-'Ejercicio 3 - TIR'!$C$13)/('Ejercicio 3 - TIR'!$E$13-'Ejercicio 3 - TIR'!$C$13),'Ejercicio 3 - TIR'!$C$13+SQRT(('Ejercicio 3 - TIR'!$E$13-'Ejercicio 3 - TIR'!$C$13)*('Ejercicio 3 - TIR'!$D$13-'Ejercicio 3 - TIR'!$C$13)*B9),'Ejercicio 3 - TIR'!$E$13-SQRT(('Ejercicio 3 - TIR'!$E$13-'Ejercicio 3 - TIR'!$C$13)*('Ejercicio 3 - TIR'!$E$13-'Ejercicio 3 - TIR'!$D$13)*(1-B9))) -> 84607.241 | D9: =RAND() -> 0.54967136 | E9: =IF(D9<=('Ejercicio 3 - TIR'!$D$14-'Ejercicio 3 - TIR'!$C$14)/('Ejercicio 3 - TIR'!$E$14-'Ejercicio 3 - TIR'!$C$14),'Ejercicio 3 - TIR'!$C$14+SQRT(('Ejercicio 3 - TIR'!$E$14-'Ejercicio 3 - TIR'!$C$14)*('Ejercicio 3 - TIR'!$D$14-'Ejercicio 3 - TIR'!$C$14)*D9),'Ejercicio 3 - TIR'!$E$14-SQRT(('Ejercicio 3 - TIR'!$E$14-'Ejercicio 3 - TIR'!$C$14)*('Ejercicio 3 - TIR'!$E$14-'Ejercicio 3 - TIR'!$D$14)*(1-D9))) -> 31781.162 | F9: =RAND() -> 0.33877514 | G9: =IF(F9<=('Ejercicio 3 - TIR'!$D$18-'Ejercicio 3 - TIR'!$C$18)/('Ejercicio 3 - TIR'!$E$18-'Ejercicio 3 - TIR'!$C$18),'Ejercicio 3 - TIR'!$C$18+SQRT(('Ejercicio 3 - TIR'!$E$18-'Ejercicio 3 - TIR'!$C$18)*('Ejercicio 3 - TIR'!$D$18-'Ejercicio 3 - TIR'!$C$18)*F9),'Ejercicio 3 - TIR'!$E$18-SQRT(('Ejercicio 3 - TIR'!$E$18-'Ejercicio 3 - TIR'!$C$18)*('Ejercicio 3 - TIR'!$E$18-'Ejercicio 3 - TIR'!$D$18)*(1-F9))) -> 37128.553 | H9: =RAND() -> 0.91794748 | I9: =IF(H9<=('Ejercicio 3 - TIR'!$D$18-'Ejercicio 3 - TIR'!$C$18)/('Ejercicio 3 - TIR'!$E$18-'Ejercicio 3 - TIR'!$C$18),'Ejercicio 3 - TIR'!$C$18+SQRT(('Ejercicio 3 - TIR'!$E$18-'Ejercicio 3 - TIR'!$C$18)*('Ejercicio 3 - TIR'!$D$18-'Ejercicio 3 - TIR'!$C$18)*H9),'Ejercicio 3 - TIR'!$E$18-SQRT(('Ejercicio 3 - TIR'!$E$18-'Ejercicio 3 - TIR'!$C$18)*('Ejercicio 3 - TIR'!$E$18-'Ejercicio 3 - TIR'!$D$18)*(1-H9))) -> 42519.287 | J9: =RAND() -> 0.21533648 | K9: =IF(J9<=('Ejercicio 3 - TIR'!$D$18-'Ejercicio 3 - TIR'!$C$18)/('Ejercicio 3 - TIR'!$E$18-'Ejercicio 3 - TIR'!$C$18),'Ejercicio 3 - TIR'!$C$18+SQRT(('Ejercicio 3 - TIR'!$E$18-'Ejercicio 3 - TIR'!$C$18)*('Ejercicio 3 - TIR'!$D$18-'Ejercicio 3 - TIR'!$C$18)*J9),'Ejercicio 3 - TIR'!$E$18-SQRT(('Ejercicio 3 - TIR'!$E$18-'Ejercicio 3 - TIR'!$C$18)*('Ejercicio 3 - TIR'!$E$18-'Ejercicio 3 - TIR'!$D$18)*(1-J9))) -> 35683.35 | L9: =RAND() -> 0.63874881 | M9: =IF(L9<=('Ejercicio 3 - TIR'!$D$18-'Ejercicio 3 - TIR'!$C$18)/('Ejercicio 3 - TIR'!$E$18-'Ejercicio 3 - TIR'!$C$18),'Ejercicio 3 - TIR'!$C$18+SQRT(('Ejercicio 3 - TIR'!$E$18-'Ejercicio 3 - TIR'!$C$18)*('Ejercicio 3 - TIR'!$D$18-'Ejercicio 3 - TIR'!$C$18)*L9),'Ejercicio 3 - TIR'!$E$18-SQRT(('Ejercicio 3 - TIR'!$E$18-'Ejercicio 3 - TIR'!$C$18)*('Ejercicio 3 - TIR'!$E$18-'Ejercicio 3 - TIR'!$D$18)*(1-L9))) -> 39788.377 | N9: =RAND() -> 0.085265524 | O9: =IF(N9<=('Ejercicio 3 - TIR'!$D$18-'Ejercicio 3 - TIR'!$C$18)/('Ejercicio 3 - TIR'!$E$18-'Ejercicio 3 - TIR'!$C$18),'Ejercicio 3 - TIR'!$C$18+SQRT(('Ejercicio 3 - TIR'!$E$18-'Ejercicio 3 - TIR'!$C$18)*('Ejercicio 3 - TIR'!$D$18-'Ejercicio 3 - TIR'!$C$18)*N9),'Ejercicio 3 - TIR'!$E$18-SQRT(('Ejercicio 3 - TIR'!$E$18-'Ejercicio 3 - TIR'!$C$18)*('Ejercicio 3 - TIR'!$E$18-'Ejercicio 3 - TIR'!$D$18)*(1-N9))) -> 33576.287 | P9: =RAND() -> 0.82884869 | Q9: =IF(P9<=('Ejercicio 3 - TIR'!$D$22-'Ejercicio 3 - TIR'!$C$22)/('Ejercicio 3 - TIR'!$E$22-'Ejercicio 3 - TIR'!$C$22),'Ejercicio 3 - TIR'!$C$22+SQRT(('Ejercicio 3 - TIR'!$E$22-'Ejercicio 3 - TIR'!$C$22)*('Ejercicio 3 - TIR'!$D$22-'Ejercicio 3 - TIR'!$C$22)*P9),'Ejercicio 3 - TIR'!$E$22-SQRT(('Ejercicio 3 - TIR'!$E$22-'Ejercicio 3 - TIR'!$C$22)*('Ejercicio 3 - TIR'!$E$22-'Ejercicio 3 - TIR'!$D$22)*(1-P9))) -> 0.16244801 | R9: =RAND() -> 0.70390751 | S9: =IF(R9<=('Ejercicio 3 - TIR'!$D$23-'Ejercicio 3 - TIR'!$C$23)/('Ejercicio 3 - TIR'!$E$23-'Ejercicio 3 - TIR'!$C$23),'Ejercicio 3 - TIR'!$C$23+SQRT(('Ejercicio 3 - TIR'!$E$23-'Ejercicio 3 - TIR'!$C$23)*('Ejercicio 3 - TIR'!$D$23-'Ejercicio 3 - TIR'!$C$23)*R9),'Ejercicio 3 - TIR'!$E$23-SQRT(('Ejercicio 3 - TIR'!$E$23-'Ejercicio 3 - TIR'!$C$23)*('Ejercicio 3 - TIR'!$E$23-'Ejercicio 3 - TIR'!$D$23)*(1-R9))) -> 0.15691393 | T9: =RAND() -> 0.2527926 | U9: =IF(T9<=('Ejercicio 3 - TIR'!$D$24-'Ejercicio 3 - TIR'!$C$24)/('Ejercicio 3 - TIR'!$E$24-'Ejercicio 3 - TIR'!$C$24),'Ejercicio 3 - TIR'!$C$24+SQRT(('Ejercicio 3 - TIR'!$E$24-'Ejercicio 3 - TIR'!$C$24)*('Ejercicio 3 - TIR'!$D$24-'Ejercicio 3 - TIR'!$C$24)*T9),'Ejercicio 3 - TIR'!$E$24-SQRT(('Ejercicio 3 - TIR'!$E$24-'Ejercicio 3 - TIR'!$C$24)*('Ejercicio 3 - TIR'!$E$24-'Ejercicio 3 - TIR'!$D$24)*(1-T9))) -> 0.1730405 | V9: =RAND() -> 0.75518724 | W9: =IF(V9<=('Ejercicio 3 - TIR'!$D$25-'Ejercicio 3 - TIR'!$C$25)/('Ejercicio 3 - TIR'!$E$25-'Ejercicio 3 - TIR'!$C$25),'Ejercicio 3 - TIR'!$C$25+SQRT(('Ejercicio 3 - TIR'!$E$25-'Ejercicio 3 - TIR'!$C$25)*('Ejercicio 3 - TIR'!$D$25-'Ejercicio 3 - TIR'!$C$25)*V9),'Ejercicio 3 - TIR'!$E$25-SQRT(('Ejercicio 3 - TIR'!$E$25-'Ejercicio 3 - TIR'!$C$25)*('Ejercicio 3 - TIR'!$E$25-'Ejercicio 3 - TIR'!$D$25)*(1-V9))) -> 0.22072809 | X9: =RAND() -> 0.30736453 | Y9: =IF(X9<=('Ejercicio 3 - TIR'!$D$26-'Ejercicio 3 - TIR'!$C$26)/('Ejercicio 3 - TIR'!$E$26-'Ejercicio 3 - TIR'!$C$26),'Ejercicio 3 - TIR'!$C$26+SQRT(('Ejercicio 3 - TIR'!$E$26-'Ejercicio 3 - TIR'!$C$26)*('Ejercicio 3 - TIR'!$D$26-'Ejercicio 3 - TIR'!$C$26)*X9),'Ejercicio 3 - TIR'!$E$26-SQRT(('Ejercicio 3 - TIR'!$E$26-'Ejercicio 3 - TIR'!$C$26)*('Ejercicio 3 - TIR'!$E$26-'Ejercicio 3 - TIR'!$D$26)*(1-X9))) -> 0.21880771 | Z9: =(1+Q9) -> 1.162448 | AA9: =Z9*(1+S9) -> 1.3448523 | AB9: =AA9*(1+U9) -> 1.5775662 | AC9: =AB9*(1+W9) -> 1.9257794 | AD9: =AC9*(1+Y9) -> 2.3471548 | AE9: =E9*Q9 -> 5162.7866 | AF9: =AE9*(1+S9) -> 5972.8997 | AG9: =AF9*(1+U9) -> 7006.4532 | AH9: =AG9*(1+W9) -> 8552.9743 | AI9: =AH9*(1+Y9) -> 10424.431 | AJ9: =G9*Z9 -> 43160.013 | AK9: =I9*AA9 -> 57182.16 | AL9: =K9*AB9 -> 56292.848 | AM9: =M9*AC9 -> 76623.636 | AN9: =O9*AD9 -> 78808.742 | AO9: =C9/'Ejercicio 3 - TIR'!$D$7 -> 16921.448 | AP9: =AJ9-AO9 -> 26238.565 | AQ9: =AK9-AO9 -> 40260.712 | AR9: =AL9-AO9 -> 39371.4 | AS9: =AM9-AO9 -> 59702.188 | AT9: =AN9-AO9 -> 61887.294 | AU9: =AP9*'Ejercicio 3 - TIR'!$D$5 -> 13119.282 | AV9: =AQ9*'Ejercicio 3 - TIR'!$D$5 -> 20130.356 | AW9: =AR9*'Ejercicio 3 - TIR'!$D$5 -> 19685.7 | AX9: =AS9*'Ejercicio 3 - TIR'!$D$5 -> 29851.094 | AY9: =AT9*'Ejercicio 3 - TIR'!$D$5 -> 30943.647 | AZ9: =AJ9-AU9-AE9 -> 24877.944 | BA9: =AK9-AV9-AF9 -> 31078.905 | BB9: =AL9-AW9-AG9 -> 29600.695 | BC9: =AM9-AX9-AH9 -> 38219.568 | BD9: =AN9-AY9-AI9 -> 37440.664 | BE9: =AZ9/Z9 -> 21401.339 | BF9: =BA9/AA9 -> 23109.53 | BG9: =BB9/AB9 -> 18763.52 | BH9: =BC9/AC9 -> 19846.286 | BI9: =BD9/AD9 -> 15951.511 | BJ9: =E9*AD9 -> 74595.306 | BK9: =0.2*C9*AD9 -> 39717.258 | BL9: =BJ9+BK9 -> 114312.56 | BM9: =BK9*'Ejercicio 3 - TIR'!$D$5 -> 19858.629 | BN9: =BL9-BM9 -> 94453.935 | BO9: =BN9/AD9 -> 40241.886 | BP9: =-(C9+E9) -> -116388.4 | BQ9: =BE9 -> 21401.339 | BR9: =BF9 -> 23109.53 | BS9: =BG9 -> 18763.52 | BT9: =BH9 -> 19846.286 | BU9: =BI9+BO9 -> 56193.397 | BV9: =IFERROR(IRR(BP9:BU9,0.1),NA())*100 -> 5.4066131
A10: 9 | B10: =RAND() -> 0.13167715 | C10: =IF(B10<=('Ejercicio 3 - TIR'!$D$13-'Ejercicio 3 - TIR'!$C$13)/('Ejercicio 3 - TIR'!$E$13-'Ejercicio 3 - TIR'!$C$13),'Ejercicio 3 - TIR'!$C$13+SQRT(('Ejercicio 3 - TIR'!$E$13-'Ejercicio 3 - TIR'!$C$13)*('Ejercicio 3 - TIR'!$D$13-'Ejercicio 3 - TIR'!$C$13)*B10),'Ejercicio 3 - TIR'!$E$13-SQRT(('Ejercicio 3 - TIR'!$E$13-'Ejercicio 3 - TIR'!$C$13)*('Ejercicio 3 - TIR'!$E$13-'Ejercicio 3 - TIR'!$D$13)*(1-B10))) -> 67257.469 | D10: =RAND() -> 0.11302775 | E10: =IF(D10<=('Ejercicio 3 - TIR'!$D$14-'Ejercicio 3 - TIR'!$C$14)/('Ejercicio 3 - TIR'!$E$14-'Ejercicio 3 - TIR'!$C$14),'Ejercicio 3 - TIR'!$C$14+SQRT(('Ejercicio 3 - TIR'!$E$14-'Ejercicio 3 - TIR'!$C$14)*('Ejercicio 3 - TIR'!$D$14-'Ejercicio 3 - TIR'!$C$14)*D10),'Ejercicio 3 - TIR'!$E$14-SQRT(('Ejercicio 3 - TIR'!$E$14-'Ejercicio 3 - TIR'!$C$14)*('Ejercicio 3 - TIR'!$E$14-'Ejercicio 3 - TIR'!$D$14)*(1-D10))) -> 27911.543 | F10: =RAND() -> 0.15832979 | G10: =IF(F10<=('Ejercicio 3 - TIR'!$D$18-'Ejercicio 3 - TIR'!$C$18)/('Ejercicio 3 - TIR'!$E$18-'Ejercicio 3 - TIR'!$C$18),'Ejercicio 3 - TIR'!$C$18+SQRT(('Ejercicio 3 - TIR'!$E$18-'Ejercicio 3 - TIR'!$C$18)*('Ejercicio 3 - TIR'!$D$18-'Ejercicio 3 - TIR'!$C$18)*F10),'Ejercicio 3 - TIR'!$E$18-SQRT(('Ejercicio 3 - TIR'!$E$18-'Ejercicio 3 - TIR'!$C$18)*('Ejercicio 3 - TIR'!$E$18-'Ejercicio 3 - TIR'!$D$18)*(1-F10))) -> 34873.343 | H10: =RAND() -> 0.84050733 | I10: =IF(H10<=('Ejercicio 3 - TIR'!$D$18-'Ejercicio 3 - TIR'!$C$18)/('Ejercicio 3 - TIR'!$E$18-'Ejercicio 3 - TIR'!$C$18),'Ejercicio 3 - TIR'!$C$18+SQRT(('Ejercicio 3 - TIR'!$E$18-'Ejercicio 3 - TIR'!$C$18)*('Ejercicio 3 - TIR'!$D$18-'Ejercicio 3 - TIR'!$C$18)*H10),'Ejercicio 3 - TIR'!$E$18-SQRT(('Ejercicio 3 - TIR'!$E$18-'Ejercicio 3 - TIR'!$C$18)*('Ejercicio 3 - TIR'!$E$18-'Ejercicio 3 - TIR'!$D$18)*(1-H10))) -> 41541.395 | J10: =RAND() -> 0.94832384 | K10: =IF(J10<=('Ejercicio 3 - TIR'!$D$18-'Ejercicio 3 - TIR'!$C$18)/('Ejercicio 3 - TIR'!$E$18-'Ejercicio 3 - TIR'!$C$18),'Ejercicio 3 - TIR'!$C$18+SQRT(('Ejercicio 3 - TIR'!$E$18-'Ejercicio 3 - TIR'!$C$18)*('Ejercicio 3 - TIR'!$D$18-'Ejercicio 3 - TIR'!$C$18)*J10),'Ejercicio 3 - TIR'!$E$18-SQRT(('Ejercicio 3 - TIR'!$E$18-'Ejercicio 3 - TIR'!$C$18)*('Ejercicio 3 - TIR'!$E$18-'Ejercicio 3 - TIR'!$D$18)*(1-J10))) -> 43031.317 | L10: =RAND() -> 0.90419359 | M10: =IF(L10<=('Ejercicio 3 - TIR'!$D$18-'Ejercicio 3 - TIR'!$C$18)/('Ejercicio 3 - TIR'!$E$18-'Ejercicio 3 - TIR'!$C$18),'Ejercicio 3 - TIR'!$C$18+SQRT(('Ejercicio 3 - TIR'!$E$18-'Ejercicio 3 - TIR'!$C$18)*('Ejercicio 3 - TIR'!$D$18-'Ejercicio 3 - TIR'!$C$18)*L10),'Ejercicio 3 - TIR'!$E$18-SQRT(('Ejercicio 3 - TIR'!$E$18-'Ejercicio 3 - TIR'!$C$18)*('Ejercicio 3 - TIR'!$E$18-'Ejercicio 3 - TIR'!$D$18)*(1-L10))) -> 42319.425 | N10: =RAND() -> 0.39055014 | O10: =IF(N10<=('Ejercicio 3 - TIR'!$D$18-'Ejercicio 3 - TIR'!$C$18)/('Ejercicio 3 - TIR'!$E$18-'Ejercicio 3 - TIR'!$C$18),'Ejercicio 3 - TIR'!$C$18+SQRT(('Ejercicio 3 - TIR'!$E$18-'Ejercicio 3 - TIR'!$C$18)*('Ejercicio 3 - TIR'!$D$18-'Ejercicio 3 - TIR'!$C$18)*N10),'Ejercicio 3 - TIR'!$E$18-SQRT(('Ejercicio 3 - TIR'!$E$18-'Ejercicio 3 - TIR'!$C$18)*('Ejercicio 3 - TIR'!$E$18-'Ejercicio 3 - TIR'!$D$18)*(1-N10))) -> 37653.922 | P10: =RAND() -> 0.82149081 | Q10: =IF(P10<=('Ejercicio 3 - TIR'!$D$22-'Ejercicio 3 - TIR'!$C$22)/('Ejercicio 3 - TIR'!$E$22-'Ejercicio 3 - TIR'!$C$22),'Ejercicio 3 - TIR'!$C$22+SQRT(('Ejercicio 3 - TIR'!$E$22-'Ejercicio 3 - TIR'!$C$22)*('Ejercicio 3 - TIR'!$D$22-'Ejercicio 3 - TIR'!$C$22)*P10),'Ejercicio 3 - TIR'!$E$22-SQRT(('Ejercicio 3 - TIR'!$E$22-'Ejercicio 3 - TIR'!$C$22)*('Ejercicio 3 - TIR'!$E$22-'Ejercicio 3 - TIR'!$D$22)*(1-P10))) -> 0.1620747 | R10: =RAND() -> 0.54641565 | S10: =IF(R10<=('Ejercicio 3 - TIR'!$D$23-'Ejercicio 3 - TIR'!$C$23)/('Ejercicio 3 - TIR'!$E$23-'Ejercicio 3 - TIR'!$C$23),'Ejercicio 3 - TIR'!$C$23+SQRT(('Ejercicio 3 - TIR'!$E$23-'Ejercicio 3 - TIR'!$C$23)*('Ejercicio 3 - TIR'!$D$23-'Ejercicio 3 - TIR'!$C$23)*R10),'Ejercicio 3 - TIR'!$E$23-SQRT(('Ejercicio 3 - TIR'!$E$23-'Ejercicio 3 - TIR'!$C$23)*('Ejercicio 3 - TIR'!$E$23-'Ejercicio 3 - TIR'!$D$23)*(1-R10))) -> 0.15142638 | T10: =RAND() -> 0.92237984 | U10: =IF(T10<=('Ejercicio 3 - TIR'!$D$24-'Ejercicio 3 - TIR'!$C$24)/('Ejercicio 3 - TIR'!$E$24-'Ejercicio 3 - TIR'!$C$24),'Ejercicio 3 - TIR'!$C$24+SQRT(('Ejercicio 3 - TIR'!$E$24-'Ejercicio 3 - TIR'!$C$24)*('Ejercicio 3 - TIR'!$D$24-'Ejercicio 3 - TIR'!$C$24)*T10),'Ejercicio 3 - TIR'!$E$24-SQRT(('Ejercicio 3 - TIR'!$E$24-'Ejercicio 3 - TIR'!$C$24)*('Ejercicio 3 - TIR'!$E$24-'Ejercicio 3 - TIR'!$D$24)*(1-T10))) -> 0.20525766 | V10: =RAND() -> 0.64187831 | W10: =IF(V10<=('Ejercicio 3 - TIR'!$D$25-'Ejercicio 3 - TIR'!$C$25)/('Ejercicio 3 - TIR'!$E$25-'Ejercicio 3 - TIR'!$C$25),'Ejercicio 3 - TIR'!$C$25+SQRT(('Ejercicio 3 - TIR'!$E$25-'Ejercicio 3 - TIR'!$C$25)*('Ejercicio 3 - TIR'!$D$25-'Ejercicio 3 - TIR'!$C$25)*V10),'Ejercicio 3 - TIR'!$E$25-SQRT(('Ejercicio 3 - TIR'!$E$25-'Ejercicio 3 - TIR'!$C$25)*('Ejercicio 3 - TIR'!$E$25-'Ejercicio 3 - TIR'!$D$25)*(1-V10))) -> 0.21459624 | X10: =RAND() -> 0.95278107 | Y10: =IF(X10<=('Ejercicio 3 - TIR'!$D$26-'Ejercicio 3 - TIR'!$C$26)/('Ejercicio 3 - TIR'!$E$26-'Ejercicio 3 - TIR'!$C$26),'Ejercicio 3 - TIR'!$C$26+SQRT(('Ejercicio 3 - TIR'!$E$26-'Ejercicio 3 - TIR'!$C$26)*('Ejercicio 3 - TIR'!$D$26-'Ejercicio 3 - TIR'!$C$26)*X10),'Ejercicio 3 - TIR'!$E$26-SQRT(('Ejercicio 3 - TIR'!$E$26-'Ejercicio 3 - TIR'!$C$26)*('Ejercicio 3 - TIR'!$E$26-'Ejercicio 3 - TIR'!$D$26)*(1-X10))) -> 0.26403184 | Z10: =(1+Q10) -> 1.1620747 | AA10: =Z10*(1+S10) -> 1.3380435 | AB10: =AA10*(1+U10) -> 1.6126871 | AC10: =AB10*(1+W10) -> 1.9587637 | AD10: =AC10*(1+Y10) -> 2.4759397 | AE10: =E10*Q10 -> 4523.7548 | AF10: =AE10*(1+S10) -> 5208.7706 | AG10: =AF10*(1+U10) -> 6277.9107 | AH10: =AG10*(1+W10) -> 7625.1268 | AI10: =AH10*(1+Y10) -> 9638.403 | AJ10: =G10*Z10 -> 40525.429 | AK10: =I10*AA10 -> 55584.191 | AL10: =K10*AB10 -> 69396.052 | AM10: =M10*AC10 -> 82893.756 | AN10: =O10*AD10 -> 93228.841 | AO10: =C10/'Ejercicio 3 - TIR'!$D$7 -> 13451.494 | AP10: =AJ10-AO10 -> 27073.935 | AQ10: =AK10-AO10 -> 42132.698 | AR10: =AL10-AO10 -> 55944.558 | AS10: =AM10-AO10 -> 69442.262 | AT10: =AN10-AO10 -> 79777.347 | AU10: =AP10*'Ejercicio 3 - TIR'!$D$5 -> 13536.968 | AV10: =AQ10*'Ejercicio 3 - TIR'!$D$5 -> 21066.349 | AW10: =AR10*'Ejercicio 3 - TIR'!$D$5 -> 27972.279 | AX10: =AS10*'Ejercicio 3 - TIR'!$D$5 -> 34721.131 | AY10: =AT10*'Ejercicio 3 - TIR'!$D$5 -> 39888.674 | AZ10: =AJ10-AU10-AE10 -> 22464.707 | BA10: =AK10-AV10-AF10 -> 29309.072 | BB10: =AL10-AW10-AG10 -> 35145.862 | BC10: =AM10-AX10-AH10 -> 40547.498 | BD10: =AN10-AY10-AI10 -> 43701.764 | BE10: =AZ10/Z10 -> 19331.551 | BF10: =BA10/AA10 -> 21904.425 | BG10: =BB10/AB10 -> 21793.354 | BH10: =BC10/AC10 -> 20700.556 | BI10: =BD10/AD10 -> 17650.577 | BJ10: =E10*AD10 -> 69107.298 | BK10: =0.2*C10*AD10 -> 33305.088 | BL10: =BJ10+BK10 -> 102412.39 | BM10: =BK10*'Ejercicio 3 - TIR'!$D$5 -> 16652.544 | BN10: =BL10-BM10 -> 85759.842 | BO10: =BN10/AD10 -> 34637.29 | BP10: =-(C10+E10) -> -95169.012 | BQ10: =BE10 -> 19331.551 | BR10: =BF10 -> 21904.425 | BS10: =BG10 -> 21793.354 | BT10: =BH10 -> 20700.556 | BU10: =BI10+BO10 -> 52287.867 | BV10: =IFERROR(IRR(BP10:BU10,0.1),NA())*100 -> 11.225087
A11: 10 | B11: =RAND() -> 0.26430426 | C11: =IF(B11<=('Ejercicio 3 - TIR'!$D$13-'Ejercicio 3 - TIR'!$C$13)/('Ejercicio 3 - TIR'!$E$13-'Ejercicio 3 - TIR'!$C$13),'Ejercicio 3 - TIR'!$C$13+SQRT(('Ejercicio 3 - TIR'!$E$13-'Ejercicio 3 - TIR'!$C$13)*('Ejercicio 3 - TIR'!$D$13-'Ejercicio 3 - TIR'!$C$13)*B11),'Ejercicio 3 - TIR'!$E$13-SQRT(('Ejercicio 3 - TIR'!$E$13-'Ejercicio 3 - TIR'!$C$13)*('Ejercicio 3 - TIR'!$E$13-'Ejercicio 3 - TIR'!$D$13)*(1-B11))) -> 70287.462 | D11: =RAND() -> 0.32240061 | E11: =IF(D11<=('Ejercicio 3 - TIR'!$D$14-'Ejercicio 3 - TIR'!$C$14)/('Ejercicio 3 - TIR'!$E$14-'Ejercicio 3 - TIR'!$C$14),'Ejercicio 3 - TIR'!$C$14+SQRT(('Ejercicio 3 - TIR'!$E$14-'Ejercicio 3 - TIR'!$C$14)*('Ejercicio 3 - TIR'!$D$14-'Ejercicio 3 - TIR'!$C$14)*D11),'Ejercicio 3 - TIR'!$E$14-SQRT(('Ejercicio 3 - TIR'!$E$14-'Ejercicio 3 - TIR'!$C$14)*('Ejercicio 3 - TIR'!$E$14-'Ejercicio 3 - TIR'!$D$14)*(1-D11))) -> 29917.321 | F11: =RAND() -> 0.77466222 | G11: =IF(F11<=('Ejercicio 3 - TIR'!$D$18-'Ejercicio 3 - TIR'!$C$18)/('Ejercicio 3 - TIR'!$E$18-'Ejercicio 3 - TIR'!$C$18),'Ejercicio 3 - TIR'!$C$18+SQRT(('Ejercicio 3 - TIR'!$E$18-'Ejercicio 3 - TIR'!$C$18)*('Ejercicio 3 - TIR'!$D$18-'Ejercicio 3 - TIR'!$C$18)*F11),'Ejercicio 3 - TIR'!$E$18-SQRT(('Ejercicio 3 - TIR'!$E$18-'Ejercicio 3 - TIR'!$C$18)*('Ejercicio 3 - TIR'!$E$18-'Ejercicio 3 - TIR'!$D$18)*(1-F11))) -> 40888.999 | H11: =RAND() -> 0.38218474 | I11: =IF(H11<=('Ejercicio 3 - TIR'!$D$18-'Ejercicio 3 - TIR'!$C$18)/('Ejercicio 3 - TIR'!$E$18-'Ejercicio 3 - TIR'!$C$18),'Ejercicio 3 - TIR'!$C$18+SQRT(('Ejercicio 3 - TIR'!$E$18-'Ejercicio 3 - TIR'!$C$18)*('Ejercicio 3 - TIR'!$D$18-'Ejercicio 3 - TIR'!$C$18)*H11),'Ejercicio 3 - TIR'!$E$18-SQRT(('Ejercicio 3 - TIR'!$E$18-'Ejercicio 3 - TIR'!$C$18)*('Ejercicio 3 - TIR'!$E$18-'Ejercicio 3 - TIR'!$D$18)*(1-H11))) -> 37571.506 | J11: =RAND() -> 0.21181723 | K11: =IF(J11<=('Ejercicio 3 - TIR'!$D$18-'Ejercicio 3 - TIR'!$C$18)/('Ejercicio 3 - TIR'!$E$18-'Ejercicio 3 - TIR'!$C$18),'Ejercicio 3 - TIR'!$C$18+SQRT(('Ejercicio 3 - TIR'!$E$18-'Ejercicio 3 - TIR'!$C$18)*('Ejercicio 3 - TIR'!$D$18-'Ejercicio 3 - TIR'!$C$18)*J11),'Ejercicio 3 - TIR'!$E$18-SQRT(('Ejercicio 3 - TIR'!$E$18-'Ejercicio 3 - TIR'!$C$18)*('Ejercicio 3 - TIR'!$E$18-'Ejercicio 3 - TIR'!$D$18)*(1-J11))) -> 35636.718 | L11: =RAND() -> 0.10352639 | M11: =IF(L11<=('Ejercicio 3 - TIR'!$D$18-'Ejercicio 3 - TIR'!$C$18)/('Ejercicio 3 - TIR'!$E$18-'Ejercicio 3 - TIR'!$C$18),'Ejercicio 3 - TIR'!$C$18+SQRT(('Ejercicio 3 - TIR'!$E$18-'Ejercicio 3 - TIR'!$C$18)*('Ejercicio 3 - TIR'!$D$18-'Ejercicio 3 - TIR'!$C$18)*L11),'Ejercicio 3 - TIR'!$E$18-SQRT(('Ejercicio 3 - TIR'!$E$18-'Ejercicio 3 - TIR'!$C$18)*('Ejercicio 3 - TIR'!$E$18-'Ejercicio 3 - TIR'!$D$18)*(1-L11))) -> 33940.68 | N11: =RAND() -> 0.94250949 | O11: =IF(N11<=('Ejercicio 3 - TIR'!$D$18-'Ejercicio 3 - TIR'!$C$18)/('Ejercicio 3 - TIR'!$E$18-'Ejercicio 3 - TIR'!$C$18),'Ejercicio 3 - TIR'!$C$18+SQRT(('Ejercicio 3 - TIR'!$E$18-'Ejercicio 3 - TIR'!$C$18)*('Ejercicio 3 - TIR'!$D$18-'Ejercicio 3 - TIR'!$C$18)*N11),'Ejercicio 3 - TIR'!$E$18-SQRT(('Ejercicio 3 - TIR'!$E$18-'Ejercicio 3 - TIR'!$C$18)*('Ejercicio 3 - TIR'!$E$18-'Ejercicio 3 - TIR'!$D$18)*(1-N11))) -> 42923.515 | P11: =RAND() -> 0.59152438 | Q11: =IF(P11<=('Ejercicio 3 - TIR'!$D$22-'Ejercicio 3 - TIR'!$C$22)/('Ejercicio 3 - TIR'!$E$22-'Ejercicio 3 - TIR'!$C$22),'Ejercicio 3 - TIR'!$C$22+SQRT(('Ejercicio 3 - TIR'!$E$22-'Ejercicio 3 - TIR'!$C$22)*('Ejercicio 3 - TIR'!$D$22-'Ejercicio 3 - TIR'!$C$22)*P11),'Ejercicio 3 - TIR'!$E$22-SQRT(('Ejercicio 3 - TIR'!$E$22-'Ejercicio 3 - TIR'!$C$22)*('Ejercicio 3 - TIR'!$E$22-'Ejercicio 3 - TIR'!$D$22)*(1-P11))) -> 0.15288439 | R11: =RAND() -> 0.58890579 | S11: =IF(R11<=('Ejercicio 3 - TIR'!$D$23-'Ejercicio 3 - TIR'!$C$23)/('Ejercicio 3 - TIR'!$E$23-'Ejercicio 3 - TIR'!$C$23),'Ejercicio 3 - TIR'!$C$23+SQRT(('Ejercicio 3 - TIR'!$E$23-'Ejercicio 3 - TIR'!$C$23)*('Ejercicio 3 - TIR'!$D$23-'Ejercicio 3 - TIR'!$C$23)*R11),'Ejercicio 3 - TIR'!$E$23-SQRT(('Ejercicio 3 - TIR'!$E$23-'Ejercicio 3 - TIR'!$C$23)*('Ejercicio 3 - TIR'!$E$23-'Ejercicio 3 - TIR'!$D$23)*(1-R11))) -> 0.15279762 | T11: =RAND() -> 0.96773623 | U11: =IF(T11<=('Ejercicio 3 - TIR'!$D$24-'Ejercicio 3 - TIR'!$C$24)/('Ejercicio 3 - TIR'!$E$24-'Ejercicio 3 - TIR'!$C$24),'Ejercicio 3 - TIR'!$C$24+SQRT(('Ejercicio 3 - TIR'!$E$24-'Ejercicio 3 - TIR'!$C$24)*('Ejercicio 3 - TIR'!$D$24-'Ejercicio 3 - TIR'!$C$24)*T11),'Ejercicio 3 - TIR'!$E$24-SQRT(('Ejercicio 3 - TIR'!$E$24-'Ejercicio 3 - TIR'!$C$24)*('Ejercicio 3 - TIR'!$E$24-'Ejercicio 3 - TIR'!$D$24)*(1-T11))) -> 0.21049534 | V11: =RAND() -> 0.80164043 | W11: =IF(V11<=('Ejercicio 3 - TIR'!$D$25-'Ejercicio 3 - TIR'!$C$25)/('Ejercicio 3 - TIR'!$E$25-'Ejercicio 3 - TIR'!$C$25),'Ejercicio 3 - TIR'!$C$25+SQRT(('Ejercicio 3 - TIR'!$E$25-'Ejercicio 3 - TIR'!$C$25)*('Ejercicio 3 - TIR'!$D$25-'Ejercicio 3 - TIR'!$C$25)*V11),'Ejercicio 3 - TIR'!$E$25-SQRT(('Ejercicio 3 - TIR'!$E$25-'Ejercicio 3 - TIR'!$C$25)*('Ejercicio 3 - TIR'!$E$25-'Ejercicio 3 - TIR'!$D$25)*(1-V11))) -> 0.22365121 | X11: =RAND() -> 0.33267218 | Y11: =IF(X11<=('Ejercicio 3 - TIR'!$D$26-'Ejercicio 3 - TIR'!$C$26)/('Ejercicio 3 - TIR'!$E$26-'Ejercicio 3 - TIR'!$C$26),'Ejercicio 3 - TIR'!$C$26+SQRT(('Ejercicio 3 - TIR'!$E$26-'Ejercicio 3 - TIR'!$C$26)*('Ejercicio 3 - TIR'!$D$26-'Ejercicio 3 - TIR'!$C$26)*X11),'Ejercicio 3 - TIR'!$E$26-SQRT(('Ejercicio 3 - TIR'!$E$26-'Ejercicio 3 - TIR'!$C$26)*('Ejercicio 3 - TIR'!$E$26-'Ejercicio 3 - TIR'!$D$26)*(1-X11))) -> 0.21997023 | Z11: =(1+Q11) -> 1.1528844 | AA11: =Z11*(1+S11) -> 1.3290424 | AB11: =AA11*(1+U11) -> 1.6087996 | AC11: =AB11*(1+W11) -> 1.9686096 | AD11: =AC11*(1+Y11) -> 2.4016451 | AE11: =E11*Q11 -> 4573.8915 | AF11: =AE11*(1+S11) -> 5272.7712 | AG11: =AF11*(1+U11) -> 6382.665 | AH11: =AG11*(1+W11) -> 7810.1557 | AI11: =AH11*(1+Y11) -> 9528.1575 | AJ11: =G11*Z11 -> 47140.288 | AK11: =I11*AA11 -> 49934.125 | AL11: =K11*AB11 -> 57332.337 | AM11: =M11*AC11 -> 66815.948 | AN11: =O11*AD11 -> 103087.05 | AO11: =C11/'Ejercicio 3 - TIR'!$D$7 -> 14057.493 | AP11: =AJ11-AO11 -> 33082.796 | AQ11: =AK11-AO11 -> 35876.632 | AR11: =AL11-AO11 -> 43274.845 | AS11: =AM11-AO11 -> 52758.456 | AT11: =AN11-AO11 -> 89029.558 | AU11: =AP11*'Ejercicio 3 - TIR'!$D$5 -> 16541.398 | AV11: =AQ11*'Ejercicio 3 - TIR'!$D$5 -> 17938.316 | AW11: =AR11*'Ejercicio 3 - TIR'!$D$5 -> 21637.422 | AX11: =AS11*'Ejercicio 3 - TIR'!$D$5 -> 26379.228 | AY11: =AT11*'Ejercicio 3 - TIR'!$D$5 -> 44514.779 | AZ11: =AJ11-AU11-AE11 -> 26024.999 | BA11: =AK11-AV11-AF11 -> 26723.037 | BB11: =AL11-AW11-AG11 -> 29312.25 | BC11: =AM11-AX11-AH11 -> 32626.565 | BD11: =AN11-AY11-AI11 -> 49044.114 | BE11: =AZ11/Z11 -> 22573.815 | BF11: =BA11/AA11 -> 20106.987 | BG11: =BB11/AB11 -> 18219.951 | BH11: =BC11/AC11 -> 16573.405 | BI11: =BD11/AD11 -> 20421.05 | BJ11: =E11*AD11 -> 71850.788 | BK11: =0.2*C11*AD11 -> 33761.108 | BL11: =BJ11+BK11 -> 105611.9 | BM11: =BK11*'Ejercicio 3 - TIR'!$D$5 -> 16880.554 | BN11: =BL11-BM11 -> 88731.342 | BO11: =BN11/AD11 -> 36946.067 | BP11: =-(C11+E11) -> -100204.78 | BQ11: =BE11 -> 22573.815 | BR11: =BF11 -> 20106.987 | BS11: =BG11 -> 18219.951 | BT11: =BH11 -> 16573.405 | BU11: =BI11+BO11 -> 57367.117 | BV11: =IFERROR(IRR(BP11:BU11,0.1),NA())*100 -> 9.1735748
A12: 11 | B12: =RAND() -> 0.59010196 | C12: =IF(B12<=('Ejercicio 3 - TIR'!$D$13-'Ejercicio 3 - TIR'!$C$13)/('Ejercicio 3 - TIR'!$E$13-'Ejercicio 3 - TIR'!$C$13),'Ejercicio 3 - TIR'!$C$13+SQRT(('Ejercicio 3 - TIR'!$E$13-'Ejercicio 3 - TIR'!$C$13)*('Ejercicio 3 - TIR'!$D$13-'Ejercicio 3 - TIR'!$C$13)*B12),'Ejercicio 3 - TIR'!$E$13-SQRT(('Ejercicio 3 - TIR'!$E$13-'Ejercicio 3 - TIR'!$C$13)*('Ejercicio 3 - TIR'!$E$13-'Ejercicio 3 - TIR'!$D$13)*(1-B12))) -> 77821.685 | D12: =RAND() -> 0.25873824 | E12: =IF(D12<=('Ejercicio 3 - TIR'!$D$14-'Ejercicio 3 - TIR'!$C$14)/('Ejercicio 3 - TIR'!$E$14-'Ejercicio 3 - TIR'!$C$14),'Ejercicio 3 - TIR'!$C$14+SQRT(('Ejercicio 3 - TIR'!$E$14-'Ejercicio 3 - TIR'!$C$14)*('Ejercicio 3 - TIR'!$D$14-'Ejercicio 3 - TIR'!$C$14)*D12),'Ejercicio 3 - TIR'!$E$14-SQRT(('Ejercicio 3 - TIR'!$E$14-'Ejercicio 3 - TIR'!$C$14)*('Ejercicio 3 - TIR'!$E$14-'Ejercicio 3 - TIR'!$D$14)*(1-D12))) -> 29405.152 | F12: =RAND() -> 0.33151181 | G12: =IF(F12<=('Ejercicio 3 - TIR'!$D$18-'Ejercicio 3 - TIR'!$C$18)/('Ejercicio 3 - TIR'!$E$18-'Ejercicio 3 - TIR'!$C$18),'Ejercicio 3 - TIR'!$C$18+SQRT(('Ejercicio 3 - TIR'!$E$18-'Ejercicio 3 - TIR'!$C$18)*('Ejercicio 3 - TIR'!$D$18-'Ejercicio 3 - TIR'!$C$18)*F12),'Ejercicio 3 - TIR'!$E$18-SQRT(('Ejercicio 3 - TIR'!$E$18-'Ejercicio 3 - TIR'!$C$18)*('Ejercicio 3 - TIR'!$E$18-'Ejercicio 3 - TIR'!$D$18)*(1-F12))) -> 37051.721 | H12: =RAND() -> 0.81638585 | I12: =IF(H12<=('Ejercicio 3 - TIR'!$D$18-'Ejercicio 3 - TIR'!$C$18)/('Ejercicio 3 - TIR'!$E$18-'Ejercicio 3 - TIR'!$C$18),'Ejercicio 3 - TIR'!$C$18+SQRT(('Ejercicio 3 - TIR'!$E$18-'Ejercicio 3 - TIR'!$C$18)*('Ejercicio 3 - TIR'!$D$18-'Ejercicio 3 - TIR'!$C$18)*H12),'Ejercicio 3 - TIR'!$E$18-SQRT(('Ejercicio 3 - TIR'!$E$18-'Ejercicio 3 - TIR'!$C$18)*('Ejercicio 3 - TIR'!$E$18-'Ejercicio 3 - TIR'!$D$18)*(1-H12))) -> 41289.062 | J12: =RAND() -> 0.3977918 | K12: =IF(J12<=('Ejercicio 3 - TIR'!$D$18-'Ejercicio 3 - TIR'!$C$18)/('Ejercicio 3 - TIR'!$E$18-'Ejercicio 3 - TIR'!$C$18),'Ejercicio 3 - TIR'!$C$18+SQRT(('Ejercicio 3 - TIR'!$E$18-'Ejercicio 3 - TIR'!$C$18)*('Ejercicio 3 - TIR'!$D$18-'Ejercicio 3 - TIR'!$C$18)*J12),'Ejercicio 3 - TIR'!$E$18-SQRT(('Ejercicio 3 - TIR'!$E$18-'Ejercicio 3 - TIR'!$C$18)*('Ejercicio 3 - TIR'!$E$18-'Ejercicio 3 - TIR'!$D$18)*(1-J12))) -> 37724.556 | L12: =RAND() -> 0.96251858 | M12: =IF(L12<=('Ejercicio 3 - TIR'!$D$18-'Ejercicio 3 - TIR'!$C$18)/('Ejercicio 3 - TIR'!$E$18-'Ejercicio 3 - TIR'!$C$18),'Ejercicio 3 - TIR'!$C$18+SQRT(('Ejercicio 3 - TIR'!$E$18-'Ejercicio 3 - TIR'!$C$18)*('Ejercicio 3 - TIR'!$D$18-'Ejercicio 3 - TIR'!$C$18)*L12),'Ejercicio 3 - TIR'!$E$18-SQRT(('Ejercicio 3 - TIR'!$E$18-'Ejercicio 3 - TIR'!$C$18)*('Ejercicio 3 - TIR'!$E$18-'Ejercicio 3 - TIR'!$D$18)*(1-L12))) -> 43323.364 | N12: =RAND() -> 0.78044825 | O12: =IF(N12<=('Ejercicio 3 - TIR'!$D$18-'Ejercicio 3 - TIR'!$C$18)/('Ejercicio 3 - TIR'!$E$18-'Ejercicio 3 - TIR'!$C$18),'Ejercicio 3 - TIR'!$C$18+SQRT(('Ejercicio 3 - TIR'!$E$18-'Ejercicio 3 - TIR'!$C$18)*('Ejercicio 3 - TIR'!$D$18-'Ejercicio 3 - TIR'!$C$18)*N12),'Ejercicio 3 - TIR'!$E$18-SQRT(('Ejercicio 3 - TIR'!$E$18-'Ejercicio 3 - TIR'!$C$18)*('Ejercicio 3 - TIR'!$E$18-'Ejercicio 3 - TIR'!$D$18)*(1-N12))) -> 40942.121 | P12: =RAND() -> 0.16435655 | Q12: =IF(P12<=('Ejercicio 3 - TIR'!$D$22-'Ejercicio 3 - TIR'!$C$22)/('Ejercicio 3 - TIR'!$E$22-'Ejercicio 3 - TIR'!$C$22),'Ejercicio 3 - TIR'!$C$22+SQRT(('Ejercicio 3 - TIR'!$E$22-'Ejercicio 3 - TIR'!$C$22)*('Ejercicio 3 - TIR'!$D$22-'Ejercicio 3 - TIR'!$C$22)*P12),'Ejercicio 3 - TIR'!$E$22-SQRT(('Ejercicio 3 - TIR'!$E$22-'Ejercicio 3 - TIR'!$C$22)*('Ejercicio 3 - TIR'!$E$22-'Ejercicio 3 - TIR'!$D$22)*(1-P12))) -> 0.13720005 | R12: =RAND() -> 0.68299712 | S12: =IF(R12<=('Ejercicio 3 - TIR'!$D$23-'Ejercicio 3 - TIR'!$C$23)/('Ejercicio 3 - TIR'!$E$23-'Ejercicio 3 - TIR'!$C$23),'Ejercicio 3 - TIR'!$C$23+SQRT(('Ejercicio 3 - TIR'!$E$23-'Ejercicio 3 - TIR'!$C$23)*('Ejercicio 3 - TIR'!$D$23-'Ejercicio 3 - TIR'!$C$23)*R12),'Ejercicio 3 - TIR'!$E$23-SQRT(('Ejercicio 3 - TIR'!$E$23-'Ejercicio 3 - TIR'!$C$23)*('Ejercicio 3 - TIR'!$E$23-'Ejercicio 3 - TIR'!$D$23)*(1-R12))) -> 0.15611266 | T12: =RAND() -> 0.25168807 | U12: =IF(T12<=('Ejercicio 3 - TIR'!$D$24-'Ejercicio 3 - TIR'!$C$24)/('Ejercicio 3 - TIR'!$E$24-'Ejercicio 3 - TIR'!$C$24),'Ejercicio 3 - TIR'!$C$24+SQRT(('Ejercicio 3 - TIR'!$E$24-'Ejercicio 3 - TIR'!$C$24)*('Ejercicio 3 - TIR'!$D$24-'Ejercicio 3 - TIR'!$C$24)*T12),'Ejercicio 3 - TIR'!$E$24-SQRT(('Ejercicio 3 - TIR'!$E$24-'Ejercicio 3 - TIR'!$C$24)*('Ejercicio 3 - TIR'!$E$24-'Ejercicio 3 - TIR'!$D$24)*(1-T12))) -> 0.17299011 | V12: =RAND() -> 0.67461999 | W12: =IF(V12<=('Ejercicio 3 - TIR'!$D$25-'Ejercicio 3 - TIR'!$C$25)/('Ejercicio 3 - TIR'!$E$25-'Ejercicio 3 - TIR'!$C$25),'Ejercicio 3 - TIR'!$C$25+SQRT(('Ejercicio 3 - TIR'!$E$25-'Ejercicio 3 - TIR'!$C$25)*('Ejercicio 3 - TIR'!$D$25-'Ejercicio 3 - TIR'!$C$25)*V12),'Ejercicio 3 - TIR'!$E$25-SQRT(('Ejercicio 3 - TIR'!$E$25-'Ejercicio 3 - TIR'!$C$25)*('Ejercicio 3 - TIR'!$E$25-'Ejercicio 3 - TIR'!$D$25)*(1-V12))) -> 0.21625344 | X12: =RAND() -> 0.46310365 | Y12: =IF(X12<=('Ejercicio 3 - TIR'!$D$26-'Ejercicio 3 - TIR'!$C$26)/('Ejercicio 3 - TIR'!$E$26-'Ejercicio 3 - TIR'!$C$26),'Ejercicio 3 - TIR'!$C$26+SQRT(('Ejercicio 3 - TIR'!$E$26-'Ejercicio 3 - TIR'!$C$26)*('Ejercicio 3 - TIR'!$D$26-'Ejercicio 3 - TIR'!$C$26)*X12),'Ejercicio 3 - TIR'!$E$26-SQRT(('Ejercicio 3 - TIR'!$E$26-'Ejercicio 3 - TIR'!$C$26)*('Ejercicio 3 - TIR'!$E$26-'Ejercicio 3 - TIR'!$D$26)*(1-X12))) -> 0.22615541 | Z12: =(1+Q12) -> 1.1372001 | AA12: =Z12*(1+S12) -> 1.3147314 | AB12: =AA12*(1+U12) -> 1.5421669 | AC12: =AB12*(1+W12) -> 1.8756658 | AD12: =AC12*(1+Y12) -> 2.2998578 | AE12: =E12*Q12 -> 4034.3885 | AF12: =AE12*(1+S12) -> 4664.2076 | AG12: =AF12*(1+U12) -> 5471.0693 | AH12: =AG12*(1+W12) -> 6654.2069 | AI12: =AH12*(1+Y12) -> 8159.0918 | AJ12: =G12*Z12 -> 42135.219 | AK12: =I12*AA12 -> 54284.025 | AL12: =K12*AB12 -> 58177.562 | AM12: =M12*AC12 -> 81260.153 | AN12: =O12*AD12 -> 94161.055 | AO12: =C12/'Ejercicio 3 - TIR'!$D$7 -> 15564.337 | AP12: =AJ12-AO12 -> 26570.882 | AQ12: =AK12-AO12 -> 38719.688 | AR12: =AL12-AO12 -> 42613.225 | AS12: =AM12-AO12 -> 65695.816 | AT12: =AN12-AO12 -> 78596.718 | AU12: =AP12*'Ejercicio 3 - TIR'!$D$5 -> 13285.441 | AV12: =AQ12*'Ejercicio 3 - TIR'!$D$5 -> 19359.844 | AW12: =AR12*'Ejercicio 3 - TIR'!$D$5 -> 21306.612 | AX12: =AS12*'Ejercicio 3 - TIR'!$D$5 -> 32847.908 | AY12: =AT12*'Ejercicio 3 - TIR'!$D$5 -> 39298.359 | AZ12: =AJ12-AU12-AE12 -> 24815.39 | BA12: =AK12-AV12-AF12 -> 30259.974 | BB12: =AL12-AW12-AG12 -> 31399.88 | BC12: =AM12-AX12-AH12 -> 41758.038 | BD12: =AN12-AY12-AI12 -> 46703.604 | BE12: =AZ12/Z12 -> 21821.481 | BF12: =BA12/AA12 -> 23016.088 | BG12: =BB12/AB12 -> 20360.883 | BH12: =BC12/AC12 -> 22263.048 | BI12: =BD12/AD12 -> 20307.171 | BJ12: =E12*AD12 -> 67627.668 | BK12: =0.2*C12*AD12 -> 35795.761 | BL12: =BJ12+BK12 -> 103423.43 | BM12: =BK12*'Ejercicio 3 - TIR'!$D$5 -> 17897.881 | BN12: =BL12-BM12 -> 85525.549 | BO12: =BN12/AD12 -> 37187.321 | BP12: =-(C12+E12) -> -107226.84 | BQ12: =BE12 -> 21821.481 | BR12: =BF12 -> 23016.088 | BS12: =BG12 -> 20360.883 | BT12: =BH12 -> 22263.048 | BU12: =BI12+BO12 -> 57494.492 | BV12: =IFERROR(IRR(BP12:BU12,0.1),NA())*100 -> 9.3167318
A13: 12 | B13: =RAND() -> 0.7993532 | C13: =IF(B13<=('Ejercicio 3 - TIR'!$D$13-'Ejercicio 3 - TIR'!$C$13)/('Ejercicio 3 - TIR'!$E$13-'Ejercicio 3 - TIR'!$C$13),'Ejercicio 3 - TIR'!$C$13+SQRT(('Ejercicio 3 - TIR'!$E$13-'Ejercicio 3 - TIR'!$C$13)*('Ejercicio 3 - TIR'!$D$13-'Ejercicio 3 - TIR'!$C$13)*B13),'Ejercicio 3 - TIR'!$E$13-SQRT(('Ejercicio 3 - TIR'!$E$13-'Ejercicio 3 - TIR'!$C$13)*('Ejercicio 3 - TIR'!$E$13-'Ejercicio 3 - TIR'!$D$13)*(1-B13))) -> 84483.036 | D13: =RAND() -> 0.96841544 | E13: =IF(D13<=('Ejercicio 3 - TIR'!$D$14-'Ejercicio 3 - TIR'!$C$14)/('Ejercicio 3 - TIR'!$E$14-'Ejercicio 3 - TIR'!$C$14),'Ejercicio 3 - TIR'!$C$14+SQRT(('Ejercicio 3 - TIR'!$E$14-'Ejercicio 3 - TIR'!$C$14)*('Ejercicio 3 - TIR'!$D$14-'Ejercicio 3 - TIR'!$C$14)*D13),'Ejercicio 3 - TIR'!$E$14-SQRT(('Ejercicio 3 - TIR'!$E$14-'Ejercicio 3 - TIR'!$C$14)*('Ejercicio 3 - TIR'!$E$14-'Ejercicio 3 - TIR'!$D$14)*(1-D13))) -> 37823.378 | F13: =RAND() -> 0.92899387 | G13: =IF(F13<=('Ejercicio 3 - TIR'!$D$18-'Ejercicio 3 - TIR'!$C$18)/('Ejercicio 3 - TIR'!$E$18-'Ejercicio 3 - TIR'!$C$18),'Ejercicio 3 - TIR'!$C$18+SQRT(('Ejercicio 3 - TIR'!$E$18-'Ejercicio 3 - TIR'!$C$18)*('Ejercicio 3 - TIR'!$D$18-'Ejercicio 3 - TIR'!$C$18)*F13),'Ejercicio 3 - TIR'!$E$18-SQRT(('Ejercicio 3 - TIR'!$E$18-'Ejercicio 3 - TIR'!$C$18)*('Ejercicio 3 - TIR'!$E$18-'Ejercicio 3 - TIR'!$D$18)*(1-F13))) -> 42692.304 | H13: =RAND() -> 0.39189488 | I13: =IF(H13<=('Ejercicio 3 - TIR'!$D$18-'Ejercicio 3 - TIR'!$C$18)/('Ejercicio 3 - TIR'!$E$18-'Ejercicio 3 - TIR'!$C$18),'Ejercicio 3 - TIR'!$C$18+SQRT(('Ejercicio 3 - TIR'!$E$18-'Ejercicio 3 - TIR'!$C$18)*('Ejercicio 3 - TIR'!$D$18-'Ejercicio 3 - TIR'!$C$18)*H13),'Ejercicio 3 - TIR'!$E$18-SQRT(('Ejercicio 3 - TIR'!$E$18-'Ejercicio 3 - TIR'!$C$18)*('Ejercicio 3 - TIR'!$E$18-'Ejercicio 3 - TIR'!$D$18)*(1-H13))) -> 37667.088 | J13: =RAND() -> 0.44929146 | K13: =IF(J13<=('Ejercicio 3 - TIR'!$D$18-'Ejercicio 3 - TIR'!$C$18)/('Ejercicio 3 - TIR'!$E$18-'Ejercicio 3 - TIR'!$C$18),'Ejercicio 3 - TIR'!$C$18+SQRT(('Ejercicio 3 - TIR'!$E$18-'Ejercicio 3 - TIR'!$C$18)*('Ejercicio 3 - TIR'!$D$18-'Ejercicio 3 - TIR'!$C$18)*J13),'Ejercicio 3 - TIR'!$E$18-SQRT(('Ejercicio 3 - TIR'!$E$18-'Ejercicio 3 - TIR'!$C$18)*('Ejercicio 3 - TIR'!$E$18-'Ejercicio 3 - TIR'!$D$18)*(1-J13))) -> 38209.368 | L13: =RAND() -> 0.06996538 | M13: =IF(L13<=('Ejercicio 3 - TIR'!$D$18-'Ejercicio 3 - TIR'!$C$18)/('Ejercicio 3 - TIR'!$E$18-'Ejercicio 3 - TIR'!$C$18),'Ejercicio 3 - TIR'!$C$18+SQRT(('Ejercicio 3 - TIR'!$E$18-'Ejercicio 3 - TIR'!$C$18)*('Ejercicio 3 - TIR'!$D$18-'Ejercicio 3 - TIR'!$C$18)*L13),'Ejercicio 3 - TIR'!$E$18-SQRT(('Ejercicio 3 - TIR'!$E$18-'Ejercicio 3 - TIR'!$C$18)*('Ejercicio 3 - TIR'!$E$18-'Ejercicio 3 - TIR'!$D$18)*(1-L13))) -> 33239.569 | N13: =RAND() -> 0.75964937 | O13: =IF(N13<=('Ejercicio 3 - TIR'!$D$18-'Ejercicio 3 - TIR'!$C$18)/('Ejercicio 3 - TIR'!$E$18-'Ejercicio 3 - TIR'!$C$18),'Ejercicio 3 - TIR'!$C$18+SQRT(('Ejercicio 3 - TIR'!$E$18-'Ejercicio 3 - TIR'!$C$18)*('Ejercicio 3 - TIR'!$D$18-'Ejercicio 3 - TIR'!$C$18)*N13),'Ejercicio 3 - TIR'!$E$18-SQRT(('Ejercicio 3 - TIR'!$E$18-'Ejercicio 3 - TIR'!$C$18)*('Ejercicio 3 - TIR'!$E$18-'Ejercicio 3 - TIR'!$D$18)*(1-N13))) -> 40754.261 | P13: =RAND() -> 0.9294381 | Q13: =IF(P13<=('Ejercicio 3 - TIR'!$D$22-'Ejercicio 3 - TIR'!$C$22)/('Ejercicio 3 - TIR'!$E$22-'Ejercicio 3 - TIR'!$C$22),'Ejercicio 3 - TIR'!$C$22+SQRT(('Ejercicio 3 - TIR'!$E$22-'Ejercicio 3 - TIR'!$C$22)*('Ejercicio 3 - TIR'!$D$22-'Ejercicio 3 - TIR'!$C$22)*P13),'Ejercicio 3 - TIR'!$E$22-SQRT(('Ejercicio 3 - TIR'!$E$22-'Ejercicio 3 - TIR'!$C$22)*('Ejercicio 3 - TIR'!$E$22-'Ejercicio 3 - TIR'!$D$22)*(1-P13))) -> 0.16873007 | R13: =RAND() -> 0.76523709 | S13: =IF(R13<=('Ejercicio 3 - TIR'!$D$23-'Ejercicio 3 - TIR'!$C$23)/('Ejercicio 3 - TIR'!$E$23-'Ejercicio 3 - TIR'!$C$23),'Ejercicio 3 - TIR'!$C$23+SQRT(('Ejercicio 3 - TIR'!$E$23-'Ejercicio 3 - TIR'!$C$23)*('Ejercicio 3 - TIR'!$D$23-'Ejercicio 3 - TIR'!$C$23)*R13),'Ejercicio 3 - TIR'!$E$23-SQRT(('Ejercicio 3 - TIR'!$E$23-'Ejercicio 3 - TIR'!$C$23)*('Ejercicio 3 - TIR'!$E$23-'Ejercicio 3 - TIR'!$D$23)*(1-R13))) -> 0.15944341 | T13: =RAND() -> 0.6412174 | U13: =IF(T13<=('Ejercicio 3 - TIR'!$D$24-'Ejercicio 3 - TIR'!$C$24)/('Ejercicio 3 - TIR'!$E$24-'Ejercicio 3 - TIR'!$C$24),'Ejercicio 3 - TIR'!$C$24+SQRT(('Ejercicio 3 - TIR'!$E$24-'Ejercicio 3 - TIR'!$C$24)*('Ejercicio 3 - TIR'!$D$24-'Ejercicio 3 - TIR'!$C$24)*T13),'Ejercicio 3 - TIR'!$E$24-SQRT(('Ejercicio 3 - TIR'!$E$24-'Ejercicio 3 - TIR'!$C$24)*('Ejercicio 3 - TIR'!$E$24-'Ejercicio 3 - TIR'!$D$24)*(1-T13))) -> 0.18830471 | V13: =RAND() -> 0.37024597 | W13: =IF(V13<=('Ejercicio 3 - TIR'!$D$25-'Ejercicio 3 - TIR'!$C$25)/('Ejercicio 3 - TIR'!$E$25-'Ejercicio 3 - TIR'!$C$25),'Ejercicio 3 - TIR'!$C$25+SQRT(('Ejercicio 3 - TIR'!$E$25-'Ejercicio 3 - TIR'!$C$25)*('Ejercicio 3 - TIR'!$D$25-'Ejercicio 3 - TIR'!$C$25)*V13),'Ejercicio 3 - TIR'!$E$25-SQRT(('Ejercicio 3 - TIR'!$E$25-'Ejercicio 3 - TIR'!$C$25)*('Ejercicio 3 - TIR'!$E$25-'Ejercicio 3 - TIR'!$D$25)*(1-V13))) -> 0.20305174 | X13: =RAND() -> 0.83425948 | Y13: =IF(X13<=('Ejercicio 3 - TIR'!$D$26-'Ejercicio 3 - TIR'!$C$26)/('Ejercicio 3 - TIR'!$E$26-'Ejercicio 3 - TIR'!$C$26),'Ejercicio 3 - TIR'!$C$26+SQRT(('Ejercicio 3 - TIR'!$E$26-'Ejercicio 3 - TIR'!$C$26)*('Ejercicio 3 - TIR'!$D$26-'Ejercicio 3 - TIR'!$C$26)*X13),'Ejercicio 3 - TIR'!$E$26-SQRT(('Ejercicio 3 - TIR'!$E$26-'Ejercicio 3 - TIR'!$C$26)*('Ejercicio 3 - TIR'!$E$26-'Ejercicio 3 - TIR'!$D$26)*(1-X13))) -> 0.25008347 | Z13: =(1+Q13) -> 1.1687301 | AA13: =Z13*(1+S13) -> 1.3550764 | AB13: =AA13*(1+U13) -> 1.6102436 | AC13: =AB13*(1+W13) -> 1.9372064 | AD13: =AC13*(1+Y13) -> 2.4216697 | AE13: =E13*Q13 -> 6381.941 | AF13: =AE13*(1+S13) -> 7399.4995 | AG13: =AF13*(1+U13) -> 8792.8601 | AH13: =AG13*(1+W13) -> 10578.266 | AI13: =AH13*(1+Y13) -> 13223.715 | AJ13: =G13*Z13 -> 49895.78 | AK13: =I13*AA13 -> 51041.781 | AL13: =K13*AB13 -> 61526.392 | AM13: =M13*AC13 -> 64391.906 | AN13: =O13*AD13 -> 98693.36 | AO13: =C13/'Ejercicio 3 - TIR'!$D$7 -> 16896.607 | AP13: =AJ13-AO13 -> 32999.172 | AQ13: =AK13-AO13 -> 34145.173 | AR13: =AL13-AO13 -> 44629.784 | AS13: =AM13-AO13 -> 47495.299 | AT13: =AN13-AO13 -> 81796.753 | AU13: =AP13*'Ejercicio 3 - TIR'!$D$5 -> 16499.586 | AV13: =AQ13*'Ejercicio 3 - TIR'!$D$5 -> 17072.587 | AW13: =AR13*'Ejercicio 3 - TIR'!$D$5 -> 22314.892 | AX13: =AS13*'Ejercicio 3 - TIR'!$D$5 -> 23747.65 | AY13: =AT13*'Ejercicio 3 - TIR'!$D$5 -> 40898.377 | AZ13: =AJ13-AU13-AE13 -> 27014.252 | BA13: =AK13-AV13-AF13 -> 26569.694 | BB13: =AL13-AW13-AG13 -> 30418.639 | BC13: =AM13-AX13-AH13 -> 30065.991 | BD13: =AN13-AY13-AI13 -> 44571.269 | BE13: =AZ13/Z13 -> 23114.193 | BF13: =BA13/AA13 -> 19607.525 | BG13: =BB13/AB13 -> 18890.706 | BH13: =BC13/AC13 -> 15520.283 | BI13: =BD13/AD13 -> 18405.181 | BJ13: =E13*AD13 -> 91595.729 | BK13: =0.2*C13*AD13 -> 40918.002 | BL13: =BJ13+BK13 -> 132513.73 | BM13: =BK13*'Ejercicio 3 - TIR'!$D$5 -> 20459.001 | BN13: =BL13-BM13 -> 112054.73 | BO13: =BN13/AD13 -> 46271.681 | BP13: =-(C13+E13) -> -122306.41 | BQ13: =BE13 -> 23114.193 | BR13: =BF13 -> 19607.525 | BS13: =BG13 -> 18890.706 | BT13: =BH13 -> 15520.283 | BU13: =BI13+BO13 -> 64676.862 | BV13: =IFERROR(IRR(BP13:BU13,0.1),NA())*100 -> 4.3105149
... A1001: 1000 | B1001: =RAND() -> 0.97695829 | C1001: =IF(B1001<=('Ejercicio 3 - TIR'!$D$13-'Ejercicio 3 - TIR'!$C$13)/('Ejercicio 3 - TIR'!$E$13-'Ejercicio 3 - TIR'!$C$13),'Ejercicio 3 - TIR'!$C$13+SQRT(('Ejercicio 3 - TIR'!$E$13-'Ejercicio 3 - TIR'!$C$13)*('Ejercicio 3 - TIR'!$D$13-'Ejercicio 3 - TIR'!$C$13)*B1001),'Ejercicio 3 - TIR'!$E$13-SQRT(('Ejercicio 3 - TIR'!$E$13-'Ejercicio 3 - TIR'!$C$13)*('Ejercicio 3 - TIR'!$E$13-'Ejercicio 3 - TIR'!$D$13)*(1-B1001))) -> 94741.668 | D1001: =RAND() -> 0.40823982 | E1001: =IF(D1001<=('Ejercicio 3 - TIR'!$D$14-'Ejercicio 3 - TIR'!$C$14)/('Ejercicio 3 - TIR'!$E$14-'Ejercicio 3 - TIR'!$C$14),'Ejercicio 3 - TIR'!$C$14+SQRT(('Ejercicio 3 - TIR'!$E$14-'Ejercicio 3 - TIR'!$C$14)*('Ejercicio 3 - TIR'!$D$14-'Ejercicio 3 - TIR'!$C$14)*D1001),'Ejercicio 3 - TIR'!$E$14-SQRT(('Ejercicio 3 - TIR'!$E$14-'Ejercicio 3 - TIR'!$C$14)*('Ejercicio 3 - TIR'!$E$14-'Ejercicio 3 - TIR'!$D$14)*(1-D1001))) -> 30578.534 | F1001: =RAND() -> 0.04289974 | G1001: =IF(F1001<=('Ejercicio 3 - TIR'!$D$18-'Ejercicio 3 - TIR'!$C$18)/('Ejercicio 3 - TIR'!$E$18-'Ejercicio 3 - TIR'!$C$18),'Ejercicio 3 - TIR'!$C$18+SQRT(('Ejercicio 3 - TIR'!$E$18-'Ejercicio 3 - TIR'!$C$18)*('Ejercicio 3 - TIR'!$D$18-'Ejercicio 3 - TIR'!$C$18)*F1001),'Ejercicio 3 - TIR'!$E$18-SQRT(('Ejercicio 3 - TIR'!$E$18-'Ejercicio 3 - TIR'!$C$18)*('Ejercicio 3 - TIR'!$E$18-'Ejercicio 3 - TIR'!$D$18)*(1-F1001))) -> 32536.722 | H1001: =RAND() -> 0.72842579 | I1001: =IF(H1001<=('Ejercicio 3 - TIR'!$D$18-'Ejercicio 3 - TIR'!$C$18)/('Ejercicio 3 - TIR'!$E$18-'Ejercicio 3 - TIR'!$C$18),'Ejercicio 3 - TIR'!$C$18+SQRT(('Ejercicio 3 - TIR'!$E$18-'Ejercicio 3 - TIR'!$C$18)*('Ejercicio 3 - TIR'!$D$18-'Ejercicio 3 - TIR'!$C$18)*H1001),'Ejercicio 3 - TIR'!$E$18-SQRT(('Ejercicio 3 - TIR'!$E$18-'Ejercicio 3 - TIR'!$C$18)*('Ejercicio 3 - TIR'!$E$18-'Ejercicio 3 - TIR'!$D$18)*(1-H1001))) -> 40486.901 | J1001: =RAND() -> 0.61748855 | K1001: =IF(J1001<=('Ejercicio 3 - TIR'!$D$18-'Ejercicio 3 - TIR'!$C$18)/('Ejercicio 3 - TIR'!$E$18-'Ejercicio 3 - TIR'!$C$18),'Ejercicio 3 - TIR'!$C$18+SQRT(('Ejercicio 3 - TIR'!$E$18-'Ejercicio 3 - TIR'!$C$18)*('Ejercicio 3 - TIR'!$D$18-'Ejercicio 3 - TIR'!$C$18)*J1001),'Ejercicio 3 - TIR'!$E$18-SQRT(('Ejercicio 3 - TIR'!$E$18-'Ejercicio 3 - TIR'!$C$18)*('Ejercicio 3 - TIR'!$E$18-'Ejercicio 3 - TIR'!$D$18)*(1-J1001))) -> 39624.099 | L1001: =RAND() -> 0.65625603 | M1001: =IF(L1001<=('Ejercicio 3 - TIR'!$D$18-'Ejercicio 3 - TIR'!$C$18)/('Ejercicio 3 - TIR'!$E$18-'Ejercicio 3 - TIR'!$C$18),'Ejercicio 3 - TIR'!$C$18+SQRT(('Ejercicio 3 - TIR'!$E$18-'Ejercicio 3 - TIR'!$C$18)*('Ejercicio 3 - TIR'!$D$18-'Ejercicio 3 - TIR'!$C$18)*L1001),'Ejercicio 3 - TIR'!$E$18-SQRT(('Ejercicio 3 - TIR'!$E$18-'Ejercicio 3 - TIR'!$C$18)*('Ejercicio 3 - TIR'!$E$18-'Ejercicio 3 - TIR'!$D$18)*(1-L1001))) -> 39921.613 | N1001: =RAND() -> 0.89210534 | O1001: =IF(N1001<=('Ejercicio 3 - TIR'!$D$18-'Ejercicio 3 - TIR'!$C$18)/('Ejercicio 3 - TIR'!$E$18-'Ejercicio 3 - TIR'!$C$18),'Ejercicio 3 - TIR'!$C$18+SQRT(('Ejercicio 3 - TIR'!$E$18-'Ejercicio 3 - TIR'!$C$18)*('Ejercicio 3 - TIR'!$D$18-'Ejercicio 3 - TIR'!$C$18)*N1001),'Ejercicio 3 - TIR'!$E$18-SQRT(('Ejercicio 3 - TIR'!$E$18-'Ejercicio 3 - TIR'!$C$18)*('Ejercicio 3 - TIR'!$E$18-'Ejercicio 3 - TIR'!$D$18)*(1-N1001))) -> 42155.338 | P1001: =RAND() -> 0.76869991 | Q1001: =IF(P1001<=('Ejercicio 3 - TIR'!$D$22-'Ejercicio 3 - TIR'!$C$22)/('Ejercicio 3 - TIR'!$E$22-'Ejercicio 3 - TIR'!$C$22),'Ejercicio 3 - TIR'!$C$22+SQRT(('Ejercicio 3 - TIR'!$E$22-'Ejercicio 3 - TIR'!$C$22)*('Ejercicio 3 - TIR'!$D$22-'Ejercicio 3 - TIR'!$C$22)*P1001),'Ejercicio 3 - TIR'!$E$22-SQRT(('Ejercicio 3 - TIR'!$E$22-'Ejercicio 3 - TIR'!$C$22)*('Ejercicio 3 - TIR'!$E$22-'Ejercicio 3 - TIR'!$D$22)*(1-P1001))) -> 0.15959558 | R1001: =RAND() -> 0.82640141 | S1001: =IF(R1001<=('Ejercicio 3 - TIR'!$D$23-'Ejercicio 3 - TIR'!$C$23)/('Ejercicio 3 - TIR'!$E$23-'Ejercicio 3 - TIR'!$C$23),'Ejercicio 3 - TIR'!$C$23+SQRT(('Ejercicio 3 - TIR'!$E$23-'Ejercicio 3 - TIR'!$C$23)*('Ejercicio 3 - TIR'!$D$23-'Ejercicio 3 - TIR'!$C$23)*R1001),'Ejercicio 3 - TIR'!$E$23-SQRT(('Ejercicio 3 - TIR'!$E$23-'Ejercicio 3 - TIR'!$C$23)*('Ejercicio 3 - TIR'!$E$23-'Ejercicio 3 - TIR'!$D$23)*(1-R1001))) -> 0.16232297 | T1001: =RAND() -> 0.47598469 | U1001: =IF(T1001<=('Ejercicio 3 - TIR'!$D$24-'Ejercicio 3 - TIR'!$C$24)/('Ejercicio 3 - TIR'!$E$24-'Ejercicio 3 - TIR'!$C$24),'Ejercicio 3 - TIR'!$C$24+SQRT(('Ejercicio 3 - TIR'!$E$24-'Ejercicio 3 - TIR'!$C$24)*('Ejercicio 3 - TIR'!$D$24-'Ejercicio 3 - TIR'!$C$24)*T1001),'Ejercicio 3 - TIR'!$E$24-SQRT(('Ejercicio 3 - TIR'!$E$24-'Ejercicio 3 - TIR'!$C$24)*('Ejercicio 3 - TIR'!$E$24-'Ejercicio 3 - TIR'!$D$24)*(1-T1001))) -> 0.18169539 | V1001: =RAND() -> 0.76362479 | W1001: =IF(V1001<=('Ejercicio 3 - TIR'!$D$25-'Ejercicio 3 - TIR'!$C$25)/('Ejercicio 3 - TIR'!$E$25-'Ejercicio 3 - TIR'!$C$25),'Ejercicio 3 - TIR'!$C$25+SQRT(('Ejercicio 3 - TIR'!$E$25-'Ejercicio 3 - TIR'!$C$25)*('Ejercicio 3 - TIR'!$D$25-'Ejercicio 3 - TIR'!$C$25)*V1001),'Ejercicio 3 - TIR'!$E$25-SQRT(('Ejercicio 3 - TIR'!$E$25-'Ejercicio 3 - TIR'!$C$25)*('Ejercicio 3 - TIR'!$E$25-'Ejercicio 3 - TIR'!$D$25)*(1-V1001))) -> 0.22123695 | X1001: =RAND() -> 0.29512466 | Y1001: =IF(X1001<=('Ejercicio 3 - TIR'!$D$26-'Ejercicio 3 - TIR'!$C$26)/('Ejercicio 3 - TIR'!$E$26-'Ejercicio 3 - TIR'!$C$26),'Ejercicio 3 - TIR'!$C$26+SQRT(('Ejercicio 3 - TIR'!$E$26-'Ejercicio 3 - TIR'!$C$26)*('Ejercicio 3 - TIR'!$D$26-'Ejercicio 3 - TIR'!$C$26)*X1001),'Ejercicio 3 - TIR'!$E$26-SQRT(('Ejercicio 3 - TIR'!$E$26-'Ejercicio 3 - TIR'!$C$26)*('Ejercicio 3 - TIR'!$E$26-'Ejercicio 3 - TIR'!$D$26)*(1-X1001))) -> 0.21822829 | Z1001: =(1+Q1001) -> 1.1595956 | AA1001: =Z1001*(1+S1001) -> 1.3478246 | AB1001: =AA1001*(1+U1001) -> 1.5927181 | AC1001: =AB1001*(1+W1001) -> 1.9450862 | AD1001: =AC1001*(1+Y1001) -> 2.369559 | AE1001: =E1001*Q1001 -> 4880.199 | AF1001: =AE1001*(1+S1001) -> 5672.3673 | AG1001: =AF1001*(1+U1001) -> 6703.0104 | AH1001: =AG1001*(1+W1001) -> 8185.9639 | AI1001: =AH1001*(1+Y1001) -> 9972.3728 | AJ1001: =G1001*Z1001 -> 37729.44 | AK1001: =I1001*AA1001 -> 54569.24 | AL1001: =K1001*AB1001 -> 63110.02 | AM1001: =M1001*AC1001 -> 77650.978 | AN1001: =O1001*AD1001 -> 99889.563 | AO1001: =C1001/'Ejercicio 3 - TIR'!$D$7 -> 18948.334 | AP1001: =AJ1001-AO1001 -> 18781.106 | AQ1001: =AK1001-AO1001 -> 35620.906 | AR1001: =AL1001-AO1001 -> 44161.686 | AS1001: =AM1001-AO1001 -> 58702.645 | AT1001: =AN1001-AO1001 -> 80941.229 | AU1001: =AP1001*'Ejercicio 3 - TIR'!$D$5 -> 9390.5531 | AV1001: =AQ1001*'Ejercicio 3 - TIR'!$D$5 -> 17810.453 | AW1001: =AR1001*'Ejercicio 3 - TIR'!$D$5 -> 22080.843 | AX1001: =AS1001*'Ejercicio 3 - TIR'!$D$5 -> 29351.322 | AY1001: =AT1001*'Ejercicio 3 - TIR'!$D$5 -> 40470.615 | AZ1001: =AJ1001-AU1001-AE1001 -> 23458.688 | BA1001: =AK1001-AV1001-AF1001 -> 31086.419 | BB1001: =AL1001-AW1001-AG1001 -> 34326.166 | BC1001: =AM1001-AX1001-AH1001 -> 40113.692 | BD1001: =AN1001-AY1001-AI1001 -> 49446.575 | BE1001: =AZ1001/Z1001 -> 20230.06 | BF1001: =BA1001/AA1001 -> 23064.143 | BG1001: =BB1001/AB1001 -> 21551.941 | BH1001: =BC1001/AC1001 -> 20623.092 | BI1001: =BD1001/AD1001 -> 20867.417 | BJ1001: =E1001*AD1001 -> 72457.641 | BK1001: =0.2*C1001*AD1001 -> 44899.195 | BL1001: =BJ1001+BK1001 -> 117356.84 | BM1001: =BK1001*'Ejercicio 3 - TIR'!$D$5 -> 22449.598 | BN1001: =BL1001-BM1001 -> 94907.238 | BO1001: =BN1001/AD1001 -> 40052.7 | BP1001: =-(C1001+E1001) -> -125320.2 | BQ1001: =BE1001 -> 20230.06 | BR1001: =BF1001 -> 23064.143 | BS1001: =BG1001 -> 21551.941 | BT1001: =BH1001 -> 20623.092 | BU1001: =BI1001+BO1001 -> 60920.117 | BV1001: =IFERROR(IRR(BP1001:BU1001,0.1),NA())*100 -> 4.5543392

Sheet Ejercicio 4 - Camiones
A1: Ejercicio 4
A3: Nº camiones a comprar: | B3: 11 | O3: Comparación de 8 escenarios (conectada — ver fila 285)
A4: (simulación interactiva individual) | O4: N° camiones | P4: Costo Fijo ($) | Q4: Costo Externo ($) | R4: Costo Total ($)
K5: Tabla de Capacidad por Camión (ton/día) | O5: 8 | P5: 800000 | Q5: =SUM(I$291:I$540) -> 649974.09 | R5: =P5+Q5 -> 1449974.1
A6: Tabla de Producción Diaria (toneladas) | F6: Prob. acumulada (F) | G6: Lím. inf. ton (G) | H6: Lím. sup. ton (H) | K6: Prob. acum. (K) | L6: Lím. inf. ton (L) | M6: Lím. sup. ton (M) | O6: 9 | P6: 900000 | Q6: =SUM(R$291:R$540) -> 534230.53 | R6: =P6+Q6 -> 1434230.5
F7: 0 | G7: 50 | H7: 55 | K7: 0 | L7: 4 | M7: 4.5 | O7: 10 | P7: 1000000 | Q7: =SUM(AA$291:AA$540) -> 406364.53 | R7: =P7+Q7 -> 1406364.5
F8: 0.1 | G8: 55 | H8: 60 | K8: 0.3 | L8: 4.5 | M8: 5 | O8: 11 | P8: 1100000 | Q8: =SUM(AJ$291:AJ$540) -> 282762.94 | R8: =P8+Q8 -> 1382762.9
F9: 0.25 | G9: 60 | H9: 65 | K9: 0.7 | L9: 5 | M9: 5.5 | O9: 12 | P9: 1200000 | Q9: =SUM(AS$291:AS$540) -> 207365.44 | R9: =P9+Q9 -> 1407365.4
F10: 0.55 | G10: 65 | H10: 70 | K10: 0.9 | L10: 5.5 | M10: 6 | O10: 13 | P10: 1300000 | Q10: =SUM(BB$291:BB$540) -> 99767.409 | R10: =P10+Q10 -> 1399767.4
F11: 0.9 | G11: 75 | H11: 80 | O11: 14 | P11: 1400000 | Q11: =SUM(BK$291:BK$540) -> 69566.311 | R11: =P11+Q11 -> 1469566.3
F12: 0.98 | G12: 80 | H12: 85 | O12: 15 | P12: 1500000 | Q12: =SUM(BT$291:BT$540) -> 27746.103 | R12: =P12+Q12 -> 1527746.1
A14: Día | B14: R_Producción | C14: Producción del Día | D14: R_Camión | E14: Capacidad Prom. x Camión | F14: Capacidad Flotilla Total | G14: Excedente (Ton) | H14: Costo Flete Externo
A15: 1 | B15: =RAND() -> 0.24221358 | C15: =VLOOKUP(B15,$F$7:$H$12,2,TRUE())+(RAND()*(VLOOKUP(B15,$F$7:$H$12,3,TRUE())-VLOOKUP(B15,$F$7:$H$12,2,TRUE()))) -> 56.560006 | D15: =RAND() -> 0.12720625 | E15: =VLOOKUP(D15,$K$7:$M$10,2,TRUE())+(RAND()*(VLOOKUP(D15,$K$7:$M$10,3,TRUE())-VLOOKUP(D15,$K$7:$M$10,2,TRUE()))) -> 4.1935535 | F15: =E15*$B$3 -> 46.129089 | G15: =MAX(C15-F15,0) -> 10.430918 | H15: =G15*100 -> 1043.0918
A16: =A15+1 -> 2 | B16: =RAND() -> 0.14529822 | C16: =VLOOKUP(B16,$F$7:$H$12,2,TRUE())+(RAND()*(VLOOKUP(B16,$F$7:$H$12,3,TRUE())-VLOOKUP(B16,$F$7:$H$12,2,TRUE()))) -> 55.934692 | D16: =RAND() -> 0.28012205 | E16: =VLOOKUP(D16,$K$7:$M$10,2,TRUE())+(RAND()*(VLOOKUP(D16,$K$7:$M$10,3,TRUE())-VLOOKUP(D16,$K$7:$M$10,2,TRUE()))) -> 4.4444489 | F16: =E16*$B$3 -> 48.888938 | G16: =MAX(C16-F16,0) -> 7.0457542 | H16: =G16*100 -> 704.57542
A17: =A16+1 -> 3 | B17: =RAND() -> 0.34659794 | C17: =VLOOKUP(B17,$F$7:$H$12,2,TRUE())+(RAND()*(VLOOKUP(B17,$F$7:$H$12,3,TRUE())-VLOOKUP(B17,$F$7:$H$12,2,TRUE()))) -> 62.801717 | D17: =RAND() -> 0.30498296 | E17: =VLOOKUP(D17,$K$7:$M$10,2,TRUE())+(RAND()*(VLOOKUP(D17,$K$7:$M$10,3,TRUE())-VLOOKUP(D17,$K$7:$M$10,2,TRUE()))) -> 4.6988726 | F17: =E17*$B$3 -> 51.687598 | G17: =MAX(C17-F17,0) -> 11.114119 | H17: =G17*100 -> 1111.4119
A18: =A17+1 -> 4 | B18: =RAND() -> 0.99890445 | C18: =VLOOKUP(B18,$F$7:$H$12,2,TRUE())+(RAND()*(VLOOKUP(B18,$F$7:$H$12,3,TRUE())-VLOOKUP(B18,$F$7:$H$12,2,TRUE()))) -> 81.299102 | D18: =RAND() -> 0.015518557 | E18: =VLOOKUP(D18,$K$7:$M$10,2,TRUE())+(RAND()*(VLOOKUP(D18,$K$7:$M$10,3,TRUE())-VLOOKUP(D18,$K$7:$M$10,2,TRUE()))) -> 4.0152899 | F18: =E18*$B$3 -> 44.168189 | G18: =MAX(C18-F18,0) -> 37.130913 | H18: =G18*100 -> 3713.0913
A19: =A18+1 -> 5 | B19: =RAND() -> 0.5240204 | C19: =VLOOKUP(B19,$F$7:$H$12,2,TRUE())+(RAND()*(VLOOKUP(B19,$F$7:$H$12,3,TRUE())-VLOOKUP(B19,$F$7:$H$12,2,TRUE()))) -> 61.233974 | D19: =RAND() -> 0.33596709 | E19: =VLOOKUP(D19,$K$7:$M$10,2,TRUE())+(RAND()*(VLOOKUP(D19,$K$7:$M$10,3,TRUE())-VLOOKUP(D19,$K$7:$M$10,2,TRUE()))) -> 4.5610011 | F19: =E19*$B$3 -> 50.171012 | G19: =MAX(C19-F19,0) -> 11.062962 | H19: =G19*100 -> 1106.2962
A20: =A19+1 -> 6 | B20: =RAND() -> 0.74994198 | C20: =VLOOKUP(B20,$F$7:$H$12,2,TRUE())+(RAND()*(VLOOKUP(B20,$F$7:$H$12,3,TRUE())-VLOOKUP(B20,$F$7:$H$12,2,TRUE()))) -> 69.334144 | D20: =RAND() -> 0.78560619 | E20: =VLOOKUP(D20,$K$7:$M$10,2,TRUE())+(RAND()*(VLOOKUP(D20,$K$7:$M$10,3,TRUE())-VLOOKUP(D20,$K$7:$M$10,2,TRUE()))) -> 5.3887715 | F20: =E20*$B$3 -> 59.276486 | G20: =MAX(C20-F20,0) -> 10.057658 | H20: =G20*100 -> 1005.7658
A21: =A20+1 -> 7 | B21: =RAND() -> 0.416028 | C21: =VLOOKUP(B21,$F$7:$H$12,2,TRUE())+(RAND()*(VLOOKUP(B21,$F$7:$H$12,3,TRUE())-VLOOKUP(B21,$F$7:$H$12,2,TRUE()))) -> 64.29248 | D21: =RAND() -> 0.18233389 | E21: =VLOOKUP(D21,$K$7:$M$10,2,TRUE())+(RAND()*(VLOOKUP(D21,$K$7:$M$10,3,TRUE())-VLOOKUP(D21,$K$7:$M$10,2,TRUE()))) -> 4.0970269 | F21: =E21*$B$3 -> 45.067295 | G21: =MAX(C21-F21,0) -> 19.225185 | H21: =G21*100 -> 1922.5185
A22: =A21+1 -> 8 | B22: =RAND() -> 0.13371611 | C22: =VLOOKUP(B22,$F$7:$H$12,2,TRUE())+(RAND()*(VLOOKUP(B22,$F$7:$H$12,3,TRUE())-VLOOKUP(B22,$F$7:$H$12,2,TRUE()))) -> 55.581172 | D22: =RAND() -> 0.33934479 | E22: =VLOOKUP(D22,$K$7:$M$10,2,TRUE())+(RAND()*(VLOOKUP(D22,$K$7:$M$10,3,TRUE())-VLOOKUP(D22,$K$7:$M$10,2,TRUE()))) -> 4.6605623 | F22: =E22*$B$3 -> 51.266186 | G22: =MAX(C22-F22,0) -> 4.3149863 | H22: =G22*100 -> 431.49863
A23: =A22+1 -> 9 | B23: =RAND() -> 0.2136378 | C23: =VLOOKUP(B23,$F$7:$H$12,2,TRUE())+(RAND()*(VLOOKUP(B23,$F$7:$H$12,3,TRUE())-VLOOKUP(B23,$F$7:$H$12,2,TRUE()))) -> 58.162356 | D23: =RAND() -> 0.64294298 | E23: =VLOOKUP(D23,$K$7:$M$10,2,TRUE())+(RAND()*(VLOOKUP(D23,$K$7:$M$10,3,TRUE())-VLOOKUP(D23,$K$7:$M$10,2,TRUE()))) -> 4.5554994 | F23: =E23*$B$3 -> 50.110494 | G23: =MAX(C23-F23,0) -> 8.0518622 | H23: =G23*100 -> 805.18622
A24: =A23+1 -> 10 | B24: =RAND() -> 0.71289457 | C24: =VLOOKUP(B24,$F$7:$H$12,2,TRUE())+(RAND()*(VLOOKUP(B24,$F$7:$H$12,3,TRUE())-VLOOKUP(B24,$F$7:$H$12,2,TRUE()))) -> 66.168662 | D24: =RAND() -> 0.29528216 | E24: =VLOOKUP(D24,$K$7:$M$10,2,TRUE())+(RAND()*(VLOOKUP(D24,$K$7:$M$10,3,TRUE())-VLOOKUP(D24,$K$7:$M$10,2,TRUE()))) -> 4.3838968 | F24: =E24*$B$3 -> 48.222865 | G24: =MAX(C24-F24,0) -> 17.945796 | H24: =G24*100 -> 1794.5796
A25: =A24+1 -> 11 | B25: =RAND() -> 0.0057145968 | C25: =VLOOKUP(B25,$F$7:$H$12,2,TRUE())+(RAND()*(VLOOKUP(B25,$F$7:$H$12,3,TRUE())-VLOOKUP(B25,$F$7:$H$12,2,TRUE()))) -> 54.400848 | D25: =RAND() -> 0.01871903 | E25: =VLOOKUP(D25,$K$7:$M$10,2,TRUE())+(RAND()*(VLOOKUP(D25,$K$7:$M$10,3,TRUE())-VLOOKUP(D25,$K$7:$M$10,2,TRUE()))) -> 4.2742385 | F25: =E25*$B$3 -> 47.016624 | G25: =MAX(C25-F25,0) -> 7.3842239 | H25: =G25*100 -> 738.42239
A26: =A25+1 -> 12 | B26: =RAND() -> 0.32944278 | C26: =VLOOKUP(B26,$F$7:$H$12,2,TRUE())+(RAND()*(VLOOKUP(B26,$F$7:$H$12,3,TRUE())-VLOOKUP(B26,$F$7:$H$12,2,TRUE()))) -> 63.613088 | D26: =RAND() -> 0.98089402 | E26: =VLOOKUP(D26,$K$7:$M$10,2,TRUE())+(RAND()*(VLOOKUP(D26,$K$7:$M$10,3,TRUE())-VLOOKUP(D26,$K$7:$M$10,2,TRUE()))) -> 5.8655139 | F26: =E26*$B$3 -> 64.520653 | G26: =MAX(C26-F26,0) -> 0 | H26: =G26*100 -> 0
A27: =A26+1 -> 13 | B27: =RAND() -> 0.72351492 | C27: =VLOOKUP(B27,$F$7:$H$12,2,TRUE())+(RAND()*(VLOOKUP(B27,$F$7:$H$12,3,TRUE())-VLOOKUP(B27,$F$7:$H$12,2,TRUE()))) -> 68.596622 | D27: =RAND() -> 0.91272239 | E27: =VLOOKUP(D27,$K$7:$M$10,2,TRUE())+(RAND()*(VLOOKUP(D27,$K$7:$M$10,3,TRUE())-VLOOKUP(D27,$K$7:$M$10,2,TRUE()))) -> 5.7754234 | F27: =E27*$B$3 -> 63.529657 | G27: =MAX(C27-F27,0) -> 5.0669644 | H27: =G27*100 -> 506.69644
... A37: =A36+1 -> 23 | B37: =RAND() -> 0.43653445 | C37: =VLOOKUP(B37,$F$7:$H$12,2,TRUE())+(RAND()*(VLOOKUP(B37,$F$7:$H$12,3,TRUE())-VLOOKUP(B37,$F$7:$H$12,2,TRUE()))) -> 60.256858 | D37: =RAND() -> 0.39758234 | E37: =VLOOKUP(D37,$K$7:$M$10,2,TRUE())+(RAND()*(VLOOKUP(D37,$K$7:$M$10,3,TRUE())-VLOOKUP(D37,$K$7:$M$10,2,TRUE()))) -> 4.8477233 | F37: =E37*$B$3 -> 53.324956 | G37: =MAX(C37-F37,0) -> 6.9319024 | H37: =G37*100 -> 693.19024
A38: =A37+1 -> 24 | B38: =RAND() -> 0.25796175 | C38: =VLOOKUP(B38,$F$7:$H$12,2,TRUE())+(RAND()*(VLOOKUP(B38,$F$7:$H$12,3,TRUE())-VLOOKUP(B38,$F$7:$H$12,2,TRUE()))) -> 60.207863 | D38: =RAND() -> 0.74907706 | E38: =VLOOKUP(D38,$K$7:$M$10,2,TRUE())+(RAND()*(VLOOKUP(D38,$K$7:$M$10,3,TRUE())-VLOOKUP(D38,$K$7:$M$10,2,TRUE()))) -> 5.4378958 | F38: =E38*$B$3 -> 59.816854 | G38: =MAX(C38-F38,0) -> 0.39100915 | H38: =G38*100 -> 39.100915 | J38: OPT. CAMIONES | K38: {=INDEX(O5:O12,MATCH(MIN(R5:R12),R5:R12,0))} -> 11
A39: =A38+1 -> 25 | B39: =RAND() -> 0.63366394 | C39: =VLOOKUP(B39,$F$7:$H$12,2,TRUE())+(RAND()*(VLOOKUP(B39,$F$7:$H$12,3,TRUE())-VLOOKUP(B39,$F$7:$H$12,2,TRUE()))) -> 66.790062 | D39: =RAND() -> 0.12179372 | E39: =VLOOKUP(D39,$K$7:$M$10,2,TRUE())+(RAND()*(VLOOKUP(D39,$K$7:$M$10,3,TRUE())-VLOOKUP(D39,$K$7:$M$10,2,TRUE()))) -> 4.1789092 | F39: =E39*$B$3 -> 45.968002 | G39: =MAX(C39-F39,0) -> 20.82206 | H39: =G39*100 -> 2082.206
A40: =A39+1 -> 26 | B40: =RAND() -> 0.45229152 | C40: =VLOOKUP(B40,$F$7:$H$12,2,TRUE())+(RAND()*(VLOOKUP(B40,$F$7:$H$12,3,TRUE())-VLOOKUP(B40,$F$7:$H$12,2,TRUE()))) -> 60.707233 | D40: =RAND() -> 0.33985443 | E40: =VLOOKUP(D40,$K$7:$M$10,2,TRUE())+(RAND()*(VLOOKUP(D40,$K$7:$M$10,3,TRUE())-VLOOKUP(D40,$K$7:$M$10,2,TRUE()))) -> 4.9012912 | F40: =E40*$B$3 -> 53.914203 | G40: =MAX(C40-F40,0) -> 6.7930303 | H40: =G40*100 -> 679.30303
A41: =A40+1 -> 27 | B41: =RAND() -> 0.38685368 | C41: =VLOOKUP(B41,$F$7:$H$12,2,TRUE())+(RAND()*(VLOOKUP(B41,$F$7:$H$12,3,TRUE())-VLOOKUP(B41,$F$7:$H$12,2,TRUE()))) -> 63.068394 | D41: =RAND() -> 0.44576471 | E41: =VLOOKUP(D41,$K$7:$M$10,2,TRUE())+(RAND()*(VLOOKUP(D41,$K$7:$M$10,3,TRUE())-VLOOKUP(D41,$K$7:$M$10,2,TRUE()))) -> 4.5023687 | F41: =E41*$B$3 -> 49.526056 | G41: =MAX(C41-F41,0) -> 13.542338 | H41: =G41*100 -> 1354.2338
A42: =A41+1 -> 28 | B42: =RAND() -> 0.77453852 | C42: =VLOOKUP(B42,$F$7:$H$12,2,TRUE())+(RAND()*(VLOOKUP(B42,$F$7:$H$12,3,TRUE())-VLOOKUP(B42,$F$7:$H$12,2,TRUE()))) -> 67.413652 | D42: =RAND() -> 0.29185845 | E42: =VLOOKUP(D42,$K$7:$M$10,2,TRUE())+(RAND()*(VLOOKUP(D42,$K$7:$M$10,3,TRUE())-VLOOKUP(D42,$K$7:$M$10,2,TRUE()))) -> 4.0625811 | F42: =E42*$B$3 -> 44.688392 | G42: =MAX(C42-F42,0) -> 22.72526 | H42: =G42*100 -> 2272.526
A43: =A42+1 -> 29 | B43: =RAND() -> 0.018086542 | C43: =VLOOKUP(B43,$F$7:$H$12,2,TRUE())+(RAND()*(VLOOKUP(B43,$F$7:$H$12,3,TRUE())-VLOOKUP(B43,$F$7:$H$12,2,TRUE()))) -> 50.7501 | D43: =RAND() -> 0.26125911 | E43: =VLOOKUP(D43,$K$7:$M$10,2,TRUE())+(RAND()*(VLOOKUP(D43,$K$7:$M$10,3,TRUE())-VLOOKUP(D43,$K$7:$M$10,2,TRUE()))) -> 4.3346204 | F43: =E43*$B$3 -> 47.680824 | G43: =MAX(C43-F43,0) -> 3.069276 | H43: =G43*100 -> 306.9276
A44: =A43+1 -> 30 | B44: =RAND() -> 0.053294097 | C44: =VLOOKUP(B44,$F$7:$H$12,2,TRUE())+(RAND()*(VLOOKUP(B44,$F$7:$H$12,3,TRUE())-VLOOKUP(B44,$F$7:$H$12,2,TRUE()))) -> 51.448017 | D44: =RAND() -> 0.31889162 | E44: =VLOOKUP(D44,$K$7:$M$10,2,TRUE())+(RAND()*(VLOOKUP(D44,$K$7:$M$10,3,TRUE())-VLOOKUP(D44,$K$7:$M$10,2,TRUE()))) -> 4.5136325 | F44: =E44*$B$3 -> 49.649957 | G44: =MAX(C44-F44,0) -> 1.7980596 | H44: =G44*100 -> 179.80596
A45: =A44+1 -> 31 | B45: =RAND() -> 0.081654963 | C45: =VLOOKUP(B45,$F$7:$H$12,2,TRUE())+(RAND()*(VLOOKUP(B45,$F$7:$H$12,3,TRUE())-VLOOKUP(B45,$F$7:$H$12,2,TRUE()))) -> 54.630976 | D45: =RAND() -> 0.18776858 | E45: =VLOOKUP(D45,$K$7:$M$10,2,TRUE())+(RAND()*(VLOOKUP(D45,$K$7:$M$10,3,TRUE())-VLOOKUP(D45,$K$7:$M$10,2,TRUE()))) -> 4.2874461 | F45: =E45*$B$3 -> 47.161907 | G45: =MAX(C45-F45,0) -> 7.4690691 | H45: =G45*100 -> 746.90691
A46: =A45+1 -> 32 | B46: =RAND() -> 0.67078467 | C46: =VLOOKUP(B46,$F$7:$H$12,2,TRUE())+(RAND()*(VLOOKUP(B46,$F$7:$H$12,3,TRUE())-VLOOKUP(B46,$F$7:$H$12,2,TRUE()))) -> 68.74185 | D46: =RAND() -> 0.88736921 | E46: =VLOOKUP(D46,$K$7:$M$10,2,TRUE())+(RAND()*(VLOOKUP(D46,$K$7:$M$10,3,TRUE())-VLOOKUP(D46,$K$7:$M$10,2,TRUE()))) -> 5.2729448 | F46: =E46*$B$3 -> 58.002393 | G46: =MAX(C46-F46,0) -> 10.739457 | H46: =G46*100 -> 1073.9457
A47: =A46+1 -> 33 | B47: =RAND() -> 0.1108516 | C47: =VLOOKUP(B47,$F$7:$H$12,2,TRUE())+(RAND()*(VLOOKUP(B47,$F$7:$H$12,3,TRUE())-VLOOKUP(B47,$F$7:$H$12,2,TRUE()))) -> 55.131097 | D47: =RAND() -> 0.062741034 | E47: =VLOOKUP(D47,$K$7:$M$10,2,TRUE())+(RAND()*(VLOOKUP(D47,$K$7:$M$10,3,TRUE())-VLOOKUP(D47,$K$7:$M$10,2,TRUE()))) -> 4.1663093 | F47: =E47*$B$3 -> 45.829402 | G47: =MAX(C47-F47,0) -> 9.3016949 | H47: =G47*100 -> 930.16949
A48: =A47+1 -> 34 | B48: =RAND() -> 0.8272908 | C48: =VLOOKUP(B48,$F$7:$H$12,2,TRUE())+(RAND()*(VLOOKUP(B48,$F$7:$H$12,3,TRUE())-VLOOKUP(B48,$F$7:$H$12,2,TRUE()))) -> 68.614647 | D48: =RAND() -> 0.80582624 | E48: =VLOOKUP(D48,$K$7:$M$10,2,TRUE())+(RAND()*(VLOOKUP(D48,$K$7:$M$10,3,TRUE())-VLOOKUP(D48,$K$7:$M$10,2,TRUE()))) -> 5.0732194 | F48: =E48*$B$3 -> 55.805413 | G48: =MAX(C48-F48,0) -> 12.809234 | H48: =G48*100 -> 1280.9234
A49: =A48+1 -> 35 | B49: =RAND() -> 0.36285846 | C49: =VLOOKUP(B49,$F$7:$H$12,2,TRUE())+(RAND()*(VLOOKUP(B49,$F$7:$H$12,3,TRUE())-VLOOKUP(B49,$F$7:$H$12,2,TRUE()))) -> 62.660353 | D49: =RAND() -> 0.71842567 | E49: =VLOOKUP(D49,$K$7:$M$10,2,TRUE())+(RAND()*(VLOOKUP(D49,$K$7:$M$10,3,TRUE())-VLOOKUP(D49,$K$7:$M$10,2,TRUE()))) -> 5.1493322 | F49: =E49*$B$3 -> 56.642654 | G49: =MAX(C49-F49,0) -> 6.0176991 | H49: =G49*100 -> 601.76991
A50: =A49+1 -> 36 | B50: =RAND() -> 0.84870054 | C50: =VLOOKUP(B50,$F$7:$H$12,2,TRUE())+(RAND()*(VLOOKUP(B50,$F$7:$H$12,3,TRUE())-VLOOKUP(B50,$F$7:$H$12,2,TRUE()))) -> 69.823218 | D50: =RAND() -> 0.24135695 | E50: =VLOOKUP(D50,$K$7:$M$10,2,TRUE())+(RAND()*(VLOOKUP(D50,$K$7:$M$10,3,TRUE())-VLOOKUP(D50,$K$7:$M$10,2,TRUE()))) -> 4.135281 | F50: =E50*$B$3 -> 45.488091 | G50: =MAX(C50-F50,0) -> 24.335127 | H50: =G50*100 -> 2433.5127
... A264: =A263+1 -> 250 | B264: =RAND() -> 0.27023259 | C264: =VLOOKUP(B264,$F$7:$H$12,2,TRUE())+(RAND()*(VLOOKUP(B264,$F$7:$H$12,3,TRUE())-VLOOKUP(B264,$F$7:$H$12,2,TRUE()))) -> 62.987781 | D264: =RAND() -> 0.16381719 | E264: =VLOOKUP(D264,$K$7:$M$10,2,TRUE())+(RAND()*(VLOOKUP(D264,$K$7:$M$10,3,TRUE())-VLOOKUP(D264,$K$7:$M$10,2,TRUE()))) -> 4.1845057 | F264: =E264*$B$3 -> 46.029563 | G264: =MAX(C264-F264,0) -> 16.958218 | H264: =G264*100 -> 1695.8218
A266: Costo Anual de Camiones = | B266: =$B$3*100000 -> 1100000
A267: Costo Anual Flete Externo = | B267: =SUM(H15:H264) -> 281616.89
A268: COSTO TOTAL = | B268: =B266+B267 -> 1381616.9
A285: 8 simulaciones independientes corriendo en paralelo (N = 8 a 15)
B288: N = 8 | K288: N = 9 | T288: N = 10 | AC288: N = 11 | AL288: N = 12 | AU288: N = 13 | BD288: N = 14 | BM288: N = 15
B289: Día | C289: R_Prod | D289: Producción | E289: R_Cam | F289: Capacidad | G289: Flota | H289: Excedente | I289: CostoFlete | K289: Día | L289: R_Prod | M289: Producción | N289: R_Cam | O289: Capacidad | P289: Flota | Q289: Excedente | R289: CostoFlete | T289: Día | U289: R_Prod | V289: Producción | W289: R_Cam | X289: Capacidad | Y289: Flota | Z289: Excedente | AA289: CostoFlete | AC289: Día | AD289: R_Prod | AE289: Producción | AF289: R_Cam | AG289: Capacidad | AH289: Flota | AI289: Excedente | AJ289: CostoFlete | AL289: Día | AM289: R_Prod | AN289: Producción | AO289: R_Cam | AP289: Capacidad | AQ289: Flota | AR289: Excedente | AS289: CostoFlete | AU289: Día | AV289: R_Prod | AW289: Producción | AX289: R_Cam | AY289: Capacidad | AZ289: Flota | BA289: Excedente | BB289: CostoFlete | BD289: Día | BE289: R_Prod | BF289: Producción | BG289: R_Cam | BH289: Capacidad | BI289: Flota | BJ289: Excedente | BK289: CostoFlete | BM289: Día | BN289: R_Prod | BO289: Producción | BP289: R_Cam | BQ289: Capacidad | BR289: Flota | BS289: Excedente | BT289: CostoFlete
B291: 1 | C291: =RAND() -> 0.56304945 | D291: =VLOOKUP(C291,$F$7:$H$12,2,TRUE())+(RAND()*(VLOOKUP(C291,$F$7:$H$12,3,TRUE())-VLOOKUP(C291,$F$7:$H$12,2,TRUE()))) -> 68.435876 | E291: =RAND() -> 0.0043592843 | F291: =VLOOKUP(E291,$K$7:$M$10,2,TRUE())+(RAND()*(VLOOKUP(E291,$K$7:$M$10,3,TRUE())-VLOOKUP(E291,$K$7:$M$10,2,TRUE()))) -> 4.0692959 | G291: =F291*8 -> 32.554367 | H291: =MAX(D291-G291,0) -> 35.881509 | I291: =H291*100 -> 3588.1509 | K291: 1 | L291: =RAND() -> 0.28910531 | M291: =VLOOKUP(L291,$F$7:$H$12,2,TRUE())+(RAND()*(VLOOKUP(L291,$F$7:$H$12,3,TRUE())-VLOOKUP(L291,$F$7:$H$12,2,TRUE()))) -> 63.255543 | N291: =RAND() -> 0.25585459 | O291: =VLOOKUP(N291,$K$7:$M$10,2,TRUE())+(RAND()*(VLOOKUP(N291,$K$7:$M$10,3,TRUE())-VLOOKUP(N291,$K$7:$M$10,2,TRUE()))) -> 4.3102818 | P291: =O291*9 -> 38.792537 | Q291: =MAX(M291-P291,0) -> 24.463007 | R291: =Q291*100 -> 2446.3007 | T291: 1 | U291: =RAND() -> 0.085476834 | V291: =VLOOKUP(U291,$F$7:$H$12,2,TRUE())+(RAND()*(VLOOKUP(U291,$F$7:$H$12,3,TRUE())-VLOOKUP(U291,$F$7:$H$12,2,TRUE()))) -> 51.535295 | W291: =RAND() -> 0.69693849 | X291: =VLOOKUP(W291,$K$7:$M$10,2,TRUE())+(RAND()*(VLOOKUP(W291,$K$7:$M$10,3,TRUE())-VLOOKUP(W291,$K$7:$M$10,2,TRUE()))) -> 4.8394369 | Y291: =X291*10 -> 48.394369 | Z291: =MAX(V291-Y291,0) -> 3.140926 | AA291: =Z291*100 -> 314.0926 | AC291: 1 | AD291: =RAND() -> 0.35842707 | AE291: =VLOOKUP(AD291,$F$7:$H$12,2,TRUE())+(RAND()*(VLOOKUP(AD291,$F$7:$H$12,3,TRUE())-VLOOKUP(AD291,$F$7:$H$12,2,TRUE()))) -> 61.430426 | AF291: =RAND() -> 0.10278398 | AG291: =VLOOKUP(AF291,$K$7:$M$10,2,TRUE())+(RAND()*(VLOOKUP(AF291,$K$7:$M$10,3,TRUE())-VLOOKUP(AF291,$K$7:$M$10,2,TRUE()))) -> 4.0294035 | AH291: =AG291*11 -> 44.323438 | AI291: =MAX(AE291-AH291,0) -> 17.106987 | AJ291: =AI291*100 -> 1710.6987 | AL291: 1 | AM291: =RAND() -> 0.7992119 | AN291: =VLOOKUP(AM291,$F$7:$H$12,2,TRUE())+(RAND()*(VLOOKUP(AM291,$F$7:$H$12,3,TRUE())-VLOOKUP(AM291,$F$7:$H$12,2,TRUE()))) -> 65.843983 | AO291: =RAND() -> 0.31955484 | AP291: =VLOOKUP(AO291,$K$7:$M$10,2,TRUE())+(RAND()*(VLOOKUP(AO291,$K$7:$M$10,3,TRUE())-VLOOKUP(AO291,$K$7:$M$10,2,TRUE()))) -> 4.6918543 | AQ291: =AP291*12 -> 56.302252 | AR291: =MAX(AN291-AQ291,0) -> 9.5417307 | AS291: =AR291*100 -> 954.17307 | AU291: 1 | AV291: =RAND() -> 0.59896509 | AW291: =VLOOKUP(AV291,$F$7:$H$12,2,TRUE())+(RAND()*(VLOOKUP(AV291,$F$7:$H$12,3,TRUE())-VLOOKUP(AV291,$F$7:$H$12,2,TRUE()))) -> 68.212081 | AX291: =RAND() -> 0.092030278 | AY291: =VLOOKUP(AX291,$K$7:$M$10,2,TRUE())+(RAND()*(VLOOKUP(AX291,$K$7:$M$10,3,TRUE())-VLOOKUP(AX291,$K$7:$M$10,2,TRUE()))) -> 4.4637976 | AZ291: =AY291*13 -> 58.029369 | BA291: =MAX(AW291-AZ291,0) -> 10.182712 | BB291: =BA291*100 -> 1018.2712 | BD291: 1 | BE291: =RAND() -> 0.49532686 | BF291: =VLOOKUP(BE291,$F$7:$H$12,2,TRUE())+(RAND()*(VLOOKUP(BE291,$F$7:$H$12,3,TRUE())-VLOOKUP(BE291,$F$7:$H$12,2,TRUE()))) -> 61.381837 | BG291: =RAND() -> 0.65852633 | BH291: =VLOOKUP(BG291,$K$7:$M$10,2,TRUE())+(RAND()*(VLOOKUP(BG291,$K$7:$M$10,3,TRUE())-VLOOKUP(BG291,$K$7:$M$10,2,TRUE()))) -> 4.9487392 | BI291: =BH291*14 -> 69.282349 | BJ291: =MAX(BF291-BI291,0) -> 0 | BK291: =BJ291*100 -> 0 | BM291: 1 | BN291: =RAND() -> 0.53268112 | BO291: =VLOOKUP(BN291,$F$7:$H$12,2,TRUE())+(RAND()*(VLOOKUP(BN291,$F$7:$H$12,3,TRUE())-VLOOKUP(BN291,$F$7:$H$12,2,TRUE()))) -> 63.143477 | BP291: =RAND() -> 0.660569 | BQ291: =VLOOKUP(BP291,$K$7:$M$10,2,TRUE())+(RAND()*(VLOOKUP(BP291,$K$7:$M$10,3,TRUE())-VLOOKUP(BP291,$K$7:$M$10,2,TRUE()))) -> 4.6116788 | BR291: =BQ291*15 -> 69.175182 | BS291: =MAX(BO291-BR291,0) -> 0 | BT291: =BS291*100 -> 0
B292: =B291+1 -> 2 | C292: =RAND() -> 0.053339196 | D292: =VLOOKUP(C292,$F$7:$H$12,2,TRUE())+(RAND()*(VLOOKUP(C292,$F$7:$H$12,3,TRUE())-VLOOKUP(C292,$F$7:$H$12,2,TRUE()))) -> 53.983058 | E292: =RAND() -> 0.71089956 | F292: =VLOOKUP(E292,$K$7:$M$10,2,TRUE())+(RAND()*(VLOOKUP(E292,$K$7:$M$10,3,TRUE())-VLOOKUP(E292,$K$7:$M$10,2,TRUE()))) -> 5.2314875 | G292: =F292*8 -> 41.8519 | H292: =MAX(D292-G292,0) -> 12.131158 | I292: =H292*100 -> 1213.1158 | K292: =K291+1 -> 2 | L292: =RAND() -> 0.069194136 | M292: =VLOOKUP(L292,$F$7:$H$12,2,TRUE())+(RAND()*(VLOOKUP(L292,$F$7:$H$12,3,TRUE())-VLOOKUP(L292,$F$7:$H$12,2,TRUE()))) -> 50.889107 | N292: =RAND() -> 0.74678141 | O292: =VLOOKUP(N292,$K$7:$M$10,2,TRUE())+(RAND()*(VLOOKUP(N292,$K$7:$M$10,3,TRUE())-VLOOKUP(N292,$K$7:$M$10,2,TRUE()))) -> 5.052711 | P292: =O292*9 -> 45.474399 | Q292: =MAX(M292-P292,0) -> 5.4147081 | R292: =Q292*100 -> 541.47081 | T292: =T291+1 -> 2 | U292: =RAND() -> 0.44575188 | V292: =VLOOKUP(U292,$F$7:$H$12,2,TRUE())+(RAND()*(VLOOKUP(U292,$F$7:$H$12,3,TRUE())-VLOOKUP(U292,$F$7:$H$12,2,TRUE()))) -> 61.811518 | W292: =RAND() -> 0.16813524 | X292: =VLOOKUP(W292,$K$7:$M$10,2,TRUE())+(RAND()*(VLOOKUP(W292,$K$7:$M$10,3,TRUE())-VLOOKUP(W292,$K$7:$M$10,2,TRUE()))) -> 4.3104668 | Y292: =X292*10 -> 43.104668 | Z292: =MAX(V292-Y292,0) -> 18.70685 | AA292: =Z292*100 -> 1870.685 | AC292: =AC291+1 -> 2 | AD292: =RAND() -> 0.66529037 | AE292: =VLOOKUP(AD292,$F$7:$H$12,2,TRUE())+(RAND()*(VLOOKUP(AD292,$F$7:$H$12,3,TRUE())-VLOOKUP(AD292,$F$7:$H$12,2,TRUE()))) -> 68.645435 | AF292: =RAND() -> 0.67680255 | AG292: =VLOOKUP(AF292,$K$7:$M$10,2,TRUE())+(RAND()*(VLOOKUP(AF292,$K$7:$M$10,3,TRUE())-VLOOKUP(AF292,$K$7:$M$10,2,TRUE()))) -> 4.8901541 | AH292: =AG292*11 -> 53.791695 | AI292: =MAX(AE292-AH292,0) -> 14.85374 | AJ292: =AI292*100 -> 1485.374 | AL292: =AL291+1 -> 2 | AM292: =RAND() -> 0.94230512 | AN292: =VLOOKUP(AM292,$F$7:$H$12,2,TRUE())+(RAND()*(VLOOKUP(AM292,$F$7:$H$12,3,TRUE())-VLOOKUP(AM292,$F$7:$H$12,2,TRUE()))) -> 79.512554 | AO292: =RAND() -> 0.29589154 | AP292: =VLOOKUP(AO292,$K$7:$M$10,2,TRUE())+(RAND()*(VLOOKUP(AO292,$K$7:$M$10,3,TRUE())-VLOOKUP(AO292,$K$7:$M$10,2,TRUE()))) -> 4.1486518 | AQ292: =AP292*12 -> 49.783822 | AR292: =MAX(AN292-AQ292,0) -> 29.728732 | AS292: =AR292*100 -> 2972.8732 | AU292: =AU291+1 -> 2 | AV292: =RAND() -> 0.73076664 | AW292: =VLOOKUP(AV292,$F$7:$H$12,2,TRUE())+(RAND()*(VLOOKUP(AV292,$F$7:$H$12,3,TRUE())-VLOOKUP(AV292,$F$7:$H$12,2,TRUE()))) -> 66.315184 | AX292: =RAND() -> 0.05196623 | AY292: =VLOOKUP(AX292,$K$7:$M$10,2,TRUE())+(RAND()*(VLOOKUP(AX292,$K$7:$M$10,3,TRUE())-VLOOKUP(AX292,$K$7:$M$10,2,TRUE()))) -> 4.3869781 | AZ292: =AY292*13 -> 57.030715 | BA292: =MAX(AW292-AZ292,0) -> 9.2844687 | BB292: =BA292*100 -> 928.44687 | BD292: =BD291+1 -> 2 | BE292: =RAND() -> 0.63582148 | BF292: =VLOOKUP(BE292,$F$7:$H$12,2,TRUE())+(RAND()*(VLOOKUP(BE292,$F$7:$H$12,3,TRUE())-VLOOKUP(BE292,$F$7:$H$12,2,TRUE()))) -> 69.117243 | BG292: =RAND() -> 0.5031837 | BH292: =VLOOKUP(BG292,$K$7:$M$10,2,TRUE())+(RAND()*(VLOOKUP(BG292,$K$7:$M$10,3,TRUE())-VLOOKUP(BG292,$K$7:$M$10,2,TRUE()))) -> 4.5157513 | BI292: =BH292*14 -> 63.220518 | BJ292: =MAX(BF292-BI292,0) -> 5.8967251 | BK292: =BJ292*100 -> 589.67251 | BM292: =BM291+1 -> 2 | BN292: =RAND() -> 0.096864304 | BO292: =VLOOKUP(BN292,$F$7:$H$12,2,TRUE())+(RAND()*(VLOOKUP(BN292,$F$7:$H$12,3,TRUE())-VLOOKUP(BN292,$F$7:$H$12,2,TRUE()))) -> 53.893489 | BP292: =RAND() -> 0.080512262 | BQ292: =VLOOKUP(BP292,$K$7:$M$10,2,TRUE())+(RAND()*(VLOOKUP(BP292,$K$7:$M$10,3,TRUE())-VLOOKUP(BP292,$K$7:$M$10,2,TRUE()))) -> 4.188922 | BR292: =BQ292*15 -> 62.83383 | BS292: =MAX(BO292-BR292,0) -> 0 | BT292: =BS292*100 -> 0
B293: =B292+1 -> 3 | C293: =RAND() -> 0.77595554 | D293: =VLOOKUP(C293,$F$7:$H$12,2,TRUE())+(RAND()*(VLOOKUP(C293,$F$7:$H$12,3,TRUE())-VLOOKUP(C293,$F$7:$H$12,2,TRUE()))) -> 65.820732 | E293: =RAND() -> 0.80181769 | F293: =VLOOKUP(E293,$K$7:$M$10,2,TRUE())+(RAND()*(VLOOKUP(E293,$K$7:$M$10,3,TRUE())-VLOOKUP(E293,$K$7:$M$10,2,TRUE()))) -> 5.0446824 | G293: =F293*8 -> 40.357459 | H293: =MAX(D293-G293,0) -> 25.463273 | I293: =H293*100 -> 2546.3273 | K293: =K292+1 -> 3 | L293: =RAND() -> 0.78395492 | M293: =VLOOKUP(L293,$F$7:$H$12,2,TRUE())+(RAND()*(VLOOKUP(L293,$F$7:$H$12,3,TRUE())-VLOOKUP(L293,$F$7:$H$12,2,TRUE()))) -> 66.457959 | N293: =RAND() -> 0.125608 | O293: =VLOOKUP(N293,$K$7:$M$10,2,TRUE())+(RAND()*(VLOOKUP(N293,$K$7:$M$10,3,TRUE())-VLOOKUP(N293,$K$7:$M$10,2,TRUE()))) -> 4.0124124 | P293: =O293*9 -> 36.111712 | Q293: =MAX(M293-P293,0) -> 30.346248 | R293: =Q293*100 -> 3034.6248 | T293: =T292+1 -> 3 | U293: =RAND() -> 0.28559028 | V293: =VLOOKUP(U293,$F$7:$H$12,2,TRUE())+(RAND()*(VLOOKUP(U293,$F$7:$H$12,3,TRUE())-VLOOKUP(U293,$F$7:$H$12,2,TRUE()))) -> 62.342404 | W293: =RAND() -> 0.21223438 | X293: =VLOOKUP(W293,$K$7:$M$10,2,TRUE())+(RAND()*(VLOOKUP(W293,$K$7:$M$10,3,TRUE())-VLOOKUP(W293,$K$7:$M$10,2,TRUE()))) -> 4.0218873 | Y293: =X293*10 -> 40.218873 | Z293: =MAX(V293-Y293,0) -> 22.123531 | AA293: =Z293*100 -> 2212.3531 | AC293: =AC292+1 -> 3 | AD293: =RAND() -> 0.39892495 | AE293: =VLOOKUP(AD293,$F$7:$H$12,2,TRUE())+(RAND()*(VLOOKUP(AD293,$F$7:$H$12,3,TRUE())-VLOOKUP(AD293,$F$7:$H$12,2,TRUE()))) -> 60.607253 | AF293: =RAND() -> 0.78281573 | AG293: =VLOOKUP(AF293,$K$7:$M$10,2,TRUE())+(RAND()*(VLOOKUP(AF293,$K$7:$M$10,3,TRUE())-VLOOKUP(AF293,$K$7:$M$10,2,TRUE()))) -> 5.4927023 | AH293: =AG293*11 -> 60.419726 | AI293: =MAX(AE293-AH293,0) -> 0.18752687 | AJ293: =AI293*100 -> 18.752687 | AL293: =AL292+1 -> 3 | AM293: =RAND() -> 0.30281559 | AN293: =VLOOKUP(AM293,$F$7:$H$12,2,TRUE())+(RAND()*(VLOOKUP(AM293,$F$7:$H$12,3,TRUE())-VLOOKUP(AM293,$F$7:$H$12,2,TRUE()))) -> 61.164469 | AO293: =RAND() -> 0.47451187 | AP293: =VLOOKUP(AO293,$K$7:$M$10,2,TRUE())+(RAND()*(VLOOKUP(AO293,$K$7:$M$10,3,TRUE())-VLOOKUP(AO293,$K$7:$M$10,2,TRUE()))) -> 4.7244181 | AQ293: =AP293*12 -> 56.693017 | AR293: =MAX(AN293-AQ293,0) -> 4.4714525 | AS293: =AR293*100 -> 447.14525 | AU293: =AU292+1 -> 3 | AV293: =RAND() -> 0.78917706 | AW293: =VLOOKUP(AV293,$F$7:$H$12,2,TRUE())+(RAND()*(VLOOKUP(AV293,$F$7:$H$12,3,TRUE())-VLOOKUP(AV293,$F$7:$H$12,2,TRUE()))) -> 65.458421 | AX293: =RAND() -> 0.43691402 | AY293: =VLOOKUP(AX293,$K$7:$M$10,2,TRUE())+(RAND()*(VLOOKUP(AX293,$K$7:$M$10,3,TRUE())-VLOOKUP(AX293,$K$7:$M$10,2,TRUE()))) -> 4.7510867 | AZ293: =AY293*13 -> 61.764127 | BA293: =MAX(AW293-AZ293,0) -> 3.6942938 | BB293: =BA293*100 -> 369.42938 | BD293: =BD292+1 -> 3 | BE293: =RAND() -> 0.0087894385 | BF293: =VLOOKUP(BE293,$F$7:$H$12,2,TRUE())+(RAND()*(VLOOKUP(BE293,$F$7:$H$12,3,TRUE())-VLOOKUP(BE293,$F$7:$H$12,2,TRUE()))) -> 54.013482 | BG293: =RAND() -> 0.38043989 | BH293: =VLOOKUP(BG293,$K$7:$M$10,2,TRUE())+(RAND()*(VLOOKUP(BG293,$K$7:$M$10,3,TRUE())-VLOOKUP(BG293,$K$7:$M$10,2,TRUE()))) -> 4.515523 | BI293: =BH293*14 -> 63.217322 | BJ293: =MAX(BF293-BI293,0) -> 0 | BK293: =BJ293*100 -> 0 | BM293: =BM292+1 -> 3 | BN293: =RAND() -> 0.92052141 | BO293: =VLOOKUP(BN293,$F$7:$H$12,2,TRUE())+(RAND()*(VLOOKUP(BN293,$F$7:$H$12,3,TRUE())-VLOOKUP(BN293,$F$7:$H$12,2,TRUE()))) -> 75.314237 | BP293: =RAND() -> 0.48502779 | BQ293: =VLOOKUP(BP293,$K$7:$M$10,2,TRUE())+(RAND()*(VLOOKUP(BP293,$K$7:$M$10,3,TRUE())-VLOOKUP(BP293,$K$7:$M$10,2,TRUE()))) -> 4.982659 | BR293: =BQ293*15 -> 74.739885 | BS293: =MAX(BO293-BR293,0) -> 0.5743527 | BT293: =BS293*100 -> 57.43527
B294: =B293+1 -> 4 | C294: =RAND() -> 0.82158121 | D294: =VLOOKUP(C294,$F$7:$H$12,2,TRUE())+(RAND()*(VLOOKUP(C294,$F$7:$H$12,3,TRUE())-VLOOKUP(C294,$F$7:$H$12,2,TRUE()))) -> 68.647766 | E294: =RAND() -> 0.60108947 | F294: =VLOOKUP(E294,$K$7:$M$10,2,TRUE())+(RAND()*(VLOOKUP(E294,$K$7:$M$10,3,TRUE())-VLOOKUP(E294,$K$7:$M$10,2,TRUE()))) -> 4.5740199 | G294: =F294*8 -> 36.592159 | H294: =MAX(D294-G294,0) -> 32.055606 | I294: =H294*100 -> 3205.5606 | K294: =K293+1 -> 4 | L294: =RAND() -> 0.16672742 | M294: =VLOOKUP(L294,$F$7:$H$12,2,TRUE())+(RAND()*(VLOOKUP(L294,$F$7:$H$12,3,TRUE())-VLOOKUP(L294,$F$7:$H$12,2,TRUE()))) -> 58.178472 | N294: =RAND() -> 0.74374912 | O294: =VLOOKUP(N294,$K$7:$M$10,2,TRUE())+(RAND()*(VLOOKUP(N294,$K$7:$M$10,3,TRUE())-VLOOKUP(N294,$K$7:$M$10,2,TRUE()))) -> 5.3069029 | P294: =O294*9 -> 47.762126 | Q294: =MAX(M294-P294,0) -> 10.416346 | R294: =Q294*100 -> 1041.6346 | T294: =T293+1 -> 4 | U294: =RAND() -> 0.48776944 | V294: =VLOOKUP(U294,$F$7:$H$12,2,TRUE())+(RAND()*(VLOOKUP(U294,$F$7:$H$12,3,TRUE())-VLOOKUP(U294,$F$7:$H$12,2,TRUE()))) -> 61.73498 | W294: =RAND() -> 0.089094075 | X294: =VLOOKUP(W294,$K$7:$M$10,2,TRUE())+(RAND()*(VLOOKUP(W294,$K$7:$M$10,3,TRUE())-VLOOKUP(W294,$K$7:$M$10,2,TRUE()))) -> 4.1924312 | Y294: =X294*10 -> 41.924312 | Z294: =MAX(V294-Y294,0) -> 19.810667 | AA294: =Z294*100 -> 1981.0667 | AC294: =AC293+1 -> 4 | AD294: =RAND() -> 0.082457656 | AE294: =VLOOKUP(AD294,$F$7:$H$12,2,TRUE())+(RAND()*(VLOOKUP(AD294,$F$7:$H$12,3,TRUE())-VLOOKUP(AD294,$F$7:$H$12,2,TRUE()))) -> 51.541338 | AF294: =RAND() -> 0.99669703 | AG294: =VLOOKUP(AF294,$K$7:$M$10,2,TRUE())+(RAND()*(VLOOKUP(AF294,$K$7:$M$10,3,TRUE())-VLOOKUP(AF294,$K$7:$M$10,2,TRUE()))) -> 5.6312435 | AH294: =AG294*11 -> 61.943678 | AI294: =MAX(AE294-AH294,0) -> 0 | AJ294: =AI294*100 -> 0 | AL294: =AL293+1 -> 4 | AM294: =RAND() -> 0.092277239 | AN294: =VLOOKUP(AM294,$F$7:$H$12,2,TRUE())+(RAND()*(VLOOKUP(AM294,$F$7:$H$12,3,TRUE())-VLOOKUP(AM294,$F$7:$H$12,2,TRUE()))) -> 51.708076 | AO294: =RAND() -> 0.79969426 | AP294: =VLOOKUP(AO294,$K$7:$M$10,2,TRUE())+(RAND()*(VLOOKUP(AO294,$K$7:$M$10,3,TRUE())-VLOOKUP(AO294,$K$7:$M$10,2,TRUE()))) -> 5.1344872 | AQ294: =AP294*12 -> 61.613847 | AR294: =MAX(AN294-AQ294,0) -> 0 | AS294: =AR294*100 -> 0 | AU294: =AU293+1 -> 4 | AV294: =RAND() -> 0.72999075 | AW294: =VLOOKUP(AV294,$F$7:$H$12,2,TRUE())+(RAND()*(VLOOKUP(AV294,$F$7:$H$12,3,TRUE())-VLOOKUP(AV294,$F$7:$H$12,2,TRUE()))) -> 66.316839 | AX294: =RAND() -> 0.24816855 | AY294: =VLOOKUP(AX294,$K$7:$M$10,2,TRUE())+(RAND()*(VLOOKUP(AX294,$K$7:$M$10,3,TRUE())-VLOOKUP(AX294,$K$7:$M$10,2,TRUE()))) -> 4.105308 | AZ294: =AY294*13 -> 53.369004 | BA294: =MAX(AW294-AZ294,0) -> 12.947836 | BB294: =BA294*100 -> 1294.7836 | BD294: =BD293+1 -> 4 | BE294: =RAND() -> 0.41848676 | BF294: =VLOOKUP(BE294,$F$7:$H$12,2,TRUE())+(RAND()*(VLOOKUP(BE294,$F$7:$H$12,3,TRUE())-VLOOKUP(BE294,$F$7:$H$12,2,TRUE()))) -> 63.483653 | BG294: =RAND() -> 0.54434508 | BH294: =VLOOKUP(BG294,$K$7:$M$10,2,TRUE())+(RAND()*(VLOOKUP(BG294,$K$7:$M$10,3,TRUE())-VLOOKUP(BG294,$K$7:$M$10,2,TRUE()))) -> 4.7396614 | BI294: =BH294*14 -> 66.35526 | BJ294: =MAX(BF294-BI294,0) -> 0 | BK294: =BJ294*100 -> 0 | BM294: =BM293+1 -> 4 | BN294: =RAND() -> 0.53292389 | BO294: =VLOOKUP(BN294,$F$7:$H$12,2,TRUE())+(RAND()*(VLOOKUP(BN294,$F$7:$H$12,3,TRUE())-VLOOKUP(BN294,$F$7:$H$12,2,TRUE()))) -> 60.782442 | BP294: =RAND() -> 0.074916506 | BQ294: =VLOOKUP(BP294,$K$7:$M$10,2,TRUE())+(RAND()*(VLOOKUP(BP294,$K$7:$M$10,3,TRUE())-VLOOKUP(BP294,$K$7:$M$10,2,TRUE()))) -> 4.0848567 | BR294: =BQ294*15 -> 61.272851 | BS294: =MAX(BO294-BR294,0) -> 0 | BT294: =BS294*100 -> 0
B295: =B294+1 -> 5 | C295: =RAND() -> 0.35825924 | D295: =VLOOKUP(C295,$F$7:$H$12,2,TRUE())+(RAND()*(VLOOKUP(C295,$F$7:$H$12,3,TRUE())-VLOOKUP(C295,$F$7:$H$12,2,TRUE()))) -> 60.419599 | E295: =RAND() -> 0.97315506 | F295: =VLOOKUP(E295,$K$7:$M$10,2,TRUE())+(RAND()*(VLOOKUP(E295,$K$7:$M$10,3,TRUE())-VLOOKUP(E295,$K$7:$M$10,2,TRUE()))) -> 5.8641036 | G295: =F295*8 -> 46.912829 | H295: =MAX(D295-G295,0) -> 13.50677 | I295: =H295*100 -> 1350.677 | K295: =K294+1 -> 5 | L295: =RAND() -> 0.034814589 | M295: =VLOOKUP(L295,$F$7:$H$12,2,TRUE())+(RAND()*(VLOOKUP(L295,$F$7:$H$12,3,TRUE())-VLOOKUP(L295,$F$7:$H$12,2,TRUE()))) -> 54.741931 | N295: =RAND() -> 0.17673697 | O295: =VLOOKUP(N295,$K$7:$M$10,2,TRUE())+(RAND()*(VLOOKUP(N295,$K$7:$M$10,3,TRUE())-VLOOKUP(N295,$K$7:$M$10,2,TRUE()))) -> 4.0531013 | P295: =O295*9 -> 36.477911 | Q295: =MAX(M295-P295,0) -> 18.26402 | R295: =Q295*100 -> 1826.402 | T295: =T294+1 -> 5 | U295: =RAND() -> 0.36804824 | V295: =VLOOKUP(U295,$F$7:$H$12,2,TRUE())+(RAND()*(VLOOKUP(U295,$F$7:$H$12,3,TRUE())-VLOOKUP(U295,$F$7:$H$12,2,TRUE()))) -> 64.906199 | W295: =RAND() -> 0.20329307 | X295: =VLOOKUP(W295,$K$7:$M$10,2,TRUE())+(RAND()*(VLOOKUP(W295,$K$7:$M$10,3,TRUE())-VLOOKUP(W295,$K$7:$M$10,2,TRUE()))) -> 4.3569703 | Y295: =X295*10 -> 43.569703 | Z295: =MAX(V295-Y295,0) -> 21.336496 | AA295: =Z295*100 -> 2133.6496 | AC295: =AC294+1 -> 5 | AD295: =RAND() -> 0.24329234 | AE295: =VLOOKUP(AD295,$F$7:$H$12,2,TRUE())+(RAND()*(VLOOKUP(AD295,$F$7:$H$12,3,TRUE())-VLOOKUP(AD295,$F$7:$H$12,2,TRUE()))) -> 58.639295 | AF295: =RAND() -> 0.87851498 | AG295: =VLOOKUP(AF295,$K$7:$M$10,2,TRUE())+(RAND()*(VLOOKUP(AF295,$K$7:$M$10,3,TRUE())-VLOOKUP(AF295,$K$7:$M$10,2,TRUE()))) -> 5.1121988 | AH295: =AG295*11 -> 56.234187 | AI295: =MAX(AE295-AH295,0) -> 2.4051082 | AJ295: =AI295*100 -> 240.51082 | AL295: =AL294+1 -> 5 | AM295: =RAND() -> 0.15063941 | AN295: =VLOOKUP(AM295,$F$7:$H$12,2,TRUE())+(RAND()*(VLOOKUP(AM295,$F$7:$H$12,3,TRUE())-VLOOKUP(AM295,$F$7:$H$12,2,TRUE()))) -> 56.866873 | AO295: =RAND() -> 0.6591654 | AP295: =VLOOKUP(AO295,$K$7:$M$10,2,TRUE())+(RAND()*(VLOOKUP(AO295,$K$7:$M$10,3,TRUE())-VLOOKUP(AO295,$K$7:$M$10,2,TRUE()))) -> 4.9702833 | AQ295: =AP295*12 -> 59.643399 | AR295: =MAX(AN295-AQ295,0) -> 0 | AS295: =AR295*100 -> 0 | AU295: =AU294+1 -> 5 | AV295: =RAND() -> 0.040340898 | AW295: =VLOOKUP(AV295,$F$7:$H$12,2,TRUE())+(RAND()*(VLOOKUP(AV295,$F$7:$H$12,3,TRUE())-VLOOKUP(AV295,$F$7:$H$12,2,TRUE()))) -> 51.460248 | AX295: =RAND() -> 0.81081859 | AY295: =VLOOKUP(AX295,$K$7:$M$10,2,TRUE())+(RAND()*(VLOOKUP(AX295,$K$7:$M$10,3,TRUE())-VLOOKUP(AX295,$K$7:$M$10,2,TRUE()))) -> 5.2829957 | AZ295: =AY295*13 -> 68.678944 | BA295: =MAX(AW295-AZ295,0) -> 0 | BB295: =BA295*100 -> 0 | BD295: =BD294+1 -> 5 | BE295: =RAND() -> 0.41691306 | BF295: =VLOOKUP(BE295,$F$7:$H$12,2,TRUE())+(RAND()*(VLOOKUP(BE295,$F$7:$H$12,3,TRUE())-VLOOKUP(BE295,$F$7:$H$12,2,TRUE()))) -> 61.024792 | BG295: =RAND() -> 0.76747876 | BH295: =VLOOKUP(BG295,$K$7:$M$10,2,TRUE())+(RAND()*(VLOOKUP(BG295,$K$7:$M$10,3,TRUE())-VLOOKUP(BG295,$K$7:$M$10,2,TRUE()))) -> 5.4866618 | BI295: =BH295*14 -> 76.813265 | BJ295: =MAX(BF295-BI295,0) -> 0 | BK295: =BJ295*100 -> 0 | BM295: =BM294+1 -> 5 | BN295: =RAND() -> 0.21528706 | BO295: =VLOOKUP(BN295,$F$7:$H$12,2,TRUE())+(RAND()*(VLOOKUP(BN295,$F$7:$H$12,3,TRUE())-VLOOKUP(BN295,$F$7:$H$12,2,TRUE()))) -> 56.753296 | BP295: =RAND() -> 0.34064886 | BQ295: =VLOOKUP(BP295,$K$7:$M$10,2,TRUE())+(RAND()*(VLOOKUP(BP295,$K$7:$M$10,3,TRUE())-VLOOKUP(BP295,$K$7:$M$10,2,TRUE()))) -> 4.8384344 | BR295: =BQ295*15 -> 72.576515 | BS295: =MAX(BO295-BR295,0) -> 0 | BT295: =BS295*100 -> 0
B296: =B295+1 -> 6 | C296: =RAND() -> 0.43859403 | D296: =VLOOKUP(C296,$F$7:$H$12,2,TRUE())+(RAND()*(VLOOKUP(C296,$F$7:$H$12,3,TRUE())-VLOOKUP(C296,$F$7:$H$12,2,TRUE()))) -> 61.195992 | E296: =RAND() -> 0.80265181 | F296: =VLOOKUP(E296,$K$7:$M$10,2,TRUE())+(RAND()*(VLOOKUP(E296,$K$7:$M$10,3,TRUE())-VLOOKUP(E296,$K$7:$M$10,2,TRUE()))) -> 5.067718 | G296: =F296*8 -> 40.541744 | H296: =MAX(D296-G296,0) -> 20.654248 | I296: =H296*100 -> 2065.4248 | K296: =K295+1 -> 6 | L296: =RAND() -> 0.453321 | M296: =VLOOKUP(L296,$F$7:$H$12,2,TRUE())+(RAND()*(VLOOKUP(L296,$F$7:$H$12,3,TRUE())-VLOOKUP(L296,$F$7:$H$12,2,TRUE()))) -> 61.311758 | N296: =RAND() -> 0.29941633 | O296: =VLOOKUP(N296,$K$7:$M$10,2,TRUE())+(RAND()*(VLOOKUP(N296,$K$7:$M$10,3,TRUE())-VLOOKUP(N296,$K$7:$M$10,2,TRUE()))) -> 4.3344311 | P296: =O296*9 -> 39.00988 | Q296: =MAX(M296-P296,0) -> 22.301878 | R296: =Q296*100 -> 2230.1878 | T296: =T295+1 -> 6 | U296: =RAND() -> 0.40762476 | V296: =VLOOKUP(U296,$F$7:$H$12,2,TRUE())+(RAND()*(VLOOKUP(U296,$F$7:$H$12,3,TRUE())-VLOOKUP(U296,$F$7:$H$12,2,TRUE()))) -> 62.739501 | W296: =RAND() -> 0.59588004 | X296: =VLOOKUP(W296,$K$7:$M$10,2,TRUE())+(RAND()*(VLOOKUP(W296,$K$7:$M$10,3,TRUE())-VLOOKUP(W296,$K$7:$M$10,2,TRUE()))) -> 4.9500639 | Y296: =X296*10 -> 49.500639 | Z296: =MAX(V296-Y296,0) -> 13.238862 | AA296: =Z296*100 -> 1323.8862 | AC296: =AC295+1 -> 6 | AD296: =RAND() -> 0.24645547 | AE296: =VLOOKUP(AD296,$F$7:$H$12,2,TRUE())+(RAND()*(VLOOKUP(AD296,$F$7:$H$12,3,TRUE())-VLOOKUP(AD296,$F$7:$H$12,2,TRUE()))) -> 58.47934 | AF296: =RAND() -> 0.59043959 | AG296: =VLOOKUP(AF296,$K$7:$M$10,2,TRUE())+(RAND()*(VLOOKUP(AF296,$K$7:$M$10,3,TRUE())-VLOOKUP(AF296,$K$7:$M$10,2,TRUE()))) -> 4.5252062 | AH296: =AG296*11 -> 49.777268 | AI296: =MAX(AE296-AH296,0) -> 8.7020717 | AJ296: =AI296*100 -> 870.20717 | AL296: =AL295+1 -> 6 | AM296: =RAND() -> 0.85255166 | AN296: =VLOOKUP(AM296,$F$7:$H$12,2,TRUE())+(RAND()*(VLOOKUP(AM296,$F$7:$H$12,3,TRUE())-VLOOKUP(AM296,$F$7:$H$12,2,TRUE()))) -> 68.143819 | AO296: =RAND() -> 0.80431011 | AP296: =VLOOKUP(AO296,$K$7:$M$10,2,TRUE())+(RAND()*(VLOOKUP(AO296,$K$7:$M$10,3,TRUE())-VLOOKUP(AO296,$K$7:$M$10,2,TRUE()))) -> 5.4686575 | AQ296: =AP296*12 -> 65.623889 | AR296: =MAX(AN296-AQ296,0) -> 2.5199292 | AS296: =AR296*100 -> 251.99292 | AU296: =AU295+1 -> 6 | AV296: =RAND() -> 0.54749469 | AW296: =VLOOKUP(AV296,$F$7:$H$12,2,TRUE())+(RAND()*(VLOOKUP(AV296,$F$7:$H$12,3,TRUE())-VLOOKUP(AV296,$F$7:$H$12,2,TRUE()))) -> 63.120859 | AX296: =RAND() -> 0.12225764 | AY296: =VLOOKUP(AX296,$K$7:$M$10,2,TRUE())+(RAND()*(VLOOKUP(AX296,$K$7:$M$10,3,TRUE())-VLOOKUP(AX296,$K$7:$M$10,2,TRUE()))) -> 4.1910752 | AZ296: =AY296*13 -> 54.483978 | BA296: =MAX(AW296-AZ296,0) -> 8.6368809 | BB296: =BA296*100 -> 863.68809 | BD296: =BD295+1 -> 6 | BE296: =RAND() -> 0.44619217 | BF296: =VLOOKUP(BE296,$F$7:$H$12,2,TRUE())+(RAND()*(VLOOKUP(BE296,$F$7:$H$12,3,TRUE())-VLOOKUP(BE296,$F$7:$H$12,2,TRUE()))) -> 62.337 | BG296: =RAND() -> 0.23844094 | BH296: =VLOOKUP(BG296,$K$7:$M$10,2,TRUE())+(RAND()*(VLOOKUP(BG296,$K$7:$M$10,3,TRUE())-VLOOKUP(BG296,$K$7:$M$10,2,TRUE()))) -> 4.1768575 | BI296: =BH296*14 -> 58.476005 | BJ296: =MAX(BF296-BI296,0) -> 3.8609952 | BK296: =BJ296*100 -> 386.09952 | BM296: =BM295+1 -> 6 | BN296: =RAND() -> 0.95971595 | BO296: =VLOOKUP(BN296,$F$7:$H$12,2,TRUE())+(RAND()*(VLOOKUP(BN296,$F$7:$H$12,3,TRUE())-VLOOKUP(BN296,$F$7:$H$12,2,TRUE()))) -> 76.163193 | BP296: =RAND() -> 0.88680023 | BQ296: =VLOOKUP(BP296,$K$7:$M$10,2,TRUE())+(RAND()*(VLOOKUP(BP296,$K$7:$M$10,3,TRUE())-VLOOKUP(BP296,$K$7:$M$10,2,TRUE()))) -> 5.1201347 | BR296: =BQ296*15 -> 76.802021 | BS296: =MAX(BO296-BR296,0) -> 0 | BT296: =BS296*100 -> 0
B297: =B296+1 -> 7 | C297: =RAND() -> 0.14561261 | D297: =VLOOKUP(C297,$F$7:$H$12,2,TRUE())+(RAND()*(VLOOKUP(C297,$F$7:$H$12,3,TRUE())-VLOOKUP(C297,$F$7:$H$12,2,TRUE()))) -> 59.006654 | E297: =RAND() -> 0.3847614 | F297: =VLOOKUP(E297,$K$7:$M$10,2,TRUE())+(RAND()*(VLOOKUP(E297,$K$7:$M$10,3,TRUE())-VLOOKUP(E297,$K$7:$M$10,2,TRUE()))) -> 4.9798311 | G297: =F297*8 -> 39.838649 | H297: =MAX(D297-G297,0) -> 19.168006 | I297: =H297*100 -> 1916.8006 | K297: =K296+1 -> 7 | L297: =RAND() -> 0.86291954 | M297: =VLOOKUP(L297,$F$7:$H$12,2,TRUE())+(RAND()*(VLOOKUP(L297,$F$7:$H$12,3,TRUE())-VLOOKUP(L297,$F$7:$H$12,2,TRUE()))) -> 65.505136 | N297: =RAND() -> 0.98428494 | O297: =VLOOKUP(N297,$K$7:$M$10,2,TRUE())+(RAND()*(VLOOKUP(N297,$K$7:$M$10,3,TRUE())-VLOOKUP(N297,$K$7:$M$10,2,TRUE()))) -> 5.5676915 | P297: =O297*9 -> 50.109224 | Q297: =MAX(M297-P297,0) -> 15.395913 | R297: =Q297*100 -> 1539.5913 | T297: =T296+1 -> 7 | U297: =RAND() -> 0.32287688 | V297: =VLOOKUP(U297,$F$7:$H$12,2,TRUE())+(RAND()*(VLOOKUP(U297,$F$7:$H$12,3,TRUE())-VLOOKUP(U297,$F$7:$H$12,2,TRUE()))) -> 61.615869 | W297: =RAND() -> 0.097856688 | X297: =VLOOKUP(W297,$K$7:$M$10,2,TRUE())+(RAND()*(VLOOKUP(W297,$K$7:$M$10,3,TRUE())-VLOOKUP(W297,$K$7:$M$10,2,TRUE()))) -> 4.0050743 | Y297: =X297*10 -> 40.050743 | Z297: =MAX(V297-Y297,0) -> 21.565126 | AA297: =Z297*100 -> 2156.5126 | AC297: =AC296+1 -> 7 | AD297: =RAND() -> 0.12800505 | AE297: =VLOOKUP(AD297,$F$7:$H$12,2,TRUE())+(RAND()*(VLOOKUP(AD297,$F$7:$H$12,3,TRUE())-VLOOKUP(AD297,$F$7:$H$12,2,TRUE()))) -> 58.519589 | AF297: =RAND() -> 0.53354355 | AG297: =VLOOKUP(AF297,$K$7:$M$10,2,TRUE())+(RAND()*(VLOOKUP(AF297,$K$7:$M$10,3,TRUE())-VLOOKUP(AF297,$K$7:$M$10,2,TRUE()))) -> 4.9453501 | AH297: =AG297*11 -> 54.398851 | AI297: =MAX(AE297-AH297,0) -> 4.1207387 | AJ297: =AI297*100 -> 412.07387 | AL297: =AL296+1 -> 7 | AM297: =RAND() -> 0.98308125 | AN297: =VLOOKUP(AM297,$F$7:$H$12,2,TRUE())+(RAND()*(VLOOKUP(AM297,$F$7:$H$12,3,TRUE())-VLOOKUP(AM297,$F$7:$H$12,2,TRUE()))) -> 84.459749 | AO297: =RAND() -> 0.83862988 | AP297: =VLOOKUP(AO297,$K$7:$M$10,2,TRUE())+(RAND()*(VLOOKUP(AO297,$K$7:$M$10,3,TRUE())-VLOOKUP(AO297,$K$7:$M$10,2,TRUE()))) -> 5.2498582 | AQ297: =AP297*12 -> 62.998298 | AR297: =MAX(AN297-AQ297,0) -> 21.461451 | AS297: =AR297*100 -> 2146.1451 | AU297: =AU296+1 -> 7 | AV297: =RAND() -> 0.20860495 | AW297: =VLOOKUP(AV297,$F$7:$H$12,2,TRUE())+(RAND()*(VLOOKUP(AV297,$F$7:$H$12,3,TRUE())-VLOOKUP(AV297,$F$7:$H$12,2,TRUE()))) -> 56.202116 | AX297: =RAND() -> 0.9136502 | AY297: =VLOOKUP(AX297,$K$7:$M$10,2,TRUE())+(RAND()*(VLOOKUP(AX297,$K$7:$M$10,3,TRUE())-VLOOKUP(AX297,$K$7:$M$10,2,TRUE()))) -> 5.9306043 | AZ297: =AY297*13 -> 77.097856 | BA297: =MAX(AW297-AZ297,0) -> 0 | BB297: =BA297*100 -> 0 | BD297: =BD296+1 -> 7 | BE297: =RAND() -> 0.50170639 | BF297: =VLOOKUP(BE297,$F$7:$H$12,2,TRUE())+(RAND()*(VLOOKUP(BE297,$F$7:$H$12,3,TRUE())-VLOOKUP(BE297,$F$7:$H$12,2,TRUE()))) -> 60.255309 | BG297: =RAND() -> 0.74349574 | BH297: =VLOOKUP(BG297,$K$7:$M$10,2,TRUE())+(RAND()*(VLOOKUP(BG297,$K$7:$M$10,3,TRUE())-VLOOKUP(BG297,$K$7:$M$10,2,TRUE()))) -> 5.4344469 | BI297: =BH297*14 -> 76.082257 | BJ297: =MAX(BF297-BI297,0) -> 0 | BK297: =BJ297*100 -> 0 | BM297: =BM296+1 -> 7 | BN297: =RAND() -> 0.061878851 | BO297: =VLOOKUP(BN297,$F$7:$H$12,2,TRUE())+(RAND()*(VLOOKUP(BN297,$F$7:$H$12,3,TRUE())-VLOOKUP(BN297,$F$7:$H$12,2,TRUE()))) -> 53.993419 | BP297: =RAND() -> 0.94588201 | BQ297: =VLOOKUP(BP297,$K$7:$M$10,2,TRUE())+(RAND()*(VLOOKUP(BP297,$K$7:$M$10,3,TRUE())-VLOOKUP(BP297,$K$7:$M$10,2,TRUE()))) -> 5.781177 | BR297: =BQ297*15 -> 86.717655 | BS297: =MAX(BO297-BR297,0) -> 0 | BT297: =BS297*100 -> 0
B298: =B297+1 -> 8 | C298: =RAND() -> 0.75291793 | D298: =VLOOKUP(C298,$F$7:$H$12,2,TRUE())+(RAND()*(VLOOKUP(C298,$F$7:$H$12,3,TRUE())-VLOOKUP(C298,$F$7:$H$12,2,TRUE()))) -> 68.697206 | E298: =RAND() -> 0.58517298 | F298: =VLOOKUP(E298,$K$7:$M$10,2,TRUE())+(RAND()*(VLOOKUP(E298,$K$7:$M$10,3,TRUE())-VLOOKUP(E298,$K$7:$M$10,2,TRUE()))) -> 4.9346766 | G298: =F298*8 -> 39.477413 | H298: =MAX(D298-G298,0) -> 29.219793 | I298: =H298*100 -> 2921.9793 | K298: =K297+1 -> 8 | L298: =RAND() -> 0.68880222 | M298: =VLOOKUP(L298,$F$7:$H$12,2,TRUE())+(RAND()*(VLOOKUP(L298,$F$7:$H$12,3,TRUE())-VLOOKUP(L298,$F$7:$H$12,2,TRUE()))) -> 68.904021 | N298: =RAND() -> 0.10421782 | O298: =VLOOKUP(N298,$K$7:$M$10,2,TRUE())+(RAND()*(VLOOKUP(N298,$K$7:$M$10,3,TRUE())-VLOOKUP(N298,$K$7:$M$10,2,TRUE()))) -> 4.0843695 | P298: =O298*9 -> 36.759326 | Q298: =MAX(M298-P298,0) -> 32.144696 | R298: =Q298*100 -> 3214.4696 | T298: =T297+1 -> 8 | U298: =RAND() -> 0.65435762 | V298: =VLOOKUP(U298,$F$7:$H$12,2,TRUE())+(RAND()*(VLOOKUP(U298,$F$7:$H$12,3,TRUE())-VLOOKUP(U298,$F$7:$H$12,2,TRUE()))) -> 69.918506 | W298: =RAND() -> 0.76650992 | X298: =VLOOKUP(W298,$K$7:$M$10,2,TRUE())+(RAND()*(VLOOKUP(W298,$K$7:$M$10,3,TRUE())-VLOOKUP(W298,$K$7:$M$10,2,TRUE()))) -> 5.4749001 | Y298: =X298*10 -> 54.749001 | Z298: =MAX(V298-Y298,0) -> 15.169505 | AA298: =Z298*100 -> 1516.9505 | AC298: =AC297+1 -> 8 | AD298: =RAND() -> 0.91620361 | AE298: =VLOOKUP(AD298,$F$7:$H$12,2,TRUE())+(RAND()*(VLOOKUP(AD298,$F$7:$H$12,3,TRUE())-VLOOKUP(AD298,$F$7:$H$12,2,TRUE()))) -> 75.837069 | AF298: =RAND() -> 0.74359343 | AG298: =VLOOKUP(AF298,$K$7:$M$10,2,TRUE())+(RAND()*(VLOOKUP(AF298,$K$7:$M$10,3,TRUE())-VLOOKUP(AF298,$K$7:$M$10,2,TRUE()))) -> 5.0800354 | AH298: =AG298*11 -> 55.880389 | AI298: =MAX(AE298-AH298,0) -> 19.956681 | AJ298: =AI298*100 -> 1995.6681 | AL298: =AL297+1 -> 8 | AM298: =RAND() -> 0.30528113 | AN298: =VLOOKUP(AM298,$F$7:$H$12,2,TRUE())+(RAND()*(VLOOKUP(AM298,$F$7:$H$12,3,TRUE())-VLOOKUP(AM298,$F$7:$H$12,2,TRUE()))) -> 62.766825 | AO298: =RAND() -> 0.63385418 | AP298: =VLOOKUP(AO298,$K$7:$M$10,2,TRUE())+(RAND()*(VLOOKUP(AO298,$K$7:$M$10,3,TRUE())-VLOOKUP(AO298,$K$7:$M$10,2,TRUE()))) -> 4.9566018 | AQ298: =AP298*12 -> 59.479222 | AR298: =MAX(AN298-AQ298,0) -> 3.2876029 | AS298: =AR298*100 -> 328.76029 | AU298: =AU297+1 -> 8 | AV298: =RAND() -> 0.011185619 | AW298: =VLOOKUP(AV298,$F$7:$H$12,2,TRUE())+(RAND()*(VLOOKUP(AV298,$F$7:$H$12,3,TRUE())-VLOOKUP(AV298,$F$7:$H$12,2,TRUE()))) -> 53.345185 | AX298: =RAND() -> 0.921889 | AY298: =VLOOKUP(AX298,$K$7:$M$10,2,TRUE())+(RAND()*(VLOOKUP(AX298,$K$7:$M$10,3,TRUE())-VLOOKUP(AX298,$K$7:$M$10,2,TRUE()))) -> 5.502974 | AZ298: =AY298*13 -> 71.538663 | BA298: =MAX(AW298-AZ298,0) -> 0 | BB298: =BA298*100 -> 0 | BD298: =BD297+1 -> 8 | BE298: =RAND() -> 0.96633423 | BF298: =VLOOKUP(BE298,$F$7:$H$12,2,TRUE())+(RAND()*(VLOOKUP(BE298,$F$7:$H$12,3,TRUE())-VLOOKUP(BE298,$F$7:$H$12,2,TRUE()))) -> 79.158406 | BG298: =RAND() -> 0.44011902 | BH298: =VLOOKUP(BG298,$K$7:$M$10,2,TRUE())+(RAND()*(VLOOKUP(BG298,$K$7:$M$10,3,TRUE())-VLOOKUP(BG298,$K$7:$M$10,2,TRUE()))) -> 4.7840455 | BI298: =BH298*14 -> 66.976637 | BJ298: =MAX(BF298-BI298,0) -> 12.181769 | BK298: =BJ298*100 -> 1218.1769 | BM298: =BM297+1 -> 8 | BN298: =RAND() -> 0.48433743 | BO298: =VLOOKUP(BN298,$F$7:$H$12,2,TRUE())+(RAND()*(VLOOKUP(BN298,$F$7:$H$12,3,TRUE())-VLOOKUP(BN298,$F$7:$H$12,2,TRUE()))) -> 62.207303 | BP298: =RAND() -> 0.097142769 | BQ298: =VLOOKUP(BP298,$K$7:$M$10,2,TRUE())+(RAND()*(VLOOKUP(BP298,$K$7:$M$10,3,TRUE())-VLOOKUP(BP298,$K$7:$M$10,2,TRUE()))) -> 4.483062 | BR298: =BQ298*15 -> 67.24593 | BS298: =MAX(BO298-BR298,0) -> 0 | BT298: =BS298*100 -> 0
B299: =B298+1 -> 9 | C299: =RAND() -> 0.81434095 | D299: =VLOOKUP(C299,$F$7:$H$12,2,TRUE())+(RAND()*(VLOOKUP(C299,$F$7:$H$12,3,TRUE())-VLOOKUP(C299,$F$7:$H$12,2,TRUE()))) -> 68.621771 | E299: =RAND() -> 0.87958612 | F299: =VLOOKUP(E299,$K$7:$M$10,2,TRUE())+(RAND()*(VLOOKUP(E299,$K$7:$M$10,3,TRUE())-VLOOKUP(E299,$K$7:$M$10,2,TRUE()))) -> 5.1798774 | G299: =F299*8 -> 41.439019 | H299: =MAX(D299-G299,0) -> 27.182752 | I299: =H299*100 -> 2718.2752 | K299: =K298+1 -> 9 | L299: =RAND() -> 0.42040352 | M299: =VLOOKUP(L299,$F$7:$H$12,2,TRUE())+(RAND()*(VLOOKUP(L299,$F$7:$H$12,3,TRUE())-VLOOKUP(L299,$F$7:$H$12,2,TRUE()))) -> 63.322077 | N299: =RAND() -> 0.83725592 | O299: =VLOOKUP(N299,$K$7:$M$10,2,TRUE())+(RAND()*(VLOOKUP(N299,$K$7:$M$10,3,TRUE())-VLOOKUP(N299,$K$7:$M$10,2,TRUE()))) -> 5.3066431 | P299: =O299*9 -> 47.759788 | Q299: =MAX(M299-P299,0) -> 15.562289 | R299: =Q299*100 -> 1556.2289 | T299: =T298+1 -> 9 | U299: =RAND() -> 0.67465311 | V299: =VLOOKUP(U299,$F$7:$H$12,2,TRUE())+(RAND()*(VLOOKUP(U299,$F$7:$H$12,3,TRUE())-VLOOKUP(U299,$F$7:$H$12,2,TRUE()))) -> 69.304012 | W299: =RAND() -> 0.9994084 | X299: =VLOOKUP(W299,$K$7:$M$10,2,TRUE())+(RAND()*(VLOOKUP(W299,$K$7:$M$10,3,TRUE())-VLOOKUP(W299,$K$7:$M$10,2,TRUE()))) -> 5.7642011 | Y299: =X299*10 -> 57.642011 | Z299: =MAX(V299-Y299,0) -> 11.662001 | AA299: =Z299*100 -> 1166.2001 | AC299: =AC298+1 -> 9 | AD299: =RAND() -> 0.24020212 | AE299: =VLOOKUP(AD299,$F$7:$H$12,2,TRUE())+(RAND()*(VLOOKUP(AD299,$F$7:$H$12,3,TRUE())-VLOOKUP(AD299,$F$7:$H$12,2,TRUE()))) -> 59.51558 | AF299: =RAND() -> 0.14446079 | AG299: =VLOOKUP(AF299,$K$7:$M$10,2,TRUE())+(RAND()*(VLOOKUP(AF299,$K$7:$M$10,3,TRUE())-VLOOKUP(AF299,$K$7:$M$10,2,TRUE()))) -> 4.2364268 | AH299: =AG299*11 -> 46.600695 | AI299: =MAX(AE299-AH299,0) -> 12.914885 | AJ299: =AI299*100 -> 1291.4885 | AL299: =AL298+1 -> 9 | AM299: =RAND() -> 0.6962703 | AN299: =VLOOKUP(AM299,$F$7:$H$12,2,TRUE())+(RAND()*(VLOOKUP(AM299,$F$7:$H$12,3,TRUE())-VLOOKUP(AM299,$F$7:$H$12,2,TRUE()))) -> 67.096358 | AO299: =RAND() -> 0.85552333 | AP299: =VLOOKUP(AO299,$K$7:$M$10,2,TRUE())+(RAND()*(VLOOKUP(AO299,$K$7:$M$10,3,TRUE())-VLOOKUP(AO299,$K$7:$M$10,2,TRUE()))) -> 5.162789 | AQ299: =AP299*12 -> 61.953468 | AR299: =MAX(AN299-AQ299,0) -> 5.1428893 | AS299: =AR299*100 -> 514.28893 | AU299: =AU298+1 -> 9 | AV299: =RAND() -> 0.62983803 | AW299: =VLOOKUP(AV299,$F$7:$H$12,2,TRUE())+(RAND()*(VLOOKUP(AV299,$F$7:$H$12,3,TRUE())-VLOOKUP(AV299,$F$7:$H$12,2,TRUE()))) -> 67.293768 | AX299: =RAND() -> 0.3020091 | AY299: =VLOOKUP(AX299,$K$7:$M$10,2,TRUE())+(RAND()*(VLOOKUP(AX299,$K$7:$M$10,3,TRUE())-VLOOKUP(AX299,$K$7:$M$10,2,TRUE()))) -> 4.8279762 | AZ299: =AY299*13 -> 62.763691 | BA299: =MAX(AW299-AZ299,0) -> 4.5300773 | BB299: =BA299*100 -> 453.00773 | BD299: =BD298+1 -> 9 | BE299: =RAND() -> 0.50332229 | BF299: =VLOOKUP(BE299,$F$7:$H$12,2,TRUE())+(RAND()*(VLOOKUP(BE299,$F$7:$H$12,3,TRUE())-VLOOKUP(BE299,$F$7:$H$12,2,TRUE()))) -> 60.069927 | BG299: =RAND() -> 0.0014924405 | BH299: =VLOOKUP(BG299,$K$7:$M$10,2,TRUE())+(RAND()*(VLOOKUP(BG299,$K$7:$M$10,3,TRUE())-VLOOKUP(BG299,$K$7:$M$10,2,TRUE()))) -> 4.1287725 | BI299: =BH299*14 -> 57.802816 | BJ299: =MAX(BF299-BI299,0) -> 2.2671111 | BK299: =BJ299*100 -> 226.71111 | BM299: =BM298+1 -> 9 | BN299: =RAND() -> 0.97791139 | BO299: =VLOOKUP(BN299,$F$7:$H$12,2,TRUE())+(RAND()*(VLOOKUP(BN299,$F$7:$H$12,3,TRUE())-VLOOKUP(BN299,$F$7:$H$12,2,TRUE()))) -> 78.4157 | BP299: =RAND() -> 0.44325478 | BQ299: =VLOOKUP(BP299,$K$7:$M$10,2,TRUE())+(RAND()*(VLOOKUP(BP299,$K$7:$M$10,3,TRUE())-VLOOKUP(BP299,$K$7:$M$10,2,TRUE()))) -> 4.9282951 | BR299: =BQ299*15 -> 73.924427 | BS299: =MAX(BO299-BR299,0) -> 4.4912736 | BT299: =BS299*100 -> 449.12736
B300: =B299+1 -> 10 | C300: =RAND() -> 0.45522576 | D300: =VLOOKUP(C300,$F$7:$H$12,2,TRUE())+(RAND()*(VLOOKUP(C300,$F$7:$H$12,3,TRUE())-VLOOKUP(C300,$F$7:$H$12,2,TRUE()))) -> 61.854815 | E300: =RAND() -> 0.6847739 | F300: =VLOOKUP(E300,$K$7:$M$10,2,TRUE())+(RAND()*(VLOOKUP(E300,$K$7:$M$10,3,TRUE())-VLOOKUP(E300,$K$7:$M$10,2,TRUE()))) -> 4.5685142 | G300: =F300*8 -> 36.548113 | H300: =MAX(D300-G300,0) -> 25.306702 | I300: =H300*100 -> 2530.6702 | K300: =K299+1 -> 10 | L300: =RAND() -> 0.097593584 | M300: =VLOOKUP(L300,$F$7:$H$12,2,TRUE())+(RAND()*(VLOOKUP(L300,$F$7:$H$12,3,TRUE())-VLOOKUP(L300,$F$7:$H$12,2,TRUE()))) -> 50.407876 | N300: =RAND() -> 0.18098656 | O300: =VLOOKUP(N300,$K$7:$M$10,2,TRUE())+(RAND()*(VLOOKUP(N300,$K$7:$M$10,3,TRUE())-VLOOKUP(N300,$K$7:$M$10,2,TRUE()))) -> 4.212455 | P300: =O300*9 -> 37.912095 | Q300: =MAX(M300-P300,0) -> 12.495781 | R300: =Q300*100 -> 1249.5781 | T300: =T299+1 -> 10 | U300: =RAND() -> 0.87886173 | V300: =VLOOKUP(U300,$F$7:$H$12,2,TRUE())+(RAND()*(VLOOKUP(U300,$F$7:$H$12,3,TRUE())-VLOOKUP(U300,$F$7:$H$12,2,TRUE()))) -> 65.572296 | W300: =RAND() -> 0.22262312 | X300: =VLOOKUP(W300,$K$7:$M$10,2,TRUE())+(RAND()*(VLOOKUP(W300,$K$7:$M$10,3,TRUE())-VLOOKUP(W300,$K$7:$M$10,2,TRUE()))) -> 4.005079 | Y300: =X300*10 -> 40.05079 | Z300: =MAX(V300-Y300,0) -> 25.521506 | AA300: =Z300*100 -> 2552.1506 | AC300: =AC299+1 -> 10 | AD300: =RAND() -> 0.48462895 | AE300: =VLOOKUP(AD300,$F$7:$H$12,2,TRUE())+(RAND()*(VLOOKUP(AD300,$F$7:$H$12,3,TRUE())-VLOOKUP(AD300,$F$7:$H$12,2,TRUE()))) -> 64.60117 | AF300: =RAND() -> 0.84875601 | AG300: =VLOOKUP(AF300,$K$7:$M$10,2,TRUE())+(RAND()*(VLOOKUP(AF300,$K$7:$M$10,3,TRUE())-VLOOKUP(AF300,$K$7:$M$10,2,TRUE()))) -> 5.1403897 | AH300: =AG300*11 -> 56.544286 | AI300: =MAX(AE300-AH300,0) -> 8.056884 | AJ300: =AI300*100 -> 805.6884 | AL300: =AL299+1 -> 10 | AM300: =RAND() -> 0.71424138 | AN300: =VLOOKUP(AM300,$F$7:$H$12,2,TRUE())+(RAND()*(VLOOKUP(AM300,$F$7:$H$12,3,TRUE())-VLOOKUP(AM300,$F$7:$H$12,2,TRUE()))) -> 65.639137 | AO300: =RAND() -> 0.11120031 | AP300: =VLOOKUP(AO300,$K$7:$M$10,2,TRUE())+(RAND()*(VLOOKUP(AO300,$K$7:$M$10,3,TRUE())-VLOOKUP(AO300,$K$7:$M$10,2,TRUE()))) -> 4.1128252 | AQ300: =AP300*12 -> 49.353903 | AR300: =MAX(AN300-AQ300,0) -> 16.285235 | AS300: =AR300*100 -> 1628.5235 | AU300: =AU299+1 -> 10 | AV300: =RAND() -> 0.35199739 | AW300: =VLOOKUP(AV300,$F$7:$H$12,2,TRUE())+(RAND()*(VLOOKUP(AV300,$F$7:$H$12,3,TRUE())-VLOOKUP(AV300,$F$7:$H$12,2,TRUE()))) -> 64.265741 | AX300: =RAND() -> 0.12729879 | AY300: =VLOOKUP(AX300,$K$7:$M$10,2,TRUE())+(RAND()*(VLOOKUP(AX300,$K$7:$M$10,3,TRUE())-VLOOKUP(AX300,$K$7:$M$10,2,TRUE()))) -> 4.0390586 | AZ300: =AY300*13 -> 52.507762 | BA300: =MAX(AW300-AZ300,0) -> 11.757979 | BB300: =BA300*100 -> 1175.7979 | BD300: =BD299+1 -> 10 | BE300: =RAND() -> 0.085843009 | BF300: =VLOOKUP(BE300,$F$7:$H$12,2,TRUE())+(RAND()*(VLOOKUP(BE300,$F$7:$H$12,3,TRUE())-VLOOKUP(BE300,$F$7:$H$12,2,TRUE()))) -> 50.432936 | BG300: =RAND() -> 0.49482941 | BH300: =VLOOKUP(BG300,$K$7:$M$10,2,TRUE())+(RAND()*(VLOOKUP(BG300,$K$7:$M$10,3,TRUE())-VLOOKUP(BG300,$K$7:$M$10,2,TRUE()))) -> 4.8520741 | BI300: =BH300*14 -> 67.929038 | BJ300: =MAX(BF300-BI300,0) -> 0 | BK300: =BJ300*100 -> 0 | BM300: =BM299+1 -> 10 | BN300: =RAND() -> 0.75706931 | BO300: =VLOOKUP(BN300,$F$7:$H$12,2,TRUE())+(RAND()*(VLOOKUP(BN300,$F$7:$H$12,3,TRUE())-VLOOKUP(BN300,$F$7:$H$12,2,TRUE()))) -> 65.121221 | BP300: =RAND() -> 0.10452734 | BQ300: =VLOOKUP(BP300,$K$7:$M$10,2,TRUE())+(RAND()*(VLOOKUP(BP300,$K$7:$M$10,3,TRUE())-VLOOKUP(BP300,$K$7:$M$10,2,TRUE()))) -> 4.3119333 | BR300: =BQ300*15 -> 64.679 | BS300: =MAX(BO300-BR300,0) -> 0.4422212 | BT300: =BS300*100 -> 44.22212
B301: =B300+1 -> 11 | C301: =RAND() -> 0.94341493 | D301: =VLOOKUP(C301,$F$7:$H$12,2,TRUE())+(RAND()*(VLOOKUP(C301,$F$7:$H$12,3,TRUE())-VLOOKUP(C301,$F$7:$H$12,2,TRUE()))) -> 79.07543 | E301: =RAND() -> 0.82351567 | F301: =VLOOKUP(E301,$K$7:$M$10,2,TRUE())+(RAND()*(VLOOKUP(E301,$K$7:$M$10,3,TRUE())-VLOOKUP(E301,$K$7:$M$10,2,TRUE()))) -> 5.1473143 | G301: =F301*8 -> 41.178514 | H301: =MAX(D301-G301,0) -> 37.896916 | I301: =H301*100 -> 3789.6916 | K301: =K300+1 -> 11 | L301: =RAND() -> 0.61537086 | M301: =VLOOKUP(L301,$F$7:$H$12,2,TRUE())+(RAND()*(VLOOKUP(L301,$F$7:$H$12,3,TRUE())-VLOOKUP(L301,$F$7:$H$12,2,TRUE()))) -> 67.695024 | N301: =RAND() -> 0.67173338 | O301: =VLOOKUP(N301,$K$7:$M$10,2,TRUE())+(RAND()*(VLOOKUP(N301,$K$7:$M$10,3,TRUE())-VLOOKUP(N301,$K$7:$M$10,2,TRUE()))) -> 4.8570013 | P301: =O301*9 -> 43.713012 | Q301: =MAX(M301-P301,0) -> 23.982012 | R301: =Q301*100 -> 2398.2012 | T301: =T300+1 -> 11 | U301: =RAND() -> 0.37740689 | V301: =VLOOKUP(U301,$F$7:$H$12,2,TRUE())+(RAND()*(VLOOKUP(U301,$F$7:$H$12,3,TRUE())-VLOOKUP(U301,$F$7:$H$12,2,TRUE()))) -> 60.359427 | W301: =RAND() -> 0.54422644 | X301: =VLOOKUP(W301,$K$7:$M$10,2,TRUE())+(RAND()*(VLOOKUP(W301,$K$7:$M$10,3,TRUE())-VLOOKUP(W301,$K$7:$M$10,2,TRUE()))) -> 4.693183 | Y301: =X301*10 -> 46.93183 | Z301: =MAX(V301-Y301,0) -> 13.427596 | AA301: =Z301*100 -> 1342.7596 | AC301: =AC300+1 -> 11 | AD301: =RAND() -> 0.13846329 | AE301: =VLOOKUP(AD301,$F$7:$H$12,2,TRUE())+(RAND()*(VLOOKUP(AD301,$F$7:$H$12,3,TRUE())-VLOOKUP(AD301,$F$7:$H$12,2,TRUE()))) -> 56.407054 | AF301: =RAND() -> 0.48026824 | AG301: =VLOOKUP(AF301,$K$7:$M$10,2,TRUE())+(RAND()*(VLOOKUP(AF301,$K$7:$M$10,3,TRUE())-VLOOKUP(AF301,$K$7:$M$10,2,TRUE()))) -> 4.6761464 | AH301: =AG301*11 -> 51.43761 | AI301: =MAX(AE301-AH301,0) -> 4.9694439 | AJ301: =AI301*100 -> 496.94439 | AL301: =AL300+1 -> 11 | AM301: =RAND() -> 0.58323145 | AN301: =VLOOKUP(AM301,$F$7:$H$12,2,TRUE())+(RAND()*(VLOOKUP(AM301,$F$7:$H$12,3,TRUE())-VLOOKUP(AM301,$F$7:$H$12,2,TRUE()))) -> 67.025295 | AO301: =RAND() -> 0.59352067 | AP301: =VLOOKUP(AO301,$K$7:$M$10,2,TRUE())+(RAND()*(VLOOKUP(AO301,$K$7:$M$10,3,TRUE())-VLOOKUP(AO301,$K$7:$M$10,2,TRUE()))) -> 4.5579896 | AQ301: =AP301*12 -> 54.695875 | AR301: =MAX(AN301-AQ301,0) -> 12.32942 | AS301: =AR301*100 -> 1232.942 | AU301: =AU300+1 -> 11 | AV301: =RAND() -> 0.081356455 | AW301: =VLOOKUP(AV301,$F$7:$H$12,2,TRUE())+(RAND()*(VLOOKUP(AV301,$F$7:$H$12,3,TRUE())-VLOOKUP(AV301,$F$7:$H$12,2,TRUE()))) -> 50.503282 | AX301: =RAND() -> 0.30658362 | AY301: =VLOOKUP(AX301,$K$7:$M$10,2,TRUE())+(RAND()*(VLOOKUP(AX301,$K$7:$M$10,3,TRUE())-VLOOKUP(AX301,$K$7:$M$10,2,TRUE()))) -> 4.6382358 | AZ301: =AY301*13 -> 60.297065 | BA301: =MAX(AW301-AZ301,0) -> 0 | BB301: =BA301*100 -> 0 | BD301: =BD300+1 -> 11 | BE301: =RAND() -> 0.072913838 | BF301: =VLOOKUP(BE301,$F$7:$H$12,2,TRUE())+(RAND()*(VLOOKUP(BE301,$F$7:$H$12,3,TRUE())-VLOOKUP(BE301,$F$7:$H$12,2,TRUE()))) -> 52.865863 | BG301: =RAND() -> 0.6421019 | BH301: =VLOOKUP(BG301,$K$7:$M$10,2,TRUE())+(RAND()*(VLOOKUP(BG301,$K$7:$M$10,3,TRUE())-VLOOKUP(BG301,$K$7:$M$10,2,TRUE()))) -> 4.6970732 | BI301: =BH301*14 -> 65.759025 | BJ301: =MAX(BF301-BI301,0) -> 0 | BK301: =BJ301*100 -> 0 | BM301: =BM300+1 -> 11 | BN301: =RAND() -> 0.57484358 | BO301: =VLOOKUP(BN301,$F$7:$H$12,2,TRUE())+(RAND()*(VLOOKUP(BN301,$F$7:$H$12,3,TRUE())-VLOOKUP(BN301,$F$7:$H$12,2,TRUE()))) -> 68.663718 | BP301: =RAND() -> 0.15645895 | BQ301: =VLOOKUP(BP301,$K$7:$M$10,2,TRUE())+(RAND()*(VLOOKUP(BP301,$K$7:$M$10,3,TRUE())-VLOOKUP(BP301,$K$7:$M$10,2,TRUE()))) -> 4.4048191 | BR301: =BQ301*15 -> 66.072286 | BS301: =MAX(BO301-BR301,0) -> 2.5914319 | BT301: =BS301*100 -> 259.14319
B302: =B301+1 -> 12 | C302: =RAND() -> 0.77164429 | D302: =VLOOKUP(C302,$F$7:$H$12,2,TRUE())+(RAND()*(VLOOKUP(C302,$F$7:$H$12,3,TRUE())-VLOOKUP(C302,$F$7:$H$12,2,TRUE()))) -> 66.569062 | E302: =RAND() -> 0.78167098 | F302: =VLOOKUP(E302,$K$7:$M$10,2,TRUE())+(RAND()*(VLOOKUP(E302,$K$7:$M$10,3,TRUE())-VLOOKUP(E302,$K$7:$M$10,2,TRUE()))) -> 5.3240463 | G302: =F302*8 -> 42.592371 | H302: =MAX(D302-G302,0) -> 23.976691 | I302: =H302*100 -> 2397.6691 | K302: =K301+1 -> 12 | L302: =RAND() -> 0.52592907 | M302: =VLOOKUP(L302,$F$7:$H$12,2,TRUE())+(RAND()*(VLOOKUP(L302,$F$7:$H$12,3,TRUE())-VLOOKUP(L302,$F$7:$H$12,2,TRUE()))) -> 63.03925 | N302: =RAND() -> 0.089812476 | O302: =VLOOKUP(N302,$K$7:$M$10,2,TRUE())+(RAND()*(VLOOKUP(N302,$K$7:$M$10,3,TRUE())-VLOOKUP(N302,$K$7:$M$10,2,TRUE()))) -> 4.4692097 | P302: =O302*9 -> 40.222887 | Q302: =MAX(M302-P302,0) -> 22.816363 | R302: =Q302*100 -> 2281.6363 | T302: =T301+1 -> 12 | U302: =RAND() -> 0.46981632 | V302: =VLOOKUP(U302,$F$7:$H$12,2,TRUE())+(RAND()*(VLOOKUP(U302,$F$7:$H$12,3,TRUE())-VLOOKUP(U302,$F$7:$H$12,2,TRUE()))) -> 60.13391 | W302: =RAND() -> 0.68431983 | X302: =VLOOKUP(W302,$K$7:$M$10,2,TRUE())+(RAND()*(VLOOKUP(W302,$K$7:$M$10,3,TRUE())-VLOOKUP(W302,$K$7:$M$10,2,TRUE()))) -> 4.640044 | Y302: =X302*10 -> 46.40044 | Z302: =MAX(V302-Y302,0) -> 13.73347 | AA302: =Z302*100 -> 1373.347 | AC302: =AC301+1 -> 12 | AD302: =RAND() -> 0.13965884 | AE302: =VLOOKUP(AD302,$F$7:$H$12,2,TRUE())+(RAND()*(VLOOKUP(AD302,$F$7:$H$12,3,TRUE())-VLOOKUP(AD302,$F$7:$H$12,2,TRUE()))) -> 59.49523 | AF302: =RAND() -> 0.5603471 | AG302: =VLOOKUP(AF302,$K$7:$M$10,2,TRUE())+(RAND()*(VLOOKUP(AF302,$K$7:$M$10,3,TRUE())-VLOOKUP(AF302,$K$7:$M$10,2,TRUE()))) -> 4.9223138 | AH302: =AG302*11 -> 54.145452 | AI302: =MAX(AE302-AH302,0) -> 5.3497787 | AJ302: =AI302*100 -> 534.97787 | AL302: =AL301+1 -> 12 | AM302: =RAND() -> 0.011426117 | AN302: =VLOOKUP(AM302,$F$7:$H$12,2,TRUE())+(RAND()*(VLOOKUP(AM302,$F$7:$H$12,3,TRUE())-VLOOKUP(AM302,$F$7:$H$12,2,TRUE()))) -> 53.594064 | AO302: =RAND() -> 0.058142564 | AP302: =VLOOKUP(AO302,$K$7:$M$10,2,TRUE())+(RAND()*(VLOOKUP(AO302,$K$7:$M$10,3,TRUE())-VLOOKUP(AO302,$K$7:$M$10,2,TRUE()))) -> 4.3694083 | AQ302: =AP302*12 -> 52.432899 | AR302: =MAX(AN302-AQ302,0) -> 1.1611649 | AS302: =AR302*100 -> 116.11649 | AU302: =AU301+1 -> 12 | AV302: =RAND() -> 0.60929606 | AW302: =VLOOKUP(AV302,$F$7:$H$12,2,TRUE())+(RAND()*(VLOOKUP(AV302,$F$7:$H$12,3,TRUE())-VLOOKUP(AV302,$F$7:$H$12,2,TRUE()))) -> 69.042427 | AX302: =RAND() -> 0.99962883 | AY302: =VLOOKUP(AX302,$K$7:$M$10,2,TRUE())+(RAND()*(VLOOKUP(AX302,$K$7:$M$10,3,TRUE())-VLOOKUP(AX302,$K$7:$M$10,2,TRUE()))) -> 5.5812893 | AZ302: =AY302*13 -> 72.55676 | BA302: =MAX(AW302-AZ302,0) -> 0 | BB302: =BA302*100 -> 0 | BD302: =BD301+1 -> 12 | BE302: =RAND() -> 0.36350373 | BF302: =VLOOKUP(BE302,$F$7:$H$12,2,TRUE())+(RAND()*(VLOOKUP(BE302,$F$7:$H$12,3,TRUE())-VLOOKUP(BE302,$F$7:$H$12,2,TRUE()))) -> 60.823893 | BG302: =RAND() -> 0.5511343 | BH302: =VLOOKUP(BG302,$K$7:$M$10,2,TRUE())+(RAND()*(VLOOKUP(BG302,$K$7:$M$10,3,TRUE())-VLOOKUP(BG302,$K$7:$M$10,2,TRUE()))) -> 4.7585068 | BI302: =BH302*14 -> 66.619095 | BJ302: =MAX(BF302-BI302,0) -> 0 | BK302: =BJ302*100 -> 0 | BM302: =BM301+1 -> 12 | BN302: =RAND() -> 0.81959296 | BO302: =VLOOKUP(BN302,$F$7:$H$12,2,TRUE())+(RAND()*(VLOOKUP(BN302,$F$7:$H$12,3,TRUE())-VLOOKUP(BN302,$F$7:$H$12,2,TRUE()))) -> 67.637966 | BP302: =RAND() -> 0.57970184 | BQ302: =VLOOKUP(BP302,$K$7:$M$10,2,TRUE())+(RAND()*(VLOOKUP(BP302,$K$7:$M$10,3,TRUE())-VLOOKUP(BP302,$K$7:$M$10,2,TRUE()))) -> 4.891759 | BR302: =BQ302*15 -> 73.376385 | BS302: =MAX(BO302-BR302,0) -> 0 | BT302: =BS302*100 -> 0
B303: =B302+1 -> 13 | C303: =RAND() -> 0.034520447 | D303: =VLOOKUP(C303,$F$7:$H$12,2,TRUE())+(RAND()*(VLOOKUP(C303,$F$7:$H$12,3,TRUE())-VLOOKUP(C303,$F$7:$H$12,2,TRUE()))) -> 54.588084 | E303: =RAND() -> 0.79552849 | F303: =VLOOKUP(E303,$K$7:$M$10,2,TRUE())+(RAND()*(VLOOKUP(E303,$K$7:$M$10,3,TRUE())-VLOOKUP(E303,$K$7:$M$10,2,TRUE()))) -> 5.0766975 | G303: =F303*8 -> 40.61358 | H303: =MAX(D303-G303,0) -> 13.974504 | I303: =H303*100 -> 1397.4504 | K303: =K302+1 -> 13 | L303: =RAND() -> 0.75519777 | M303: =VLOOKUP(L303,$F$7:$H$12,2,TRUE())+(RAND()*(VLOOKUP(L303,$F$7:$H$12,3,TRUE())-VLOOKUP(L303,$F$7:$H$12,2,TRUE()))) -> 68.898318 | N303: =RAND() -> 0.57236474 | O303: =VLOOKUP(N303,$K$7:$M$10,2,TRUE())+(RAND()*(VLOOKUP(N303,$K$7:$M$10,3,TRUE())-VLOOKUP(N303,$K$7:$M$10,2,TRUE()))) -> 4.8427443 | P303: =O303*9 -> 43.584699 | Q303: =MAX(M303-P303,0) -> 25.313619 | R303: =Q303*100 -> 2531.3619 | T303: =T302+1 -> 13 | U303: =RAND() -> 0.79687325 | V303: =VLOOKUP(U303,$F$7:$H$12,2,TRUE())+(RAND()*(VLOOKUP(U303,$F$7:$H$12,3,TRUE())-VLOOKUP(U303,$F$7:$H$12,2,TRUE()))) -> 66.027122 | W303: =RAND() -> 0.66070967 | X303: =VLOOKUP(W303,$K$7:$M$10,2,TRUE())+(RAND()*(VLOOKUP(W303,$K$7:$M$10,3,TRUE())-VLOOKUP(W303,$K$7:$M$10,2,TRUE()))) -> 4.8625481 | Y303: =X303*10 -> 48.625481 | Z303: =MAX(V303-Y303,0) -> 17.40164 | AA303: =Z303*100 -> 1740.164 | AC303: =AC302+1 -> 13 | AD303: =RAND() -> 0.58736414 | AE303: =VLOOKUP(AD303,$F$7:$H$12,2,TRUE())+(RAND()*(VLOOKUP(AD303,$F$7:$H$12,3,TRUE())-VLOOKUP(AD303,$F$7:$H$12,2,TRUE()))) -> 68.492185 | AF303: =RAND() -> 0.8707882 | AG303: =VLOOKUP(AF303,$K$7:$M$10,2,TRUE())+(RAND()*(VLOOKUP(AF303,$K$7:$M$10,3,TRUE())-VLOOKUP(AF303,$K$7:$M$10,2,TRUE()))) -> 5.2225851 | AH303: =AG303*11 -> 57.448436 | AI303: =MAX(AE303-AH303,0) -> 11.043749 | AJ303: =AI303*100 -> 1104.3749 | AL303: =AL302+1 -> 13 | AM303: =RAND() -> 0.95874835 | AN303: =VLOOKUP(AM303,$F$7:$H$12,2,TRUE())+(RAND()*(VLOOKUP(AM303,$F$7:$H$12,3,TRUE())-VLOOKUP(AM303,$F$7:$H$12,2,TRUE()))) -> 79.80731 | AO303: =RAND() -> 0.14792524 | AP303: =VLOOKUP(AO303,$K$7:$M$10,2,TRUE())+(RAND()*(VLOOKUP(AO303,$K$7:$M$10,3,TRUE())-VLOOKUP(AO303,$K$7:$M$10,2,TRUE()))) -> 4.2241107 | AQ303: =AP303*12 -> 50.689328 | AR303: =MAX(AN303-AQ303,0) -> 29.117983 | AS303: =AR303*100 -> 2911.7983 | AU303: =AU302+1 -> 13 | AV303: =RAND() -> 0.099790063 | AW303: =VLOOKUP(AV303,$F$7:$H$12,2,TRUE())+(RAND()*(VLOOKUP(AV303,$F$7:$H$12,3,TRUE())-VLOOKUP(AV303,$F$7:$H$12,2,TRUE()))) -> 54.479953 | AX303: =RAND() -> 0.12095822 | AY303: =VLOOKUP(AX303,$K$7:$M$10,2,TRUE())+(RAND()*(VLOOKUP(AX303,$K$7:$M$10,3,TRUE())-VLOOKUP(AX303,$K$7:$M$10,2,TRUE()))) -> 4.4982663 | AZ303: =AY303*13 -> 58.477462 | BA303: =MAX(AW303-AZ303,0) -> 0 | BB303: =BA303*100 -> 0 | BD303: =BD302+1 -> 13 | BE303: =RAND() -> 0.78467961 | BF303: =VLOOKUP(BE303,$F$7:$H$12,2,TRUE())+(RAND()*(VLOOKUP(BE303,$F$7:$H$12,3,TRUE())-VLOOKUP(BE303,$F$7:$H$12,2,TRUE()))) -> 69.204859 | BG303: =RAND() -> 0.84430773 | BH303: =VLOOKUP(BG303,$K$7:$M$10,2,TRUE())+(RAND()*(VLOOKUP(BG303,$K$7:$M$10,3,TRUE())-VLOOKUP(BG303,$K$7:$M$10,2,TRUE()))) -> 5.1763815 | BI303: =BH303*14 -> 72.469341 | BJ303: =MAX(BF303-BI303,0) -> 0 | BK303: =BJ303*100 -> 0 | BM303: =BM302+1 -> 13 | BN303: =RAND() -> 0.09139826 | BO303: =VLOOKUP(BN303,$F$7:$H$12,2,TRUE())+(RAND()*(VLOOKUP(BN303,$F$7:$H$12,3,TRUE())-VLOOKUP(BN303,$F$7:$H$12,2,TRUE()))) -> 52.79486 | BP303: =RAND() -> 0.92276228 | BQ303: =VLOOKUP(BP303,$K$7:$M$10,2,TRUE())+(RAND()*(VLOOKUP(BP303,$K$7:$M$10,3,TRUE())-VLOOKUP(BP303,$K$7:$M$10,2,TRUE()))) -> 5.7858353 | BR303: =BQ303*15 -> 86.787529 | BS303: =MAX(BO303-BR303,0) -> 0 | BT303: =BS303*100 -> 0
... B540: =B539+1 -> 250 | C540: =RAND() -> 0.71529521 | D540: =VLOOKUP(C540,$F$7:$H$12,2,TRUE())+(RAND()*(VLOOKUP(C540,$F$7:$H$12,3,TRUE())-VLOOKUP(C540,$F$7:$H$12,2,TRUE()))) -> 67.062115 | E540: =RAND() -> 0.47000721 | F540: =VLOOKUP(E540,$K$7:$M$10,2,TRUE())+(RAND()*(VLOOKUP(E540,$K$7:$M$10,3,TRUE())-VLOOKUP(E540,$K$7:$M$10,2,TRUE()))) -> 4.6897581 | G540: =F540*8 -> 37.518065 | H540: =MAX(D540-G540,0) -> 29.544049 | I540: =H540*100 -> 2954.4049 | K540: =K539+1 -> 250 | L540: =RAND() -> 0.54657655 | M540: =VLOOKUP(L540,$F$7:$H$12,2,TRUE())+(RAND()*(VLOOKUP(L540,$F$7:$H$12,3,TRUE())-VLOOKUP(L540,$F$7:$H$12,2,TRUE()))) -> 64.768971 | N540: =RAND() -> 0.58660528 | O540: =VLOOKUP(N540,$K$7:$M$10,2,TRUE())+(RAND()*(VLOOKUP(N540,$K$7:$M$10,3,TRUE())-VLOOKUP(N540,$K$7:$M$10,2,TRUE()))) -> 4.6495539 | P540: =O540*9 -> 41.845985 | Q540: =MAX(M540-P540,0) -> 22.922986 | R540: =Q540*100 -> 2292.2986 | T540: =T539+1 -> 250 | U540: =RAND() -> 0.37749514 | V540: =VLOOKUP(U540,$F$7:$H$12,2,TRUE())+(RAND()*(VLOOKUP(U540,$F$7:$H$12,3,TRUE())-VLOOKUP(U540,$F$7:$H$12,2,TRUE()))) -> 61.869229 | W540: =RAND() -> 0.60071845 | X540: =VLOOKUP(W540,$K$7:$M$10,2,TRUE())+(RAND()*(VLOOKUP(W540,$K$7:$M$10,3,TRUE())-VLOOKUP(W540,$K$7:$M$10,2,TRUE()))) -> 4.7101674 | Y540: =X540*10 -> 47.101674 | Z540: =MAX(V540-Y540,0) -> 14.767555 | AA540: =Z540*100 -> 1476.7555 | AC540: =AC539+1 -> 250 | AD540: =RAND() -> 0.72284224 | AE540: =VLOOKUP(AD540,$F$7:$H$12,2,TRUE())+(RAND()*(VLOOKUP(AD540,$F$7:$H$12,3,TRUE())-VLOOKUP(AD540,$F$7:$H$12,2,TRUE()))) -> 69.410651 | AF540: =RAND() -> 0.92147151 | AG540: =VLOOKUP(AF540,$K$7:$M$10,2,TRUE())+(RAND()*(VLOOKUP(AF540,$K$7:$M$10,3,TRUE())-VLOOKUP(AF540,$K$7:$M$10,2,TRUE()))) -> 5.5302541 | AH540: =AG540*11 -> 60.832795 | AI540: =MAX(AE540-AH540,0) -> 8.5778558 | AJ540: =AI540*100 -> 857.78558 | AL540: =AL539+1 -> 250 | AM540: =RAND() -> 0.34083425 | AN540: =VLOOKUP(AM540,$F$7:$H$12,2,TRUE())+(RAND()*(VLOOKUP(AM540,$F$7:$H$12,3,TRUE())-VLOOKUP(AM540,$F$7:$H$12,2,TRUE()))) -> 61.38931 | AO540: =RAND() -> 0.70149425 | AP540: =VLOOKUP(AO540,$K$7:$M$10,2,TRUE())+(RAND()*(VLOOKUP(AO540,$K$7:$M$10,3,TRUE())-VLOOKUP(AO540,$K$7:$M$10,2,TRUE()))) -> 5.0776082 | AQ540: =AP540*12 -> 60.931299 | AR540: =MAX(AN540-AQ540,0) -> 0.4580112 | AS540: =AR540*100 -> 45.80112 | AU540: =AU539+1 -> 250 | AV540: =RAND() -> 0.72757233 | AW540: =VLOOKUP(AV540,$F$7:$H$12,2,TRUE())+(RAND()*(VLOOKUP(AV540,$F$7:$H$12,3,TRUE())-VLOOKUP(AV540,$F$7:$H$12,2,TRUE()))) -> 68.860916 | AX540: =RAND() -> 0.9610756 | AY540: =VLOOKUP(AX540,$K$7:$M$10,2,TRUE())+(RAND()*(VLOOKUP(AX540,$K$7:$M$10,3,TRUE())-VLOOKUP(AX540,$K$7:$M$10,2,TRUE()))) -> 5.55099 | AZ540: =AY540*13 -> 72.16287 | BA540: =MAX(AW540-AZ540,0) -> 0 | BB540: =BA540*100 -> 0 | BD540: =BD539+1 -> 250 | BE540: =RAND() -> 0.43636095 | BF540: =VLOOKUP(BE540,$F$7:$H$12,2,TRUE())+(RAND()*(VLOOKUP(BE540,$F$7:$H$12,3,TRUE())-VLOOKUP(BE540,$F$7:$H$12,2,TRUE()))) -> 63.981799 | BG540: =RAND() -> 0.43857628 | BH540: =VLOOKUP(BG540,$K$7:$M$10,2,TRUE())+(RAND()*(VLOOKUP(BG540,$K$7:$M$10,3,TRUE())-VLOOKUP(BG540,$K$7:$M$10,2,TRUE()))) -> 4.7166488 | BI540: =BH540*14 -> 66.033083 | BJ540: =MAX(BF540-BI540,0) -> 0 | BK540: =BJ540*100 -> 0 | BM540: =BM539+1 -> 250 | BN540: =RAND() -> 0.92712545 | BO540: =VLOOKUP(BN540,$F$7:$H$12,2,TRUE())+(RAND()*(VLOOKUP(BN540,$F$7:$H$12,3,TRUE())-VLOOKUP(BN540,$F$7:$H$12,2,TRUE()))) -> 79.925139 | BP540: =RAND() -> 0.62837241 | BQ540: =VLOOKUP(BP540,$K$7:$M$10,2,TRUE())+(RAND()*(VLOOKUP(BP540,$K$7:$M$10,3,TRUE())-VLOOKUP(BP540,$K$7:$M$10,2,TRUE()))) -> 4.984814 | BR540: =BQ540*15 -> 74.772211 | BS540: =MAX(BO540-BR540,0) -> 5.1529286 | BT540: =BS540*100 -> 515.29286
